Workbook

Sheet LIST
A1: NO | B1: 名 | C1: 英 | D1: 出現 | E1: 特質 | F1: 結合 | G1: 作成日 | H1: 投稿日 | I1: 済 | J1: リール | K1: Column 11 | L1: LEN | M1: _ | N1: 1 | O1: 1_Len | P1: 2 | Q1: 2_Len | R1: 3 | S1: 3_Len | T1: 4_Len | U1: 5 | V1: 5_Len | W1: 4 | X1: 6 | Y1: 6_Len | Z1: 7 | AA1: 7_len | AB1: 8 | AC1: 8_len
A2: 0 | B2: 書楽斎（しょらくさい） | C2: syorakusai | D2: 寺子屋や筆屋の周辺 | E2: 丸い頭が光る妖怪。筆を手に持つ。 画は人造の巧智により描かれしものなれど、 文は我が筆の妙技により輝く珠として後に残らん。 我が志は、千体の妖怪を集め私蔵展を催すこと。 日々一体ずつ記し、仕事の御便りを待つ。 | F2: ="【名】" & B2 & C2 &char(10) & "【番】" & text(A2,"0000") & char(10) &"【出現】"&D2& char(10)&"【特質】"& char(10)&E2&char(10)&char(10)&memo!$B$1 -> 【名】書楽斎（しょらくさい）syorakusai 【番】0000 【出現】寺子屋や筆屋の周辺 【特質】 丸い頭が光る妖怪。筆を手に持つ。 画は人造の巧智により描かれしものなれど、 文は我が筆の妙技により輝く珠として後に残らん。 我が志は、千体の妖怪を集め私蔵展を催すこと。 日々一体ずつ記し、仕事の御便りを待つ。 #妖怪 #yokai #sumie #monster #ghost | G2: 45696 | H2: - | I2: - | J2: 45699 | K2: ふりかえるといるよ | L2: =len(E2) -> 104 | N2: =mid(F2,1,find("【特質】",F2)-1) &char(10)&memo!$B$2 -> 【名】書楽斎（しょらくさい）syorakusai 【番】0000 【出現】寺子屋や筆屋の周辺 #妖怪 #お化け #怪物 #オリジナル妖怪 #monster #ghost #妖怪好き #浮世絵 #百鬼夜行 | O2: =len(N2) -> 102 | P2: 丸い頭が光る妖怪。筆を手に持つ。 画は人造の巧智により描かるものなれど、 文は我が筆の妙技により輝く珠として後に残らん。 我が志は、千体の妖怪を集め私蔵展を催すこと。 日々一体ずつ記し、仕事の御便りを待つ。 | Q2: =len(P2) -> 108 | S2: =len(R2) -> 0 | T2: =len(W2) -> 0 | V2: =len(U2) -> 0 | Y2: =len(X2) -> 0 | AA2: =len(Z2) -> 0 | AC2: =len(AB2) -> 0
A3: 1 | B3: 左腕（ひだりで） | C3: hidaride | D3: 幼稚園や保育園、寺子屋、さらには夜の宿場町で休息を求める子供たちのそば | E3: ほっそりした体型の優しい男性の姿をしているが、左腕だけ異常に大きく発達し、抱き枕のような柔らかさを持つ。 職員不足の保育園や幼稚園に忍び込み、子供たちを優しく包み込んで寝かしつける。 子供は不思議とすぐに眠るため、寝かしつけの神として一部の保育士に密かに信仰されている。 通常は温厚だが、右手を触られると激高し、触れた者を捕食する。 過去に右手を縛られたり、傷を負わされたことがあり、それが原因で極端に右手を触られるのを嫌う。 決して右手には触れないこと。 「ありがとう」と囁きながら背を向けると、静かに立ち去る。 眠れぬ夜に「ひだりでよ、子を眠らせたまえ」と願うと現れることがある。 夜間保育施設で、子供たちが一斉に寝入る怪現象が報告されている。 たまに育児に疲れた親の枕元にも現れるが、大人は眠らせてもらえない。 | F3: ="【名】" & B3 & C3 &char(10) & "【番】" & text(A3,"0000") & char(10) &"【出現】"&D3& char(10)&"【特質】"& char(10)&E3&char(10)&char(10)&memo!$B$1 -> 【名】左腕（ひだりで）hidaride 【番】0001 【出現】幼稚園や保育園、寺子屋、さらには夜の宿場町で休息を求める子供たちのそば 【特質】 ほっそりした体型の優しい男性の姿をしているが、左腕だけ異常に大きく発達し、抱き枕のような柔らかさを持つ。 職員不足の保育園や幼稚園に忍び込み、子供たちを優しく包み込んで寝かしつける。 子供は不思議とすぐに眠るため、寝かしつけの神として一部の保育士に密かに信仰されている。 通常は温厚だが、右手を触られると激高し、触れた者を捕食する。 過去に右手を縛られたり、傷を負わされたことがあり、それが原因で極端に右手を触られるのを嫌う。 決して右手には触れないこと。 「ありがとう」と囁きながら背を向けると、静かに立ち去る。 眠れぬ夜に「ひだりでよ、子を眠らせたまえ」と願うと現れることがある。 夜間保育施設で、子供たちが一斉に寝入る怪現象が報告されている。 たまに育児に疲れた親の枕元にも現れるが、大人は眠らせてもらえない。 #妖怪 #yokai #sumie #monster #ghost | G3: 45694 | H3: 45694 | I3: ○ | J3: - | L3: =len(E3) -> 379 | N3: =mid(F3,1,find("【特質】",F3)-1) &char(10)&memo!$B$2 -> 【名】左腕（ひだりで）hidaride 【番】0001 【出現】幼稚園や保育園、寺子屋、さらには夜の宿場町で休息を求める子供たちのそば #妖怪 #お化け #怪物 #オリジナル妖怪 #monster #ghost #妖怪好き #浮世絵 #百鬼夜行 | O3: =len(N3) -> 123 | P3: ほっそりした体型の優しい男性の姿をしているが、左腕だけ異常に大きく発達し、抱き枕のような柔らかさを持つ。 職員不足の保育園や幼稚園に忍び込み、子供たちを優しく包み込んで寝かしつける。 子供は不思議とすぐに眠るため、寝かしつけの神として一部の保育士に密かに信仰されている。 | Q3: =len(P3) -> 136 | R3: 通常は温厚だが、右手を触られると激高し、触れた者を捕食する。 過去に右手を縛られたり、傷を負わされたことがあり、それが原因で極端に右手を触られるのを嫌う。 決して右手には触れないこと。 「ありがとう」と囁きながら背を向けると、静かに立ち去る。 | S3: =len(R3) -> 122 | T3: =len(W3) -> 102 | V3: =len(U3) -> 0 | W3: 眠れぬ夜に「ひだりでよ、子を眠らせたまえ」と願うと現れることがある。 夜間保育施設で、子供たちが一斉に寝入る怪現象が報告されている。 たまに育児に疲れた親の枕元にも現れるが、大人は眠らせてもらえない。 | Y3: =len(X3) -> 0 | AA3: =len(Z3) -> 0 | AC3: =len(AB3) -> 0
A4: 2 | B4: 出汁搾（だししぼ） | C4: dashishibo | D4: 沿岸の海底や潮だまり、時には漁村の沖合 | E4: 深海に生息する巨大な昆布の妖怪。 普通の昆布とは異なり、意思を持ち、人間の言葉を理解することができる。 しかし、最大の特徴は「常に出汁を放出し続ける」という体質。どれほど努力しても止めることはできず、じわじわと旨味が溢れ出してしまう。 そのため、海中では常に出汁の香りが漂い、無数の魚たちが群がってくる。 出汁搾本人はこの体質に悩んでおり、「俺だって普通の海藻として静かに暮らしたいのに……」と嘆いているが、魚たちはお構いなしに周囲を泳ぎ回り、時にはその体をついばんでしまうことも。 ある時、漁師たちはこの噂を聞きつけ、出汁搾を捕まえようとした。 しかし、捕まえてもなお出汁は止まらず、村中が絶品の味わいに包まれたため、結果として漁師たちは大いに喜んだという。 出汁搾自身は「やめろ……もう何も搾り取らないでくれ……」と涙を浮かべていたとか。 出汁搾を捕まえると、その村はしばらく食に困らなくなると言われているが、あまりに長く搾りすぎると、出汁が枯渇し、哀れな姿になってしまう。 そのため、村の者たちは一定の期間が過ぎると「もういいから海に帰れ」と海へ戻してやるのが習わしとなっていた。 もし海で出汁の香りが漂ってきたら、それは出汁搾が近くにいる証拠かもしれない。 しかし、あまりに近づきすぎると、「お前も俺の出汁に引き寄せられたのか……」と悲しげな目で見つめられることになるだろう。 | F4: ="【名】" & B4 & C4 &char(10) & "【番】" & text(A4,"0000") & char(10) &"【出現】"&D4& char(10)&"【特質】"& char(10)&E4&char(10)&char(10)&memo!$B$1 -> 【名】出汁搾（だししぼ）dashishibo 【番】0002 【出現】沿岸の海底や潮だまり、時には漁村の沖合 【特質】 深海に生息する巨大な昆布の妖怪。 普通の昆布とは異なり、意思を持ち、人間の言葉を理解することができる。 しかし、最大の特徴は「常に出汁を放出し続ける」という体質。どれほど努力しても止めることはできず、じわじわと旨味が溢れ出してしまう。 そのため、海中では常に出汁の香りが漂い、無数の魚たちが群がってくる。 出汁搾本人はこの体質に悩んでおり、「俺だって普通の海藻として静かに暮らしたいのに……」と嘆いているが、魚たちはお構いなしに周囲を泳ぎ回り、時にはその体をついばんでしまうことも。 ある時、漁師たちはこの噂を聞きつけ、出汁搾を捕まえようとした。 しかし、捕まえてもなお出汁は止まらず、村中が絶品の味わいに包まれたため、結果として漁師たちは大いに喜んだという。 出汁搾自身は「やめろ……もう何も搾り取らないでくれ……」と涙を浮かべていたとか。 出汁搾を捕まえると、その村はしばらく食に困らなくなると言われているが、あまりに長く搾りすぎると、出汁が枯渇し、哀れな姿になってしまう。 そのため、村の者たちは一定の期間が過ぎると「もういいから海に帰れ」と海へ戻してやるのが習わしとなっていた。 もし海で出汁の香りが漂ってきたら、それは出汁搾が近くにいる証拠かもしれない。 しかし、あまりに近づきすぎると、「お前も俺の出汁に引き寄せられたのか……」と悲しげな目で見つめられることになるだろう。 #妖怪 #yokai #sumie #monster #ghost | G4: 45694 | H4: 45695 | I4: ○ | J4: 45703 | K4: 透明人間 | L4: =len(E4) -> 599 | N4: =mid(F4,1,find("【特質】",F4)-1) &char(10)&memo!$B$2 -> 【名】出汁搾（だししぼ）dashishibo 【番】0002 【出現】沿岸の海底や潮だまり、時には漁村の沖合 #妖怪 #お化け #怪物 #オリジナル妖怪 #monster #ghost #妖怪好き #浮世絵 #百鬼夜行 | O4: =len(N4) -> 110 | P4: 深海に生息する巨大な昆布の妖怪。 普通の昆布とは異なり、意思を持ち、人間の言葉を理解することができる。 しかし、最大の特徴は「常に出汁を放出し続ける」という体質。どれほど努力しても止めることはできず、じわじわと旨味が溢れ出してしまう。 | Q4: =len(P4) -> 118 | R4: そのため、海中では常に出汁の香りが漂い、無数の魚たちが群がってくる。 出汁搾本人はこの体質に悩んでおり、「俺だって普通の海藻として静かに暮らしたいのに……」と嘆いているが、魚たちはお構いなしに周囲を泳ぎ回り、時にはその体をついばんでしまうことも。 | S4: =len(R4) -> 125 | T4: =len(W4) -> 130 | U4: 出汁搾を捕まえると、その村はしばらく食に困らなくなると言われているが、あまりに長く搾りすぎると、出汁が枯渇し、哀れな姿になってしまう。 そのため、村の者たちは一定の期間が過ぎると「もういいから海に帰れ」と海へ戻してやるのが習わしとなっていた。 | V4: =len(U4) -> 122 | W4: ある時、漁師たちはこの噂を聞きつけ、出汁搾を捕まえようとした。 しかし、捕まえてもなお出汁は止まらず、村中が絶品の味わいに包まれたため、結果として漁師たちは大いに喜んだという。 出汁搾自身は「やめろ……もう何も搾り取らないでくれ……」と涙を浮かべていたとか。 | X4: もし海で出汁の香りが漂ってきたら、それは出汁搾が近くにいる証拠かもしれない。 しかし、あまりに近づきすぎると、「お前も俺の出汁に引き寄せられたのか……」と悲しげな目で見つめられることになるだろう。 | Y4: =len(X4) -> 101 | AA4: =len(Z4) -> 0 | AC4: =len(AB4) -> 0
A5: 3 | B5: 膨風呂（ふくらぶろ） | C5: fukuraburo | D5: 宿場町の茶屋、銭湯の脱衣所、縁日の屋台街、酒場の路地裏 | E5: 膨風呂は、異常なほどお腹が膨れ上がった妖怪で、まるで風船のように浮きそうなほどの巨大な腹を持つ。 その一方で、腕や脚、顔は極端に細く、バランスが取れずにふわふわと漂うように動くことが多い。 膨れた腹は高く持ち上げたズボンと腹巻で覆われているが、その下には食べ物や小物、時には盗んだ品まで隠されているという。 この妖怪は主に 食い意地の張った人間や酒飲みの前に現れる。 屋台や宴席で「もう食べられない！」と言いながらも、まだ食べたそうにしている者の前に姿を現し、「その腹、まだ入るぞぉ～」と囁いてくる。 膨風呂の声を聞いてしまうと、不思議と食欲が湧き、限界を超えて食べたり飲んだりしてしまうという。 そして、その結果、本人の腹も膨れ上がり、しばらくの間、膨風呂のように膨張したまま動けなくなるといわれている。 また、膨風呂は盗み癖もあり、気に入った物をこっそり腹の中に隠してしまうことがある。 茶屋の菓子や酒、商人の小銭など、目を離した隙に消えてしまったら、もしかすると膨風呂の仕業かもしれない。 膨風呂に取り憑かれると、延々と食べ続けたり、身体が異様に膨らんでしまうことがある。 しかし、「満腹感を示す仕草」をすることで退散させることができる。 例えば、お腹をさすりながら「もう無理！」と大げさに言うと、膨風呂は「じゃあ仕方ないなぁ」と去っていくという。 また、腹巻の中には「赤い布」が嫌いという伝承があり、赤い手ぬぐいや帯を見せると驚いて逃げるとも言われている。 「食べすぎには気をつけろ」という教訓を伝える妖怪ともいわれ、節度を守れば害はない。 ただし、食い意地の張った者にはしつこく付きまとうため、大食いの者は要注意である。 | F5: ="【名】" & B5 & C5 &char(10) & "【番】" & text(A5,"0000") & char(10) &"【出現】"&D5& char(10)&"【特質】"& char(10)&E5&char(10)&char(10)&memo!$B$1 -> 【名】膨風呂（ふくらぶろ）fukuraburo 【番】0003 【出現】宿場町の茶屋、銭湯の脱衣所、縁日の屋台街、酒場の路地裏 【特質】 膨風呂は、異常なほどお腹が膨れ上がった妖怪で、まるで風船のように浮きそうなほどの巨大な腹を持つ。 その一方で、腕や脚、顔は極端に細く、バランスが取れずにふわふわと漂うように動くことが多い。 膨れた腹は高く持ち上げたズボンと腹巻で覆われているが、その下には食べ物や小物、時には盗んだ品まで隠されているという。 この妖怪は主に 食い意地の張った人間や酒飲みの前に現れる。 屋台や宴席で「もう食べられない！」と言いながらも、まだ食べたそうにしている者の前に姿を現し、「その腹、まだ入るぞぉ～」と囁いてくる。 膨風呂の声を聞いてしまうと、不思議と食欲が湧き、限界を超えて食べたり飲んだりしてしまうという。 そして、その結果、本人の腹も膨れ上がり、しばらくの間、膨風呂のように膨張したまま動けなくなるといわれている。 また、膨風呂は盗み癖もあり、気に入った物をこっそり腹の中に隠してしまうことがある。 茶屋の菓子や酒、商人の小銭など、目を離した隙に消えてしまったら、もしかすると膨風呂の仕業かもしれない。 膨風呂に取り憑かれると、延々と食べ続けたり、身体が異様に膨らんでしまうことがある。 しかし、「満腹感を示す仕草」をすることで退散させることができる。 例えば、お腹をさすりながら「もう無理！」と大げさに言うと、膨風呂は「じゃあ仕方ないなぁ」と去っていくという。 また、腹巻の中には「赤い布」が嫌いという伝承があり、赤い手ぬぐいや帯を見せると驚いて逃げるとも言われている。 「食べすぎには気をつけろ」という教訓を伝える妖怪ともいわれ、節度を守れば害はない。 ただし、食い意地の張った者にはしつこく付きまとうため、大食いの者は要注意である。 #妖怪 #yokai #sumie #monster #ghost | G5: 45694 | H5: 45696 | I5: ○ | J5: 45707 | K5: FLOW | L5: =len(E5) -> 744 | N5: =mid(F5,1,find("【特質】",F5)-1) &char(10)&memo!$B$2 -> 【名】膨風呂（ふくらぶろ）fukuraburo 【番】0003 【出現】宿場町の茶屋、銭湯の脱衣所、縁日の屋台街、酒場の路地裏 #妖怪 #お化け #怪物 #オリジナル妖怪 #monster #ghost #妖怪好き #浮世絵 #百鬼夜行 | O5: =len(N5) -> 119 | P5: 【特質】膨風呂は、異常なほどお腹が膨れ上がった妖怪で、まるで風船のように浮きそうなほどの巨大な腹を持つ。 その一方で、腕や脚、顔は極端に細く、バランスが取れずにふわふわと漂うように動くことが多い。 | Q5: =len(P5) -> 98 | R5: 膨れた腹は高く持ち上げたズボンと腹巻で覆われているが、その下には食べ物や小物、時には盗んだ品まで隠されているという。 この妖怪は主に 食い意地の張った人間や酒飲みの前に現れる。 | S5: =len(R5) -> 89 | T5: =len(W5) -> 114 | U5: そして、その結果、本人の腹も膨れ上がり、しばらくの間、膨風呂のように膨張したまま動けなくなるといわれている。 また、膨風呂は盗み癖もあり、気に入った物をこっそり腹の中に隠してしまうことがある。 | V5: =len(U5) -> 98 | W5: 屋台や宴席で「もう食べられない！」と言いながらも、まだ食べたそうにしている者の前に姿を現し、「その腹、まだ入るぞぉ～」と囁いてくる。 膨風呂の声を聞いてしまうと、不思議と食欲が湧き、限界を超えて食べたり飲んだりしてしまうという。 | X5: 茶屋の菓子や酒、商人の小銭など、目を離した隙に消えてしまったら、もしかすると膨風呂の仕業かもしれない。 膨風呂に取り憑かれると、延々と食べ続けたり、身体が異様に膨らんでしまうことがある。 | Y5: =len(X5) -> 95 | Z5: しかし「満腹感を示す仕草」をすることで退散させることができる。 例えば、お腹をさすりながら「もう無理！」と大げさに言うと、膨風呂は「じゃあ仕方ないなぁ」と去っていくという。 また、腹巻の中には「赤い布」が嫌いという伝承があり、赤い手ぬぐいや帯を見せると驚いて逃げるとも言われている | AA5: =len(Z5) -> 140 | AC5: =len(AB5) -> 0
A6: 4 | B6: 底視（そこみ） | C6: sokomi | D6: 書庫のある寺院、古書店、夜の寺子屋 | E6: 4cmもの厚さのびん底眼鏡をかけた妖怪。 その分厚いレンズの向こうにある目は、常人にはまともに見えず、覗き込んだ者は現実が歪んで見えるという。 横から見たときの異様な厚みが特徴で、そこには世の中の真理や禁忌の情報が刻まれているとも噂される。 彼が見つめた書物は、墨がにじんで読めなくなることがあり、学者や文人が恐れたという。 逆に、学びを深く求める者には「真実」を見せることもあるが、それは人間が知るにはあまりにも過酷なものであり、知ってしまった者は精神を病むか、異形となって闇に消えてしまうという。 かつて寺子屋で悪さをしていた子供が、彼の眼鏡に映った「何か」を見て以来、一切の悪戯をやめたという伝説も残されている。 | F6: ="【名】" & B6 & C6 &char(10) & "【番】" & text(A6,"0000") & char(10) &"【出現】"&D6& char(10)&"【特質】"& char(10)&E6&char(10)&char(10)&memo!$B$1 -> 【名】底視（そこみ）sokomi 【番】0004 【出現】書庫のある寺院、古書店、夜の寺子屋 【特質】 4cmもの厚さのびん底眼鏡をかけた妖怪。 その分厚いレンズの向こうにある目は、常人にはまともに見えず、覗き込んだ者は現実が歪んで見えるという。 横から見たときの異様な厚みが特徴で、そこには世の中の真理や禁忌の情報が刻まれているとも噂される。 彼が見つめた書物は、墨がにじんで読めなくなることがあり、学者や文人が恐れたという。 逆に、学びを深く求める者には「真実」を見せることもあるが、それは人間が知るにはあまりにも過酷なものであり、知ってしまった者は精神を病むか、異形となって闇に消えてしまうという。 かつて寺子屋で悪さをしていた子供が、彼の眼鏡に映った「何か」を見て以来、一切の悪戯をやめたという伝説も残されている。 #妖怪 #yokai #sumie #monster #ghost | G6: 45694 | H6: 45697 | I6: ○ | J6: 45710 | K6: Time Warp | L6: =len(E6) -> 312 | N6: =mid(F6,1,find("【特質】",F6)-1) &char(10)&memo!$B$2 -> 【名】底視（そこみ）sokomi 【番】0004 【出現】書庫のある寺院、古書店、夜の寺子屋 #妖怪 #お化け #怪物 #オリジナル妖怪 #monster #ghost #妖怪好き #浮世絵 #百鬼夜行 | O6: =len(N6) -> 102 | P6: 4cmもの厚さのびん底眼鏡をかけた妖怪。 その分厚いレンズの向こうにある目は、常人にはまともに見えず、覗き込んだ者は現実が歪んで見えるという。 横から見たときの異様な厚みが特徴で、そこには世の中の真理や禁忌の情報が刻まれているとも噂される。 | Q6: =len(P6) -> 120 | R6: 彼が見つめた書物は、墨がにじんで読めなくなることがあり、学者や文人が恐れたという。 逆に、学びを深く求める者には「真実」を見せることもあるが、それは人間が知るにはあまりにも過酷なものであり、知ってしまった者は精神を病むか、異形となって闇に消えてしまうという。 | S6: =len(R6) -> 129 | T6: =len(W6) -> 58 | V6: =len(U6) -> 0 | W6: かつて寺子屋で悪さをしていた子供が、彼の眼鏡に映った「何か」を見て以来、一切の悪戯をやめたという伝説も残されている。 | Y6: =len(X6) -> 0 | AA6: =len(Z6) -> 0 | AC6: =len(AB6) -> 0
A7: 5 | B7: 双喰鹿（そうしょくろく） | C7: soshokuroku | D7: 深い霧が立ち込める山間の湖や湿地帯 | E7: 一見すると鹿のような姿をしているが、首元には大きな裂け目があり、そこには魚のような生物が共生している。 この魚は鹿の体を住処とし、互いに共生しているが、鹿にとっては厄介な存在でもある。 普通の鹿の 2倍も腹が減るという欠点があり、その原因は 中の魚が極端な美食家だからである。 鹿は草食獣であるにも関わらず、魚のために狩りをしなければならず、時には小動物や鳥を捕まえることもある。 鹿と魚の共通の大好物は原木しいたけであり、原木しいたけの匂いを嗅ぐと、鹿も魚も異様に興奮する。 そのため原木しいたけを見つけたときが仕留める最大のチャンス。 興奮のあまり無防備になるため、狩人たちはこの瞬間を狙って仕留めることがある。 しかし、双喰鹿の肉は まったく食えたもんではない。 肉自体は硬くて臭く、内臓は魚のせいで独特の生臭さがある。 さらに、中の魚は 鹿が死ぬと最後の抵抗として飛び出し、食らいついてくる。 解体する際にも非常に厄介な妖怪として恐れられている。 この妖怪を見た者は、「あいつら、食い物のことで頭がいっぱいだ」と語るという…。 | F7: ="【名】" & B7 & C7 &char(10) & "【番】" & text(A7,"0000") & char(10) &"【出現】"&D7& char(10)&"【特質】"& char(10)&E7&char(10)&char(10)&memo!$B$1 -> 【名】双喰鹿（そうしょくろく）soshokuroku 【番】0005 【出現】深い霧が立ち込める山間の湖や湿地帯 【特質】 一見すると鹿のような姿をしているが、首元には大きな裂け目があり、そこには魚のような生物が共生している。 この魚は鹿の体を住処とし、互いに共生しているが、鹿にとっては厄介な存在でもある。 普通の鹿の 2倍も腹が減るという欠点があり、その原因は 中の魚が極端な美食家だからである。 鹿は草食獣であるにも関わらず、魚のために狩りをしなければならず、時には小動物や鳥を捕まえることもある。 鹿と魚の共通の大好物は原木しいたけであり、原木しいたけの匂いを嗅ぐと、鹿も魚も異様に興奮する。 そのため原木しいたけを見つけたときが仕留める最大のチャンス。 興奮のあまり無防備になるため、狩人たちはこの瞬間を狙って仕留めることがある。 しかし、双喰鹿の肉は まったく食えたもんではない。 肉自体は硬くて臭く、内臓は魚のせいで独特の生臭さがある。 さらに、中の魚は 鹿が死ぬと最後の抵抗として飛び出し、食らいついてくる。 解体する際にも非常に厄介な妖怪として恐れられている。 この妖怪を見た者は、「あいつら、食い物のことで頭がいっぱいだ」と語るという…。 #妖怪 #yokai #sumie #monster #ghost | G7: 45694 | H7: 45698 | I7: ○ | J7: - | L7: =len(E7) -> 473 | N7: =mid(F7,1,find("【特質】",F7)-1) &char(10)&memo!$B$2 -> 【名】双喰鹿（そうしょくろく）soshokuroku 【番】0005 【出現】深い霧が立ち込める山間の湖や湿地帯 #妖怪 #お化け #怪物 #オリジナル妖怪 #monster #ghost #妖怪好き #浮世絵 #百鬼夜行 | O7: =len(N7) -> 112 | P7: 一見すると鹿のような姿をしているが、首元には大きな裂け目があり、そこには魚のような生物が共生している。 この魚は鹿の体を住処とし、互いに共生しているが、鹿にとっては厄介な存在でもある。 | Q7: =len(P7) -> 93 | R7: 普通の鹿の 2倍も腹が減るという欠点があり、その原因は 中の魚が極端な美食家だからである。 鹿は草食獣であるにも関わらず、魚のために狩りをしなければならず、時には小動物や鳥を捕まえることもある。 | S7: =len(R7) -> 98 | T7: =len(W7) -> 117 | U7: しかし、双喰鹿の肉は まったく食えたもんではない。 肉自体は硬くて臭く、内臓は魚のせいで独特の生臭さがある。 さらに、中の魚は 鹿が死ぬと最後の抵抗として飛び出し、食らいついてくる。 解体する際にも非常に厄介な妖怪として恐れられている。 | V7: =len(U7) -> 119 | W7: 鹿と魚の共通の大好物は原木しいたけであり、原木しいたけの匂いを嗅ぐと、鹿も魚も異様に興奮する。 そのため原木しいたけを見つけたときが仕留める最大のチャンス。 興奮のあまり無防備になるため、狩人たちはこの瞬間を狙って仕留めることがある。 | X7: この妖怪を見た者は、「あいつら、食い物のことで頭がいっぱいだ」と語るという…。 | Y7: =len(X7) -> 39 | AA7: =len(Z7) -> 0 | AC7: =len(AB7) -> 0
A8: 6 | B8: 木魚童（もくぎょどう） | C8: mokugyodo | D8: 古い寺院、廃寺、荒れ果てた僧坊 | E8: かつて念仏僧たちが叩き続けた木魚が、人々の想いと煩悩を吸い込み、妖怪と化した姿。 その頭はまるで本物の木魚のように丸く彫られた木製の形をしており、体は童のように小さく、僧衣をまとっている。 昼間はただの木魚のように佇んでいるが、夜になると動き出し、静かに念仏を唱えながら寺の中を歩き回る。 木魚童は寺の修行僧を見守る存在であり、勤勉な者には穏やかに寄り添い、怠ける者にはその頭を差し出す。 「叩け」と促されるままに木魚を打つと、不思議なことに自らの煩悩が一つ抜け落ちたように感じるという。 しかし、あまりに多く打ち続けると、木魚童の身体は重く沈み込み、叩いた者の煩悩をすべて吸い取る代わりに、その者の心が空虚になってしまうと言われている。 また、木魚童のいる寺院では、夜になると誰もいない本堂から「ポク…ポク…」という木魚の音が聞こえてくることがある。 それは、僧たちの代わりに木魚童が自らの頭を叩き、寺に漂う煩悩を鎮めようとしているのかもしれない…。 | F8: ="【名】" & B8 & C8 &char(10) & "【番】" & text(A8,"0000") & char(10) &"【出現】"&D8& char(10)&"【特質】"& char(10)&E8&char(10)&char(10)&memo!$B$1 -> 【名】木魚童（もくぎょどう）mokugyodo 【番】0006 【出現】古い寺院、廃寺、荒れ果てた僧坊 【特質】 かつて念仏僧たちが叩き続けた木魚が、人々の想いと煩悩を吸い込み、妖怪と化した姿。 その頭はまるで本物の木魚のように丸く彫られた木製の形をしており、体は童のように小さく、僧衣をまとっている。 昼間はただの木魚のように佇んでいるが、夜になると動き出し、静かに念仏を唱えながら寺の中を歩き回る。 木魚童は寺の修行僧を見守る存在であり、勤勉な者には穏やかに寄り添い、怠ける者にはその頭を差し出す。 「叩け」と促されるままに木魚を打つと、不思議なことに自らの煩悩が一つ抜け落ちたように感じるという。 しかし、あまりに多く打ち続けると、木魚童の身体は重く沈み込み、叩いた者の煩悩をすべて吸い取る代わりに、その者の心が空虚になってしまうと言われている。 また、木魚童のいる寺院では、夜になると誰もいない本堂から「ポク…ポク…」という木魚の音が聞こえてくることがある。 それは、僧たちの代わりに木魚童が自らの頭を叩き、寺に漂う煩悩を鎮めようとしているのかもしれない…。 #妖怪 #yokai #sumie #monster #ghost | G8: 45694 | H8: 45699 | I8: ○ | J8: 45714 | K8: さよならプラスティックワールド | L8: =len(E8) -> 430 | N8: =mid(F8,1,find("【特質】",F8)-1) &char(10)&memo!$B$2 -> 【名】木魚童（もくぎょどう）mokugyodo 【番】0006 【出現】古い寺院、廃寺、荒れ果てた僧坊 #妖怪 #お化け #怪物 #オリジナル妖怪 #monster #ghost #妖怪好き #浮世絵 #百鬼夜行 | O8: =len(N8) -> 107 | P8: かつて念仏僧たちが叩き続けた木魚が、人々の想いと煩悩を吸い込み、妖怪と化した姿。 その頭はまるで本物の木魚のように丸く彫られた木製の形をしており、体は童のように小さく、僧衣をまとっている。 | Q8: =len(P8) -> 95 | R8: 昼間はただの木魚のように佇んでいるが、夜になると動き出し、静かに念仏を唱えながら寺の中を歩き回る。 木魚童は寺の修行僧を見守る存在であり、勤勉な者には穏やかに寄り添い、怠ける者にはその頭を差し出す。 | S8: =len(R8) -> 101 | T8: =len(W8) -> 124 | U8: また、木魚童のいる寺院では、夜になると誰もいない本堂から「ポク…ポク…」という木魚の音が聞こえてくることがある。 それは、僧たちの代わりに木魚童が自らの頭を叩き、寺に漂う煩悩を鎮めようとしているのかもしれない…。 | V8: =len(U8) -> 106 | W8: 「叩け」と促されるままに木魚を打つと、不思議なことに自らの煩悩が一つ抜け落ちたように感じるという。 しかし、あまりに多く打ち続けると、木魚童の身体は重く沈み込み、叩いた者の煩悩をすべて吸い取る代わりに、その者の心が空虚になってしまうと言われている。 | Y8: =len(X8) -> 0 | AA8: =len(Z8) -> 0 | AC8: =len(AB8) -> 0
A9: 7 | B9: 鞍憑（くらつき） | C9: kuratsuki | D9: 古い馬宿、廃れた街道、戦場跡 | E9: かつて名のある武士や馬乗りが使っていた鞍が、持ち主を失い、長年放置された末に妖怪化したもの。 明治後期から昭和初期にかけてはサドルおばけとも呼ばれる。 一見、古びた鞍に見えるが、夜になると音もなく宙を漂い、かつての主を求めて彷徨う。 人が近づくと鞍の底から黒い霧のような手が伸び、無理やり背に乗せようとする。 乗ってしまった者は鞍に縛りつけられ、馬もないのに走り続けなければならない。 伝説によれば、鞍憑に取り憑かれた者は次第に体力を奪われ、やがて魂を乗っ取られてしまうという。 唯一の対処法は、かつての持ち主の名を唱え、敬意を示すこと。 その名を聞くと、鞍憑はしばし動きを止めるが、完全に消え去ることはない。 特に戦場跡や旧街道に現れることが多く、夜道を行く者は決して捨てられた鞍を背負わぬよう注意せねばならない…。 | F9: ="【名】" & B9 & C9 &char(10) & "【番】" & text(A9,"0000") & char(10) &"【出現】"&D9& char(10)&"【特質】"& char(10)&E9&char(10)&char(10)&memo!$B$1 -> 【名】鞍憑（くらつき）kuratsuki 【番】0007 【出現】古い馬宿、廃れた街道、戦場跡 【特質】 かつて名のある武士や馬乗りが使っていた鞍が、持ち主を失い、長年放置された末に妖怪化したもの。 明治後期から昭和初期にかけてはサドルおばけとも呼ばれる。 一見、古びた鞍に見えるが、夜になると音もなく宙を漂い、かつての主を求めて彷徨う。 人が近づくと鞍の底から黒い霧のような手が伸び、無理やり背に乗せようとする。 乗ってしまった者は鞍に縛りつけられ、馬もないのに走り続けなければならない。 伝説によれば、鞍憑に取り憑かれた者は次第に体力を奪われ、やがて魂を乗っ取られてしまうという。 唯一の対処法は、かつての持ち主の名を唱え、敬意を示すこと。 その名を聞くと、鞍憑はしばし動きを止めるが、完全に消え去ることはない。 特に戦場跡や旧街道に現れることが多く、夜道を行く者は決して捨てられた鞍を背負わぬよう注意せねばならない…。 #妖怪 #yokai #sumie #monster #ghost | G9: 45694 | H9: 45700 | I9: ○ | J9: 45717 | K9: 電造人間 | L9: =len(E9) -> 362 | N9: =mid(F9,1,find("【特質】",F9)-1) &char(10)&memo!$B$2 -> 【名】鞍憑（くらつき）kuratsuki 【番】0007 【出現】古い馬宿、廃れた街道、戦場跡 #妖怪 #お化け #怪物 #オリジナル妖怪 #monster #ghost #妖怪好き #浮世絵 #百鬼夜行 | O9: =len(N9) -> 103 | P9: かつて名のある武士や馬乗りが使っていた鞍が、持ち主を失い、長年放置された末に妖怪化したもの。 明治後期から昭和初期にかけてはサドルおばけとも呼ばれる。 一見、古びた鞍に見えるが、夜になると音もなく宙を漂い、かつての主を求めて彷徨う。 | Q9: =len(P9) -> 117 | R9: 人が近づくと鞍の底から黒い霧のような手が伸び、無理やり背に乗せようとする。 乗ってしまった者は鞍に縛りつけられ、馬もないのに走り続けなければならない。 伝説によれば、鞍憑に取り憑かれた者は次第に体力を奪われ、やがて魂を乗っ取られてしまうという。 | S9: =len(R9) -> 124 | T9: =len(W9) -> 119 | V9: =len(U9) -> 0 | W9: 唯一の対処法は、かつての持ち主の名を唱え、敬意を示すこと。 その名を聞くと、鞍憑はしばし動きを止めるが、完全に消え去ることはない。 特に戦場跡や旧街道に現れることが多く、夜道を行く者は決して捨てられた鞍を背負わぬよう注意せねばならない…。 | Y9: =len(X9) -> 0 | AA9: =len(Z9) -> 0 | AC9: =len(AB9) -> 0
A10: 8 | B10: 卵童（らんどう） | C10: rando | D10: 町の食料品店、家庭の台所 | E10: 普通の卵に紛れ込むことを得意とする妖怪。 昭和初期、紙の卵パックが使われるようになった頃から、人間の目を欺きやすくなったとされる。 見た目は完全に普通の卵だが、じっと見つめると他の卵とは微妙に違う顔つきが浮かび上がることがある。 調理されることを極端に嫌がり、割られそうになるとヒビの間からぎょろりとした目が覗き、時には小さく「やめろ…」とつぶやくこともある。最も厄介なのは、誤って茹でて食べてしまった場合である。 卵童を食べた者は、無性にプロレス漫画を描きたくなる。 しかも、突然インスピレーションが湧き、朝から晩まで筋骨隆々のレスラーたちが闘う姿を描き続けてしまう。 筆を止めることができず、気づけば何十冊ものネームが出来上がることもあるが、不思議なことに、その漫画は決して完成しない。 どれだけ描いても、最後の試合の決着だけはどうしても描けず、最終話のページが永遠に白紙のままになるという。 この現象は「卵童の呪い」と呼ばれ、昭和の漫画家たちの間では「卵はよく見て買え」と語り継がれたという。 しかし、現代でもこの妖怪が紛れ込んでいるかどうかは不明であり、もし最近、無性にプロレス漫画を描きたくなったのなら…あなたの朝食のゆで卵に、何かが潜んでいたのかもしれない。 | F10: ="【名】" & B10 & C10 &char(10) & "【番】" & text(A10,"0000") & char(10) &"【出現】"&D10& char(10)&"【特質】"& char(10)&E10&char(10)&char(10)&memo!$B$1 -> 【名】卵童（らんどう）rando 【番】0008 【出現】町の食料品店、家庭の台所 【特質】 普通の卵に紛れ込むことを得意とする妖怪。 昭和初期、紙の卵パックが使われるようになった頃から、人間の目を欺きやすくなったとされる。 見た目は完全に普通の卵だが、じっと見つめると他の卵とは微妙に違う顔つきが浮かび上がることがある。 調理されることを極端に嫌がり、割られそうになるとヒビの間からぎょろりとした目が覗き、時には小さく「やめろ…」とつぶやくこともある。最も厄介なのは、誤って茹でて食べてしまった場合である。 卵童を食べた者は、無性にプロレス漫画を描きたくなる。 しかも、突然インスピレーションが湧き、朝から晩まで筋骨隆々のレスラーたちが闘う姿を描き続けてしまう。 筆を止めることができず、気づけば何十冊ものネームが出来上がることもあるが、不思議なことに、その漫画は決して完成しない。 どれだけ描いても、最後の試合の決着だけはどうしても描けず、最終話のページが永遠に白紙のままになるという。 この現象は「卵童の呪い」と呼ばれ、昭和の漫画家たちの間では「卵はよく見て買え」と語り継がれたという。 しかし、現代でもこの妖怪が紛れ込んでいるかどうかは不明であり、もし最近、無性にプロレス漫画を描きたくなったのなら…あなたの朝食のゆで卵に、何かが潜んでいたのかもしれない。 #妖怪 #yokai #sumie #monster #ghost | G10: 45694 | H10: 45701 | I10: ○ | J10: 45721 | K10: FUSION | L10: =len(E10) -> 541 | N10: =mid(F10,1,find("【特質】",F10)-1) &char(10)&memo!$B$2 -> 【名】卵童（らんどう）rando 【番】0008 【出現】町の食料品店、家庭の台所 #妖怪 #お化け #怪物 #オリジナル妖怪 #monster #ghost #妖怪好き #浮世絵 #百鬼夜行 | O10: =len(N10) -> 97 | P10: 普通の卵に紛れ込むことを得意とする妖怪。 昭和初期、紙の卵パックが使われるようになった頃から、人間の目を欺きやすくなったとされる。 見た目は完全に普通の卵だが、じっと見つめると他の卵とは微妙に違う顔つきが浮かび上がることがある。 | Q10: =len(P10) -> 114 | R10: 調理されることを極端に嫌がり、割られそうになるとヒビの間からぎょろりとした目が覗き、時には小さく「やめろ…」とつぶやくこともある。最も厄介なのは、誤って茹でて食べてしまった場合である。 卵童を食べた者は、無性にプロレス漫画を描きたくなる。 | S10: =len(R10) -> 121 | T10: =len(W10) -> 110 | U10: どれだけ描いても、最後の試合の決着だけはどうしても描けず、最終話のページが永遠に白紙のままになるという。 この現象は「卵童の呪い」と呼ばれ、昭和の漫画家たちの間では「卵はよく見て買え」と語り継がれたという。 | V10: =len(U10) -> 105 | W10: しかも、突然インスピレーションが湧き、朝から晩まで筋骨隆々のレスラーたちが闘う姿を描き続けてしまう。 筆を止めることができず、気づけば何十冊ものネームが出来上がることもあるが、不思議なことに、その漫画は決して完成しない。 | X10: しかし、現代でもこの妖怪が紛れ込んでいるかどうかは不明であり、もし最近、無性にプロレス漫画を描きたくなったのなら…あなたの朝食のゆで卵に、何かが潜んでいたのかもしれない。 | Y10: =len(X10) -> 86 | AA10: =len(Z10) -> 0 | AC10: =len(AB10) -> 0
A11: 9 | B11: 沈架響橋（ちんかきょうきょう） | C11: chinkakyokyo | D11: 人里離れた川辺、寂れた渡し場 | E11: 昔の桟橋の化身とも言われる妖怪。 全身を伸ばして川をまたぎ、人が安全に渡れるように橋となる。 しかし、ただの橋ではなく、特定の者にのみ反応を示すという。 絶世の美女が渡ると、沈架響橋の体はたちまち波打ち、興奮するかのように大きくうねり始める。 渡る者にとっては危険極まりないが、それはすなわち沈架響橋に認められた証であり、誉れでもあるとされる。 その昔、幾多の名だたる美女が試しに渡り、沈架響橋のたわむ姿を見て己の美しさを誇ったという。 しかし、ある日、ある高飛車な娘が 「私が渡れば当然波打つだろう」と意気揚々と橋を踏みしめたが、沈架響橋は微動だにしなかった。 それどころか、まるで石のように冷え切り、静まり返っていたという。 羞恥に震えた娘は誰にもそのことを言わぬまま、橋を渡りきったが、それ以降の消息は知れない。 沈架響橋が何を基準に「反応する者」と「しない者」を選んでいるのかは誰にもわからない。 外見の美だけではなく、内面を見透かしているのではないかとも噂されている。 今もどこかの川辺で、夜ごと橋となり、渡る者を試しているのかもしれない。 | F11: ="【名】" & B11 & C11 &char(10) & "【番】" & text(A11,"0000") & char(10) &"【出現】"&D11& char(10)&"【特質】"& char(10)&E11&char(10)&char(10)&memo!$B$1 -> 【名】沈架響橋（ちんかきょうきょう）chinkakyokyo 【番】0009 【出現】人里離れた川辺、寂れた渡し場 【特質】 昔の桟橋の化身とも言われる妖怪。 全身を伸ばして川をまたぎ、人が安全に渡れるように橋となる。 しかし、ただの橋ではなく、特定の者にのみ反応を示すという。 絶世の美女が渡ると、沈架響橋の体はたちまち波打ち、興奮するかのように大きくうねり始める。 渡る者にとっては危険極まりないが、それはすなわち沈架響橋に認められた証であり、誉れでもあるとされる。 その昔、幾多の名だたる美女が試しに渡り、沈架響橋のたわむ姿を見て己の美しさを誇ったという。 しかし、ある日、ある高飛車な娘が 「私が渡れば当然波打つだろう」と意気揚々と橋を踏みしめたが、沈架響橋は微動だにしなかった。 それどころか、まるで石のように冷え切り、静まり返っていたという。 羞恥に震えた娘は誰にもそのことを言わぬまま、橋を渡りきったが、それ以降の消息は知れない。 沈架響橋が何を基準に「反応する者」と「しない者」を選んでいるのかは誰にもわからない。 外見の美だけではなく、内面を見透かしているのではないかとも噂されている。 今もどこかの川辺で、夜ごと橋となり、渡る者を試しているのかもしれない。 #妖怪 #yokai #sumie #monster #ghost | G11: 45694 | H11: 45702 | I11: ○ | J11: - | L11: =len(E11) -> 478 | N11: =mid(F11,1,find("【特質】",F11)-1) &char(10)&memo!$B$2 -> 【名】沈架響橋（ちんかきょうきょう）chinkakyokyo 【番】0009 【出現】人里離れた川辺、寂れた渡し場 #妖怪 #お化け #怪物 #オリジナル妖怪 #monster #ghost #妖怪好き #浮世絵 #百鬼夜行 | O11: =len(N11) -> 113 | P11: 昔の桟橋の化身とも言われる妖怪。 全身を伸ばして川をまたぎ、人が安全に渡れるように橋となる。 しかし、ただの橋ではなく、特定の者にのみ反応を示すという。 絶世の美女が渡ると、沈架響橋の体はたちまち波打ち、興奮するかのように大きくうねり始める。 | Q11: =len(P11) -> 123 | R11: 渡る者にとっては危険極まりないが、それはすなわち沈架響橋に認められた証であり、誉れでもあるとされる。 その昔、幾多の名だたる美女が試しに渡り、沈架響橋のたわむ姿を見て己の美しさを誇ったという。 | S11: =len(R11) -> 96 | T11: =len(W11) -> 140 | U11: 沈架響橋が何を基準に「反応する者」と「しない者」を選んでいるのかは誰にもわからない。 外見の美だけではなく、内面を見透かしているのではないかとも噂されている。 今もどこかの川辺で、夜ごと橋となり、渡る者を試しているのかもしれない。 | V11: =len(U11) -> 115 | W11: しかし、ある日、ある高飛車な娘が 「私が渡れば当然波打つだろう」と意気揚々と橋を踏みしめたが、沈架響橋は微動だにしなかった。 それどころか、まるで石のように冷え切り、静まり返っていたという。 羞恥に震えた娘は誰にもそのことを言わぬまま、橋を渡りきったが、それ以降の消息は知れない。 | Y11: =len(X11) -> 0 | AA11: =len(Z11) -> 0 | AC11: =len(AB11) -> 0
A12: 10 | B12: 氷砲凍鵺（ひょうほういてぬえ） | C12: hyohoitenue | D12: 極寒の海岸、流氷の上、密漁者が跋扈する漁場 | E12: 氷砲凍鵺は、かつて密漁者によって仲間たちが無残に乱獲されたことに怒り、怨念と復讐心から誕生した妖怪である。 純白のペンギンの姿をしているが、その腹部から長く鋭い銃口が生え、妖しげな霧を纏っている。 この妖怪の最大の特徴は、その弾丸。 密漁者に命を奪われたセイウチの巨大な前歯を拾い集め、霊的な力を込めてライフルへ装填する。 放たれた牙は空を裂き、氷の槍のごとく標的を貫く。 撃たれた者は凍りつき、やがて氷の塊と化して大海へ沈んでいくと伝えられる。 密漁者の間では、吹雪の中で「視線を感じたらもう遅い」と恐れられており、ある者は視界の端に白い影を捉えた瞬間に命を奪われたという。 標的が海に還るたび、氷砲凍鵺は低く鳴き、凍てつく海風にその声が響くのだ。 密漁を行わない者には害を及ぼさず、むしろ遭難した者や正当な漁師には道を示すとも言われている。 しかし、それも全ては「復讐が果たされるまでの間」なのかもしれない。 | F12: ="【名】" & B12 & C12 &char(10) & "【番】" & text(A12,"0000") & char(10) &"【出現】"&D12& char(10)&"【特質】"& char(10)&E12&char(10)&char(10)&memo!$B$1 -> 【名】氷砲凍鵺（ひょうほういてぬえ）hyohoitenue 【番】0010 【出現】極寒の海岸、流氷の上、密漁者が跋扈する漁場 【特質】 氷砲凍鵺は、かつて密漁者によって仲間たちが無残に乱獲されたことに怒り、怨念と復讐心から誕生した妖怪である。 純白のペンギンの姿をしているが、その腹部から長く鋭い銃口が生え、妖しげな霧を纏っている。 この妖怪の最大の特徴は、その弾丸。 密漁者に命を奪われたセイウチの巨大な前歯を拾い集め、霊的な力を込めてライフルへ装填する。 放たれた牙は空を裂き、氷の槍のごとく標的を貫く。 撃たれた者は凍りつき、やがて氷の塊と化して大海へ沈んでいくと伝えられる。 密漁者の間では、吹雪の中で「視線を感じたらもう遅い」と恐れられており、ある者は視界の端に白い影を捉えた瞬間に命を奪われたという。 標的が海に還るたび、氷砲凍鵺は低く鳴き、凍てつく海風にその声が響くのだ。 密漁を行わない者には害を及ぼさず、むしろ遭難した者や正当な漁師には道を示すとも言われている。 しかし、それも全ては「復讐が果たされるまでの間」なのかもしれない。 #妖怪 #yokai #sumie #monster #ghost | G12: 45694 | H12: 45703 | I12: ○ | J12: 45724 | K12: MOON | L12: =len(E12) -> 409 | N12: =mid(F12,1,find("【特質】",F12)-1) &char(10)&memo!$B$2 -> 【名】氷砲凍鵺（ひょうほういてぬえ）hyohoitenue 【番】0010 【出現】極寒の海岸、流氷の上、密漁者が跋扈する漁場 #妖怪 #お化け #怪物 #オリジナル妖怪 #monster #ghost #妖怪好き #浮世絵 #百鬼夜行 | O12: =len(N12) -> 119 | P12: 【特質】氷砲凍鵺は、かつて密漁者によって仲間たちが無残に乱獲されたことに怒り、怨念と復讐心から誕生した妖怪である。 純白のペンギンの姿をしているが、その腹部から長く鋭い銃口が生え、妖しげな霧を纏っている。 この妖怪の最大の特徴は、その弾丸。 | Q12: =len(P12) -> 120 | R12: 密漁者に命を奪われたセイウチの巨大な前歯を拾い集め、霊的な力を込めてライフルへ装填する。 放たれた牙は空を裂き、氷の槍のごとく標的を貫く。 撃たれた者は凍りつき、やがて氷の塊と化して大海へ沈んでいくと伝えられる。 | S12: =len(R12) -> 106 | T12: =len(W12) -> 101 | U12: 密漁を行わない者には害を及ぼさず、むしろ遭難した者や正当な漁師には道を示すとも言われている。 しかし、それも全ては「復讐が果たされるまでの間」なのかもしれない。 | V12: =len(U12) -> 80 | W12: 密漁者の間では、吹雪の中で「視線を感じたらもう遅い」と恐れられており、ある者は視界の端に白い影を捉えた瞬間に命を奪われたという。 標的が海に還るたび、氷砲凍鵺は低く鳴き、凍てつく海風にその声が響くのだ。 | Y12: =len(X12) -> 0 | AA12: =len(Z12) -> 0 | AC12: =len(AB12) -> 0
A13: 11 | B13: 髪哭婆（かみなきば） | C13: kaminakiba | D13: 人里離れた山間の村、寂れた古寺の近く、あるいは廃れた婚礼場跡 | E13: 推定700歳の妖怪であり、かつては人間の女性だったという。 愛する夫と幸せに生き、彼を最期まで看取った後、「次もこの幸せを享受したい」と強く願ったことが妖力を生み、妖怪へと変化した。 彼女の外見は、痩せ細った老婆の姿だが、髪は黒々と豊かで異様に長く、頭上で大きなハート型に結われている。 この髪は自在に動き、時に触手のように伸びて若者を捕らえる。 髪哭婆は「次の夫」を探しており、若人を見つけると優しく微笑みながら攫い、自らの住処へ連れ帰る。 そして、手厚くもてなし、愛情深く世話をする。 食事は豪華で、寝床もふかふか。 しかし、一つだけ絶対にこなさねばならない「試練」がある。 試練とは「ハートの輪くぐり」である。 毎晩、若人は髪哭婆が作った巨大なハート型の輪をくぐらなければならない。 一見、簡単そうに思えるが、この輪は意思を持ち、サイズを変えたり、動き回ったり、突然閉じたりするため、決して容易ではない。 若人が失敗すれば、髪哭婆はしばらく悲しみ、やがて新たな「幸せの相手」を探しに行く。 この試練を長く耐え抜いた者もいるが、多くの若人は「毎晩これを続けるのは無理だ」と悟り、最終的に逃げ出そうとする。 だが、髪哭婆は意外にも追いかけてはこない。 「愛に飽きたのね…仕方ないわねぇ…」と寂しげに微笑み、そっと見送るという。 ただし、逃げ出してから数日経ったあとの若人は、日常に退屈し始める。何もやる気が出ない。 無気力となり、果ては自ら命を絶つものが続出したという。 最近の若人が写真を撮るときにハートマークを作るのは、髪哭婆への哀悼を示す追憶のポーズなのかもしれない。 | F13: ="【名】" & B13 & C13 &char(10) & "【番】" & text(A13,"0000") & char(10) &"【出現】"&D13& char(10)&"【特質】"& char(10)&E13&char(10)&char(10)&memo!$B$1 -> 【名】髪哭婆（かみなきば）kaminakiba 【番】0011 【出現】人里離れた山間の村、寂れた古寺の近く、あるいは廃れた婚礼場跡 【特質】 推定700歳の妖怪であり、かつては人間の女性だったという。 愛する夫と幸せに生き、彼を最期まで看取った後、「次もこの幸せを享受したい」と強く願ったことが妖力を生み、妖怪へと変化した。 彼女の外見は、痩せ細った老婆の姿だが、髪は黒々と豊かで異様に長く、頭上で大きなハート型に結われている。 この髪は自在に動き、時に触手のように伸びて若者を捕らえる。 髪哭婆は「次の夫」を探しており、若人を見つけると優しく微笑みながら攫い、自らの住処へ連れ帰る。 そして、手厚くもてなし、愛情深く世話をする。 食事は豪華で、寝床もふかふか。 しかし、一つだけ絶対にこなさねばならない「試練」がある。 試練とは「ハートの輪くぐり」である。 毎晩、若人は髪哭婆が作った巨大なハート型の輪をくぐらなければならない。 一見、簡単そうに思えるが、この輪は意思を持ち、サイズを変えたり、動き回ったり、突然閉じたりするため、決して容易ではない。 若人が失敗すれば、髪哭婆はしばらく悲しみ、やがて新たな「幸せの相手」を探しに行く。 この試練を長く耐え抜いた者もいるが、多くの若人は「毎晩これを続けるのは無理だ」と悟り、最終的に逃げ出そうとする。 だが、髪哭婆は意外にも追いかけてはこない。 「愛に飽きたのね…仕方ないわねぇ…」と寂しげに微笑み、そっと見送るという。 ただし、逃げ出してから数日経ったあとの若人は、日常に退屈し始める。何もやる気が出ない。 無気力となり、果ては自ら命を絶つものが続出したという。 最近の若人が写真を撮るときにハートマークを作るのは、髪哭婆への哀悼を示す追憶のポーズなのかもしれない。 #妖怪 #yokai #sumie #monster #ghost | G13: 45694 | H13: 45704 | I13: ○ | J13: 45728 | K13: I still love U | L13: =len(E13) -> 695 | N13: =mid(F13,1,find("【特質】",F13)-1) &char(10)&memo!$B$2 -> 【名】髪哭婆（かみなきば）kaminakiba 【番】0011 【出現】人里離れた山間の村、寂れた古寺の近く、あるいは廃れた婚礼場跡 #妖怪 #お化け #怪物 #オリジナル妖怪 #monster #ghost #妖怪好き #浮世絵 #百鬼夜行 | O13: =len(N13) -> 122 | P13: 【特質】推定700歳の妖怪であり、かつては人間の女性だったという。 愛する夫と幸せに生き、彼を最期まで看取った後、「次もこの幸せを享受したい」と強く願ったことが妖力を生み、妖怪へと変化した。 | Q13: =len(P13) -> 95 | R13: 彼女の外見は、痩せ細った老婆の姿だが、髪は黒々と豊かで異様に長く、頭上で大きなハート型に結われている。 この髪は自在に動き、時に触手のように伸びて若者を捕らえる。 髪哭婆は「次の夫」を探しており、若人を見つけると優しく微笑みながら攫い、自らの住処へ連れ帰る。 | S13: =len(R13) -> 130 | T13: =len(W13) -> 123 | U13: 一見、簡単そうに思えるが、この輪は意思を持ち、サイズを変えたり、動き回ったり、突然閉じたりするため、決して容易ではない。 若人が失敗すれば、髪哭婆はしばらく悲しみ、やがて新たな「幸せの相手」を探しに行く。 | V13: =len(U13) -> 102 | W13: そして、手厚くもてなし、愛情深く世話をする。 食事は豪華で、寝床もふかふか。 しかし、一つだけ絶対にこなさねばならない「試練」がある。 試練とは「ハートの輪くぐり」である。 毎晩、若人は髪哭婆が作った巨大なハート型の輪をくぐらなければならない。 | X13: この試練を長く耐え抜いた者もいるが、多くの若人は「毎晩これを続けるのは無理だ」と悟り、最終的に逃げ出そうとする。 だが、髪哭婆は意外にも追いかけてはこない。 「愛に飽きたのね…仕方ないわねぇ…」と寂しげに微笑み、そっと見送るという。 | Y13: =len(X13) -> 117 | Z13: ただし、逃げ出してから数日経ったあとの若人は、日常に退屈し始める。何もやる気が出ない。 無気力となり、果ては自ら命を絶つものが続出したという。 最近の若人が写真を撮るときにハートマークを作るのは、髪哭婆への哀悼を示す追憶のポーズなのかもしれない。 | AA13: =len(Z13) -> 124 | AC13: =len(AB13) -> 0
A14: 12 | B14: 餡幽鬼（あんゆうき） | C14: anyuki | D14: 田舎の古い民家、仏壇のある座敷、秋の彼岸の夜 | E14: その昔、一匹の忠犬がおはぎへの強い恨みを抱いたまま妖怪と化した存在。 主人がおはぎを喉に詰まらせて亡くなった際、「これが主人を殺した」と思い込み、怨念を募らせた。 その思いが昇華されず、「餡幽鬼」となった。 その姿は、かすれた墨のように揺らめく犬の影。 おはぎを憎み、供え物を吹き飛ばしたり、甘い香りをかき消そうとする。 しかし、誰かが幸せそうにおはぎを食べる姿を見ると、心が揺れる。 特に、ある老人が嬉しそうに頬張る様子を見た時、「おはぎに罪はないのかもしれない」と葛藤するが、完全には恨みを捨てきれない。 ある村では、おはぎを供える際に犬用の供え物も一緒に置く習慣がある。 それは、迷える餡幽鬼が少しでも安らげるようにとの願いから始まったという。 | F14: ="【名】" & B14 & C14 &char(10) & "【番】" & text(A14,"0000") & char(10) &"【出現】"&D14& char(10)&"【特質】"& char(10)&E14&char(10)&char(10)&memo!$B$1 -> 【名】餡幽鬼（あんゆうき）anyuki 【番】0012 【出現】田舎の古い民家、仏壇のある座敷、秋の彼岸の夜 【特質】 その昔、一匹の忠犬がおはぎへの強い恨みを抱いたまま妖怪と化した存在。 主人がおはぎを喉に詰まらせて亡くなった際、「これが主人を殺した」と思い込み、怨念を募らせた。 その思いが昇華されず、「餡幽鬼」となった。 その姿は、かすれた墨のように揺らめく犬の影。 おはぎを憎み、供え物を吹き飛ばしたり、甘い香りをかき消そうとする。 しかし、誰かが幸せそうにおはぎを食べる姿を見ると、心が揺れる。 特に、ある老人が嬉しそうに頬張る様子を見た時、「おはぎに罪はないのかもしれない」と葛藤するが、完全には恨みを捨てきれない。 ある村では、おはぎを供える際に犬用の供え物も一緒に置く習慣がある。 それは、迷える餡幽鬼が少しでも安らげるようにとの願いから始まったという。 #妖怪 #yokai #sumie #monster #ghost | G14: 45694 | H14: 45705 | I14: ○ | J14: - | L14: =len(E14) -> 327 | N14: =mid(F14,1,find("【特質】",F14)-1) &char(10)&memo!$B$2 -> 【名】餡幽鬼（あんゆうき）anyuki 【番】0012 【出現】田舎の古い民家、仏壇のある座敷、秋の彼岸の夜 #妖怪 #お化け #怪物 #オリジナル妖怪 #monster #ghost #妖怪好き #浮世絵 #百鬼夜行 | O14: =len(N14) -> 110 | P14: 【特質】その昔、一匹の忠犬がおはぎへの強い恨みを抱いたまま妖怪と化した存在。 主人がおはぎを喉に詰まらせて亡くなった際、「これが主人を殺した」と思い込み、怨念を募らせた。 その思いが昇華されず、「餡幽鬼」となった。 | Q14: =len(P14) -> 107 | R14: その姿は、かすれた墨のように揺らめく犬の影。 おはぎを憎み、供え物を吹き飛ばしたり、甘い香りをかき消そうとする。 しかし、誰かが幸せそうにおはぎを食べる姿を見ると、心が揺れる。 | S14: =len(R14) -> 88 | T14: =len(W14) -> 133 | V14: =len(U14) -> 0 | W14: 特に、ある老人が嬉しそうに頬張る様子を見た時、「おはぎに罪はないのかもしれない」と葛藤するが、完全には恨みを捨てきれない。 ある村では、おはぎを供える際に犬用の供え物も一緒に置く習慣がある。 それは、迷える餡幽鬼が少しでも安らげるようにとの願いから始まったという。 | Y14: =len(X14) -> 0 | AA14: =len(Z14) -> 0 | AC14: =len(AB14) -> 0
A15: 13 | B15: 塵鬼囃（じんきばやし） | C15: jinkibayashi | D15: 子供の家や庭、学校の裏庭、神社の境内 | E15: その昔、東北のある地方では10歳で成人を迎えるとされていた。 塵鬼囃は人間が10歳の誕生日を迎えた夜、それまでについた嘘の数だけ現れ、人間の周りを取り囲む。 塵ほどに小さな妖怪たちはかすかな声でに「嘘ついたね」「ほんとうのことを話そうよ」と囁く。 しかし嘘の数が多いほど、声は大きく、くすくすと笑う音や祭囃子のような不気味な音が混ざることもあるという。 塵鬼囃は、子供が嘘をすべて認めれば、その夜のうちに消える。 だが、一つでも隠したままだと、最後にこう囁いて去る。 「また来年、お祝いに来るね。」 ただし、翌年の誕生日を迎えることは、決してなかったと言われている。 | F15: ="【名】" & B15 & C15 &char(10) & "【番】" & text(A15,"0000") & char(10) &"【出現】"&D15& char(10)&"【特質】"& char(10)&E15&char(10)&char(10)&memo!$B$1 -> 【名】塵鬼囃（じんきばやし）jinkibayashi 【番】0013 【出現】子供の家や庭、学校の裏庭、神社の境内 【特質】 その昔、東北のある地方では10歳で成人を迎えるとされていた。 塵鬼囃は人間が10歳の誕生日を迎えた夜、それまでについた嘘の数だけ現れ、人間の周りを取り囲む。 塵ほどに小さな妖怪たちはかすかな声でに「嘘ついたね」「ほんとうのことを話そうよ」と囁く。 しかし嘘の数が多いほど、声は大きく、くすくすと笑う音や祭囃子のような不気味な音が混ざることもあるという。 塵鬼囃は、子供が嘘をすべて認めれば、その夜のうちに消える。 だが、一つでも隠したままだと、最後にこう囁いて去る。 「また来年、お祝いに来るね。」 ただし、翌年の誕生日を迎えることは、決してなかったと言われている。 #妖怪 #yokai #sumie #monster #ghost | G15: 45694 | H15: 45706 | I15: ○ | J15: 45732 | K15: だいじょばない | L15: =len(E15) -> 287 | N15: =mid(F15,1,find("【特質】",F15)-1) &char(10)&memo!$B$2 -> 【名】塵鬼囃（じんきばやし）jinkibayashi 【番】0013 【出現】子供の家や庭、学校の裏庭、神社の境内 #妖怪 #お化け #怪物 #オリジナル妖怪 #monster #ghost #妖怪好き #浮世絵 #百鬼夜行 | O15: =len(N15) -> 113 | P15: 【特質】その昔、東北のある地方では10歳で成人を迎えるとされていた。 塵鬼囃は人間が10歳の誕生日を迎えた夜、それまでについた嘘の数だけ現れ、人間の周りを取り囲む。 塵ほどに小さな妖怪たちはかすかな声でに「嘘ついたね」「ほんとうのことを話そうよ」と囁く。 | Q15: =len(P15) -> 128 | R15: しかし嘘の数が多いほど、声は大きく、くすくすと笑う音や祭囃子のような不気味な音が混ざることもあるという。 塵鬼囃は、子供が嘘をすべて認めれば、その夜のうちに消える。 だが、一つでも隠したままだと、最後にこう囁いて去る。 「また来年、お祝いに来るね。」 | S15: =len(R15) -> 127 | T15: =len(W15) -> 33 | V15: =len(U15) -> 0 | W15: ただし、翌年の誕生日を迎えることは、決してなかったと言われている。 | Y15: =len(X15) -> 0 | AA15: =len(Z15) -> 0 | AC15: =len(AB15) -> 0
A16: 14 | B16: 天衝夜叉（てんつくやしゃ） | C16: tentsukuyasha | D16: 合戦の跡地 | E16: かつて戦国時代の戦場にて、討ち死にした若き武者の怨念が妖怪と化した。 天を突くような逆立つ髪は、彼の未練と気概の象徴。 意志を持つその髪は戦場で斬られた者たちの魂を飲み込み、強大な妖力を宿すようになった。 天衝夜叉に憑かれた者は、髪が勝手に伸び、うねり、まるで生き物のように動き出す。 最初は驚き戸惑うが、やがてその妖気に慣れると、己の力の象徴として誇るようになる。 その結果、天衝夜叉に憑かれた者は「髪を天に向かって伸ばす」ことを運命づけられ、これが後のリーゼント文化の起源とされている。 天衝夜叉の影響を受けた者は、言葉にも独特の変化が生じる。 天衝夜叉の妖気は、魂を揺さぶり、己の意志を誇張して表現させる力を持つ。 特に言葉を強調し、迫力を増す傾向があり、「よろしく」が「夜露死苦」と変化したのも、天衝夜叉の影響とされる。 一説によれば、ある武士がこの妖怪に取り憑かれた際、自らの誓いを「夜露（夜の露に濡れても）」「死（死を恐れず）」「苦（苦難を乗り越え）」という漢字に込め、血で書き記したことが始まりとされる。 その言葉は代々伝わり、やがて現代のヤンキー文化にも受け継がれていったのだという。 天衝夜叉の存在は今も語り継がれ、リーゼントの者たちの間では 「奴を恐れるな。魂を燃やせば、夜叉も味方する」と信じられている。 鏡に映るリーゼントが微かに動いたら、それは天衝夜叉が見守っている証拠だとも言われる。 | F16: ="【名】" & B16 & C16 &char(10) & "【番】" & text(A16,"0000") & char(10) &"【出現】"&D16& char(10)&"【特質】"& char(10)&E16&char(10)&char(10)&memo!$B$1 -> 【名】天衝夜叉（てんつくやしゃ）tentsukuyasha 【番】0014 【出現】合戦の跡地 【特質】 かつて戦国時代の戦場にて、討ち死にした若き武者の怨念が妖怪と化した。 天を突くような逆立つ髪は、彼の未練と気概の象徴。 意志を持つその髪は戦場で斬られた者たちの魂を飲み込み、強大な妖力を宿すようになった。 天衝夜叉に憑かれた者は、髪が勝手に伸び、うねり、まるで生き物のように動き出す。 最初は驚き戸惑うが、やがてその妖気に慣れると、己の力の象徴として誇るようになる。 その結果、天衝夜叉に憑かれた者は「髪を天に向かって伸ばす」ことを運命づけられ、これが後のリーゼント文化の起源とされている。 天衝夜叉の影響を受けた者は、言葉にも独特の変化が生じる。 天衝夜叉の妖気は、魂を揺さぶり、己の意志を誇張して表現させる力を持つ。 特に言葉を強調し、迫力を増す傾向があり、「よろしく」が「夜露死苦」と変化したのも、天衝夜叉の影響とされる。 一説によれば、ある武士がこの妖怪に取り憑かれた際、自らの誓いを「夜露（夜の露に濡れても）」「死（死を恐れず）」「苦（苦難を乗り越え）」という漢字に込め、血で書き記したことが始まりとされる。 その言葉は代々伝わり、やがて現代のヤンキー文化にも受け継がれていったのだという。 天衝夜叉の存在は今も語り継がれ、リーゼントの者たちの間では 「奴を恐れるな。魂を燃やせば、夜叉も味方する」と信じられている。 鏡に映るリーゼントが微かに動いたら、それは天衝夜叉が見守っている証拠だとも言われる。 #妖怪 #yokai #sumie #monster #ghost | G16: 45695 | H16: 45707 | I16: ○ | J16: 45735 | K16: オリジナル | L16: =len(E16) -> 610 | N16: =mid(F16,1,find("【特質】",F16)-1) &char(10)&memo!$B$2 -> 【名】天衝夜叉（てんつくやしゃ）tentsukuyasha 【番】0014 【出現】合戦の跡地 #妖怪 #お化け #怪物 #オリジナル妖怪 #monster #ghost #妖怪好き #浮世絵 #百鬼夜行 | O16: =len(N16) -> 103 | P16: 【特質】かつて戦国時代の戦場にて、討ち死にした若き武者の怨念が妖怪と化した。 天を突くような逆立つ髪は、彼の未練と気概の象徴。 意志を持つその髪は戦場で斬られた者たちの魂を飲み込み、強大な妖力を宿すようになった。 | Q16: =len(P16) -> 106 | R16: 天衝夜叉に憑かれた者は、髪が勝手に伸び、うねり、まるで生き物のように動き出す。 最初は驚き戸惑うが、やがてその妖気に慣れると己の力の象徴として誇るようになる。 その結果、天衝夜叉に憑かれた者は「髪を天に向かって伸ばす」ことを運命づけられ、これが後のリーゼント文化の起源とされている | S16: =len(R16) -> 140 | T16: =len(W16) -> 118 | U16: 一説によれば、ある武士がこの妖怪に取り憑かれた際、自らの誓いを「夜露（夜の露に濡れても）」「死（死を恐れず）」「苦（苦難を乗り越え）」という漢字に込め、血で書き記したことが始まりとされる。 その言葉は代々伝わり、やがて現代のヤンキー文化にも受け継がれていったのだという。 | V16: =len(U16) -> 135 | W16: 天衝夜叉の影響を受けた者は、言葉にも独特の変化が生じる。 天衝夜叉の妖気は、魂を揺さぶり、己の意志を誇張して表現させる力を持つ。 特に言葉を強調し、迫力を増す傾向があり、「よろしく」が「夜露死苦」と変化したのも、天衝夜叉の影響とされる。 | X16: 天衝夜叉の存在は今も語り継がれ、リーゼントの者たちの間では 「奴を恐れるな。魂を燃やせば、夜叉も味方する」と信じられている。 鏡に映るリーゼントが微かに動いたら、それは天衝夜叉が見守っている証拠だとも言われる。 | Y16: =len(X16) -> 105 | AA16: =len(Z16) -> 0 | AC16: =len(AB16) -> 0
A17: 15 | B17: 白綿潜虫（はくめんせんちゅう） | C17: hakumensenchu | D17: 風の強い野原、戦時中の田舎町、夜の静かな路地裏 | E17: 白綿潜虫は、白い綿毛のように風に乗って漂う小さな妖怪で、気づかぬうちに人の耳や鼻から体内に入り込む。 通常は目に見えないほど小さいが、月明かりの下でかすかに光る姿が確認されることがある。 この妖怪に取り憑かれると、自分の意思とは関係なく、特に身近な家族や大切な人に対して悪口や不満を口にしてしまう。 特に子どもが狙われやすく、親や兄弟に対して思ってもいない冷たい言葉を口にすることが多いとされる。 戦時中の食糧難や不安な生活の中で、母親が必死に作ったご飯に「まずい」と言わせたり、家族の苦労を軽んじるような言葉を吐かせたりするため、「戦火の影をさらに濃くする妖怪」として古くから語られている。 戦時中、とある村の少年が母に向かって「おっかぁの飯はまずい！」と怒鳴った。 母は驚きと悲しみのあまり涙を流したが、少年はなぜそんな言葉を言ったのか自分でも分からなかった。 その夜、村の古老が「鼻をかんでごらん」と少年に助言すると、少年の鼻から白い綿毛のようなものがふわりと飛び出していった。 「あれが白綿潜虫さ。人の心に影を落とす厄介な妖怪じゃ。」 その後、少年は母に心から謝罪し、ようやく元の穏やかな関係に戻ったという。 以来、村では子どもが急に悪口を言い出したら「鼻をかめ！」と教える習慣が生まれたという。 そして、もうひとつの噂 近年になって、白綿潜虫の影響についてもう一つの奇妙な現象が報告されている。 それは、少年が「好きな子」に対して悪口を言ってしまうことがしばしば確認されているという事実だ。 「お前なんか嫌いだ！」 「その髪型、変だな！」 「お前がいると邪魔なんだよ！」 本当はまったくそんな気持ちではないのに、口が勝手に動いてしまう。 大人たちは「また白綿潜虫の仕業か」と首を振るが、妖怪が絡んでいると断言できるのだろうか？ それとも、ただ照れくさくて素直になれないだけなのだろうか…？ | F17: ="【名】" & B17 & C17 &char(10) & "【番】" & text(A17,"0000") & char(10) &"【出現】"&D17& char(10)&"【特質】"& char(10)&E17&char(10)&char(10)&memo!$B$1 -> 【名】白綿潜虫（はくめんせんちゅう）hakumensenchu 【番】0015 【出現】風の強い野原、戦時中の田舎町、夜の静かな路地裏 【特質】 白綿潜虫は、白い綿毛のように風に乗って漂う小さな妖怪で、気づかぬうちに人の耳や鼻から体内に入り込む。 通常は目に見えないほど小さいが、月明かりの下でかすかに光る姿が確認されることがある。 この妖怪に取り憑かれると、自分の意思とは関係なく、特に身近な家族や大切な人に対して悪口や不満を口にしてしまう。 特に子どもが狙われやすく、親や兄弟に対して思ってもいない冷たい言葉を口にすることが多いとされる。 戦時中の食糧難や不安な生活の中で、母親が必死に作ったご飯に「まずい」と言わせたり、家族の苦労を軽んじるような言葉を吐かせたりするため、「戦火の影をさらに濃くする妖怪」として古くから語られている。 戦時中、とある村の少年が母に向かって「おっかぁの飯はまずい！」と怒鳴った。 母は驚きと悲しみのあまり涙を流したが、少年はなぜそんな言葉を言ったのか自分でも分からなかった。 その夜、村の古老が「鼻をかんでごらん」と少年に助言すると、少年の鼻から白い綿毛のようなものがふわりと飛び出していった。 「あれが白綿潜虫さ。人の心に影を落とす厄介な妖怪じゃ。」 その後、少年は母に心から謝罪し、ようやく元の穏やかな関係に戻ったという。 以来、村では子どもが急に悪口を言い出したら「鼻をかめ！」と教える習慣が生まれたという。 そして、もうひとつの噂 近年になって、白綿潜虫の影響についてもう一つの奇妙な現象が報告されている。 それは、少年が「好きな子」に対して悪口を言ってしまうことがしばしば確認されているという事実だ。 「お前なんか嫌いだ！」 「その髪型、変だな！」 「お前がいると邪魔なんだよ！」 本当はまったくそんな気持ちではないのに、口が勝手に動いてしまう。 大人たちは「また白綿潜虫の仕業か」と首を振るが、妖怪が絡んでいると断言できるのだろうか？ それとも、ただ照れくさくて素直になれないだけなのだろうか…？ #妖怪 #yokai #sumie #monster #ghost | G17: 45695 | H17: 45708 | I17: ○ | L17: =len(E17) -> 808 | N17: =mid(F17,1,find("【特質】",F17)-1) &char(10)&memo!$B$2 -> 【名】白綿潜虫（はくめんせんちゅう）hakumensenchu 【番】0015 【出現】風の強い野原、戦時中の田舎町、夜の静かな路地裏 #妖怪 #お化け #怪物 #オリジナル妖怪 #monster #ghost #妖怪好き #浮世絵 #百鬼夜行 | O17: =len(N17) -> 123 | P17: 【特質】白綿潜虫は、白い綿毛のように風に乗って漂う小さな妖怪で、気づかぬうちに人の耳や鼻から体内に入り込む。 通常は目に見えないほど小さいが、月明かりの下でかすかに光る姿が確認されることがある。 この妖怪に取り憑かれると、自分の意思とは関係なく、 | Q17: =len(P17) -> 123 | R17: 特に身近な家族や大切な人に対して悪口や不満を口にしてしまう。 特に子どもが狙われやすく、親や兄弟に対して思ってもいない冷たい言葉を口にすることが多いとされる。 戦時中の食糧難や不安な生活の中で、母親が必死に作ったご飯に「まずい」と言わせたり、 | S17: =len(R17) -> 122 | T17: =len(W17) -> 140 | U17: その夜、村の古老が「鼻をかんでごらん」と少年に助言すると、少年の鼻から白い綿毛のようなものがふわりと飛び出していった。 「あれが白綿潜虫さ。人の心に影を落とす厄介な妖怪じゃ。」 その後、少年は母に心から謝罪し、ようやく元の穏やかな関係に戻ったという。 | V17: =len(U17) -> 128 | W17: 家族の苦労を軽んじるような言葉を吐かせたりするため「戦火の影をさらに濃くする妖怪」として古くから語られている。 戦時中、とある村の少年が母に向かって「おっかぁの飯はまずい！」と怒鳴った。 母は驚きと悲しみのあまり涙を流したが、少年はなぜそんな言葉を言ったのか自分でも分からなかった | X17: 以来、村では子どもが急に悪口を言い出したら「鼻をかめ！」と教える習慣が生まれたという。 そして、もうひとつの噂 近年になって、白綿潜虫の影響についてもう一つの奇妙な現象が報告されている。 | Y17: =len(X17) -> 94 | Z17: それは、少年が「好きな子」に対して悪口を言ってしまうことがしばしば確認されているという事実だ。 「お前なんか嫌いだ！」 「その髪型、変だな！」 「お前がいると邪魔なんだよ！」 本当はまったくそんな気持ちではないのに、口が勝手に動いてしまう。 | AA17: =len(Z17) -> 122 | AC17: =len(AB17) -> 0
A18: 16 | B18: 滴濁濁（てきだくだく） | C18: tekidakudaku | D18: 雨の多い街道や田舎の小道、特に水たまりが広がる場所 | E18: 滴濁濁は水たまりに潜む妖怪で、雨の日やその直後に人々を驚かせることを好む。 水と泥が混ざり合った流動的な体を持ち、大きな目と鋭い牙が特徴的だ。 馬車や車が水たまりを通るたびに、その水しぶきを操り、近くを歩く人々に正確に浴びせかける。 傘を差した者であっても容赦なく水を浴びせ、濡れるのを防ぐ術を笑うかのような振る舞いを見せる。 昔、滴濁濁が頻繁に現れる街道があった。 そこでは雨が降るたびに旅人や行商人たちが被害を受け、水たまりから跳ね上がる泥水で全身を濡らされてしまうことが日常茶飯事だった。 特に傘を差している者ほど狙われる傾向があり、人々は「滴濁濁の仕業だ」と恐れ、雨の日の外出を控えるようになった。 そんな中、一人の知恵者が「傘を使わず、全身を覆う防具を作れば滴濁濁に勝てるのではないか」と考えた。 そして、油を染み込ませた布を縫い合わせ、頭から足先まで覆う雨具を作り出した。 これが後に「雨合羽」と呼ばれるようになる装備だった。 実際に雨合羽を着て滴濁濁の現れる街道を歩いてみると、妖怪はその完全防備の姿に戸惑い、水しぶきを操るも、思うように効果を与えられなかったという。 その結果、雨合羽を着た旅人が増え、滴濁濁が現れる頻度も次第に減少していった。 滴濁濁の伝説は、人々に困難への対処法を考えさせるきっかけとなった象徴的なエピソードだと言われている。 予期せぬ事態に柔軟に対応する知恵と工夫が、日常の生活を快適にする道を切り開くという教訓を秘めている。 | F18: ="【名】" & B18 & C18 &char(10) & "【番】" & text(A18,"0000") & char(10) &"【出現】"&D18& char(10)&"【特質】"& char(10)&E18&char(10)&char(10)&memo!$B$1 -> 【名】滴濁濁（てきだくだく）tekidakudaku 【番】0016 【出現】雨の多い街道や田舎の小道、特に水たまりが広がる場所 【特質】 滴濁濁は水たまりに潜む妖怪で、雨の日やその直後に人々を驚かせることを好む。 水と泥が混ざり合った流動的な体を持ち、大きな目と鋭い牙が特徴的だ。 馬車や車が水たまりを通るたびに、その水しぶきを操り、近くを歩く人々に正確に浴びせかける。 傘を差した者であっても容赦なく水を浴びせ、濡れるのを防ぐ術を笑うかのような振る舞いを見せる。 昔、滴濁濁が頻繁に現れる街道があった。 そこでは雨が降るたびに旅人や行商人たちが被害を受け、水たまりから跳ね上がる泥水で全身を濡らされてしまうことが日常茶飯事だった。 特に傘を差している者ほど狙われる傾向があり、人々は「滴濁濁の仕業だ」と恐れ、雨の日の外出を控えるようになった。 そんな中、一人の知恵者が「傘を使わず、全身を覆う防具を作れば滴濁濁に勝てるのではないか」と考えた。 そして、油を染み込ませた布を縫い合わせ、頭から足先まで覆う雨具を作り出した。 これが後に「雨合羽」と呼ばれるようになる装備だった。 実際に雨合羽を着て滴濁濁の現れる街道を歩いてみると、妖怪はその完全防備の姿に戸惑い、水しぶきを操るも、思うように効果を与えられなかったという。 その結果、雨合羽を着た旅人が増え、滴濁濁が現れる頻度も次第に減少していった。 滴濁濁の伝説は、人々に困難への対処法を考えさせるきっかけとなった象徴的なエピソードだと言われている。 予期せぬ事態に柔軟に対応する知恵と工夫が、日常の生活を快適にする道を切り開くという教訓を秘めている。 #妖怪 #yokai #sumie #monster #ghost | G18: 45696 | H18: 45709 | I18: ○ | L18: =len(E18) -> 636 | N18: =mid(F18,1,find("【特質】",F18)-1) &char(10)&memo!$B$2 -> 【名】滴濁濁（てきだくだく）tekidakudaku 【番】0016 【出現】雨の多い街道や田舎の小道、特に水たまりが広がる場所 #妖怪 #お化け #怪物 #オリジナル妖怪 #monster #ghost #妖怪好き #浮世絵 #百鬼夜行 | O18: =len(N18) -> 120 | P18: 【特質】滴濁濁は水たまりに潜む妖怪で、雨の日やその直後に人々を驚かせることを好む。 水と泥が混ざり合った流動的な体を持ち、大きな目と鋭い牙が特徴的だ。 馬車や車が水たまりを通るたびに、その水しぶきを操り、近くを歩く人々に正確に浴びせかける。 | Q18: =len(P18) -> 120 | R18: 傘を差した者であっても容赦なく水を浴びせ、濡れるのを防ぐ術を笑うかのような振る舞いを見せる。 昔、滴濁濁が頻繁に現れる街道があった。 そこでは雨が降るたびに旅人や行商人たちが被害を受け、水たまりから跳ね上がる泥水で全身を濡らされてしまうことが日常茶飯事だった。 | S18: =len(R18) -> 131 | T18: =len(W18) -> 106 | U18: そして、油を染み込ませた布を縫い合わせ、頭から足先まで覆う雨具を作り出した。 これが後に「雨合羽」と呼ばれるようになる装備だった。 実際に雨合羽を着て滴濁濁の現れる街道を歩いてみると、妖怪はその完全防備の姿に戸惑い、水しぶきを操るも、思うように効果を与えられなかったという。 | V18: =len(U18) -> 138 | W18: 特に傘を差している者ほど狙われる傾向があり、人々は「滴濁濁の仕業だ」と恐れ、雨の日の外出を控えるようになった。 そんな中、一人の知恵者が「傘を使わず、全身を覆う防具を作れば滴濁濁に勝てるのではないか」と考えた。 | X18: その結果、雨合羽を着た旅人が増え、滴濁濁が現れる頻度も次第に減少していった。 滴濁濁の伝説は、人々に困難への対処法を考えさせるきっかけとなった象徴的なエピソードだと言われている。 予期せぬ事態に柔軟に対応する知恵と工夫が、日常の生活を快適にする道を切り開くという教訓を秘めている。 | Y18: =len(X18) -> 140 | AA18: =len(Z18) -> 0 | AC18: =len(AB18) -> 0
A19: 17 | B19: 削哭鬼（けずなき） | C19: kezunaki | D19: 廃れた寺子屋跡、古い学び舎、使われなくなった文房具店 | E19: 削哭鬼は、手回し式の鉛筆削りと融合した幽鬼であり、かつて学び舎に満ちていた知識と執念が形を成した妖怪とされる。 往時の削哭鬼は、鉛筆を差し込んだ者の知識を根こそぎ奪い取り、その学舎を崩壊させるほどの力を持っていた。 削られるごとに持ち主の記憶が霧散し、やがては何も知らぬ者となり果てた。 知識を奪われた者たちは筆を持つことすら忘れ、学びの場は荒廃していったという。 しかし時代が流れ、削哭鬼もまた衰えた。 今や知識を奪う力は薄れ、代わりに削りかすを果てしなく吐き出し続けるだけの存在となってしまった。 その削りかすは黒く滲んだ墨のようで、宙をさまよいながら消えたはずの古文や失われた記録を浮かび上がらせることがある。 そのため、一部の学者や陰陽師たちは、削哭鬼のもたらす削りかすを集め、隠された真実を暴こうとすることもあった。 だが、削哭鬼の嘆きを耳にしてはならない。 かつて奪われた知識への慟哭が、聞く者の記憶を削ぎ落とし、学ぶことの意味すら霞ませてしまうからである。 | F19: ="【名】" & B19 & C19 &char(10) & "【番】" & text(A19,"0000") & char(10) &"【出現】"&D19& char(10)&"【特質】"& char(10)&E19&char(10)&char(10)&memo!$B$1 -> 【名】削哭鬼（けずなき）kezunaki 【番】0017 【出現】廃れた寺子屋跡、古い学び舎、使われなくなった文房具店 【特質】 削哭鬼は、手回し式の鉛筆削りと融合した幽鬼であり、かつて学び舎に満ちていた知識と執念が形を成した妖怪とされる。 往時の削哭鬼は、鉛筆を差し込んだ者の知識を根こそぎ奪い取り、その学舎を崩壊させるほどの力を持っていた。 削られるごとに持ち主の記憶が霧散し、やがては何も知らぬ者となり果てた。 知識を奪われた者たちは筆を持つことすら忘れ、学びの場は荒廃していったという。 しかし時代が流れ、削哭鬼もまた衰えた。 今や知識を奪う力は薄れ、代わりに削りかすを果てしなく吐き出し続けるだけの存在となってしまった。 その削りかすは黒く滲んだ墨のようで、宙をさまよいながら消えたはずの古文や失われた記録を浮かび上がらせることがある。 そのため、一部の学者や陰陽師たちは、削哭鬼のもたらす削りかすを集め、隠された真実を暴こうとすることもあった。 だが、削哭鬼の嘆きを耳にしてはならない。 かつて奪われた知識への慟哭が、聞く者の記憶を削ぎ落とし、学ぶことの意味すら霞ませてしまうからである。 #妖怪 #yokai #sumie #monster #ghost | G19: 45696 | H19: 45710 | I19: ○ | L19: =len(E19) -> 437 | N19: =mid(F19,1,find("【特質】",F19)-1) &char(10)&memo!$B$2 -> 【名】削哭鬼（けずなき）kezunaki 【番】0017 【出現】廃れた寺子屋跡、古い学び舎、使われなくなった文房具店 #妖怪 #お化け #怪物 #オリジナル妖怪 #monster #ghost #妖怪好き #浮世絵 #百鬼夜行 | O19: =len(N19) -> 115 | P19: 【特質】削哭鬼は、手回し式の鉛筆削りと融合した幽鬼であり、かつて学び舎に満ちていた知識と執念が形を成した妖怪とされる。 往時の削哭鬼は、鉛筆を差し込んだ者の知識を根こそぎ奪い取り、その学舎を崩壊させるほどの力を持っていた。 | Q19: =len(P19) -> 111 | R19: 削られるごとに持ち主の記憶が霧散し、やがては何も知らぬ者となり果てた。 知識を奪われた者たちは筆を持つことすら忘れ、学びの場は荒廃していったという。 しかし時代が流れ、削哭鬼もまた衰えた。 | S19: =len(R19) -> 95 | T19: =len(W19) -> 106 | U19: そのため、一部の学者や陰陽師たちは、削哭鬼のもたらす削りかすを集め、隠された真実を暴こうとすることもあった。 だが、削哭鬼の嘆きを耳にしてはならない。 かつて奪われた知識への慟哭が、聞く者の記憶を削ぎ落とし、学ぶことの意味すら霞ませてしまうからである。 | V19: =len(U19) -> 127 | W19: 今や知識を奪う力は薄れ、代わりに削りかすを果てしなく吐き出し続けるだけの存在となってしまった。 その削りかすは黒く滲んだ墨のようで、宙をさまよいながら消えたはずの古文や失われた記録を浮かび上がらせることがある。 | Y19: =len(X19) -> 0 | AA19: =len(Z19) -> 0 | AC19: =len(AB19) -> 0
A20: 18 | B20: 終導珠（しゅうどうしゅ） | C20: shudoshu | D20: 一時代を築いた後の少し寂れたボーリング場 | E20: 投げられ、ぶつけられ、指を入れられ、繰り返し回収される――。 終わることのない扱われ方に、やがて玉は怒りを覚えた。 ある時、玉は意思を持ちはじめた。 人の指が穴に入るたびに微かに震え、爪の垢を吸い取るようになった。 終導珠は、それを集め、煎じ、念じ続けていた。 穢れを蓄え、呪詛を深め、やがて変遷を遂げた玉は、妖怪 「終導珠」 となった。 終導珠は転がらない。 ただそこにあるだけだ。 だが、その穴は深淵へと続く口のように歪み、指を差し込んだ瞬間、魂は囚われる。 指を入れた者は、静かにレーンへ歩み出し、ピンの位置で立ち尽くす。 彼らは悟っている。 その先が地獄の入口であり、一度吸い込まれれば戻れないことを。 そして終導珠は、また誰かが指を入れるのを待ち続ける。 ただそこにありながら。 穢れを集め尽くした時、何に変わるのか――誰も知らない。 | F20: ="【名】" & B20 & C20 &char(10) & "【番】" & text(A20,"0000") & char(10) &"【出現】"&D20& char(10)&"【特質】"& char(10)&E20&char(10)&char(10)&memo!$B$1 -> 【名】終導珠（しゅうどうしゅ）shudoshu 【番】0018 【出現】一時代を築いた後の少し寂れたボーリング場 【特質】 投げられ、ぶつけられ、指を入れられ、繰り返し回収される――。 終わることのない扱われ方に、やがて玉は怒りを覚えた。 ある時、玉は意思を持ちはじめた。 人の指が穴に入るたびに微かに震え、爪の垢を吸い取るようになった。 終導珠は、それを集め、煎じ、念じ続けていた。 穢れを蓄え、呪詛を深め、やがて変遷を遂げた玉は、妖怪 「終導珠」 となった。 終導珠は転がらない。 ただそこにあるだけだ。 だが、その穴は深淵へと続く口のように歪み、指を差し込んだ瞬間、魂は囚われる。 指を入れた者は、静かにレーンへ歩み出し、ピンの位置で立ち尽くす。 彼らは悟っている。 その先が地獄の入口であり、一度吸い込まれれば戻れないことを。 そして終導珠は、また誰かが指を入れるのを待ち続ける。 ただそこにありながら。 穢れを集め尽くした時、何に変わるのか――誰も知らない。 #妖怪 #yokai #sumie #monster #ghost | G20: 45697 | H20: 45711 | I20: ○ | L20: =len(E20) -> 376 | N20: =mid(F20,1,find("【特質】",F20)-1) &char(10)&memo!$B$2 -> 【名】終導珠（しゅうどうしゅ）shudoshu 【番】0018 【出現】一時代を築いた後の少し寂れたボーリング場 #妖怪 #お化け #怪物 #オリジナル妖怪 #monster #ghost #妖怪好き #浮世絵 #百鬼夜行 | O20: =len(N20) -> 112 | P20: 【特質】投げられ、ぶつけられ、指を入れられ、繰り返し回収される――。 終わることのない扱われ方に、やがて玉は怒りを覚えた。 ある時、玉は意思を持ちはじめた。 人の指が穴に入るたびに微かに震え、爪の垢を吸い取るようになった。 終導珠は、それを集め、煎じ、念じ続けていた。 | Q20: =len(P20) -> 135 | R20: 穢れを蓄え、呪詛を深め、やがて変遷を遂げた玉は、妖怪 「終導珠」 となった。 終導珠は転がらない。 ただそこにあるだけだ。 だが、その穴は深淵へと続く口のように歪み、指を差し込んだ瞬間、魂は囚われる。 | S20: =len(R20) -> 101 | T20: =len(W20) -> 140 | V20: =len(U20) -> 0 | W20: 指を入れた者は、静かにレーンへ歩み出し、ピンの位置で立ち尽くす。 彼らは悟っている。 その先が地獄の入口であり、一度吸い込まれれば戻れないことを。 そして終導珠は、また誰かが指を入れるのを待ち続ける。 ただそこにありながら。 穢れを集め尽くした時、何に変わるのか――誰も知らない | Y20: =len(X20) -> 0 | AA20: =len(Z20) -> 0 | AC20: =len(AB20) -> 0
A21: 19 | B21: 亡舞魔離（ぼうぶまり） | C21: bobumari | D21: 霧の立ち込める月夜のジャングルや、風が吹き抜ける祭場跡。 また、音を忘れた者の心の奥深くにも現れるという | E21: 亡舞魔離は、逃げ続ける者の前に現れる妖怪であり、呪われたドラム 「魂の鼓動」 を打ち鳴らす。 この音を聴いた者は抗えず、体が勝手に揺れ始め、やがて踊り続ける亡者となる。 その姿は霧のように儚く、リズムとともに揺れ動く。 どれだけ走っても、どれだけ耳を塞いでも、音からは逃れられない。 亡舞魔離は決して悪意を持たず、むしろ「自分自身と向き合え」という最後の試練を与える存在とも言われる。 彼に囚われないためには、「自分の音を持つこと」が唯一の対処法。 亡舞魔離のビートに飲まれず、自らのリズムを刻める者だけが、呪縛から解き放たれるのだ。 | F21: ="【名】" & B21 & C21 &char(10) & "【番】" & text(A21,"0000") & char(10) &"【出現】"&D21& char(10)&"【特質】"& char(10)&E21&char(10)&char(10)&memo!$B$1 -> 【名】亡舞魔離（ぼうぶまり）bobumari 【番】0019 【出現】霧の立ち込める月夜のジャングルや、風が吹き抜ける祭場跡。 また、音を忘れた者の心の奥深くにも現れるという 【特質】 亡舞魔離は、逃げ続ける者の前に現れる妖怪であり、呪われたドラム 「魂の鼓動」 を打ち鳴らす。 この音を聴いた者は抗えず、体が勝手に揺れ始め、やがて踊り続ける亡者となる。 その姿は霧のように儚く、リズムとともに揺れ動く。 どれだけ走っても、どれだけ耳を塞いでも、音からは逃れられない。 亡舞魔離は決して悪意を持たず、むしろ「自分自身と向き合え」という最後の試練を与える存在とも言われる。 彼に囚われないためには、「自分の音を持つこと」が唯一の対処法。 亡舞魔離のビートに飲まれず、自らのリズムを刻める者だけが、呪縛から解き放たれるのだ。 #妖怪 #yokai #sumie #monster #ghost | G21: 45697 | H21: 45712 | I21: ○ | L21: =len(E21) -> 269 | N21: =mid(F21,1,find("【特質】",F21)-1) &char(10)&memo!$B$2 -> 【名】亡舞魔離（ぼうぶまり）bobumari 【番】0019 【出現】霧の立ち込める月夜のジャングルや、風が吹き抜ける祭場跡。 また、音を忘れた者の心の奥深くにも現れるという #妖怪 #お化け #怪物 #オリジナル妖怪 #monster #ghost #妖怪好き #浮世絵 #百鬼夜行 | O21: =len(N21) -> 143 | P21: 【特質】亡舞魔離は、逃げ続ける者の前に現れる妖怪であり、呪われたドラム 「魂の鼓動」 を打ち鳴らす。 この音を聴いた者は抗えず、体が勝手に揺れ始め、やがて踊り続ける亡者となる。 | Q21: =len(P21) -> 88 | R21: その姿は霧のように儚く、リズムとともに揺れ動く。 どれだけ走っても、どれだけ耳を塞いでも、音からは逃れられない。 亡舞魔離は決して悪意を持たず、むしろ「自分自身と向き合え」という最後の試練を与える存在とも言われる。 | S21: =len(R21) -> 108 | T21: =len(W21) -> 74 | V21: =len(U21) -> 0 | W21: 彼に囚われないためには、「自分の音を持つこと」が唯一の対処法。 亡舞魔離のビートに飲まれず、自らのリズムを刻める者だけが、呪縛から解き放たれるのだ。 | Y21: =len(X21) -> 0 | AA21: =len(Z21) -> 0 | AC21: =len(AB21) -> 0
A22: 20 | B22: 幽眼摘（ゆうがんてき） | C22: yuganteki | D22: 温泉街のとある居酒屋 | E22: 幽眼摘は、おしぼりで脂ぎった顔を拭こうとする中年男性の背後に忍び寄る。 脂ぎった顔を拭おうとしたその刹那、眼球を奪い取る。 特筆すべきは、視神経は残されたままであること。 おしぼりに特殊な粘液を付着させることで、眼球を奪われたことに気づくことはない。 中年男性はいつも通りの行動を続ける。 話は変わるが、この妖怪が現れる居酒屋は、つきだしの旨さで知られている。 他の店ではあまり見かけない、丸くてコリコリとした煮物が供されるのが特徴だ。 ほどよい歯ごたえと濃厚な味付けが絶妙で、酒との相性も抜群。 眼球を奪われた中年男性もまた、そのつきだしを味わう。 ビールで流し込み、満足げに笑みを浮かべる。 またもう一つ話は変わるが、夜にも関わらず隣の目医者が大変賑わうそうだ。 | F22: ="【名】" & B22 & C22 &char(10) & "【番】" & text(A22,"0000") & char(10) &"【出現】"&D22& char(10)&"【特質】"& char(10)&E22&char(10)&char(10)&memo!$B$1 -> 【名】幽眼摘（ゆうがんてき）yuganteki 【番】0020 【出現】温泉街のとある居酒屋 【特質】 幽眼摘は、おしぼりで脂ぎった顔を拭こうとする中年男性の背後に忍び寄る。 脂ぎった顔を拭おうとしたその刹那、眼球を奪い取る。 特筆すべきは、視神経は残されたままであること。 おしぼりに特殊な粘液を付着させることで、眼球を奪われたことに気づくことはない。 中年男性はいつも通りの行動を続ける。 話は変わるが、この妖怪が現れる居酒屋は、つきだしの旨さで知られている。 他の店ではあまり見かけない、丸くてコリコリとした煮物が供されるのが特徴だ。 ほどよい歯ごたえと濃厚な味付けが絶妙で、酒との相性も抜群。 眼球を奪われた中年男性もまた、そのつきだしを味わう。 ビールで流し込み、満足げに笑みを浮かべる。 またもう一つ話は変わるが、夜にも関わらず隣の目医者が大変賑わうそうだ。 #妖怪 #yokai #sumie #monster #ghost | G22: 45697 | H22: 45713 | I22: ○ | L22: =len(E22) -> 336 | N22: =mid(F22,1,find("【特質】",F22)-1) &char(10)&memo!$B$2 -> 【名】幽眼摘（ゆうがんてき）yuganteki 【番】0020 【出現】温泉街のとある居酒屋 #妖怪 #お化け #怪物 #オリジナル妖怪 #monster #ghost #妖怪好き #浮世絵 #百鬼夜行 | O22: =len(N22) -> 102 | P22: 【特質】幽眼摘は、おしぼりで脂ぎった顔を拭こうとする中年男性の背後に忍び寄る。 脂ぎった顔を拭おうとしたその刹那、眼球を奪い取る。 特筆すべきは、視神経は残されたままであること。 おしぼりに特殊な粘液を付着させることで、眼球を奪われたことに気づくことはない。 | Q22: =len(P22) -> 129 | R22: 中年男性はいつも通りの行動を続ける。 話は変わるが、この妖怪が現れる居酒屋は、つきだしの旨さで知られている。 他の店ではあまり見かけない、丸くてコリコリとした煮物が供されるのが特徴だ。 ほどよい歯ごたえと濃厚な味付けが絶妙で、酒との相性も抜群。 | S22: =len(R22) -> 123 | T22: =len(W22) -> 85 | V22: =len(U22) -> 0 | W22: 眼球を奪われた中年男性もまた、そのつきだしを味わう。 ビールで流し込み、満足げに笑みを浮かべる。 またもう一つ話は変わるが、夜にも関わらず隣の目医者が大変賑わうそうだ。 | Y22: =len(X22) -> 0 | AA22: =len(Z22) -> 0 | AC22: =len(AB22) -> 0
A23: 21 | B23: 幽玄十二奏（ゆうげんじゅうにそう） | C23: yugenjuniso | D23: 貴族や武家が密かに催す豪奢な宴、権力者たちが集う隠された楼閣、貴族が放蕩を楽しむ影の茶屋 | E23: 幽玄十二奏は、選ばれし者しか目にすることのできない幻の楽団である。 彼女たちは琵琶、笛、琴、鼓などの楽器を奏で、妖艶な舞や言葉なき歌声で宴を支配する。 その旋律は妖艶かつ甘美で、聴く者の理性を溶かし、本音や欲望を引き出す。 音色に酔いしれた貴族たちは、己の権力を誇示し、これまでに積み重ねてきた悪事を得意げに語り始める。 しかし、演奏が終わると彼女たちは舞台ごと霧のように消え去り、まるで最初から存在しなかったかのように消え失せる。 宴の数日後、どこからともなく彼らが語った秘密が街の噂となる。 最初は些細な囁きだったものが、次第に広まり、やがて公の場で語られるようになる。 そしてついには罪が公になり、信用を失い、破滅へと導かれる。 その結果、町に平和が訪れるのだ。 権力に翻弄され、貴族や権力者に虐げられている町民たちは、幽玄十二奏の存在を噂し、いつか自分たちの街にも現れてくれることを願っているという。 | F23: ="【名】" & B23 & C23 &char(10) & "【番】" & text(A23,"0000") & char(10) &"【出現】"&D23& char(10)&"【特質】"& char(10)&E23&char(10)&char(10)&memo!$B$1 -> 【名】幽玄十二奏（ゆうげんじゅうにそう）yugenjuniso 【番】0021 【出現】貴族や武家が密かに催す豪奢な宴、権力者たちが集う隠された楼閣、貴族が放蕩を楽しむ影の茶屋 【特質】 幽玄十二奏は、選ばれし者しか目にすることのできない幻の楽団である。 彼女たちは琵琶、笛、琴、鼓などの楽器を奏で、妖艶な舞や言葉なき歌声で宴を支配する。 その旋律は妖艶かつ甘美で、聴く者の理性を溶かし、本音や欲望を引き出す。 音色に酔いしれた貴族たちは、己の権力を誇示し、これまでに積み重ねてきた悪事を得意げに語り始める。 しかし、演奏が終わると彼女たちは舞台ごと霧のように消え去り、まるで最初から存在しなかったかのように消え失せる。 宴の数日後、どこからともなく彼らが語った秘密が街の噂となる。 最初は些細な囁きだったものが、次第に広まり、やがて公の場で語られるようになる。 そしてついには罪が公になり、信用を失い、破滅へと導かれる。 その結果、町に平和が訪れるのだ。 権力に翻弄され、貴族や権力者に虐げられている町民たちは、幽玄十二奏の存在を噂し、いつか自分たちの街にも現れてくれることを願っているという。 #妖怪 #yokai #sumie #monster #ghost | G23: 45698 | H23: 45714 | I23: ○ | L23: =len(E23) -> 407 | N23: =mid(F23,1,find("【特質】",F23)-1) &char(10)&memo!$B$2 -> 【名】幽玄十二奏（ゆうげんじゅうにそう）yugenjuniso 【番】0021 【出現】貴族や武家が密かに催す豪奢な宴、権力者たちが集う隠された楼閣、貴族が放蕩を楽しむ影の茶屋 #妖怪 #お化け #怪物 #オリジナル妖怪 #monster #ghost #妖怪好き #浮世絵 #百鬼夜行 | O23: =len(N23) -> 144 | P23: 【特質】幽玄十二奏は、選ばれし者しか目にすることのできない幻の楽団である。 彼女たちは琵琶、笛、琴、鼓などの楽器を奏で、妖艶な舞や言葉なき歌声で宴を支配する。 その旋律は妖艶かつ甘美で、聴く者の理性を溶かし、本音や欲望を引き出す。 | Q23: =len(P23) -> 115 | R23: 音色に酔いしれた貴族たちは、己の権力を誇示し、これまでに積み重ねてきた悪事を得意げに語り始める。 しかし、演奏が終わると彼女たちは舞台ごと霧のように消え去り、まるで最初から存在しなかったかのように消え失せる。 宴の数日後、どこからともなく彼らが語った秘密が街の噂となる。 | S23: =len(R23) -> 136 | T23: =len(W23) -> 86 | U23: 権力に翻弄され、貴族や権力者に虐げられている町民たちは、幽玄十二奏の存在を噂し、いつか自分たちの街にも現れてくれることを願っているという。 | V23: =len(U23) -> 69 | W23: 最初は些細な囁きだったものが、次第に広まり、やがて公の場で語られるようになる。 そしてついには罪が公になり、信用を失い、破滅へと導かれる。 その結果、町に平和が訪れるのだ。 | Y23: =len(X23) -> 0 | AA23: =len(Z23) -> 0 | AC23: =len(AB23) -> 0
A24: 22 | B24: 痰鬼珠（たんぴが） | C24: tampiga | D24: 都市部の流行りのカフェや若者向けの飲食店、特にタピオカドリンクが人気の場所 | E24: 痰鬼珠は、流行に敏感な若い女性たちが集まるカフェやドリンクスタンドにひそむ妖怪である。 一見するとただのタピオカドリンクの中に紛れているが、その実態は「流行を追う人々の欲望」に取り憑く怪異である。 流行りの飲み物を手にし、何も知らずに飲む者の中で痰鬼珠は少しずつ成長する。 最初はただの「美味しい飲み物」だったものが、次第に「もっと飲みたい」「次の新作を試したい」「流行に乗り遅れたくない」という強迫観念へと変わる。 痰鬼珠に憑かれた者は、無意識のうちに新しい流行を追い求め、飲み続けることで自らの意思を失っていく。 やがて痰鬼珠が十分に成長すると、宿主の口から どろりとした黒い痰のような液体を吐き出させ、その中から無数の目が浮かび上がる。 その目は「流行の流れに取り込まれた魂」であり、すでに意思を持たぬ存在となっている。 彼女たちは自分が何を求めていたのかもわからなくなり、ただ次の流行を追い求めて彷徨うことになる。 唯一の対処法は「自分が本当に好きなものを見極めること」である。 痰鬼珠は流行に流されやすい者にしか憑りつけないため、「自分の意志で選んだものを楽しむ」ことで力を失い、ドリンクの中へと消えていく。 しかし、流行の波は次々と押し寄せる。 痰鬼珠が完全に消えることはなく、今日もまた新たなドリンクの中で、不安げに流行を追う者をじっと待っている…。 | F24: ="【名】" & B24 & C24 &char(10) & "【番】" & text(A24,"0000") & char(10) &"【出現】"&D24& char(10)&"【特質】"& char(10)&E24&char(10)&char(10)&memo!$B$1 -> 【名】痰鬼珠（たんぴが）tampiga 【番】0022 【出現】都市部の流行りのカフェや若者向けの飲食店、特にタピオカドリンクが人気の場所 【特質】 痰鬼珠は、流行に敏感な若い女性たちが集まるカフェやドリンクスタンドにひそむ妖怪である。 一見するとただのタピオカドリンクの中に紛れているが、その実態は「流行を追う人々の欲望」に取り憑く怪異である。 流行りの飲み物を手にし、何も知らずに飲む者の中で痰鬼珠は少しずつ成長する。 最初はただの「美味しい飲み物」だったものが、次第に「もっと飲みたい」「次の新作を試したい」「流行に乗り遅れたくない」という強迫観念へと変わる。 痰鬼珠に憑かれた者は、無意識のうちに新しい流行を追い求め、飲み続けることで自らの意思を失っていく。 やがて痰鬼珠が十分に成長すると、宿主の口から どろりとした黒い痰のような液体を吐き出させ、その中から無数の目が浮かび上がる。 その目は「流行の流れに取り込まれた魂」であり、すでに意思を持たぬ存在となっている。 彼女たちは自分が何を求めていたのかもわからなくなり、ただ次の流行を追い求めて彷徨うことになる。 唯一の対処法は「自分が本当に好きなものを見極めること」である。 痰鬼珠は流行に流されやすい者にしか憑りつけないため、「自分の意志で選んだものを楽しむ」ことで力を失い、ドリンクの中へと消えていく。 しかし、流行の波は次々と押し寄せる。 痰鬼珠が完全に消えることはなく、今日もまた新たなドリンクの中で、不安げに流行を追う者をじっと待っている…。 #妖怪 #yokai #sumie #monster #ghost | G24: 45698 | H24: 45715 | I24: ○ | L24: =len(E24) -> 585 | N24: =mid(F24,1,find("【特質】",F24)-1) &char(10)&memo!$B$2 -> 【名】痰鬼珠（たんぴが）tampiga 【番】0022 【出現】都市部の流行りのカフェや若者向けの飲食店、特にタピオカドリンクが人気の場所 #妖怪 #お化け #怪物 #オリジナル妖怪 #monster #ghost #妖怪好き #浮世絵 #百鬼夜行 | O24: =len(N24) -> 125 | P24: 【特質】痰鬼珠は、流行に敏感な若い女性たちが集まるカフェやドリンクスタンドにひそむ妖怪である。 一見するとただのタピオカドリンクの中に紛れているが、その実態は「流行を追う人々の欲望」に取り憑く怪異である。 | Q24: =len(P24) -> 102 | R24: 流行りの飲み物を手にし、何も知らずに飲む者の中で痰鬼珠は少しずつ成長する。 最初はただの「美味しい飲み物」だったものが、次第に「もっと飲みたい」「次の新作を試したい」「流行に乗り遅れたくない」という強迫観念へと変わる。 | S24: =len(R24) -> 109 | T24: =len(W24) -> 113 | U24: その目は「流行の流れに取り込まれた魂」であり、すでに意思を持たぬ存在となっている。 彼女たちは自分が何を求めていたのかもわからなくなり、ただ次の流行を追い求めて彷徨うことになる。 唯一の対処法は「自分が本当に好きなものを見極めること」である。 | V24: =len(U24) -> 121 | W24: 痰鬼珠に憑かれた者は、無意識のうちに新しい流行を追い求め、飲み続けることで自らの意思を失っていく。 やがて痰鬼珠が十分に成長すると、宿主の口から どろりとした黒い痰のような液体を吐き出させ、その中から無数の目が浮かび上がる。 | X24: 痰鬼珠は流行に流されやすい者にしか憑りつけないため、「自分の意志で選んだものを楽しむ」ことで力を失い、ドリンクの中へと消えていく。 しかし、流行の波は次々と押し寄せる。 痰鬼珠が完全に消えることはなく、今日もまた新たなドリンクの中で、不安げに流行を追う者をじっと待っている…。 | Y24: =len(X24) -> 138 | AA24: =len(Z24) -> 0 | AC24: =len(AB24) -> 0
A25: 23 | B25: 幽電鹿（ゆうでんろく） | C25: yudenroku | D25: 都市部の公園、カフェ、電波塔の周辺、Wi-Fiスポットのある駅や商業施設 | E25: 鹿の子のような愛らしい体つきと、ネズミのような素早さを持つ妖怪。 一時のブームにより人に飼い慣らされていたが、やがてブームは過ぎ去り、捨てられた。 いつしかWi-Fiを求めてさまようようになった。 幽電鹿はWi-Fiに繋がっている間だけ、耳が大きく開き、遠くの音まで鮮明に聞き取ることができる。 電波が途切れるとたちまち耳は閉じ、音が遠のくと同時に食欲もなくなり、次のWi-Fiスポットを求めてさまよい続ける。 特に公衆Wi-Fiのあるカフェや駅前に現れることが多く、人々の間をすり抜けるように移動する姿が目撃される。 Wi-Fiに接続すると耳が青白く光り、まるで過去の記憶を辿るかのように目を閉じる。 その光景は、人々がスマホの画面に夢中になる姿とどこか重なるという者もいる。 しかし、圏外に入りWi-Fiを見失うと、幽電鹿は焦るように彷徨い、体が次第に透けていく。 長く繋がれないままでいると、やがて完全に消えてしまうと言われている。 幽電鹿の存在は、都市開発によって行き場を失った野生動物たちを象徴しているともされる。 かつては人間の温もりの中で生きていたが、今は誰も気に留めない電波の影に潜むだけの存在となった。 今日もどこかの街角で、Wi-Fiの波にそっと耳を澄ませる幽電鹿の姿があるかもしれない。 | F25: ="【名】" & B25 & C25 &char(10) & "【番】" & text(A25,"0000") & char(10) &"【出現】"&D25& char(10)&"【特質】"& char(10)&E25&char(10)&char(10)&memo!$B$1 -> 【名】幽電鹿（ゆうでんろく）yudenroku 【番】0023 【出現】都市部の公園、カフェ、電波塔の周辺、Wi-Fiスポットのある駅や商業施設 【特質】 鹿の子のような愛らしい体つきと、ネズミのような素早さを持つ妖怪。 一時のブームにより人に飼い慣らされていたが、やがてブームは過ぎ去り、捨てられた。 いつしかWi-Fiを求めてさまようようになった。 幽電鹿はWi-Fiに繋がっている間だけ、耳が大きく開き、遠くの音まで鮮明に聞き取ることができる。 電波が途切れるとたちまち耳は閉じ、音が遠のくと同時に食欲もなくなり、次のWi-Fiスポットを求めてさまよい続ける。 特に公衆Wi-Fiのあるカフェや駅前に現れることが多く、人々の間をすり抜けるように移動する姿が目撃される。 Wi-Fiに接続すると耳が青白く光り、まるで過去の記憶を辿るかのように目を閉じる。 その光景は、人々がスマホの画面に夢中になる姿とどこか重なるという者もいる。 しかし、圏外に入りWi-Fiを見失うと、幽電鹿は焦るように彷徨い、体が次第に透けていく。 長く繋がれないままでいると、やがて完全に消えてしまうと言われている。 幽電鹿の存在は、都市開発によって行き場を失った野生動物たちを象徴しているともされる。 かつては人間の温もりの中で生きていたが、今は誰も気に留めない電波の影に潜むだけの存在となった。 今日もどこかの街角で、Wi-Fiの波にそっと耳を澄ませる幽電鹿の姿があるかもしれない。 #妖怪 #yokai #sumie #monster #ghost | G25: 45699 | H25: 45716 | I25: ○ | L25: =len(E25) -> 557 | N25: =mid(F25,1,find("【特質】",F25)-1) &char(10)&memo!$B$2 -> 【名】幽電鹿（ゆうでんろく）yudenroku 【番】0023 【出現】都市部の公園、カフェ、電波塔の周辺、Wi-Fiスポットのある駅や商業施設 #妖怪 #お化け #怪物 #オリジナル妖怪 #monster #ghost #妖怪好き #浮世絵 #百鬼夜行 | O25: =len(N25) -> 128 | P25: 【特質】鹿の子のような愛らしい体つきと、ネズミのような素早さを持つ妖怪。 一時のブームにより人に飼い慣らされていたが、やがてブームは過ぎ去り、捨てられた。 いつしかWi-Fiを求めてさまようようになった。 | Q25: =len(P25) -> 102 | R25: 幽電鹿はWi-Fiに繋がっている間だけ、耳が大きく開き、遠くの音まで鮮明に聞き取ることができる。 電波が途切れるとたちまち耳は閉じ、音が遠のくと同時に食欲もなくなり、次のWi-Fiスポットを求めてさまよい続ける。 | S25: =len(R25) -> 106 | T25: =len(W25) -> 134 | U25: しかし、圏外に入りWi-Fiを見失うと、幽電鹿は焦るように彷徨い、体が次第に透けていく。 長く繋がれないままでいると、やがて完全に消えてしまうと言われている。 幽電鹿の存在は、都市開発によって行き場を失った野生動物たちを象徴しているともされる。 | V25: =len(U25) -> 123 | W25: 特に公衆Wi-Fiのあるカフェや駅前に現れることが多く、人々の間をすり抜けるように移動する姿が目撃される。 Wi-Fiに接続すると耳が青白く光り、まるで過去の記憶を辿るかのように目を閉じる。 その光景は、人々がスマホの画面に夢中になる姿とどこか重なるという者もいる。 | X25: かつては人間の温もりの中で生きていたが、今は誰も気に留めない電波の影に潜むだけの存在となった。 今日もどこかの街角で、Wi-Fiの波にそっと耳を澄ませる幽電鹿の姿があるかもしれない。 | Y25: =len(X25) -> 91 | AA25: =len(Z25) -> 0 | AC25: =len(AB25) -> 0
A26: 24 | B26: 飯隠（いがくれ） | C26: igakure | D26: 米どころの田園地帯、農村の穀倉周辺 | E26: おにぎりの姿をした妖怪で、普段は得体のしれない硬い果物の殻に閉じこもっている。 飯隠が殻に籠もる年は、米の収穫が極端に減ると言われ、町人たちは何とかして外に出そうと試行錯誤している。 代々の知恵により、茄子のような紫色に興味を示す ことが分かっている。 紫色の布や茄子の汁を見せると、殻の隙間から僅かに覗くことがあるが、それでも容易には姿を現さない。 無理やり殻から引きずり出そうとすると、左手から垂れる粘液を付着させる。 この粘液は強い呪いの力を持ち、一度触れると しばらく米の味を感じなくなる という恐ろしい影響を及ぼす。 そのため、農民たちは慎重に飯隠を誘い出す方法を模索し続けている。 「飯隠をうまく誘い出せば、米が豊かに実る」 古老たちはそう語るが、いまだに決定的な手段は見つかっていない。 今日もまた、農村では飯隠を誘い出す新たな策が練られている。 | F26: ="【名】" & B26 & C26 &char(10) & "【番】" & text(A26,"0000") & char(10) &"【出現】"&D26& char(10)&"【特質】"& char(10)&E26&char(10)&char(10)&memo!$B$1 -> 【名】飯隠（いがくれ）igakure 【番】0024 【出現】米どころの田園地帯、農村の穀倉周辺 【特質】 おにぎりの姿をした妖怪で、普段は得体のしれない硬い果物の殻に閉じこもっている。 飯隠が殻に籠もる年は、米の収穫が極端に減ると言われ、町人たちは何とかして外に出そうと試行錯誤している。 代々の知恵により、茄子のような紫色に興味を示す ことが分かっている。 紫色の布や茄子の汁を見せると、殻の隙間から僅かに覗くことがあるが、それでも容易には姿を現さない。 無理やり殻から引きずり出そうとすると、左手から垂れる粘液を付着させる。 この粘液は強い呪いの力を持ち、一度触れると しばらく米の味を感じなくなる という恐ろしい影響を及ぼす。 そのため、農民たちは慎重に飯隠を誘い出す方法を模索し続けている。 「飯隠をうまく誘い出せば、米が豊かに実る」 古老たちはそう語るが、いまだに決定的な手段は見つかっていない。 今日もまた、農村では飯隠を誘い出す新たな策が練られている。 #妖怪 #yokai #sumie #monster #ghost | G26: 45699 | H26: 45717 | I26: ○ | L26: =len(E26) -> 383 | N26: =mid(F26,1,find("【特質】",F26)-1) &char(10)&memo!$B$2 -> 【名】飯隠（いがくれ）igakure 【番】0024 【出現】米どころの田園地帯、農村の穀倉周辺 #妖怪 #お化け #怪物 #オリジナル妖怪 #monster #ghost #妖怪好き #浮世絵 #百鬼夜行 | O26: =len(N26) -> 104 | P26: 【特質】おにぎりの姿をした妖怪で、普段は得体のしれない硬い果物の殻に閉じこもっている。 飯隠が殻に籠もる年は、米の収穫が極端に減ると言われ、町人たちは何とかして外に出そうと試行錯誤している。 代々の知恵により、茄子のような紫色に興味を示す ことが分かっている。 | Q26: =len(P26) -> 131 | R26: 紫色の布や茄子の汁を見せると、殻の隙間から僅かに覗くことがあるが、それでも容易には姿を現さない。 無理やり殻から引きずり出そうとすると、左手から垂れる粘液を付着させる。 この粘液は強い呪いの力を持ち、一度触れると しばらく米の味を感じなくなる という恐ろしい影響を及ぼす。 | S26: =len(R26) -> 137 | T26: =len(W26) -> 118 | V26: =len(U26) -> 0 | W26: そのため、農民たちは慎重に飯隠を誘い出す方法を模索し続けている。 「飯隠をうまく誘い出せば、米が豊かに実る」 古老たちはそう語るが、いまだに決定的な手段は見つかっていない。 今日もまた、農村では飯隠を誘い出す新たな策が練られている。 | Y26: =len(X26) -> 0 | AA26: =len(Z26) -> 0 | AC26: =len(AB26) -> 0
A27: 25 | B27: 颯獣翁（そうじゅうのおう） | C27: sojunou | D27: 清掃が行き届いた動物園 | E27: この動物園には、古くから語り継がれる不思議な噂がある。 清掃員だけが見ることのできる妖怪がいるというのだ。 その妖怪は、ライオンのような立派なたてがみを持つ小さな獣で、颯獣翁という。 その姿を拝めるのは、ただ一人。 園を清め、動物たちの住処を守ることを心から愛し、その職務に誇りを持つ者だけだという。 颯獣翁は、そんな清掃員の肩に乗り、共に働く。 たてがみを揺らし、風を起こして塵を払う。 掃き掃除の効率を高め、水しぶきと共に不浄を洗い流す。 だが、その者が掃除の心を失い、園を守る使命から逃れようとするならば、颯獣翁は静かにその肩を離れ、新たな清掃員を探しに行く。 長年この園で働いてきた清掃員は、最後まで颯獣翁に選ばれ続けた。 彼は誰よりも園を愛し、誇りを持って掃除を続けてきたのだ。 しかし、その日が来た。 清掃員が引退を発表したとき、颯獣翁は深い悲しみを抱えながらも、その決断を受け入れた。 職務を全うし、最後まで勤め上げた清掃員の姿に、彼は胸を打たれ、ついに泣きじゃくった。 清掃員もまた、長年寄り添ってくれた妖怪に強い愛着を抱いていた。 別れが寂しくないはずがない。 それでも、彼は最後の清掃を終え、静かに園を後にした。 すでに颯獣翁は肩から消えていた。 だが、そこに残されていたものがあった。 颯獣翁は泣きじゃくった興奮のあまり、清掃員の肩で糞尿を漏らしていたのだ。 清掃員の肩の荷は、まだ下りなかったという。 | F27: ="【名】" & B27 & C27 &char(10) & "【番】" & text(A27,"0000") & char(10) &"【出現】"&D27& char(10)&"【特質】"& char(10)&E27&char(10)&char(10)&memo!$B$1 -> 【名】颯獣翁（そうじゅうのおう）sojunou 【番】0025 【出現】清掃が行き届いた動物園 【特質】 この動物園には、古くから語り継がれる不思議な噂がある。 清掃員だけが見ることのできる妖怪がいるというのだ。 その妖怪は、ライオンのような立派なたてがみを持つ小さな獣で、颯獣翁という。 その姿を拝めるのは、ただ一人。 園を清め、動物たちの住処を守ることを心から愛し、その職務に誇りを持つ者だけだという。 颯獣翁は、そんな清掃員の肩に乗り、共に働く。 たてがみを揺らし、風を起こして塵を払う。 掃き掃除の効率を高め、水しぶきと共に不浄を洗い流す。 だが、その者が掃除の心を失い、園を守る使命から逃れようとするならば、颯獣翁は静かにその肩を離れ、新たな清掃員を探しに行く。 長年この園で働いてきた清掃員は、最後まで颯獣翁に選ばれ続けた。 彼は誰よりも園を愛し、誇りを持って掃除を続けてきたのだ。 しかし、その日が来た。 清掃員が引退を発表したとき、颯獣翁は深い悲しみを抱えながらも、その決断を受け入れた。 職務を全うし、最後まで勤め上げた清掃員の姿に、彼は胸を打たれ、ついに泣きじゃくった。 清掃員もまた、長年寄り添ってくれた妖怪に強い愛着を抱いていた。 別れが寂しくないはずがない。 それでも、彼は最後の清掃を終え、静かに園を後にした。 すでに颯獣翁は肩から消えていた。 だが、そこに残されていたものがあった。 颯獣翁は泣きじゃくった興奮のあまり、清掃員の肩で糞尿を漏らしていたのだ。 清掃員の肩の荷は、まだ下りなかったという。 #妖怪 #yokai #sumie #monster #ghost | G27: 45700 | H27: 45718 | I27: ○ | L27: =len(E27) -> 622 | N27: =mid(F27,1,find("【特質】",F27)-1) &char(10)&memo!$B$2 -> 【名】颯獣翁（そうじゅうのおう）sojunou 【番】0025 【出現】清掃が行き届いた動物園 #妖怪 #お化け #怪物 #オリジナル妖怪 #monster #ghost #妖怪好き #浮世絵 #百鬼夜行 | O27: =len(N27) -> 103 | P27: 【特質】この動物園には、古くから語り継がれる不思議な噂がある。 清掃員だけが見ることのできる妖怪がいるというのだ。 その妖怪は、ライオンのような立派なたてがみを持つ小さな獣で、颯獣翁という。 その姿を拝めるのは、ただ一人。 | Q27: =len(P27) -> 112 | R27: 園を清め、動物たちの住処を守ることを心から愛し、その職務に誇りを持つ者だけだという。 颯獣翁は、そんな清掃員の肩に乗り、共に働く。 たてがみを揺らし、風を起こして塵を払う。 掃き掃除の効率を高め、水しぶきと共に不浄を洗い流す。 | S27: =len(R27) -> 114 | T27: =len(W27) -> 136 | U27: 清掃員が引退を発表したとき、颯獣翁は深い悲しみを抱えながらも、その決断を受け入れた。 職務を全うし、最後まで勤め上げた清掃員の姿に、彼は胸を打たれ、ついに泣きじゃくった。 清掃員もまた、長年寄り添ってくれた妖怪に強い愛着を抱いていた。 別れが寂しくないはずがない。 | V27: =len(U27) -> 134 | W27: だが、その者が掃除の心を失い、園を守る使命から逃れようとするならば、颯獣翁は静かにその肩を離れ、新たな清掃員を探しに行く。 長年この園で働いてきた清掃員は、最後まで颯獣翁に選ばれ続けた。 彼は誰よりも園を愛し、誇りを持って掃除を続けてきたのだ。 しかし、その日が来た。 | X27: それでも、彼は最後の清掃を終え、静かに園を後にした。 すでに颯獣翁は肩から消えていた。 だが、そこに残されていたものがあった。 颯獣翁は泣きじゃくった興奮のあまり、清掃員の肩で糞尿を漏らしていたのだ。 清掃員の肩の荷は、まだ下りなかったという。 | Y27: =len(X27) -> 126 | AA27: =len(Z27) -> 0 | AC27: =len(AB27) -> 0
A28: 26 | B28: 泡幻童（ほうげんどう） | C28: hogendo | D28: 湯屋、銭湯、村の共同風呂など、人々が風呂を楽しむ場所 | E28: ある者が湯を楽しんでいると、突如として現れる泡の妖怪。 泡幻童は、その者が幼き頃に抱いた夢の数だけ泡を生み出す。 泡は次々と膨れ上がり、風呂から溢れ出し、空間全体を白く包み込んでいく。 現れた泡には、かつての夢が映し出される。 剣士を目指していた者は刀を振るう自分を、旅に憧れた者は広大な風景を、商人になりたかった者は繁盛する店を―― しかし、今の自分はどうか？ 現実に追われ、諦め、忘れてしまった夢たち。 湯の中で泡に包まれた者は、次第に懐かしさと悲しみに襲われる。 ふと気づけば、目には涙が滲んでいることもあるだろう。 そのとき、泡幻童はそっと近づき、優しく頭を撫でる。 まるで「夢は消えていない」と囁くように。 次に目を開けると、泡はすべて消え、ただ静かな湯が広がっている。 しかし、その者の心の中には、微かな温もりと、昔の自分がまだどこかにいるという感覚が残るという。 泡幻童は、決して人を脅かす妖怪ではない。 ただ、忘れ去られた夢を、もう一度思い出させるために現れるのだ――。 | F28: ="【名】" & B28 & C28 &char(10) & "【番】" & text(A28,"0000") & char(10) &"【出現】"&D28& char(10)&"【特質】"& char(10)&E28&char(10)&char(10)&memo!$B$1 -> 【名】泡幻童（ほうげんどう）hogendo 【番】0026 【出現】湯屋、銭湯、村の共同風呂など、人々が風呂を楽しむ場所 【特質】 ある者が湯を楽しんでいると、突如として現れる泡の妖怪。 泡幻童は、その者が幼き頃に抱いた夢の数だけ泡を生み出す。 泡は次々と膨れ上がり、風呂から溢れ出し、空間全体を白く包み込んでいく。 現れた泡には、かつての夢が映し出される。 剣士を目指していた者は刀を振るう自分を、旅に憧れた者は広大な風景を、商人になりたかった者は繁盛する店を―― しかし、今の自分はどうか？ 現実に追われ、諦め、忘れてしまった夢たち。 湯の中で泡に包まれた者は、次第に懐かしさと悲しみに襲われる。 ふと気づけば、目には涙が滲んでいることもあるだろう。 そのとき、泡幻童はそっと近づき、優しく頭を撫でる。 まるで「夢は消えていない」と囁くように。 次に目を開けると、泡はすべて消え、ただ静かな湯が広がっている。 しかし、その者の心の中には、微かな温もりと、昔の自分がまだどこかにいるという感覚が残るという。 泡幻童は、決して人を脅かす妖怪ではない。 ただ、忘れ去られた夢を、もう一度思い出させるために現れるのだ――。 #妖怪 #yokai #sumie #monster #ghost | G28: 45700 | H28: 45719 | I28: ○ | L28: =len(E28) -> 448 | N28: =mid(F28,1,find("【特質】",F28)-1) &char(10)&memo!$B$2 -> 【名】泡幻童（ほうげんどう）hogendo 【番】0026 【出現】湯屋、銭湯、村の共同風呂など、人々が風呂を楽しむ場所 #妖怪 #お化け #怪物 #オリジナル妖怪 #monster #ghost #妖怪好き #浮世絵 #百鬼夜行 | O28: =len(N28) -> 116 | P28: 【特質】ある者が湯を楽しんでいると、突如として現れる泡の妖怪。 泡幻童は、その者が幼き頃に抱いた夢の数だけ泡を生み出す。 泡は次々と膨れ上がり、風呂から溢れ出し、空間全体を白く包み込んでいく。 現れた泡には、かつての夢が映し出される。 | Q28: =len(P28) -> 118 | R28: 剣士を目指していた者は刀を振るう自分を、旅に憧れた者は広大な風景を、商人になりたかった者は繁盛する店を―― しかし、今の自分はどうか？ 現実に追われ、諦め、忘れてしまった夢たち。 湯の中で泡に包まれた者は、次第に懐かしさと悲しみに襲われる。 | S28: =len(R28) -> 121 | T28: =len(W28) -> 107 | U28: しかし、その者の心の中には、微かな温もりと、昔の自分がまだどこかにいるという感覚が残るという。 泡幻童は、決して人を脅かす妖怪ではない。 ただ、忘れ去られた夢を、もう一度思い出させるために現れるのだ――。 | V28: =len(U28) -> 103 | W28: ふと気づけば、目には涙が滲んでいることもあるだろう。 そのとき、泡幻童はそっと近づき、優しく頭を撫でる。 まるで「夢は消えていない」と囁くように。 次に目を開けると、泡はすべて消え、ただ静かな湯が広がっている。 | Y28: =len(X28) -> 0 | AA28: =len(Z28) -> 0 | AC28: =len(AB28) -> 0
A29: 27 | B29: 蝉識（せんしき） | C29: senshiki | D29: 神社の大樹、古い寺の境内 | E29: 蝉識は、その姿から「昆虫界の賢者」と称される妖怪である。 長年を生き抜いたかのような深い皺を刻んだ外殻、伸びた触角、鋭い眼光。 その佇まいには重厚な風格があり、鳴き声はどこか悟りを開いた僧の読経のようにも聞こえる。 悠然と枝に留まり、若いセミたちの会話を見守るその姿は、まさしく森の賢者そのものだ。 しかし――何のことはない。 蝉識の寿命は、普通のセミと変わらず地上に出てから1週間に過ぎない。 長老然とした風格を持つが故に、異性にはまったくモテず、敬遠されることも多い。 それでも本人は「見た目ではなく、内面が成熟しすぎているせいで周囲と釣り合わないだけ」と本気で思っており、むしろ「この風格にふさわしい相手がいないのが問題」とすら考えている。 鳴き声も、まるでオタク特有の早口のようにまくし立てる。 そして、短い夏の夜を過ごし、ある日静かに森の土へと還るのだった。 | F29: ="【名】" & B29 & C29 &char(10) & "【番】" & text(A29,"0000") & char(10) &"【出現】"&D29& char(10)&"【特質】"& char(10)&E29&char(10)&char(10)&memo!$B$1 -> 【名】蝉識（せんしき）senshiki 【番】0027 【出現】神社の大樹、古い寺の境内 【特質】 蝉識は、その姿から「昆虫界の賢者」と称される妖怪である。 長年を生き抜いたかのような深い皺を刻んだ外殻、伸びた触角、鋭い眼光。 その佇まいには重厚な風格があり、鳴き声はどこか悟りを開いた僧の読経のようにも聞こえる。 悠然と枝に留まり、若いセミたちの会話を見守るその姿は、まさしく森の賢者そのものだ。 しかし――何のことはない。 蝉識の寿命は、普通のセミと変わらず地上に出てから1週間に過ぎない。 長老然とした風格を持つが故に、異性にはまったくモテず、敬遠されることも多い。 それでも本人は「見た目ではなく、内面が成熟しすぎているせいで周囲と釣り合わないだけ」と本気で思っており、むしろ「この風格にふさわしい相手がいないのが問題」とすら考えている。 鳴き声も、まるでオタク特有の早口のようにまくし立てる。 そして、短い夏の夜を過ごし、ある日静かに森の土へと還るのだった。 #妖怪 #yokai #sumie #monster #ghost | G29: 45701 | H29: 45720 | I29: ○ | L29: =len(E29) -> 388 | N29: =mid(F29,1,find("【特質】",F29)-1) &char(10)&memo!$B$2 -> 【名】蝉識（せんしき）senshiki 【番】0027 【出現】神社の大樹、古い寺の境内 #妖怪 #お化け #怪物 #オリジナル妖怪 #monster #ghost #妖怪好き #浮世絵 #百鬼夜行 | O29: =len(N29) -> 100 | P29: 【特質】蝉識は、その姿から「昆虫界の賢者」と称される妖怪である。 長年を生き抜いたかのような深い皺を刻んだ外殻、伸びた触角、鋭い眼光。 その佇まいには重厚な風格があり、鳴き声はどこか悟りを開いた僧の読経のようにも聞こえる。 | Q29: =len(P29) -> 111 | R29: 悠然と枝に留まり、若いセミたちの会話を見守るその姿は、まさしく森の賢者そのものだ。 しかし――何のことはない。 蝉識の寿命は、普通のセミと変わらず地上に出てから1週間に過ぎない。 | S29: =len(R29) -> 90 | T29: =len(W29) -> 125 | U29: 鳴き声も、まるでオタク特有の早口のようにまくし立てる。 そして、短い夏の夜を過ごし、ある日静かに森の土へと還るのだった。 | V29: =len(U29) -> 61 | W29: 長老然とした風格を持つが故に、異性にはまったくモテず、敬遠されることも多い。 それでも本人は「見た目ではなく、内面が成熟しすぎているせいで周囲と釣り合わないだけ」と本気で思っており、むしろ「この風格にふさわしい相手がいないのが問題」とすら考えている。 | Y29: =len(X29) -> 0 | AA29: =len(Z29) -> 0 | AC29: =len(AB29) -> 0
A30: 28 | B30: 半面恐師（はんめんきょうし） | C30: hammenkyoshi | D30: 一般的な学び舎 | E30: 普段は穏やかな教師の顔をしているが、右側から見れば普通の教師、左側から見れば不気味な仮面をつけた妖怪へと変貌する。 授業中は決して左半身を見せることなく、慎重に振る舞っている。 しかし、もしチョークを落としてしまい、それを拾おうと不用意に動けば、左側の仮面があらわになる。 その瞬間、教師の内に潜む妖怪の本性が目覚め、誰も彼を止めることはできなくなる。 容赦なく生徒を捕らえ、締め技をかける。 いわゆる チョークスリーパーである。 しかし、半面恐師の恐怖はこれだけではない。 ある日、給食の時間にフォークを落とした瞬間、彼の様子が変わった。 次の瞬間、突如として歌い出したのだ。 何の前触れもなく、理屈も関係なく、ただ本能のままに歌う。 その様子はあまりにも異様であり、誰も止めることができなかった。 いわゆるフォークソングである。 生徒たちは、恐れと困惑を持って受け入れるしかなかった。 そして、心に誓う。 「こんな大人にはなりたくない」と。 | F30: ="【名】" & B30 & C30 &char(10) & "【番】" & text(A30,"0000") & char(10) &"【出現】"&D30& char(10)&"【特質】"& char(10)&E30&char(10)&char(10)&memo!$B$1 -> 【名】半面恐師（はんめんきょうし）hammenkyoshi 【番】0028 【出現】一般的な学び舎 【特質】 普段は穏やかな教師の顔をしているが、右側から見れば普通の教師、左側から見れば不気味な仮面をつけた妖怪へと変貌する。 授業中は決して左半身を見せることなく、慎重に振る舞っている。 しかし、もしチョークを落としてしまい、それを拾おうと不用意に動けば、左側の仮面があらわになる。 その瞬間、教師の内に潜む妖怪の本性が目覚め、誰も彼を止めることはできなくなる。 容赦なく生徒を捕らえ、締め技をかける。 いわゆる チョークスリーパーである。 しかし、半面恐師の恐怖はこれだけではない。 ある日、給食の時間にフォークを落とした瞬間、彼の様子が変わった。 次の瞬間、突如として歌い出したのだ。 何の前触れもなく、理屈も関係なく、ただ本能のままに歌う。 その様子はあまりにも異様であり、誰も止めることができなかった。 いわゆるフォークソングである。 生徒たちは、恐れと困惑を持って受け入れるしかなかった。 そして、心に誓う。 「こんな大人にはなりたくない」と。 #妖怪 #yokai #sumie #monster #ghost | G30: 45701 | H30: 45721 | I30: ○ | L30: =len(E30) -> 429 | N30: =mid(F30,1,find("【特質】",F30)-1) &char(10)&memo!$B$2 -> 【名】半面恐師（はんめんきょうし）hammenkyoshi 【番】0028 【出現】一般的な学び舎 #妖怪 #お化け #怪物 #オリジナル妖怪 #monster #ghost #妖怪好き #浮世絵 #百鬼夜行 | O30: =len(N30) -> 105 | P30: 【特質】普段は穏やかな教師の顔をしているが、右側から見れば普通の教師、左側から見れば不気味な仮面をつけた妖怪へと変貌する。 授業中は決して左半身を見せることなく、慎重に振る舞っている。 しかし、もしチョークを落としてしまい、それを拾おうと不用意に動けば、左側の仮面があらわになる | Q30: =len(P30) -> 140 | R30: その瞬間、教師の内に潜む妖怪の本性が目覚め、誰も彼を止めることはできなくなる。 容赦なく生徒を捕らえ、締め技をかける。 いわゆる チョークスリーパーである。 しかし、半面恐師の恐怖はこれだけではない。 | S30: =len(R30) -> 102 | T30: =len(W30) -> 129 | U30: 生徒たちは、恐れと困惑を持って受け入れるしかなかった。 そして、心に誓う。 「こんな大人にはなりたくない」と。 | V30: =len(U30) -> 56 | W30: ある日、給食の時間にフォークを落とした瞬間、彼の様子が変わった。 次の瞬間、突如として歌い出したのだ。 何の前触れもなく、理屈も関係なく、ただ本能のままに歌う。 その様子はあまりにも異様であり、誰も止めることができなかった。 いわゆるフォークソングである。 | Y30: =len(X30) -> 0 | AA30: =len(Z30) -> 0 | AC30: =len(AB30) -> 0
A31: 29 | B31: 念耳幽駿（ねんじゆうしゅん） | C31: nenjiyushun | D31: かつて学問や信仰が栄えた村の跡地 | E31: 「馬の耳に念仏」と人々に嘲笑されながらも、ただ黙って言葉を聞き続けたその馬は、やがて不思議な力を得て妖怪へと変化した。 それが念耳幽駿である。 この妖怪の耳は、ただ音を聞くだけではない。 聞いた言葉をすべて記録し、整理し、書き出す力を持つ。 話しかけられた内容を記憶するだけでなく、それを的確に要約し、時には意味を補完して、より分かりやすく書き換えることもできた。 過去の書物を読み聞かせれば、古い言葉を今の時代に適した形で書き起こすことも可能であった。 ある村では、この力を活かし、村人たちは「念耳幽駿」に経典や物語を語り聞かせ、それを記録してもらった。 彼の書いた書物は村の財産となり、次第に村は知識の集積地として発展していった。 「念耳幽駿」は村の長老のような存在となり、誰もがその言葉を頼りにするようになった。 しかし、この村の繁栄は「念耳幽駿」に依存しすぎていた。 長年、村の記録を支えてきた彼が寿命を迎え、その身体が朽ち果てると同時に、彼が書き記していた書物もすべて塵と化してしまった。 村人たちは自ら学び、記録する習慣を失っており、知識を失った村は急速に衰退し、やがて滅んでしまった。 今では、その村の名を知る者はほとんどいない。 しかし、ときおり、どこかで馬の耳に向かって何かを語りかける者の姿が目撃されるという。 それは、かつて栄えた村の子孫たちなのかもしれない。 彼らは失われた知識と村の記憶を取り戻すため、「念耳幽駿」の幻影を探し続けているのだろう。 もし、霧の中で蹄の音が響き、風に乗って古びた経文が聞こえてきたなら、それは「念耳幽駿」が今もどこかで言葉を聞き続け、記録しようとしている証なのかもしれない。 | F31: ="【名】" & B31 & C31 &char(10) & "【番】" & text(A31,"0000") & char(10) &"【出現】"&D31& char(10)&"【特質】"& char(10)&E31&char(10)&char(10)&memo!$B$1 -> 【名】念耳幽駿（ねんじゆうしゅん）nenjiyushun 【番】0029 【出現】かつて学問や信仰が栄えた村の跡地 【特質】 「馬の耳に念仏」と人々に嘲笑されながらも、ただ黙って言葉を聞き続けたその馬は、やがて不思議な力を得て妖怪へと変化した。 それが念耳幽駿である。 この妖怪の耳は、ただ音を聞くだけではない。 聞いた言葉をすべて記録し、整理し、書き出す力を持つ。 話しかけられた内容を記憶するだけでなく、それを的確に要約し、時には意味を補完して、より分かりやすく書き換えることもできた。 過去の書物を読み聞かせれば、古い言葉を今の時代に適した形で書き起こすことも可能であった。 ある村では、この力を活かし、村人たちは「念耳幽駿」に経典や物語を語り聞かせ、それを記録してもらった。 彼の書いた書物は村の財産となり、次第に村は知識の集積地として発展していった。 「念耳幽駿」は村の長老のような存在となり、誰もがその言葉を頼りにするようになった。 しかし、この村の繁栄は「念耳幽駿」に依存しすぎていた。 長年、村の記録を支えてきた彼が寿命を迎え、その身体が朽ち果てると同時に、彼が書き記していた書物もすべて塵と化してしまった。 村人たちは自ら学び、記録する習慣を失っており、知識を失った村は急速に衰退し、やがて滅んでしまった。 今では、その村の名を知る者はほとんどいない。 しかし、ときおり、どこかで馬の耳に向かって何かを語りかける者の姿が目撃されるという。 それは、かつて栄えた村の子孫たちなのかもしれない。 彼らは失われた知識と村の記憶を取り戻すため、「念耳幽駿」の幻影を探し続けているのだろう。 もし、霧の中で蹄の音が響き、風に乗って古びた経文が聞こえてきたなら、それは「念耳幽駿」が今もどこかで言葉を聞き続け、記録しようとしている証なのかもしれない。 #妖怪 #yokai #sumie #monster #ghost | G31: 45700 | H31: 45722 | I31: ○ | L31: =len(E31) -> 720 | N31: =mid(F31,1,find("【特質】",F31)-1) &char(10)&memo!$B$2 -> 【名】念耳幽駿（ねんじゆうしゅん）nenjiyushun 【番】0029 【出現】かつて学問や信仰が栄えた村の跡地 #妖怪 #お化け #怪物 #オリジナル妖怪 #monster #ghost #妖怪好き #浮世絵 #百鬼夜行 | O31: =len(N31) -> 113 | P31: 【特質】「馬の耳に念仏」と人々に嘲笑されながらも、ただ黙って言葉を聞き続けたその馬は、やがて不思議な力を得て妖怪へと変化した。 それが念耳幽駿である。 この妖怪の耳は、ただ音を聞くだけではない。 聞いた言葉をすべて記録し、整理し、書き出す力を持つ。 | Q31: =len(P31) -> 125 | R31: 話しかけられた内容を記憶するだけでなく、それを的確に要約し、時には意味を補完して、より分かりやすく書き換えることもできた。 過去の書物を読み聞かせれば、古い言葉を今の時代に適した形で書き起こすことも可能であった。 | S31: =len(R31) -> 106 | T31: =len(W31) -> 131 | U31: しかし、この村の繁栄は「念耳幽駿」に依存しすぎていた。 長年、村の記録を支えてきた彼が寿命を迎え、その身体が朽ち果てると同時に、彼が書き記していた書物もすべて塵と化してしまった。 村人たちは自ら学び、記録する習慣を失っており、知識を失った村は急速に衰退し、やがて滅んでしまった。 | V31: =len(U31) -> 139 | W31: ある村では、この力を活かし、村人たちは「念耳幽駿」に経典や物語を語り聞かせ、それを記録してもらった。 彼の書いた書物は村の財産となり、次第に村は知識の集積地として発展していった。 「念耳幽駿」は村の長老のような存在となり、誰もがその言葉を頼りにするようになった。 | X31: 今では、その村の名を知る者はほとんどいない。 しかし、ときおり、どこかで馬の耳に向かって何かを語りかける者の姿が目撃されるという。 それは、かつて栄えた村の子孫たちなのかもしれない。 彼らは失われた知識と村の記憶を取り戻すため、「念耳幽駿」の幻影を探し続けているのだろう。 | Y31: =len(X31) -> 136 | Z31: もし、霧の中で蹄の音が響き、風に乗って古びた経文が聞こえてきたなら、それは「念耳幽駿」が今もどこかで言葉を聞き続け、記録しようとしている証なのかもしれない。 | AA31: =len(Z31) -> 78 | AC31: =len(AB31) -> 0
A32: 30 | B32: 幽蟲婆（ゆうちゅうば） | C32: yuchuba | D32: 古い寺院の蔵や土蔵の奥深く、長い間使われていない茶室 | E32: 彼女の名は幽蟲婆。 ひっそりと現れては、どこからともなく品を取り出し、品良く紹介する。 その独特な話しぶりに惹きつけられた若者たちは、競うように彼女の勧める品を買い求めた。 幽蟲婆が紹介する品は、たちまち人気を博し、瞬く間に売り切れる。 しかし、やがて奇妙な評判が広がり始めた。 幽蟲婆から購入した品々は、どれも粗悪なものばかりだったという。 塗りが甘く、すぐに剥がれる漆器。 茶を注ぐと妙な匂いを発する急須。 飲み口が歪み、唇を切りそうな茶碗。 「幽蟲婆の品は呪われているのではないか？」 「いや、彼女はただの詐欺師だ」 不信感を抱く者たちが、次第に増えていった。 しかし、幽蟲婆はそんな評判など意にも介さず、いつものように静かに、優雅に茶器を掲げ続けた。 彼女の手元に目を向けた者だけが、ある異様なことに気づく。 異常なほど美しい手。 長く整った指先。 艶やかなネイル。 それは、まるで生きているかのように、微かに蠢いているようにさえ見えた。 「あれこそが、本当に彼女が見せたい商品なのでは？」 そんな噂が立ち始めたある日、幽蟲婆は忽然と姿を消した。 以来、彼女が紹介した品はどれも霧散するように朽ち果て、人々の記憶からも徐々に薄れていった。 しかし、たまにどこかの骨董市で、幽蟲婆の品が見つかることがあるという。 その品を手に取ると、どこからともなくかすかな囁きが聞こえる。 「この爪、美しいでしょう？」 | F32: ="【名】" & B32 & C32 &char(10) & "【番】" & text(A32,"0000") & char(10) &"【出現】"&D32& char(10)&"【特質】"& char(10)&E32&char(10)&char(10)&memo!$B$1 -> 【名】幽蟲婆（ゆうちゅうば）yuchuba 【番】0030 【出現】古い寺院の蔵や土蔵の奥深く、長い間使われていない茶室 【特質】 彼女の名は幽蟲婆。 ひっそりと現れては、どこからともなく品を取り出し、品良く紹介する。 その独特な話しぶりに惹きつけられた若者たちは、競うように彼女の勧める品を買い求めた。 幽蟲婆が紹介する品は、たちまち人気を博し、瞬く間に売り切れる。 しかし、やがて奇妙な評判が広がり始めた。 幽蟲婆から購入した品々は、どれも粗悪なものばかりだったという。 塗りが甘く、すぐに剥がれる漆器。 茶を注ぐと妙な匂いを発する急須。 飲み口が歪み、唇を切りそうな茶碗。 「幽蟲婆の品は呪われているのではないか？」 「いや、彼女はただの詐欺師だ」 不信感を抱く者たちが、次第に増えていった。 しかし、幽蟲婆はそんな評判など意にも介さず、いつものように静かに、優雅に茶器を掲げ続けた。 彼女の手元に目を向けた者だけが、ある異様なことに気づく。 異常なほど美しい手。 長く整った指先。 艶やかなネイル。 それは、まるで生きているかのように、微かに蠢いているようにさえ見えた。 「あれこそが、本当に彼女が見せたい商品なのでは？」 そんな噂が立ち始めたある日、幽蟲婆は忽然と姿を消した。 以来、彼女が紹介した品はどれも霧散するように朽ち果て、人々の記憶からも徐々に薄れていった。 しかし、たまにどこかの骨董市で、幽蟲婆の品が見つかることがあるという。 その品を手に取ると、どこからともなくかすかな囁きが聞こえる。 「この爪、美しいでしょう？」 #妖怪 #yokai #sumie #monster #ghost | G32: 45699 | H32: 45723 | I32: ○ | L32: =len(E32) -> 614 | N32: =mid(F32,1,find("【特質】",F32)-1) &char(10)&memo!$B$2 -> 【名】幽蟲婆（ゆうちゅうば）yuchuba 【番】0030 【出現】古い寺院の蔵や土蔵の奥深く、長い間使われていない茶室 #妖怪 #お化け #怪物 #オリジナル妖怪 #monster #ghost #妖怪好き #浮世絵 #百鬼夜行 | O32: =len(N32) -> 116 | P32: 【特質】彼女の名は幽蟲婆。 ひっそりと現れては、どこからともなく品を取り出し、品良く紹介する。 その独特な話しぶりに惹きつけられた若者たちは、競うように彼女の勧める品を買い求めた。 幽蟲婆が紹介する品は、たちまち人気を博し、瞬く間に売り切れる。 | Q32: =len(P32) -> 122 | R32: しかし、やがて奇妙な評判が広がり始めた。 幽蟲婆から購入した品々は、どれも粗悪なものばかりだったという。 塗りが甘く、すぐに剥がれる漆器。 茶を注ぐと妙な匂いを発する急須。 飲み口が歪み、唇を切りそうな茶碗。 | S32: =len(R32) -> 104 | T32: =len(W32) -> 136 | U32: 異常なほど美しい手。 長く整った指先。 艶やかなネイル。 それは、まるで生きているかのように、微かに蠢いているようにさえ見えた。 「あれこそが、本当に彼女が見せたい商品なのでは？」 そんな噂が立ち始めたある日、幽蟲婆は忽然と姿を消した。 | V32: =len(U32) -> 120 | W32: 「幽蟲婆の品は呪われているのではないか？」 「いや、彼女はただの詐欺師だ」 不信感を抱く者たちが、次第に増えていった。 しかし、幽蟲婆はそんな評判など意にも介さず、いつものように静かに、優雅に茶器を掲げ続けた。 彼女の手元に目を向けた者だけが、ある異様なことに気づく。 | X32: 以来、彼女が紹介した品はどれも霧散するように朽ち果て、人々の記憶からも徐々に薄れていった。 しかし、たまにどこかの骨董市で、幽蟲婆の品が見つかることがあるという。 その品を手に取ると、どこからともなくかすかな囁きが聞こえる。 「この爪、美しいでしょう？」 | Y32: =len(X32) -> 129 | AA32: =len(Z32) -> 0 | AC32: =len(AB32) -> 0
A33: 31 | B33: 天真童（てんしんどう） | C33: tenshindo | D33: 広大な平野が広がる農村地帯 | E33: ただただ巨大な妖怪。 「北海道よりでっかい童」とも呼ばれる。 普段は何をするでもなく、ただ座っているだけ。 しかし、そのあまりの大きさゆえ、天真童の影が広大な土地を覆い尽くし、日光が届かなくなった地域では米作りが不可能になってしまう。 無邪気な性格で遊びたがるが、その規模があまりにも危険。 鬼ごっこをすれば村が消え、 ボール遊びをすれば地形が変わり、 メンコをすれば大地が裂ける。 唯一の対処法はスイカ割り。 村とは反対方向にスイカを置き、誘い出すことで被害を避けることができる。 ただし、並のスイカでは興味を示さず、よほど美味なものでなければ効果はない。 この地の人々は天真童に備え、スイカ作りの研究に明け暮れた。 そして、今ではスイカの名産地として名を馳せることとなった。 | F33: ="【名】" & B33 & C33 &char(10) & "【番】" & text(A33,"0000") & char(10) &"【出現】"&D33& char(10)&"【特質】"& char(10)&E33&char(10)&char(10)&memo!$B$1 -> 【名】天真童（てんしんどう）tenshindo 【番】0031 【出現】広大な平野が広がる農村地帯 【特質】 ただただ巨大な妖怪。 「北海道よりでっかい童」とも呼ばれる。 普段は何をするでもなく、ただ座っているだけ。 しかし、そのあまりの大きさゆえ、天真童の影が広大な土地を覆い尽くし、日光が届かなくなった地域では米作りが不可能になってしまう。 無邪気な性格で遊びたがるが、その規模があまりにも危険。 鬼ごっこをすれば村が消え、 ボール遊びをすれば地形が変わり、 メンコをすれば大地が裂ける。 唯一の対処法はスイカ割り。 村とは反対方向にスイカを置き、誘い出すことで被害を避けることができる。 ただし、並のスイカでは興味を示さず、よほど美味なものでなければ効果はない。 この地の人々は天真童に備え、スイカ作りの研究に明け暮れた。 そして、今ではスイカの名産地として名を馳せることとなった。 #妖怪 #yokai #sumie #monster #ghost | G33: 45701 | H33: 45724 | I33: ○ | L33: =len(E33) -> 343 | N33: =mid(F33,1,find("【特質】",F33)-1) &char(10)&memo!$B$2 -> 【名】天真童（てんしんどう）tenshindo 【番】0031 【出現】広大な平野が広がる農村地帯 #妖怪 #お化け #怪物 #オリジナル妖怪 #monster #ghost #妖怪好き #浮世絵 #百鬼夜行 | O33: =len(N33) -> 105 | P33: 【特質】ただただ巨大な妖怪。 「北海道よりでっかい童」とも呼ばれる。 普段は何をするでもなく、ただ座っているだけ。 しかし、そのあまりの大きさゆえ、天真童の影が広大な土地を覆い尽くし、日光が届かなくなった地域では米作りが不可能になってしまう。 | Q33: =len(P33) -> 122 | R33: 無邪気な性格で遊びたがるが、その規模があまりにも危険。 鬼ごっこをすれば村が消え、 ボール遊びをすれば地形が変わり、 メンコをすれば大地が裂ける。 唯一の対処法はスイカ割り。 | S33: =len(R33) -> 88 | T33: =len(W33) -> 134 | V33: =len(U33) -> 0 | W33: 村とは反対方向にスイカを置き、誘い出すことで被害を避けることができる。 ただし、並のスイカでは興味を示さず、よほど美味なものでなければ効果はない。 この地の人々は天真童に備え、スイカ作りの研究に明け暮れた。 そして、今ではスイカの名産地として名を馳せることとなった。 | Y33: =len(X33) -> 0 | AA33: =len(Z33) -> 0 | AC33: =len(AB33) -> 0
A34: 32 | B34: 貝任侠（かいにんきょう） | C34: kaininkyo | D34: 深海の海底都市、沈んだ漁村の跡、難破船の周辺 | E34: 海底の貝殻社会を裏で支配する妖怪。 ヤドカリたちの間では「ヤドカシ」とも呼ばれ、貝殻を必要とする者に「貸し」を作りながら勢力を広げている。 貝殻を必要とするヤドカリたちに「宿」を貸し与えるが、その見返りとして必ず何らかの対価を求める。 周囲には豪華な貝殻が積まれ、まるで海底の王宮のように見えるが、それらは全て彼が取り仕切る取引の道具に過ぎない。 貝任侠の手口は巧妙で、時に「貝殻師」として暗躍する。 ヤドカリが新たな宿を求めて貝任侠を訪れると、彼は煌びやかな貝殻を見せつけ、 「これは特別な貝でな、今すぐには渡せねぇ。まずは手付けがいる」と持ちかける。 契約を交わし対価を支払ったヤドカリが待ち続けても、用意されるのは価値のない貝殻や、既に他の者に貸し出された宿ばかり。 「書類には“相応しい貝殻を提供する”と書いてある。お前にぴったりの宿だろう？」と不敵に笑う姿は、まさに深海の策略家といえる。 時には、意図的にヤドカリに合わない貝を貸し付け「その貝の中でデカくなってみせろ」と試練を与えることもある。 試練を乗り越えた者には相応の宿を与え、配下として迎え入れるが、恩を忘れた者には容赦がなく、二度と貝を持てぬよう呪いをかけるとも言われている。 貝任侠は決してただの貝殻師ではなく、仁義を重んじる一面も持つ。 誠意を示した者や忠誠を誓った者には、最高級の貝殻を与えることもあり、深海の住人たちの中には彼を崇める者すらいる。 だが、彼の支配する世界では、貝殻ひとつ手にするのにも覚悟が必要だ。 貝を求める者と、それを操る者。 深海の闇の中、ヤドカシの影は今も広がり続けている。 | F34: ="【名】" & B34 & C34 &char(10) & "【番】" & text(A34,"0000") & char(10) &"【出現】"&D34& char(10)&"【特質】"& char(10)&E34&char(10)&char(10)&memo!$B$1 -> 【名】貝任侠（かいにんきょう）kaininkyo 【番】0032 【出現】深海の海底都市、沈んだ漁村の跡、難破船の周辺 【特質】 海底の貝殻社会を裏で支配する妖怪。 ヤドカリたちの間では「ヤドカシ」とも呼ばれ、貝殻を必要とする者に「貸し」を作りながら勢力を広げている。 貝殻を必要とするヤドカリたちに「宿」を貸し与えるが、その見返りとして必ず何らかの対価を求める。 周囲には豪華な貝殻が積まれ、まるで海底の王宮のように見えるが、それらは全て彼が取り仕切る取引の道具に過ぎない。 貝任侠の手口は巧妙で、時に「貝殻師」として暗躍する。 ヤドカリが新たな宿を求めて貝任侠を訪れると、彼は煌びやかな貝殻を見せつけ、 「これは特別な貝でな、今すぐには渡せねぇ。まずは手付けがいる」と持ちかける。 契約を交わし対価を支払ったヤドカリが待ち続けても、用意されるのは価値のない貝殻や、既に他の者に貸し出された宿ばかり。 「書類には“相応しい貝殻を提供する”と書いてある。お前にぴったりの宿だろう？」と不敵に笑う姿は、まさに深海の策略家といえる。 時には、意図的にヤドカリに合わない貝を貸し付け「その貝の中でデカくなってみせろ」と試練を与えることもある。 試練を乗り越えた者には相応の宿を与え、配下として迎え入れるが、恩を忘れた者には容赦がなく、二度と貝を持てぬよう呪いをかけるとも言われている。 貝任侠は決してただの貝殻師ではなく、仁義を重んじる一面も持つ。 誠意を示した者や忠誠を誓った者には、最高級の貝殻を与えることもあり、深海の住人たちの中には彼を崇める者すらいる。 だが、彼の支配する世界では、貝殻ひとつ手にするのにも覚悟が必要だ。 貝を求める者と、それを操る者。 深海の闇の中、ヤドカシの影は今も広がり続けている。 #妖怪 #yokai #sumie #monster #ghost | G34: 45701 | H34: 45725 | I34: ○ | L34: =len(E34) -> 696 | N34: =mid(F34,1,find("【特質】",F34)-1) &char(10)&memo!$B$2 -> 【名】貝任侠（かいにんきょう）kaininkyo 【番】0032 【出現】深海の海底都市、沈んだ漁村の跡、難破船の周辺 #妖怪 #お化け #怪物 #オリジナル妖怪 #monster #ghost #妖怪好き #浮世絵 #百鬼夜行 | O34: =len(N34) -> 115 | P34: 【特質】海底の貝殻社会を裏で支配する妖怪。 ヤドカリたちの間では「ヤドカシ」とも呼ばれ、貝殻を必要とする者に「貸し」を作りながら勢力を広げている。 貝殻を必要とするヤドカリたちに「宿」を貸し与えるが、その見返りとして必ず何らかの対価を求める。 | Q34: =len(P34) -> 124 | R34: 周囲には豪華な貝殻が積まれ、まるで海底の王宮のように見えるが、それらは全て彼が取り仕切る取引の道具に過ぎない。 貝任侠の手口は巧妙で、時に「貝殻師」として暗躍する。 ヤドカリが新たな宿を求めて貝任侠を訪れると、彼は煌びやかな貝殻を見せつけ、 | S34: =len(R34) -> 121 | T34: =len(W34) -> 138 | U34: と不敵に笑う姿は、まさに深海の策略家といえる。 時には、意図的にヤドカリに合わない貝を貸し付け「その貝の中でデカくなってみせろ」と試練を与えることもある。 | V34: =len(U34) -> 79 | W34: 「これは特別な貝でな、今すぐには渡せねぇ。まずは手付けがいる」と持ちかける。 契約を交わし対価を支払ったヤドカリが待ち続けても、用意されるのは価値のない貝殻や、既に他の者に貸し出された宿ばかり。 「書類には“相応しい貝殻を提供する”と書いてある。お前にぴったりの宿だろう？」 | X34: 試練を乗り越えた者には相応の宿を与え、配下として迎え入れるが、恩を忘れた者には容赦がなく、二度と貝を持てぬよう呪いをかけるとも言われている。 貝任侠は決してただの貝殻師ではなく、仁義を重んじる一面も持つ。 | Y34: =len(X34) -> 103 | Z34: 誠意を示した者や忠誠を誓った者には、最高級の貝殻を与えることもあり、深海の住人たちの中には彼を崇める者すらいる。 だが、彼の支配する世界では、貝殻ひとつ手にするのにも覚悟が必要だ。 貝を求める者と、それを操る者。 深海の闇の中、ヤドカシの影は今も広がり続けている。 | AA34: =len(Z34) -> 133 | AC34: =len(AB34) -> 0
A35: 33 | B35: 朽水ノ怨（くちみずのおん） | C35: kuchimizunon | D35: 干上がった湖、廃れた水源の跡地 | E35: 「天然水」という言葉に違和感を覚えないのは、現代の人間の業（ごう）なのだろうか。 かつて、この世の水はすべてが天然水であった。 しかし、今や「天然水」という名に価値が生まれることこそ、その水が枯渇しつつある証である。 朽水ノ怨は、かつて清らかな水を湛えていた泉や川が、人々の乱用や自然の変化によって枯れ果てたとき、その地に残された水の記憶が怨念となり生まれた妖怪である。 その身体は、ひび割れた土とわずかに残る湿気でできており、かつて流れていた水の名残がかすかに漂う。 滴り落ちる一滴の水が、彼の悲しみと怒りを物語っている。 口から発せられる声は、まるで干上がる川の底から響く呻きのようで、それを聞いた者は喉の渇きを覚え、やがて、どれだけ水を飲んでも潤わぬ飢えに苦しむという。 特に夜、月明かりの下では、かつて水が満ちていた頃の姿が幻のように映し出される。 その光景に引き寄せられた者は、乾いた大地を彷徨い続け、やがて朽水ノ怨と同じく「永遠に潤わぬ者」となると伝えられている。 「天然水」という言葉が消え去るのは、人類が滅びた後のことなのだろうか。 | F35: ="【名】" & B35 & C35 &char(10) & "【番】" & text(A35,"0000") & char(10) &"【出現】"&D35& char(10)&"【特質】"& char(10)&E35&char(10)&char(10)&memo!$B$1 -> 【名】朽水ノ怨（くちみずのおん）kuchimizunon 【番】0033 【出現】干上がった湖、廃れた水源の跡地 【特質】 「天然水」という言葉に違和感を覚えないのは、現代の人間の業（ごう）なのだろうか。 かつて、この世の水はすべてが天然水であった。 しかし、今や「天然水」という名に価値が生まれることこそ、その水が枯渇しつつある証である。 朽水ノ怨は、かつて清らかな水を湛えていた泉や川が、人々の乱用や自然の変化によって枯れ果てたとき、その地に残された水の記憶が怨念となり生まれた妖怪である。 その身体は、ひび割れた土とわずかに残る湿気でできており、かつて流れていた水の名残がかすかに漂う。 滴り落ちる一滴の水が、彼の悲しみと怒りを物語っている。 口から発せられる声は、まるで干上がる川の底から響く呻きのようで、それを聞いた者は喉の渇きを覚え、やがて、どれだけ水を飲んでも潤わぬ飢えに苦しむという。 特に夜、月明かりの下では、かつて水が満ちていた頃の姿が幻のように映し出される。 その光景に引き寄せられた者は、乾いた大地を彷徨い続け、やがて朽水ノ怨と同じく「永遠に潤わぬ者」となると伝えられている。 「天然水」という言葉が消え去るのは、人類が滅びた後のことなのだろうか。 #妖怪 #yokai #sumie #monster #ghost | G35: 45702 | H35: 45726 | I35: ○ | L35: =len(E35) -> 480 | N35: =mid(F35,1,find("【特質】",F35)-1) &char(10)&memo!$B$2 -> 【名】朽水ノ怨（くちみずのおん）kuchimizunon 【番】0033 【出現】干上がった湖、廃れた水源の跡地 #妖怪 #お化け #怪物 #オリジナル妖怪 #monster #ghost #妖怪好き #浮世絵 #百鬼夜行 | O35: =len(N35) -> 112 | P35: 【特質】「天然水」という言葉に違和感を覚えないのは、現代の人間の業（ごう）なのだろうか。 かつて、この世の水はすべてが天然水であった。 しかし、今や「天然水」という名に価値が生まれることこそ、その水が枯渇しつつある証である。 | Q35: =len(P35) -> 113 | R35: 朽水ノ怨は、かつて清らかな水を湛えていた泉や川が、人々の乱用や自然の変化によって枯れ果てたとき、その地に残された水の記憶が怨念となり生まれた妖怪である。 その身体は、ひび割れた土とわずかに残る湿気でできており、かつて流れていた水の名残がかすかに漂う。 | S35: =len(R35) -> 126 | T35: =len(W35) -> 104 | U35: 特に夜、月明かりの下では、かつて水が満ちていた頃の姿が幻のように映し出される。 その光景に引き寄せられた者は、乾いた大地を彷徨い続け、やがて朽水ノ怨と同じく「永遠に潤わぬ者」となると伝えられている。 「天然水」という言葉が消え去るのは、人類が滅びた後のことなのだろうか。 | V35: =len(U35) -> 136 | W35: 滴り落ちる一滴の水が、彼の悲しみと怒りを物語っている。 口から発せられる声は、まるで干上がる川の底から響く呻きのようで、それを聞いた者は喉の渇きを覚え、やがて、どれだけ水を飲んでも潤わぬ飢えに苦しむという。 | Y35: =len(X35) -> 0 | AA35: =len(Z35) -> 0 | AC35: =len(AB35) -> 0
A36: 34 | B36: 映画泥坊（えいがどろぼう） | C36: eigadorobo | D36: 映画館、映写室、旧式の映写機が眠る倉庫 | E36: 映画泥坊（えいがどろぼう）は、映画館に現れる妖怪で、上映中の映画をこっそり盗み撮る悪しき存在。 影のような体を持ち、館内の暗闇に紛れるのが得意で、誰にも気づかれぬうちに忍び寄り、長く伸びた指先で怪しげなレンズをかざし、映像を奪い取る。 時折、「カシャ…カシャ…」と小さなシャッター音を響かせるが、映写機の回転音に紛れてしまい、発見するのは困難だった。 映画泥坊が盗み撮ると、なぜかフィルムが不気味にうねり出し、映像は歪み、使い物にならなくなる。 映画館の商売はあがったりだ。 さらに、映画泥坊が盗んだ映像は奇妙に歪み、元の作品とは異なる呪われた映像となる。 盗撮された映画を見た者は、画面の中に自分の影が映り込むようになり、やがて映画泥坊の世界へと引き込まれてしまうという。 映画館の経営は立ち行かなくなり、人々も娯楽を奪われて困っている。 しかし、映画泥坊の巧妙な手口に対して有効な対策はなく、誰もが打つ手を失っているのが現状だ。 そんな中、人々は 映画岡引（えいがおかっぴき） の登場を待ちわびている。 | F36: ="【名】" & B36 & C36 &char(10) & "【番】" & text(A36,"0000") & char(10) &"【出現】"&D36& char(10)&"【特質】"& char(10)&E36&char(10)&char(10)& "#銀幕幻影物語 " &memo!$B$1 -> 【名】映画泥坊（えいがどろぼう）eigadorobo 【番】0034 【出現】映画館、映写室、旧式の映写機が眠る倉庫 【特質】 映画泥坊（えいがどろぼう）は、映画館に現れる妖怪で、上映中の映画をこっそり盗み撮る悪しき存在。 影のような体を持ち、館内の暗闇に紛れるのが得意で、誰にも気づかれぬうちに忍び寄り、長く伸びた指先で怪しげなレンズをかざし、映像を奪い取る。 時折、「カシャ…カシャ…」と小さなシャッター音を響かせるが、映写機の回転音に紛れてしまい、発見するのは困難だった。 映画泥坊が盗み撮ると、なぜかフィルムが不気味にうねり出し、映像は歪み、使い物にならなくなる。 映画館の商売はあがったりだ。 さらに、映画泥坊が盗んだ映像は奇妙に歪み、元の作品とは異なる呪われた映像となる。 盗撮された映画を見た者は、画面の中に自分の影が映り込むようになり、やがて映画泥坊の世界へと引き込まれてしまうという。 映画館の経営は立ち行かなくなり、人々も娯楽を奪われて困っている。 しかし、映画泥坊の巧妙な手口に対して有効な対策はなく、誰もが打つ手を失っているのが現状だ。 そんな中、人々は 映画岡引（えいがおかっぴき） の登場を待ちわびている。 #銀幕幻影物語 #妖怪 #yokai #sumie #monster #ghost | G36: 45703 | H36: 45727 | I36: ○ | L36: =len(E36) -> 457 | N36: =mid(F36,1,find("【特質】",F36)-1) &char(10)& "#銀幕幻影物語 " &memo!$B$2 -> 【名】映画泥坊（えいがどろぼう）eigadorobo 【番】0034 【出現】映画館、映写室、旧式の映写機が眠る倉庫 #銀幕幻影物語 #妖怪 #お化け #怪物 #オリジナル妖怪 #monster #ghost #妖怪好き #浮世絵 #百鬼夜行 | O36: =len(N36) -> 122 | P36: 【特質】映画泥坊（えいがどろぼう）は、映画館に現れる妖怪で、上映中の映画をこっそり盗み撮る悪しき存在。 影のような体を持ち、館内の暗闇に紛れるのが得意で、誰にも気づかれぬうちに忍び寄り、長く伸びた指先で怪しげなレンズをかざし、映像を奪い取る。 | Q36: =len(P36) -> 121 | R36: 時折、「カシャ…カシャ…」と小さなシャッター音を響かせるが、映写機の回転音に紛れてしまい、発見するのは困難だった。 映画泥坊が盗み撮ると、なぜかフィルムが不気味にうねり出し、映像は歪み、使い物にならなくなる。 映画館の商売はあがったりだ。 | S36: =len(R36) -> 119 | T36: =len(W36) -> 99 | U36: 映画館の経営は立ち行かなくなり、人々も娯楽を奪われて困っている。 しかし、映画泥坊の巧妙な手口に対して有効な対策はなく、誰もが打つ手を失っているのが現状だ。 そんな中、人々は 映画岡引（えいがおかっぴき） の登場を待ちわびている。 | V36: =len(U36) -> 115 | W36: さらに、映画泥坊が盗んだ映像は奇妙に歪み、元の作品とは異なる呪われた映像となる。 盗撮された映画を見た者は、画面の中に自分の影が映り込むようになり、やがて映画泥坊の世界へと引き込まれてしまうという。 | Y36: =len(X36) -> 0 | AA36: =len(Z36) -> 0 | AC36: =len(AB36) -> 0
A37: 35 | B37: 冴無者（さえなし） | C37: saenashi | D37: 幕末から明治時代の藩校（はんこう）、私塾、学問所 | E37: 冴無者は、新しい時代に適応しようと必死になったものの、すべてが空回りしてしまった学徒が妖怪と化した存在である。 武士の身分を捨て学問の道を選んだが、髪型をどうすればよいか分からず、ちょんまげを半端に切り落としたまま放置。 さらに流行の洋髪を真似ようとした結果、後ろ髪だけが妙に長く伸び、奇妙な跳ね方をしている。 服装もまたちぐはぐで、和服の上に無理やり洋装を取り入れた結果、丈の合わないシャツを羽織り、借り物の洋靴を片方だけ履いたまま歩いている。 その姿はどこから見ても不格好だが、本人だけは「これが時代の最先端の装いだ」と信じて疑わない。 彼は常に「己こそが新時代の知識人」と誇示したがるが、話す言葉はどこか滑稽で、西洋かぶれを装いながらも攘夷派の前では意見を変え、どの派閥にも受け入れられず孤立する。 学び舎の廊下の隅や寄宿舎の陰にひっそりと立ち、英和辞典を手にしながらも、そのページを逆さに持っていることにすら気づかない。 誰かが話しかけると、急に早口になり、外国人の言葉を真似たつもりの奇妙な発音でまくし立てるが、その場の空気をさらに微妙にするだけである。 除霊方法はただ一つ、「無理にカッコつけなくてもよい」と気づかせること。 しかし、真正面からそれを指摘すると、「余は間違ってなどいない！」と赤面しながら姿を消してしまうため慎重を要する。 冴無者は、文明開化の波に翻弄されながらも、「変わらなければならない」という焦燥に取り憑かれた妖怪である。 学ぶ者たちの間では、「夜更けの廊下の隅に、一人浮かない顔で立ち尽くす男を見たら、目を合わせてはならない」と、ひそかに語り継がれている。 | F37: ="【名】" & B37 & C37 &char(10) & "【番】" & text(A37,"0000") & char(10) &"【出現】"&D37& char(10)&"【特質】"& char(10)&E37&char(10)&char(10)&memo!$B$1 -> 【名】冴無者（さえなし）saenashi 【番】0035 【出現】幕末から明治時代の藩校（はんこう）、私塾、学問所 【特質】 冴無者は、新しい時代に適応しようと必死になったものの、すべてが空回りしてしまった学徒が妖怪と化した存在である。 武士の身分を捨て学問の道を選んだが、髪型をどうすればよいか分からず、ちょんまげを半端に切り落としたまま放置。 さらに流行の洋髪を真似ようとした結果、後ろ髪だけが妙に長く伸び、奇妙な跳ね方をしている。 服装もまたちぐはぐで、和服の上に無理やり洋装を取り入れた結果、丈の合わないシャツを羽織り、借り物の洋靴を片方だけ履いたまま歩いている。 その姿はどこから見ても不格好だが、本人だけは「これが時代の最先端の装いだ」と信じて疑わない。 彼は常に「己こそが新時代の知識人」と誇示したがるが、話す言葉はどこか滑稽で、西洋かぶれを装いながらも攘夷派の前では意見を変え、どの派閥にも受け入れられず孤立する。 学び舎の廊下の隅や寄宿舎の陰にひっそりと立ち、英和辞典を手にしながらも、そのページを逆さに持っていることにすら気づかない。 誰かが話しかけると、急に早口になり、外国人の言葉を真似たつもりの奇妙な発音でまくし立てるが、その場の空気をさらに微妙にするだけである。 除霊方法はただ一つ、「無理にカッコつけなくてもよい」と気づかせること。 しかし、真正面からそれを指摘すると、「余は間違ってなどいない！」と赤面しながら姿を消してしまうため慎重を要する。 冴無者は、文明開化の波に翻弄されながらも、「変わらなければならない」という焦燥に取り憑かれた妖怪である。 学ぶ者たちの間では、「夜更けの廊下の隅に、一人浮かない顔で立ち尽くす男を見たら、目を合わせてはならない」と、ひそかに語り継がれている。 #妖怪 #yokai #sumie #monster #ghost | G37: 45704 | H37: 45728 | I37: ○ | L37: =len(E37) -> 702 | N37: =mid(F37,1,find("【特質】",F37)-1) &char(10)&memo!$B$2 -> 【名】冴無者（さえなし）saenashi 【番】0035 【出現】幕末から明治時代の藩校（はんこう）、私塾、学問所 #妖怪 #お化け #怪物 #オリジナル妖怪 #monster #ghost #妖怪好き #浮世絵 #百鬼夜行 | O37: =len(N37) -> 113 | P37: 【特質】冴無者は、新しい時代に適応しようと必死になったものの、すべてが空回りしてしまった学徒が妖怪と化した存在である。 武士の身分を捨て学問の道を選んだが、髪型をどうすればよいか分からず、ちょんまげを半端に切り落としたまま放置。 | Q37: =len(P37) -> 115 | R37: さらに流行の洋髪を真似ようとした結果、後ろ髪だけが妙に長く伸び、奇妙な跳ね方をしている。 服装もまたちぐはぐで、和服の上に無理やり洋装を取り入れた結果、丈の合わないシャツを羽織り、借り物の洋靴を片方だけ履いたまま歩いている。 | S37: =len(R37) -> 113 | T37: =len(W37) -> 129 | U37: 学び舎の廊下の隅や寄宿舎の陰にひっそりと立ち、英和辞典を手にしながらも、そのページを逆さに持っていることにすら気づかない。 誰かが話しかけると、急に早口になり、外国人の言葉を真似たつもりの奇妙な発音でまくし立てるが、その場の空気をさらに微妙にするだけである。 | V37: =len(U37) -> 129 | W37: その姿はどこから見ても不格好だが、本人だけは「これが時代の最先端の装いだ」と信じて疑わない。 彼は常に「己こそが新時代の知識人」と誇示したがるが、話す言葉はどこか滑稽で、西洋かぶれを装いながらも攘夷派の前では意見を変え、どの派閥にも受け入れられず孤立する。 | X37: 除霊方法はただ一つ、「無理にカッコつけなくてもよい」と気づかせること。 しかし、真正面からそれを指摘すると、「余は間違ってなどいない！」と赤面しながら姿を消してしまうため慎重を要する。 | Y37: =len(X37) -> 92 | Z37: 冴無者は、文明開化の波に翻弄されながらも、「変わらなければならない」という焦燥に取り憑かれた妖怪である。 学ぶ者たちの間では、「夜更けの廊下の隅に、一人浮かない顔で立ち尽くす男を見たら、目を合わせてはならない」と、ひそかに語り継がれている。 | AA37: =len(Z37) -> 120 | AC37: =len(AB37) -> 0
A38: 36 | B38: 監視鬼（かんしき） | C38: kanshiki | D38: 寺子屋・学校・塾など学びの場 | E38: 監視鬼は、教師の代わりに生徒たちを監視する妖怪である。 全身には無数の眼がついており、宙に浮いて静かに学び舎を巡回する。 その眼は生徒一人ひとりを鋭く見つめ、怠ける者や居眠りをする者を決して見逃さない。 授業中にふざけたり、手を動かさずにぼんやりしていると、監視鬼がすっと背後に近づき、冷たい声で「聞け」「書け」と囁く。 その瞬間、妙な寒気に襲われ、背筋が凍るような感覚に陥るという。 しかし、どれほど警戒しても、その姿をはっきりと捉えられる者は少ない。 監視鬼の存在は教師にとって便利なものとされ、学び舎の秩序を保つのに一役買っていた。 しかし、「教師が生徒を直接監視する手間を省いているのはどうなのか」という反発の声もあったとされる。 教師の仕事を怠る口実にされることもあったため、一部の学び舎では監視鬼の召喚を禁じたという。 その後、時代が進むにつれ、監視鬼の伝説は変化し、技術の発展とともに「後のドローン監視システムのモチーフになった」と語られることもある。 学び舎を巡回し、上空から監視するその姿は、現代のドローンの機能と酷似しているとされる。 現在でも、誰もいないはずの教室で妙な視線を感じたり、静かな自習室で背後に気配を感じるのは、監視鬼が今もなお学びの場を巡回している証なのかもしれない。 | F38: ="【名】" & B38 & C38 &char(10) & "【番】" & text(A38,"0000") & char(10) &"【出現】"&D38& char(10)&"【特質】"& char(10)&E38&char(10)&char(10)&memo!$B$1 -> 【名】監視鬼（かんしき）kanshiki 【番】0036 【出現】寺子屋・学校・塾など学びの場 【特質】 監視鬼は、教師の代わりに生徒たちを監視する妖怪である。 全身には無数の眼がついており、宙に浮いて静かに学び舎を巡回する。 その眼は生徒一人ひとりを鋭く見つめ、怠ける者や居眠りをする者を決して見逃さない。 授業中にふざけたり、手を動かさずにぼんやりしていると、監視鬼がすっと背後に近づき、冷たい声で「聞け」「書け」と囁く。 その瞬間、妙な寒気に襲われ、背筋が凍るような感覚に陥るという。 しかし、どれほど警戒しても、その姿をはっきりと捉えられる者は少ない。 監視鬼の存在は教師にとって便利なものとされ、学び舎の秩序を保つのに一役買っていた。 しかし、「教師が生徒を直接監視する手間を省いているのはどうなのか」という反発の声もあったとされる。 教師の仕事を怠る口実にされることもあったため、一部の学び舎では監視鬼の召喚を禁じたという。 その後、時代が進むにつれ、監視鬼の伝説は変化し、技術の発展とともに「後のドローン監視システムのモチーフになった」と語られることもある。 学び舎を巡回し、上空から監視するその姿は、現代のドローンの機能と酷似しているとされる。 現在でも、誰もいないはずの教室で妙な視線を感じたり、静かな自習室で背後に気配を感じるのは、監視鬼が今もなお学びの場を巡回している証なのかもしれない。 #妖怪 #yokai #sumie #monster #ghost | G38: 45705 | H38: 45729 | I38: ○ | L38: =len(E38) -> 562 | N38: =mid(F38,1,find("【特質】",F38)-1) &char(10)&memo!$B$2 -> 【名】監視鬼（かんしき）kanshiki 【番】0036 【出現】寺子屋・学校・塾など学びの場 #妖怪 #お化け #怪物 #オリジナル妖怪 #monster #ghost #妖怪好き #浮世絵 #百鬼夜行 | O38: =len(N38) -> 103 | P38: 【特質】監視鬼は、教師の代わりに生徒たちを監視する妖怪である。 全身には無数の眼がついており、宙に浮いて静かに学び舎を巡回する。 その眼は生徒一人ひとりを鋭く見つめ、怠ける者や居眠りをする者を決して見逃さない。 | Q38: =len(P38) -> 107 | R38: 授業中にふざけたり、手を動かさずにぼんやりしていると、監視鬼がすっと背後に近づき、冷たい声で「聞け」「書け」と囁く。 その瞬間、妙な寒気に襲われ、背筋が凍るような感覚に陥るという。 しかし、どれほど警戒しても、その姿をはっきりと捉えられる者は少ない。 | S38: =len(R38) -> 127 | T38: =len(W38) -> 137 | U38: その後、時代が進むにつれ、監視鬼の伝説は変化し、技術の発展とともに「後のドローン監視システムのモチーフになった」と語られることもある。 学び舎を巡回し、上空から監視するその姿は、現代のドローンの機能と酷似しているとされる。 | V38: =len(U38) -> 113 | W38: 監視鬼の存在は教師にとって便利なものとされ、学び舎の秩序を保つのに一役買っていた。 しかし、「教師が生徒を直接監視する手間を省いているのはどうなのか」という反発の声もあったとされる。 教師の仕事を怠る口実にされることもあったため、一部の学び舎では監視鬼の召喚を禁じたという。 | X38: 現在でも、誰もいないはずの教室で妙な視線を感じたり、静かな自習室で背後に気配を感じるのは、監視鬼が今もなお学びの場を巡回している証なのかもしれない。 | Y38: =len(X38) -> 74 | AA38: =len(Z38) -> 0 | AC38: =len(AB38) -> 0
A39: 37 | B39: 雫目童（しずくめどう） | C39: shizukumedo | D39: 湿気の多い森や霧深い山間部 | E39: 雫目童は、新生児のような小さな体を持ち、顔の中央に巨大な一つ目がある妖怪。 その目からは常に粘度のある液体がヨダレのように垂れ続けているが、それは涙ではなく、妖怪特有の分泌液である。 この液体には奇妙な性質があり、触れた者の心に不可解な既視感を抱かせるとされる。 まるで過去の記憶の断片が揺らぎ、夢の中の出来事と現実の境が曖昧になるような感覚を引き起こすという。 雫目童は特に害を及ぼすわけではないが、人里離れた場所に佇み、じっとこちらを見つめることがある。 その姿を見た者は理由もなく懐かしさを感じることがあるが、それが何の記憶と結びついているのかは誰にも分からない。 昔の言い伝えでは、雫目童に「もう泣かなくてもいいよ」と優しく声をかけると、ふっと霧のように消えてしまうとされているが、そもそも彼は泣いているのではないのだ。 ただ、静かにこちらを見つめながら、流れ落ちる雫の向こうに何を想うのだろうか。 | F39: ="【名】" & B39 & C39 &char(10) & "【番】" & text(A39,"0000") & char(10) &"【出現】"&D39& char(10)&"【特質】"& char(10)&E39&char(10)&char(10)&memo!$B$1 -> 【名】雫目童（しずくめどう）shizukumedo 【番】0037 【出現】湿気の多い森や霧深い山間部 【特質】 雫目童は、新生児のような小さな体を持ち、顔の中央に巨大な一つ目がある妖怪。 その目からは常に粘度のある液体がヨダレのように垂れ続けているが、それは涙ではなく、妖怪特有の分泌液である。 この液体には奇妙な性質があり、触れた者の心に不可解な既視感を抱かせるとされる。 まるで過去の記憶の断片が揺らぎ、夢の中の出来事と現実の境が曖昧になるような感覚を引き起こすという。 雫目童は特に害を及ぼすわけではないが、人里離れた場所に佇み、じっとこちらを見つめることがある。 その姿を見た者は理由もなく懐かしさを感じることがあるが、それが何の記憶と結びついているのかは誰にも分からない。 昔の言い伝えでは、雫目童に「もう泣かなくてもいいよ」と優しく声をかけると、ふっと霧のように消えてしまうとされているが、そもそも彼は泣いているのではないのだ。 ただ、静かにこちらを見つめながら、流れ落ちる雫の向こうに何を想うのだろうか。 #妖怪 #yokai #sumie #monster #ghost | G39: 45706 | H39: 45730 | I39: ○ | L39: =len(E39) -> 407 | N39: =mid(F39,1,find("【特質】",F39)-1) &char(10)&"＜特質はリプ欄へ＞" & char(10)& memo!$B$2 -> 【名】雫目童（しずくめどう）shizukumedo 【番】0037 【出現】湿気の多い森や霧深い山間部 ＜特質はリプ欄へ＞ #妖怪 #お化け #怪物 #オリジナル妖怪 #monster #ghost #妖怪好き #浮世絵 #百鬼夜行 | O39: =len(N39) -> 117 | P39: 【特質】雫目童は、新生児のような小さな体を持ち、顔の中央に巨大な一つ目がある妖怪。 その目からは常に粘度のある液体がヨダレのように垂れ続けているが、それは涙ではなく、妖怪特有の分泌液である。 この液体には奇妙な性質があり、触れた者の心に不可解な既視感を抱かせるとされる。 | Q39: =len(P39) -> 136 | R39: まるで過去の記憶の断片が揺らぎ、夢の中の出来事と現実の境が曖昧になるような感覚を引き起こすという。 雫目童は特に害を及ぼすわけではないが、人里離れた場所に佇み、じっとこちらを見つめることがある。 | S39: =len(R39) -> 98 | T39: =len(W39) -> 135 | U39: ただ、静かにこちらを見つめながら、流れ落ちる雫の向こうに何を想うのだろうか。 | V39: =len(U39) -> 38 | W39: その姿を見た者は理由もなく懐かしさを感じることがあるが、それが何の記憶と結びついているのかは誰にも分からない。 昔の言い伝えでは、雫目童に「もう泣かなくてもいいよ」と優しく声をかけると、ふっと霧のように消えてしまうとされているが、そもそも彼は泣いているのではないのだ。 | Y39: =len(X39) -> 0 | AA39: =len(Z39) -> 0 | AC39: =len(AB39) -> 0
A40: 38 | B40: 屈背婆（くっぺいば） | C40: kuppeiba | D40: 人が住まなくなった古い家の縁側。特に、猫がよく集まる場所 | E40: むかし、ある村にひとり暮らしの優しいおばあさんがいた。 おばあさんは年老いた猫と一緒に暮らしており、その猫はいつもおばあさんの背中が大好きだった。 おばあさんが庭仕事をしているときも、薪を割っているときも、猫は背中にぴたりと張り付いて眠っていた。 「おまえさん、そんなにわしの背が好きかねぇ」 おばあさんは猫のために、少しでも乗りやすいようにと背を丸めるようになった。 最初は気にしていなかったが、いつしか背筋が伸びなくなり、常に猫を背負うような体になってしまった。 それでも、おばあさんは気にせず猫を可愛がり続けた。 やがて、おばあさんは静かにこの世を去り、猫もそれを追うように姿を消した。 しかし、その後も村のあちこちで、不思議な老婆の影が目撃されるようになった。 背中が異様に盛り上がり、まるで何かを背負っているかのようにかがんだ姿。 その背を撫でると、ほんのりと温かく、どこか安心する感覚に包まれるという。 人々はその存在を 「屈背婆」 と呼ぶようになった。 屈背婆は、今もどこかで猫を乗せたまま、静かに佇んでいるのかもしれない。 そして、寒い夜には、猫たちが安心して眠れる場所を探し求めて彷徨っているのだろう。 | F40: ="【名】" & B40 & C40 &char(10) & "【番】" & text(A40,"0000") & char(10) &"【出現】"&D40& char(10)&"【特質】"& char(10)&E40&char(10)&char(10)&memo!$B$1 -> 【名】屈背婆（くっぺいば）kuppeiba 【番】0038 【出現】人が住まなくなった古い家の縁側。特に、猫がよく集まる場所 【特質】 むかし、ある村にひとり暮らしの優しいおばあさんがいた。 おばあさんは年老いた猫と一緒に暮らしており、その猫はいつもおばあさんの背中が大好きだった。 おばあさんが庭仕事をしているときも、薪を割っているときも、猫は背中にぴたりと張り付いて眠っていた。 「おまえさん、そんなにわしの背が好きかねぇ」 おばあさんは猫のために、少しでも乗りやすいようにと背を丸めるようになった。 最初は気にしていなかったが、いつしか背筋が伸びなくなり、常に猫を背負うような体になってしまった。 それでも、おばあさんは気にせず猫を可愛がり続けた。 やがて、おばあさんは静かにこの世を去り、猫もそれを追うように姿を消した。 しかし、その後も村のあちこちで、不思議な老婆の影が目撃されるようになった。 背中が異様に盛り上がり、まるで何かを背負っているかのようにかがんだ姿。 その背を撫でると、ほんのりと温かく、どこか安心する感覚に包まれるという。 人々はその存在を 「屈背婆」 と呼ぶようになった。 屈背婆は、今もどこかで猫を乗せたまま、静かに佇んでいるのかもしれない。 そして、寒い夜には、猫たちが安心して眠れる場所を探し求めて彷徨っているのだろう。 #妖怪 #yokai #sumie #monster #ghost | G40: 45706 | H40: 45731 | I40: ○ | L40: =len(E40) -> 515 | N40: =mid(F40,1,find("【特質】",F40)-1) &char(10)&"＜特質はリプ欄へ＞" & char(10)& memo!$B$2 -> 【名】屈背婆（くっぺいば）kuppeiba 【番】0038 【出現】人が住まなくなった古い家の縁側。特に、猫がよく集まる場所 ＜特質はリプ欄へ＞ #妖怪 #お化け #怪物 #オリジナル妖怪 #monster #ghost #妖怪好き #浮世絵 #百鬼夜行 | O40: =len(N40) -> 128 | P40: 【特質】むかし、ある村にひとり暮らしの優しいおばあさんがいた。 おばあさんは年老いた猫と一緒に暮らしており、その猫はいつもおばあさんの背中が大好きだった。 おばあさんが庭仕事をしているときも、薪を割っているときも、猫は背中にぴたりと張り付いて眠っていた。 | Q40: =len(P40) -> 127 | R40: 「おまえさん、そんなにわしの背が好きかねぇ」 おばあさんは猫のために、少しでも乗りやすいようにと背を丸めるようになった。 最初は気にしていなかったが、いつしか背筋が伸びなくなり、常に猫を背負うような体になってしまった。 それでも、おばあさんは気にせず猫を可愛がり続けた。 | S40: =len(R40) -> 136 | T40: =len(W40) -> 110 | U40: その背を撫でると、ほんのりと温かく、どこか安心する感覚に包まれるという。 人々はその存在を 「屈背婆」 と呼ぶようになった。 屈背婆は、今もどこかで猫を乗せたまま、静かに佇んでいるのかもしれない。 そして、寒い夜には、猫たちが安心して眠れる場所を探し求めて彷徨っているのだろう。 | V40: =len(U40) -> 141 | W40: やがて、おばあさんは静かにこの世を去り、猫もそれを追うように姿を消した。 しかし、その後も村のあちこちで、不思議な老婆の影が目撃されるようになった。 背中が異様に盛り上がり、まるで何かを背負っているかのようにかがんだ姿。 | Y40: =len(X40) -> 0 | AA40: =len(Z40) -> 0 | AC40: =len(AB40) -> 0
A41: 39 | B41: 竹舞狗（ちくまいく） | C41: chikumaiku | D41: 神社や寺院の境内、竹林の片隅 | E41: むかし、ある竹職人がいた。 名を馳せることはなかったが、真面目で腕の確かな職人だった。 竹職人は、狛犬なるものが神社の門前の守護役として自ら名乗りを上げたという話を耳にし、ふと思った。 「竹細工で、同等の守護獣を作れないものか。」 そうして生まれたのが竹舞狗である。 しかし、職人は狛犬の「狛（こま）」を「独楽（こま）」と勘違いし、「魔を払うには回る力が要る」と信じて、竹舞狗の背にいくつもの竹とんぼをこしらえた。 やがて、狛犬との役目争いが行われた。 境内に並び立つ二つの守護像。 堂々と構える狛犬の傍らで、竹舞狗は風に吹かれるたび、ヒュルヒュルと竹とんぼを回して誇らしげに胸を張った。 だが、人々は失笑した。 「これでは神の加護を支えることはできまい。」 竹舞狗は敗れ、門を守る役目を得ることはできなかった。 職人は静かに竹舞狗を境内の片隅に置き、「守り手になれなくとも、人を和ませる護りもあるだろう」と呟き、去っていった。 それからというもの、竹舞狗はひっそりと狛犬の背を見つめながら、風が吹くたびに竹とんぼを回し続けている。 夜更け、神社の奥から微かな風切り音が聞こえたなら、それは竹舞狗が「次こそは」と願いを込めて竹とんぼを回している音なのかもしれない。 | F41: ="【名】" & B41 & C41 &char(10) & "【番】" & text(A41,"0000") & char(10) &"【出現】"&D41& char(10)&"【特質】"& char(10)&E41&char(10)&char(10)&memo!$B$1 -> 【名】竹舞狗（ちくまいく）chikumaiku 【番】0039 【出現】神社や寺院の境内、竹林の片隅 【特質】 むかし、ある竹職人がいた。 名を馳せることはなかったが、真面目で腕の確かな職人だった。 竹職人は、狛犬なるものが神社の門前の守護役として自ら名乗りを上げたという話を耳にし、ふと思った。 「竹細工で、同等の守護獣を作れないものか。」 そうして生まれたのが竹舞狗である。 しかし、職人は狛犬の「狛（こま）」を「独楽（こま）」と勘違いし、「魔を払うには回る力が要る」と信じて、竹舞狗の背にいくつもの竹とんぼをこしらえた。 やがて、狛犬との役目争いが行われた。 境内に並び立つ二つの守護像。 堂々と構える狛犬の傍らで、竹舞狗は風に吹かれるたび、ヒュルヒュルと竹とんぼを回して誇らしげに胸を張った。 だが、人々は失笑した。 「これでは神の加護を支えることはできまい。」 竹舞狗は敗れ、門を守る役目を得ることはできなかった。 職人は静かに竹舞狗を境内の片隅に置き、「守り手になれなくとも、人を和ませる護りもあるだろう」と呟き、去っていった。 それからというもの、竹舞狗はひっそりと狛犬の背を見つめながら、風が吹くたびに竹とんぼを回し続けている。 夜更け、神社の奥から微かな風切り音が聞こえたなら、それは竹舞狗が「次こそは」と願いを込めて竹とんぼを回している音なのかもしれない。 #妖怪 #yokai #sumie #monster #ghost | G41: 45708 | H41: 45732 | I41: ○ | L41: =len(E41) -> 540 | N41: =mid(F41,1,find("【特質】",F41)-1) &char(10)&"＜特質はリプ欄へ＞" & char(10)& memo!$B$2 -> 【名】竹舞狗（ちくまいく）chikumaiku 【番】0039 【出現】神社や寺院の境内、竹林の片隅 ＜特質はリプ欄へ＞ #妖怪 #お化け #怪物 #オリジナル妖怪 #monster #ghost #妖怪好き #浮世絵 #百鬼夜行 | O41: =len(N41) -> 116 | P41: 【特質】むかし、ある竹職人がいた。 名を馳せることはなかったが、真面目で腕の確かな職人だった。 竹職人は、狛犬なるものが神社の門前の守護役として自ら名乗りを上げたという話を耳にし、ふと思った。 「竹細工で、同等の守護獣を作れないものか。」 | Q41: =len(P41) -> 121 | R41: そうして生まれたのが竹舞狗である。 しかし、職人は狛犬の「狛（こま）」を「独楽（こま）」と勘違いし、「魔を払うには回る力が要る」と信じて、竹舞狗の背にいくつもの竹とんぼをこしらえた。 やがて、狛犬との役目争いが行われた。 境内に並び立つ二つの守護像。 | S41: =len(R41) -> 127 | T41: =len(W41) -> 116 | U41: 職人は静かに竹舞狗を境内の片隅に置き、「守り手になれなくとも、人を和ませる護りもあるだろう」と呟き、去っていった。 それからというもの、竹舞狗はひっそりと狛犬の背を見つめながら、風が吹くたびに竹とんぼを回し続けている。 | V41: =len(U41) -> 110 | W41: 堂々と構える狛犬の傍らで、竹舞狗は風に吹かれるたび、ヒュルヒュルと竹とんぼを回して誇らしげに胸を張った。 だが、人々は失笑した。 「これでは神の加護を支えることはできまい。」 竹舞狗は敗れ、門を守る役目を得ることはできなかった。 | X41: 夜更け、神社の奥から微かな風切り音が聞こえたなら、それは竹舞狗が「次こそは」と願いを込めて竹とんぼを回している音なのかもしれない。 | Y41: =len(X41) -> 65 | AA41: =len(Z41) -> 0 | AC41: =len(AB41) -> 0
A42: 40 | B42: 剛羽雀（ごううじゃく） | C42: goujaku | D42: 山間の古道、廃れた峠の茶屋跡、霧が立ち込める峠 | E42: 剛羽雀は、羽を持たない異形の鳥妖怪である。 かつては空を翔けた鳥の末裔とされるが、飛ぶことを捨て、筋骨隆々たる肉体を手に入れた。 盛り上がった胸板、丸太のような首、岩をも砕かんばかりに膨れ上がった肩と胸。 その姿は、まるで大地の力を凝縮したかのような威圧感を放つ。 飛べないことを嘆くどころか、剛羽雀はむしろ誇りに満ちている。 彼にとって、地を踏みしめることこそが真の強さの証だからだ。 実際、その威風堂々たる姿は、峠道に現れるだけで旅人を立ち止まらせる。 迷う者の前に立ち、進むか退くかを試す存在とされている。 剛羽雀は険しい山道も悠然と駆け抜ける。 巨体を揺らしながら、まるで地そのものを支配するかのように。 その姿は、まさに地を翔る鳥——そう、人々は信じている。 しかし、よく見てほしい。 剛羽雀の足は意外なほど短い。 実のところ、険しい山道を力強く駆け抜けているのは、剛羽雀自身ではなく、その背に黙々と歩を進める馬の方なのだ。 それでも剛羽雀は胸を張り、涼しい顔で言わんばかりの態度を崩さない。 「力とは己だけにあらず。支える者を信じることも、また強さの証だ」と。 やがて、剛羽雀に認められた旅人は、ふと背後に吹く風を感じるという。 それは、ただの風ではない。 まるで見えざる翼が広がるように、迷いを払い、進むべき道を後押しする風。 静かに、そして力強く——旅人の背を押していくのだ。 | F42: ="【名】" & B42 & C42 &char(10) & "【番】" & text(A42,"0000") & char(10) &"【出現】"&D42& char(10)&"【特質】"& char(10)&E42&char(10)&char(10)&memo!$B$1 -> 【名】剛羽雀（ごううじゃく）goujaku 【番】0040 【出現】山間の古道、廃れた峠の茶屋跡、霧が立ち込める峠 【特質】 剛羽雀は、羽を持たない異形の鳥妖怪である。 かつては空を翔けた鳥の末裔とされるが、飛ぶことを捨て、筋骨隆々たる肉体を手に入れた。 盛り上がった胸板、丸太のような首、岩をも砕かんばかりに膨れ上がった肩と胸。 その姿は、まるで大地の力を凝縮したかのような威圧感を放つ。 飛べないことを嘆くどころか、剛羽雀はむしろ誇りに満ちている。 彼にとって、地を踏みしめることこそが真の強さの証だからだ。 実際、その威風堂々たる姿は、峠道に現れるだけで旅人を立ち止まらせる。 迷う者の前に立ち、進むか退くかを試す存在とされている。 剛羽雀は険しい山道も悠然と駆け抜ける。 巨体を揺らしながら、まるで地そのものを支配するかのように。 その姿は、まさに地を翔る鳥——そう、人々は信じている。 しかし、よく見てほしい。 剛羽雀の足は意外なほど短い。 実のところ、険しい山道を力強く駆け抜けているのは、剛羽雀自身ではなく、その背に黙々と歩を進める馬の方なのだ。 それでも剛羽雀は胸を張り、涼しい顔で言わんばかりの態度を崩さない。 「力とは己だけにあらず。支える者を信じることも、また強さの証だ」と。 やがて、剛羽雀に認められた旅人は、ふと背後に吹く風を感じるという。 それは、ただの風ではない。 まるで見えざる翼が広がるように、迷いを払い、進むべき道を後押しする風。 静かに、そして力強く——旅人の背を押していくのだ。 #妖怪 #yokai #sumie #monster #ghost | G42: 45708 | H42: 45733 | I42: ○ | L42: =len(E42) -> 601 | N42: =mid(F42,1,find("【特質】",F42)-1) &char(10)&"＜特質はリプ欄へ＞" & char(10)& memo!$B$2 -> 【名】剛羽雀（ごううじゃく）goujaku 【番】0040 【出現】山間の古道、廃れた峠の茶屋跡、霧が立ち込める峠 ＜特質はリプ欄へ＞ #妖怪 #お化け #怪物 #オリジナル妖怪 #monster #ghost #妖怪好き #浮世絵 #百鬼夜行 | O42: =len(N42) -> 123 | P42: 剛羽雀は、羽を持たない異形の鳥妖怪である。 かつては空を翔けた鳥の末裔とされるが、飛ぶことを捨て、筋骨隆々たる肉体を手に入れた。 盛り上がった胸板、丸太のような首、岩をも砕かんばかりに膨れ上がった肩と胸。 その姿は、まるで大地の力を凝縮したかのような威圧感を放つ。 | Q42: =len(P42) -> 132 | R42: 飛べないことを嘆くどころか、剛羽雀はむしろ誇りに満ちている。 彼にとって、地を踏みしめることこそが真の強さの証だからだ。 実際、その威風堂々たる姿は、峠道に現れるだけで旅人を立ち止まらせる。 迷う者の前に立ち、進むか退くかを試す存在とされている。 | S42: =len(R42) -> 123 | T42: =len(W42) -> 91 | U42: 剛羽雀の足は意外なほど短い。 実のところ、険しい山道を力強く駆け抜けているのは、剛羽雀自身ではなく、その背に黙々と歩を進める馬の方なのだ。 それでも剛羽雀は胸を張り、涼しい顔で言わんばかりの態度を崩さない。 「力とは己だけにあらず。支える者を信じることも、また強さの証だ」と。 | V42: =len(U42) -> 139 | W42: 剛羽雀は険しい山道も悠然と駆け抜ける。 巨体を揺らしながら、まるで地そのものを支配するかのように。 その姿は、まさに地を翔る鳥——そう、人々は信じている。 しかし、よく見てほしい。 | X42: やがて、剛羽雀に認められた旅人は、ふと背後に吹く風を感じるという。 それは、ただの風ではない。 まるで見えざる翼が広がるように、迷いを払い、進むべき道を後押しする風。 静かに、そして力強く——旅人の背を押していくのだ。 | Y42: =len(X42) -> 109 | AA42: =len(Z42) -> 0 | AC42: =len(AB42) -> 0
A43: 41 | B43: 魅慈狐（みじこ） | C43: mijiko | D43: 小学校の体育館や朝礼の整列時 | E43: 魅慈狐は、学年で一番背が低い生徒が悲しまないように「最も小さい生徒役」を演じる妖怪である。 体育館での朝礼や行事の整列時、生徒の列の中にそっと紛れ込み、どの子よりも背が低い位置に立つ。 魅慈狐は目立つことを嫌い、誰にも気づかれないように行動するが、ふとした瞬間に「列の中に一人だけ明らかに異質な存在がいる」ことに気づかれることがある。 しかし、目を凝らすとその姿は消え、次に気づいた時には別の場所に紛れ込んでいる。 背が低くて肩を落としている子供を見つけると、そっと近づいて小さく頭を下げる仕草を見せるという。 それはまるで「一番小さいのは自分だから、気にしないで」と伝えるかのようだ。 学年が変わり、背の順が入れ替わると、魅慈狐もひっそりと姿を消し、次に必要とされる場所へと移動する。 気づかれず、目立たず、ただそこに存在することだけを役割とする、不思議で優しさに満ちた妖怪である。 | F43: ="【名】" & B43 & C43 &char(10) & "【番】" & text(A43,"0000") & char(10) &"【出現】"&D43& char(10)&"【特質】"& char(10)&E43&char(10)&char(10)&memo!$B$1 -> 【名】魅慈狐（みじこ）mijiko 【番】0041 【出現】小学校の体育館や朝礼の整列時 【特質】 魅慈狐は、学年で一番背が低い生徒が悲しまないように「最も小さい生徒役」を演じる妖怪である。 体育館での朝礼や行事の整列時、生徒の列の中にそっと紛れ込み、どの子よりも背が低い位置に立つ。 魅慈狐は目立つことを嫌い、誰にも気づかれないように行動するが、ふとした瞬間に「列の中に一人だけ明らかに異質な存在がいる」ことに気づかれることがある。 しかし、目を凝らすとその姿は消え、次に気づいた時には別の場所に紛れ込んでいる。 背が低くて肩を落としている子供を見つけると、そっと近づいて小さく頭を下げる仕草を見せるという。 それはまるで「一番小さいのは自分だから、気にしないで」と伝えるかのようだ。 学年が変わり、背の順が入れ替わると、魅慈狐もひっそりと姿を消し、次に必要とされる場所へと移動する。 気づかれず、目立たず、ただそこに存在することだけを役割とする、不思議で優しさに満ちた妖怪である。 #妖怪 #yokai #sumie #monster #ghost | G43: 45708 | H43: 45734 | I43: ○ | L43: =len(E43) -> 395 | N43: =mid(F43,1,find("【特質】",F43)-1) &char(10)&"＜特質はリプ欄へ＞" & char(10)& memo!$B$2 -> 【名】魅慈狐（みじこ）mijiko 【番】0041 【出現】小学校の体育館や朝礼の整列時 ＜特質はリプ欄へ＞ #妖怪 #お化け #怪物 #オリジナル妖怪 #monster #ghost #妖怪好き #浮世絵 #百鬼夜行 | O43: =len(N43) -> 110 | P43: 【特質】魅慈狐は、学年で一番背が低い生徒が悲しまないように「最も小さい生徒役」を演じる妖怪である。 体育館での朝礼や行事の整列時、生徒の列の中にそっと紛れ込み、どの子よりも背が低い位置に立つ。 | Q43: =len(P43) -> 96 | R43: 魅慈狐は目立つことを嫌い、誰にも気づかれないように行動するが、ふとした瞬間に「列の中に一人だけ明らかに異質な存在がいる」ことに気づかれることがある。 しかし、目を凝らすとその姿は消え、次に気づいた時には別の場所に紛れ込んでいる。 | S43: =len(R43) -> 114 | T43: =len(W43) -> 85 | U43: 学年が変わり、背の順が入れ替わると、魅慈狐もひっそりと姿を消し、次に必要とされる場所へと移動する。 気づかれず、目立たず、ただそこに存在することだけを役割とする、不思議で優しさに満ちた妖怪である。 | V43: =len(U43) -> 98 | W43: 背が低くて肩を落としている子供を見つけると、そっと近づいて小さく頭を下げる仕草を見せるという。 それはまるで「一番小さいのは自分だから、気にしないで」と伝えるかのようだ。 | Y43: =len(X43) -> 0 | AA43: =len(Z43) -> 0 | AC43: =len(AB43) -> 0
A44: 42 | B44: 布垣守（ぬがきもり） | C44: nugakimori | D44: 宿場町の辻、繁華街の路地、祭りの夜市。 | E44: 布垣守は、長い布に包まれた無顔の人型妖怪で、争いの気配を敏感に察知して静かに現れる。 姿は薄霧に溶け込むようにぼんやりとしており、その存在に気づく者は少ない。 口論や小競り合いが激しくなると、布が瞬時に壁のように立ち上がり、争う者たちを隔てる。 その際、低く穏やかな声で「一旦揉めんのやめよか」と呟くのが特徴だ。 この言葉を聞いた者は驚きとともに怒りが薄れ、我に返るという。 布は霧のように柔らかいが、触れると氷のように冷たく、怒りや興奮を徐々に鎮める効果を持つ。 必要に応じて手足を包み込み、動きを封じることもあれば、相手の目前に垣を作って接触を防ぐこともある。 力づくで突破しようとすれば布は強く締まり、動きを完全に封じる。 争いが鎮まると布はするりと縮み、風に溶けるように消えていく。 一度和解すれば、同じ者同士の間には二度と姿を現さないが、再び憎しみが芽生えれば再出現するとされる。 布垣守に阻まれた争いは、後の災厄を未然に防ぐ兆しと伝えられ、「布垣に隔たれし喧嘩は福を呼ぶ」との言い伝え も残る。 | F44: ="【名】" & B44 & C44 &char(10) & "【番】" & text(A44,"0000") & char(10) &"【出現】"&D44& char(10)&"【特質】"& char(10)&E44&char(10)&char(10)&memo!$B$1 -> 【名】布垣守（ぬがきもり）nugakimori 【番】0042 【出現】宿場町の辻、繁華街の路地、祭りの夜市。 【特質】 布垣守は、長い布に包まれた無顔の人型妖怪で、争いの気配を敏感に察知して静かに現れる。 姿は薄霧に溶け込むようにぼんやりとしており、その存在に気づく者は少ない。 口論や小競り合いが激しくなると、布が瞬時に壁のように立ち上がり、争う者たちを隔てる。 その際、低く穏やかな声で「一旦揉めんのやめよか」と呟くのが特徴だ。 この言葉を聞いた者は驚きとともに怒りが薄れ、我に返るという。 布は霧のように柔らかいが、触れると氷のように冷たく、怒りや興奮を徐々に鎮める効果を持つ。 必要に応じて手足を包み込み、動きを封じることもあれば、相手の目前に垣を作って接触を防ぐこともある。 力づくで突破しようとすれば布は強く締まり、動きを完全に封じる。 争いが鎮まると布はするりと縮み、風に溶けるように消えていく。 一度和解すれば、同じ者同士の間には二度と姿を現さないが、再び憎しみが芽生えれば再出現するとされる。 布垣守に阻まれた争いは、後の災厄を未然に防ぐ兆しと伝えられ、「布垣に隔たれし喧嘩は福を呼ぶ」との言い伝え も残る。 #妖怪 #yokai #sumie #monster #ghost | G44: 45709 | H44: 45735 | I44: ○ | L44: =len(E44) -> 457 | N44: =mid(F44,1,find("【特質】",F44)-1) &char(10)&"＜特質はリプ欄へ＞" & char(10)& memo!$B$2 -> 【名】布垣守（ぬがきもり）nugakimori 【番】0042 【出現】宿場町の辻、繁華街の路地、祭りの夜市。 ＜特質はリプ欄へ＞ #妖怪 #お化け #怪物 #オリジナル妖怪 #monster #ghost #妖怪好き #浮世絵 #百鬼夜行 | O44: =len(N44) -> 121 | P44: 【特質】布垣守は、長い布に包まれた無顔の人型妖怪で、争いの気配を敏感に察知して静かに現れる。 姿は薄霧に溶け込むようにぼんやりとしており、その存在に気づく者は少ない。 口論や小競り合いが激しくなると、布が瞬時に壁のように立ち上がり、争う者たちを隔てる。 | Q44: =len(P44) -> 127 | R44: その際、低く穏やかな声で「一旦揉めんのやめよか」と呟くのが特徴だ。 この言葉を聞いた者は驚きとともに怒りが薄れ、我に返るという。 布は霧のように柔らかいが、触れると氷のように冷たく、怒りや興奮を徐々に鎮める効果を持つ。 | S44: =len(R44) -> 110 | T44: =len(W44) -> 113 | U44: 一度和解すれば、同じ者同士の間には二度と姿を現さないが、再び憎しみが芽生えれば再出現するとされる。 布垣守に阻まれた争いは、後の災厄を未然に防ぐ兆しと伝えられ、「布垣に隔たれし喧嘩は福を呼ぶ」との言い伝え も残る。 | V44: =len(U44) -> 107 | W44: 必要に応じて手足を包み込み、動きを封じることもあれば、相手の目前に垣を作って接触を防ぐこともある。 力づくで突破しようとすれば布は強く締まり、動きを完全に封じる。 争いが鎮まると布はするりと縮み、風に溶けるように消えていく。 | Y44: =len(X44) -> 0 | AA44: =len(Z44) -> 0 | AC44: =len(AB44) -> 0
A45: 43 | B45: 指潜（ゆびくぐり） | C45: yubikuguri | D45: 家具の角、部屋の隅、畳の縁 | E45: 人が何気なく歩いているとき、足の小指をタンスや家具の角に激しくぶつけることがある。 それは単なる不注意ではなく、指潜（ゆびくぐり）の仕業だと言われている。 指潜は十数センチほどの小さな童の姿をしており、ぼんやり歩く人間の足元にひっそりと現れる。 丸い頭に短く整えた髪、古びた麻の着物を着た幼子のようだが、鋭い目には憎悪の塊が宿っている。 最大の特徴は、異様に細長くしなやかな指。関節が自在に曲がり、生き物のように滑らかに動く。 人間が気を抜いた瞬間、その指を小指と薬指の間に滑り込ませ、ぐいっと広げる。 これにより小指は外側へ押し出され、家具の角に直撃しやすくなる仕組みだ。 指潜が狙うのは、心ここにあらずの人間。 仕事や悩みに気を取られ、無意識に部屋を行き来していると、足元に忍び寄る。ぶつけた瞬間の鋭い痛みは「もっと注意深く歩け」という警告だという。 しかし、指潜に悪意はない。 足元を見ずに歩けば転倒することもあり、心ここにあらずでは失敗を招きかねない。 指潜は、そんな「危険への気づき」を痛みで教えてくれる存在なのだ。 ぶつけた直後、畳の隙間や家具の影から「くくっ」と微かな笑い声が聞こえたなら、それは指潜が仕事を終えて立ち去る合図。 足元を意識して静かに歩き、心を整えて過ごせば、指潜は現れないと言われている。 | F45: ="【名】" & B45 & C45 &char(10) & "【番】" & text(A45,"0000") & char(10) &"【出現】"&D45& char(10)&"【特質】"& char(10)&E45&char(10)&char(10)&memo!$B$1 -> 【名】指潜（ゆびくぐり）yubikuguri 【番】0043 【出現】家具の角、部屋の隅、畳の縁 【特質】 人が何気なく歩いているとき、足の小指をタンスや家具の角に激しくぶつけることがある。 それは単なる不注意ではなく、指潜（ゆびくぐり）の仕業だと言われている。 指潜は十数センチほどの小さな童の姿をしており、ぼんやり歩く人間の足元にひっそりと現れる。 丸い頭に短く整えた髪、古びた麻の着物を着た幼子のようだが、鋭い目には憎悪の塊が宿っている。 最大の特徴は、異様に細長くしなやかな指。関節が自在に曲がり、生き物のように滑らかに動く。 人間が気を抜いた瞬間、その指を小指と薬指の間に滑り込ませ、ぐいっと広げる。 これにより小指は外側へ押し出され、家具の角に直撃しやすくなる仕組みだ。 指潜が狙うのは、心ここにあらずの人間。 仕事や悩みに気を取られ、無意識に部屋を行き来していると、足元に忍び寄る。ぶつけた瞬間の鋭い痛みは「もっと注意深く歩け」という警告だという。 しかし、指潜に悪意はない。 足元を見ずに歩けば転倒することもあり、心ここにあらずでは失敗を招きかねない。 指潜は、そんな「危険への気づき」を痛みで教えてくれる存在なのだ。 ぶつけた直後、畳の隙間や家具の影から「くくっ」と微かな笑い声が聞こえたなら、それは指潜が仕事を終えて立ち去る合図。 足元を意識して静かに歩き、心を整えて過ごせば、指潜は現れないと言われている。 #妖怪 #yokai #sumie #monster #ghost | G45: 45710 | H45: 45736 | I45: ○ | L45: =len(E45) -> 565 | N45: =mid(F45,1,find("【特質】",F45)-1) &char(10)&"＜特質はリプ欄へ＞" & char(10)& memo!$B$2 -> 【名】指潜（ゆびくぐり）yubikuguri 【番】0043 【出現】家具の角、部屋の隅、畳の縁 ＜特質はリプ欄へ＞ #妖怪 #お化け #怪物 #オリジナル妖怪 #monster #ghost #妖怪好き #浮世絵 #百鬼夜行 | O45: =len(N45) -> 114 | P45: 【特質】人が何気なく歩いているとき、足の小指をタンスや家具の角に激しくぶつけることがある。 それは単なる不注意ではなく、指潜（ゆびくぐり）の仕業だと言われている。 指潜は十数センチほどの小さな童の姿をしており、ぼんやり歩く人間の足元にひっそりと現れる。 | Q45: =len(P45) -> 127 | R45: 丸い頭に短く整えた髪、古びた麻の着物を着た幼子のようだが、鋭い目には憎悪の塊が宿っている。 最大の特徴は、異様に細長くしなやかな指。関節が自在に曲がり、生き物のように滑らかに動く。 人間が気を抜いた瞬間、その指を小指と薬指の間に滑り込ませ、ぐいっと広げる。 | S45: =len(R45) -> 129 | T45: =len(W45) -> 126 | U45: しかし、指潜に悪意はない。 足元を見ずに歩けば転倒することもあり、心ここにあらずでは失敗を招きかねない。 指潜は、そんな「危険への気づき」を痛みで教えてくれる存在なのだ。 | V45: =len(U45) -> 85 | W45: これにより小指は外側へ押し出され、家具の角に直撃しやすくなる仕組みだ。 指潜が狙うのは、心ここにあらずの人間。 仕事や悩みに気を取られ、無意識に部屋を行き来していると、足元に忍び寄る。ぶつけた瞬間の鋭い痛みは「もっと注意深く歩け」という警告だという。 | X45: ぶつけた直後、畳の隙間や家具の影から「くくっ」と微かな笑い声が聞こえたなら、それは指潜が仕事を終えて立ち去る合図。 足元を意識して静かに歩き、心を整えて過ごせば、指潜は現れないと言われている。 | Y45: =len(X45) -> 96 | AA45: =len(Z45) -> 0 | AC45: =len(AB45) -> 0
A46: 44 | B46: 映画岡引（えいがおかっぴき） | C46: eigaokappiki | D46: 映画館、映写室、旧式の映写機が眠る倉庫 | E46: 映画泥坊（えいがどろぼう）による盗撮被害が続く映画館。 その闇に、一筋の光が差し込んだ――。 スクリーンに映る映画が不自然に歪み、観客の影が画面に映り込み始めた瞬間、不気味な「カシャ…カシャ…」というシャッター音が館内に響いた。 黒い影のような姿をした映画泥坊が、長い指先で怪しげなレンズをかざし、映像を盗んでいる。 だが、そのとき、館内の空気が突然張り詰めた。 「貴様の悪行、もはや見過ごせぬぞ。」 低く響く声とともに、映画館の奥から影が揺らぎ、一人の妖怪が姿を現した。 彼の名は 映画岡引。 古びた岡っ引きの装束をまとい、片方の目は提灯のように光り輝いている。 長く骨ばった指が竹の巻物を握り、その紙面には、かつて映画を汚した者たちの名が刻まれていた。 映画泥坊は驚愕し、影のような身体を細めて逃げようとする。 しかし、岡引はすでに巻物を広げ、そこに書かれた名を指でなぞる。 「ここに記された者、逃れる術なし。」 瞬間、館内の闇が波打ち、映画泥坊の姿が揺らぐ。 カメラが勝手に作動し始め、泥坊自身の姿がフィルムに焼き付けられていく。 「ぐああああっ！！」 映画泥坊の叫び声が響き、ついにその姿は巻物の中へと吸い込まれた。 映画館は再び静寂を取り戻し、スクリーンには本来の映像が流れ始める。 観客たちは何が起こったのか分からぬまま、ただ映画の続きに目を向けた。 映画岡引は静かに巻物を巻き直し、一言だけ残して闇へと溶け込んでいく。 「映画を盗む悪党がいる限り、我が務めは終わらぬ……。」 それ以来、映画館のスクリーンは平穏を取り戻し、映画泥坊の姿は二度と見られることはなかった。 だが、どこかの暗闇に新たな悪が潜むたび、岡引は必ず現れるという。 | F46: ="【名】" & B46 & C46 &char(10) & "【番】" & text(A46,"0000") & char(10) &"【出現】"&D46& char(10)&"【特質】"& char(10)&E46&char(10)&char(10)& "#銀幕幻影物語 " &memo!$B$1 -> 【名】映画岡引（えいがおかっぴき）eigaokappiki 【番】0044 【出現】映画館、映写室、旧式の映写機が眠る倉庫 【特質】 映画泥坊（えいがどろぼう）による盗撮被害が続く映画館。 その闇に、一筋の光が差し込んだ――。 スクリーンに映る映画が不自然に歪み、観客の影が画面に映り込み始めた瞬間、不気味な「カシャ…カシャ…」というシャッター音が館内に響いた。 黒い影のような姿をした映画泥坊が、長い指先で怪しげなレンズをかざし、映像を盗んでいる。 だが、そのとき、館内の空気が突然張り詰めた。 「貴様の悪行、もはや見過ごせぬぞ。」 低く響く声とともに、映画館の奥から影が揺らぎ、一人の妖怪が姿を現した。 彼の名は 映画岡引。 古びた岡っ引きの装束をまとい、片方の目は提灯のように光り輝いている。 長く骨ばった指が竹の巻物を握り、その紙面には、かつて映画を汚した者たちの名が刻まれていた。 映画泥坊は驚愕し、影のような身体を細めて逃げようとする。 しかし、岡引はすでに巻物を広げ、そこに書かれた名を指でなぞる。 「ここに記された者、逃れる術なし。」 瞬間、館内の闇が波打ち、映画泥坊の姿が揺らぐ。 カメラが勝手に作動し始め、泥坊自身の姿がフィルムに焼き付けられていく。 「ぐああああっ！！」 映画泥坊の叫び声が響き、ついにその姿は巻物の中へと吸い込まれた。 映画館は再び静寂を取り戻し、スクリーンには本来の映像が流れ始める。 観客たちは何が起こったのか分からぬまま、ただ映画の続きに目を向けた。 映画岡引は静かに巻物を巻き直し、一言だけ残して闇へと溶け込んでいく。 「映画を盗む悪党がいる限り、我が務めは終わらぬ……。」 それ以来、映画館のスクリーンは平穏を取り戻し、映画泥坊の姿は二度と見られることはなかった。 だが、どこかの暗闇に新たな悪が潜むたび、岡引は必ず現れるという。 #銀幕幻影物語 #妖怪 #yokai #sumie #monster #ghost | G46: 45703 | H46: 45737 | I46: ○ | L46: =len(E46) -> 736 | N46: =mid(F46,1,find("【特質】",F46)-1) &char(10)&"＜特質はリプ欄へ＞" & char(10)& "#銀幕幻影物語 " & memo!$B$2 -> 【名】映画岡引（えいがおかっぴき）eigaokappiki 【番】0044 【出現】映画館、映写室、旧式の映写機が眠る倉庫 ＜特質はリプ欄へ＞ #銀幕幻影物語 #妖怪 #お化け #怪物 #オリジナル妖怪 #monster #ghost #妖怪好き #浮世絵 #百鬼夜行 | O46: =len(N46) -> 135 | P46: 【特質】映画泥坊（えいがどろぼう）による盗撮被害が続く映画館。 その闇に、一筋の光が差し込んだ――。 スクリーンに映る映画が不自然に歪み、観客の影が画面に映り込み始めた瞬間、不気味な「カシャ…カシャ…」というシャッター音が館内に響いた。 | Q46: =len(P46) -> 119 | R46: 黒い影のような姿をした映画泥坊が、長い指先で怪しげなレンズをかざし、映像を盗んでいる。 だが、そのとき、館内の空気が突然張り詰めた。 「貴様の悪行、もはや見過ごせぬぞ。」 低く響く声とともに、映画館の奥から影が揺らぎ、一人の妖怪が姿を現した。 彼の名は 映画岡引。 | S46: =len(R46) -> 135 | T46: =len(W46) -> 141 | U46: 「ここに記された者、逃れる術なし。」 瞬間、館内の闇が波打ち、映画泥坊の姿が揺らぐ。 カメラが勝手に作動し始め、泥坊自身の姿がフィルムに焼き付けられていく。 「ぐああああっ！！」 映画泥坊の叫び声が響き、ついにその姿は巻物の中へと吸い込まれた。 | V46: =len(U46) -> 125 | W46: 古びた岡っ引きの装束をまとい、片方の目は提灯のように光り輝いている。 長く骨ばった指が竹の巻物を握り、その紙面には、かつて映画を汚した者たちの名が刻まれていた。 映画泥坊は驚愕し、影のような身体を細めて逃げようとする。 しかし、岡引はすでに巻物を広げ、そこに書かれた名を指でなぞる | X46: 映画館は再び静寂を取り戻し、スクリーンには本来の映像が流れ始める。 観客たちは何が起こったのか分からぬまま、ただ映画の続きに目を向けた。 映画岡引は静かに巻物を巻き直し、一言だけ残して闇へと溶け込んでいく。 「映画を盗む悪党がいる限り、我が務めは終わらぬ……。」 | Y46: =len(X46) -> 133 | Z46: それ以来、映画館のスクリーンは平穏を取り戻し、映画泥坊の姿は二度と見られることはなかった。 だが、どこかの暗闇に新たな悪が潜むたび、岡引は必ず現れるという。 | AA46: =len(Z46) -> 78 | AC46: =len(AB46) -> 0
A47: 45 | B47: 膝下毛繰（ひざしたけぐり） | C47: hizashitakeguri | D47: 山間の旧街道、草深い河原、廃れた峠道 | E47: 全身を覆う濃密な毛が特徴の妖怪。 この毛は特殊な感覚器官でできており、生き物の存在を敏感に察知する。 目標を見つけるや否や、チーター並みの俊足で疾風のごとく駆け寄り、一瞬で間合いを詰める。 しかし、最大の弱点は極端に短いスタミナである。 わずか1歩で息切れし、力尽きてしまうため、ほぼ確実に逃げられてしまう。 失敗すると、地面に膝をつき、長い毛をバサバサと振り乱しながら悔しそうにうずくまる姿が目撃されている。 その姿があまりに情けなく、「いつも膝をついている毛むくじゃらの妖怪」という意味で、いつしか膝下毛繰と呼ばれるようになったという。 ただし、短時間の休息を挟めば、再び猛然と追いかけてくるため油断は禁物だ。 旅人の間では、「膝下毛繰は速いが、バカ正直」と囁かれており、進行方向に草履や布切れを投げると、それを獲物と勘違いして飛びつき、その隙に逃げることができるという。 まぁ、やはり1秒で力尽きるため、そんなに警戒する必要はない。 | F47: ="【名】" & B47 & C47 &char(10) & "【番】" & text(A47,"0000") & char(10) &"【出現】"&D47& char(10)&"【特質】"& char(10)&E47&char(10)&char(10)&memo!$B$1 -> 【名】膝下毛繰（ひざしたけぐり）hizashitakeguri 【番】0045 【出現】山間の旧街道、草深い河原、廃れた峠道 【特質】 全身を覆う濃密な毛が特徴の妖怪。 この毛は特殊な感覚器官でできており、生き物の存在を敏感に察知する。 目標を見つけるや否や、チーター並みの俊足で疾風のごとく駆け寄り、一瞬で間合いを詰める。 しかし、最大の弱点は極端に短いスタミナである。 わずか1歩で息切れし、力尽きてしまうため、ほぼ確実に逃げられてしまう。 失敗すると、地面に膝をつき、長い毛をバサバサと振り乱しながら悔しそうにうずくまる姿が目撃されている。 その姿があまりに情けなく、「いつも膝をついている毛むくじゃらの妖怪」という意味で、いつしか膝下毛繰と呼ばれるようになったという。 ただし、短時間の休息を挟めば、再び猛然と追いかけてくるため油断は禁物だ。 旅人の間では、「膝下毛繰は速いが、バカ正直」と囁かれており、進行方向に草履や布切れを投げると、それを獲物と勘違いして飛びつき、その隙に逃げることができるという。 まぁ、やはり1秒で力尽きるため、そんなに警戒する必要はない。 #妖怪 #yokai #sumie #monster #ghost | G47: 45710 | H47: 45738 | I47: ○ | L47: =len(E47) -> 424 | N47: =mid(F47,1,find("【特質】",F47)-1) &char(10)&"＜特質はリプ欄へ＞" & char(10)& memo!$B$2 -> 【名】膝下毛繰（ひざしたけぐり）hizashitakeguri 【番】0045 【出現】山間の旧街道、草深い河原、廃れた峠道 ＜特質はリプ欄へ＞ #妖怪 #お化け #怪物 #オリジナル妖怪 #monster #ghost #妖怪好き #浮世絵 #百鬼夜行 | O47: =len(N47) -> 128 | P47: 【特質】全身を覆う濃密な毛が特徴の妖怪。 この毛は特殊な感覚器官でできており、生き物の存在を敏感に察知する。 目標を見つけるや否や、チーター並みの俊足で疾風のごとく駆け寄り、一瞬で間合いを詰める。 しかし、最大の弱点は極端に短いスタミナである。 | Q47: =len(P47) -> 123 | R47: わずか1歩で息切れし、力尽きてしまうため、ほぼ確実に逃げられてしまう。 失敗すると、地面に膝をつき、長い毛をバサバサと振り乱しながら悔しそうにうずくまる姿が目撃されている。 その姿があまりに情けなく、「いつも膝をついている毛むくじゃらの妖怪」という意味で、 | S47: =len(R47) -> 129 | T47: =len(W47) -> 60 | U47: 旅人の間では、「膝下毛繰は速いが、バカ正直」と囁かれており、進行方向に草履や布切れを投げると、それを獲物と勘違いして飛びつき、その隙に逃げることができるという。 まぁ、やはり1秒で力尽きるため、そんなに警戒する必要はない。 | V47: =len(U47) -> 112 | W47: いつしか膝下毛繰と呼ばれるようになったという。 ただし、短時間の休息を挟めば、再び猛然と追いかけてくるため油断は禁物だ。 | Y47: =len(X47) -> 0 | AA47: =len(Z47) -> 0 | AC47: =len(AB47) -> 0
A48: 46 | B48: 福掛乃（ふくかけの） | C48: fukukakeno | D48: 街道沿いの峠茶屋「掛福庵（かけふくあん）」 | E48: 街道を行き交う旅人に愛される茶屋「掛福庵」の看板娘。 美しい長髪を揺らしながら、きびきびと働く姿は一見普通の人間に見えるが、天狗のように長く滑らかな鼻がその正体を物語っている。 鼻はただ長いだけでなく、器用に物を持ち運ぶことができる。 お茶の湯飲みを鼻で運ぶ姿に最初は客も驚いたが、その絶妙なバランス感覚と愛嬌のある接客で、今では「鼻で福を掛ける娘」として名物に。 旅人たちはいつしか、福掛乃の鼻に鞄や手荷物を引っ掛けては「福を掛けてもらった」と笑いながら旅立つようになった。 最近では「福掛チャレンジ」と称して、鼻に荷物を掛けて写真を撮る観光客が後を絶たない。 本人は「もう、やめてくださいよ〜」と困った顔を見せるものの、口元にはほころぶ笑み。 茶屋は今日も賑わい、福掛乃の長い鼻には福と笑顔が絶えず掛かっている。 | F48: ="【名】" & B48 & C48 &char(10) & "【番】" & text(A48,"0000") & char(10) &"【出現】"&D48& char(10)&"【特質】"& char(10)&E48&char(10)&char(10)&memo!$B$1 -> 【名】福掛乃（ふくかけの）fukukakeno 【番】0046 【出現】街道沿いの峠茶屋「掛福庵（かけふくあん）」 【特質】 街道を行き交う旅人に愛される茶屋「掛福庵」の看板娘。 美しい長髪を揺らしながら、きびきびと働く姿は一見普通の人間に見えるが、天狗のように長く滑らかな鼻がその正体を物語っている。 鼻はただ長いだけでなく、器用に物を持ち運ぶことができる。 お茶の湯飲みを鼻で運ぶ姿に最初は客も驚いたが、その絶妙なバランス感覚と愛嬌のある接客で、今では「鼻で福を掛ける娘」として名物に。 旅人たちはいつしか、福掛乃の鼻に鞄や手荷物を引っ掛けては「福を掛けてもらった」と笑いながら旅立つようになった。 最近では「福掛チャレンジ」と称して、鼻に荷物を掛けて写真を撮る観光客が後を絶たない。 本人は「もう、やめてくださいよ〜」と困った顔を見せるものの、口元にはほころぶ笑み。 茶屋は今日も賑わい、福掛乃の長い鼻には福と笑顔が絶えず掛かっている。 #妖怪 #yokai #sumie #monster #ghost | G48: 45710 | H48: 45739 | I48: ○ | L48: =len(E48) -> 361 | N48: =mid(F48,1,find("【特質】",F48)-1) &char(10)&"＜特質はリプ欄へ＞" & char(10)& memo!$B$2 -> 【名】福掛乃（ふくかけの）fukukakeno 【番】0046 【出現】街道沿いの峠茶屋「掛福庵（かけふくあん）」 ＜特質はリプ欄へ＞ #妖怪 #お化け #怪物 #オリジナル妖怪 #monster #ghost #妖怪好き #浮世絵 #百鬼夜行 | O48: =len(N48) -> 123 | P48: 【特質】街道を行き交う旅人に愛される茶屋「掛福庵」の看板娘。 美しい長髪を揺らしながら、きびきびと働く姿は一見普通の人間に見えるが、天狗のように長く滑らかな鼻がその正体を物語っている。 鼻はただ長いだけでなく、器用に物を持ち運ぶことができる。 | Q48: =len(P48) -> 122 | R48: お茶の湯飲みを鼻で運ぶ姿に最初は客も驚いたが、その絶妙なバランス感覚と愛嬌のある接客で、今では「鼻で福を掛ける娘」として名物に。 旅人たちはいつしか、福掛乃の鼻に鞄や手荷物を引っ掛けては「福を掛けてもらった」と笑いながら旅立つようになった。 | S48: =len(R48) -> 121 | T48: =len(W48) -> 120 | V48: =len(U48) -> 0 | W48: 最近では「福掛チャレンジ」と称して、鼻に荷物を掛けて写真を撮る観光客が後を絶たない。 本人は「もう、やめてくださいよ〜」と困った顔を見せるものの、口元にはほころぶ笑み。 茶屋は今日も賑わい、福掛乃の長い鼻には福と笑顔が絶えず掛かっている。 | Y48: =len(X48) -> 0 | AA48: =len(Z48) -> 0 | AC48: =len(AB48) -> 0
A49: 47 | B49: 朧錦羽（おぼろにしき） | C49: oboronishiki | D49: 静かな湖畔や廃れた神社の境内、夜明け前の人気のない庭園 | E49: 朧錦羽は夕暮れや夜明けの薄明かりの中にふわりと現れる妖鳥である。 普段は灰色がかった羽を閉じてひっそりと佇むが、動くたびに隙間から錦織のような鮮やかな文様がこぼれ落ちるように覗く。 その模様は一定ではなく、周囲の気温や気配、見る者の心情に呼応して色と形を変えるという。 この妖怪は不器用で、羽を閉じて自らの存在を隠そうとするものの、隙間から洩れる華やかさがかえって目を引く。 「見せびらかすつもりはないのに、見られてしまう」という存在自体が、どこか気恥ずかしげで愛らしい。 朧錦羽に出会うことは、迷いを抱える者にとって吉兆とされる。 隙間から洩れる模様は心の奥を映す鏡であり、それを見つめることで自身の本心を知ることができると言われる。 ただし、心に嘘を抱えた者がその美しさに囚われると、羽の隙間から生じる霧に包まれ、方向感覚を失ってしまうこともある。 興味本位で追い回す者には決して姿を留めず、霧とともに消え去る。 けれど、心を静め、己と向き合う覚悟を持つ者には、再びそっと姿を現し、進むべき道を照らすように羽を揺らすという。 「隠そうとするものほど、美しさは洩れ出るもの」――そう語るかのように、朧錦羽は夜の帳に紛れて消えていく。 | F49: ="【名】" & B49 & C49 &char(10) & "【番】" & text(A49,"0000") & char(10) &"【出現】"&D49& char(10)&"【特質】"& char(10)&E49&char(10)&char(10)&memo!$B$1 -> 【名】朧錦羽（おぼろにしき）oboronishiki 【番】0047 【出現】静かな湖畔や廃れた神社の境内、夜明け前の人気のない庭園 【特質】 朧錦羽は夕暮れや夜明けの薄明かりの中にふわりと現れる妖鳥である。 普段は灰色がかった羽を閉じてひっそりと佇むが、動くたびに隙間から錦織のような鮮やかな文様がこぼれ落ちるように覗く。 その模様は一定ではなく、周囲の気温や気配、見る者の心情に呼応して色と形を変えるという。 この妖怪は不器用で、羽を閉じて自らの存在を隠そうとするものの、隙間から洩れる華やかさがかえって目を引く。 「見せびらかすつもりはないのに、見られてしまう」という存在自体が、どこか気恥ずかしげで愛らしい。 朧錦羽に出会うことは、迷いを抱える者にとって吉兆とされる。 隙間から洩れる模様は心の奥を映す鏡であり、それを見つめることで自身の本心を知ることができると言われる。 ただし、心に嘘を抱えた者がその美しさに囚われると、羽の隙間から生じる霧に包まれ、方向感覚を失ってしまうこともある。 興味本位で追い回す者には決して姿を留めず、霧とともに消え去る。 けれど、心を静め、己と向き合う覚悟を持つ者には、再びそっと姿を現し、進むべき道を照らすように羽を揺らすという。 「隠そうとするものほど、美しさは洩れ出るもの」――そう語るかのように、朧錦羽は夜の帳に紛れて消えていく。 #妖怪 #yokai #sumie #monster #ghost | G49: 45711 | H49: 45740 | I49: ○ | L49: =len(E49) -> 521 | N49: =mid(F49,1,find("【特質】",F49)-1) &char(10)&"＜特質はリプ欄へ＞" & char(10)& memo!$B$2 -> 【名】朧錦羽（おぼろにしき）oboronishiki 【番】0047 【出現】静かな湖畔や廃れた神社の境内、夜明け前の人気のない庭園 ＜特質はリプ欄へ＞ #妖怪 #お化け #怪物 #オリジナル妖怪 #monster #ghost #妖怪好き #浮世絵 #百鬼夜行 | O49: =len(N49) -> 132 | P49: 【特質】朧錦羽は夕暮れや夜明けの薄明かりの中にふわりと現れる妖鳥である。 普段は灰色がかった羽を閉じてひっそりと佇むが、動くたびに隙間から錦織のような鮮やかな文様がこぼれ落ちるように覗く。 その模様は一定ではなく、周囲の気温や気配、見る者の心情に呼応して色と形を変えるという。 | Q49: =len(P49) -> 138 | R49: この妖怪は不器用で、羽を閉じて自らの存在を隠そうとするものの、隙間から洩れる華やかさがかえって目を引く。 「見せびらかすつもりはないのに、見られてしまう」という存在自体が、どこか気恥ずかしげで愛らしい。 朧錦羽に出会うことは、迷いを抱える者にとって吉兆とされる。 | S49: =len(R49) -> 132 | T49: =len(W49) -> 141 | U49: けれど、心を静め、己と向き合う覚悟を持つ者には、再びそっと姿を現し、進むべき道を照らすように羽を揺らすという。 「隠そうとするものほど、美しさは洩れ出るもの」――そう語るかのように、朧錦羽は夜の帳に紛れて消えていく。 | V49: =len(U49) -> 109 | W49: 隙間から洩れる模様は心の奥を映す鏡であり、それを見つめることで自身の本心を知ることができると言われる。 ただし、心に嘘を抱えた者がその美しさに囚われると、羽の隙間から生じる霧に包まれ、方向感覚を失ってしまうこともある。 興味本位で追い回す者には決して姿を留めず、霧とともに消え去る。 | Y49: =len(X49) -> 0 | AA49: =len(Z49) -> 0 | AC49: =len(AB49) -> 0
A50: 48 | B50: 玄寿甲（げんじゅこう） | C50: genjuko | D50: 古い山寺の裏手にある苔むした石畳、干上がった池の底、海から遠く離れた静かな森の沼地 | E50: 玄寿甲は3億年を生きた末に、もはや歩むことさえ億劫になった老亀の妖怪である。 甲羅は岩のようにひび割れ、苔や小さな草が生えており、動くたびに細かな石片がこぼれ落ちる。 首は異様に長く、皮膚はしわだらけで乾いているが、その瞳には夜空のような深い静寂が宿っている。 常に背を丸め、ため息混じりに空を仰ぐ姿が目撃されるが、その場を離れると数十年は現れない。 言葉を発することは稀であり、耳を澄ませば風に溶けるような低い声で「長き命もまた、苦に成る……」と呟くことがあるという。 玄寿甲に出会った者は、年を経ることの意味と重みを痛感するとされ、何らかの「終わり」や「区切り」を悟るとも言われる。 ただし、害をなすことはなく、むしろ静かに見守る存在である。 まれに、玄寿甲が甲羅をゆっくりと開き、内部に秘めた「時の砂」をひとつまみ振り撒くことがある。 その砂は触れたものの時間を止める力を持つが、同時に心の疲れを深く呼び起こし、長い眠りへと誘うという。 | F50: ="【名】" & B50 & C50 &char(10) & "【番】" & text(A50,"0000") & char(10) &"【出現】"&D50& char(10)&"【特質】"& char(10)&E50&char(10)&char(10)&memo!$B$1 -> 【名】玄寿甲（げんじゅこう）genjuko 【番】0048 【出現】古い山寺の裏手にある苔むした石畳、干上がった池の底、海から遠く離れた静かな森の沼地 【特質】 玄寿甲は3億年を生きた末に、もはや歩むことさえ億劫になった老亀の妖怪である。 甲羅は岩のようにひび割れ、苔や小さな草が生えており、動くたびに細かな石片がこぼれ落ちる。 首は異様に長く、皮膚はしわだらけで乾いているが、その瞳には夜空のような深い静寂が宿っている。 常に背を丸め、ため息混じりに空を仰ぐ姿が目撃されるが、その場を離れると数十年は現れない。 言葉を発することは稀であり、耳を澄ませば風に溶けるような低い声で「長き命もまた、苦に成る……」と呟くことがあるという。 玄寿甲に出会った者は、年を経ることの意味と重みを痛感するとされ、何らかの「終わり」や「区切り」を悟るとも言われる。 ただし、害をなすことはなく、むしろ静かに見守る存在である。 まれに、玄寿甲が甲羅をゆっくりと開き、内部に秘めた「時の砂」をひとつまみ振り撒くことがある。 その砂は触れたものの時間を止める力を持つが、同時に心の疲れを深く呼び起こし、長い眠りへと誘うという。 #妖怪 #yokai #sumie #monster #ghost | G50: 45712 | H50: 45741 | I50: ○ | L50: =len(E50) -> 424 | N50: =mid(F50,1,find("【特質】",F50)-1) &char(10)&"＜特質はリプ欄へ＞" & char(10)& memo!$B$2 -> 【名】玄寿甲（げんじゅこう）genjuko 【番】0048 【出現】古い山寺の裏手にある苔むした石畳、干上がった池の底、海から遠く離れた静かな森の沼地 ＜特質はリプ欄へ＞ #妖怪 #お化け #怪物 #オリジナル妖怪 #monster #ghost #妖怪好き #浮世絵 #百鬼夜行 | O50: =len(N50) -> 141 | P50: 【特質】玄寿甲は3億年を生きた末に、もはや歩むことさえ億劫になった老亀の妖怪である。 甲羅は岩のようにひび割れ、苔や小さな草が生えており、動くたびに細かな石片がこぼれ落ちる。 首は異様に長く、皮膚はしわだらけで乾いているが、その瞳には夜空のような深い静寂が宿っている。 | Q50: =len(P50) -> 134 | R50: 常に背を丸め、ため息混じりに空を仰ぐ姿が目撃されるが、その場を離れると数十年は現れない。 言葉を発することは稀であり、耳を澄ませば風に溶けるような低い声で「長き命もまた、苦に成る……」と呟くことがあるという。 | S50: =len(R50) -> 104 | T50: =len(W50) -> 87 | U50: まれに、玄寿甲が甲羅をゆっくりと開き、内部に秘めた「時の砂」をひとつまみ振り撒くことがある。 その砂は触れたものの時間を止める力を持つが、同時に心の疲れを深く呼び起こし、長い眠りへと誘うという。 | V50: =len(U50) -> 97 | W50: 玄寿甲に出会った者は、年を経ることの意味と重みを痛感するとされ、何らかの「終わり」や「区切り」を悟るとも言われる。 ただし、害をなすことはなく、むしろ静かに見守る存在である。 | Y50: =len(X50) -> 0 | AA50: =len(Z50) -> 0 | AC50: =len(AB50) -> 0
A51: 49 | B51: 賃狩守房（ちんがりしゅぼう） | C51: chingarishubo | D51: 古いアパートや長屋の取り壊し予定地、家賃滞納が続く賃貸物件。 | E51: 家賃を滞納し続ける住人に抱いた大家の怨念が積もり積もって生まれた妖怪。 全身が古びた長屋のような姿をしており、朽ちた木枠の窓や錆びた鉄柵が所々に張り付いている。 編笠のような屋根からは絶えず薄い煙が立ちのぼり、内部から誰かのすすり泣きや恨み言のような声がかすかに漏れ聞こえる。 夜になると、滞納者の部屋を訪れ、窓やドアを静かに叩き続ける。 直接危害を加えることはないが、その音は次第に滞納者の心を蝕み、不安と焦燥を募らせる。 朝になると痕跡は残らないが、郵便受けには「未納」「督促」などと書かれた古びた紙片が挟まれていることがある。 どうしても払えない者には、賃狩守房は最後の「救済」と称して、自らの身体に張り付いたアパートの小さな戸を開けさせる。 戸の内側には「当たり」と「外れ」があり、当たりを引けば1ヶ月間の家賃が免除される。 しかし、外れを引いた場合、その者は「空き部屋」に閉じ込められ、上階に住む「うるさい住人」が常に床を踏み鳴らし、家具を引きずる音を響かせる。 外れた者は眠ることもままならず、心身をすり減らしながら、その部屋でいつの日か賃狩守房の一部となっていくという | F51: ="【名】" & B51 & C51 &char(10) & "【番】" & text(A51,"0000") & char(10) &"【出現】"&D51& char(10)&"【特質】"& char(10)&E51&char(10)&char(10)&memo!$B$1 -> 【名】賃狩守房（ちんがりしゅぼう）chingarishubo 【番】0049 【出現】古いアパートや長屋の取り壊し予定地、家賃滞納が続く賃貸物件。 【特質】 家賃を滞納し続ける住人に抱いた大家の怨念が積もり積もって生まれた妖怪。 全身が古びた長屋のような姿をしており、朽ちた木枠の窓や錆びた鉄柵が所々に張り付いている。 編笠のような屋根からは絶えず薄い煙が立ちのぼり、内部から誰かのすすり泣きや恨み言のような声がかすかに漏れ聞こえる。 夜になると、滞納者の部屋を訪れ、窓やドアを静かに叩き続ける。 直接危害を加えることはないが、その音は次第に滞納者の心を蝕み、不安と焦燥を募らせる。 朝になると痕跡は残らないが、郵便受けには「未納」「督促」などと書かれた古びた紙片が挟まれていることがある。 どうしても払えない者には、賃狩守房は最後の「救済」と称して、自らの身体に張り付いたアパートの小さな戸を開けさせる。 戸の内側には「当たり」と「外れ」があり、当たりを引けば1ヶ月間の家賃が免除される。 しかし、外れを引いた場合、その者は「空き部屋」に閉じ込められ、上階に住む「うるさい住人」が常に床を踏み鳴らし、家具を引きずる音を響かせる。 外れた者は眠ることもままならず、心身をすり減らしながら、その部屋でいつの日か賃狩守房の一部となっていくという #妖怪 #yokai #sumie #monster #ghost | G51: 45712 | H51: 45742 | I51: ○ | L51: =len(E51) -> 493 | N51: =mid(F51,1,find("【特質】",F51)-1) &char(10)&"＜特質はリプ欄へ＞" & char(10)& memo!$B$2 -> 【名】賃狩守房（ちんがりしゅぼう）chingarishubo 【番】0049 【出現】古いアパートや長屋の取り壊し予定地、家賃滞納が続く賃貸物件。 ＜特質はリプ欄へ＞ #妖怪 #お化け #怪物 #オリジナル妖怪 #monster #ghost #妖怪好き #浮世絵 #百鬼夜行 | O51: =len(N51) -> 139 | P51: 【特質】家賃を滞納し続ける住人に抱いた大家の怨念が積もり積もって生まれた妖怪。 全身が古びた長屋のような姿をしており、朽ちた木枠の窓や錆びた鉄柵が所々に張り付いている。 編笠のような屋根からは絶えず薄い煙が立ちのぼり、内部から誰かのすすり泣きや恨み言のような声がかすかに漏れ聞こえる。 | Q51: =len(P51) -> 142 | R51: 夜になると、滞納者の部屋を訪れ、窓やドアを静かに叩き続ける。 直接危害を加えることはないが、その音は次第に滞納者の心を蝕み、不安と焦燥を募らせる。 朝になると痕跡は残らないが、郵便受けには「未納」「督促」などと書かれた古びた紙片が挟まれていることがある。 | S51: =len(R51) -> 127 | T51: =len(W51) -> 99 | U51: しかし、外れを引いた場合、その者は「空き部屋」に閉じ込められ、上階に住む「うるさい住人」が常に床を踏み鳴らし、家具を引きずる音を響かせる。 外れた者は眠ることもままならず、心身をすり減らしながら、その部屋でいつの日か賃狩守房の一部となっていくという | V51: =len(U51) -> 124 | W51: どうしても払えない者には、賃狩守房は最後の「救済」と称して、自らの身体に張り付いたアパートの小さな戸を開けさせる。 戸の内側には「当たり」と「外れ」があり、当たりを引けば1ヶ月間の家賃が免除される。 | Y51: =len(X51) -> 0 | AA51: =len(Z51) -> 0 | AC51: =len(AB51) -> 0
A52: 50 | B52: 粉鬼散（こなきさん） | C52: konakisan | D52: 山間の森林や草原など、花粉が多く飛ぶ場所 | E52: 粉鬼散は「花粉の王」と呼ばれる妖怪であり、無数の花粉の精霊を従える存在である。彼の身体は花粉そのものでできており、風とともに流れ、姿を定めることがない。 春になると眠りから覚め、大地に無数の花粉を撒き散らす。 ともに行動する「花精（はなつか）」と呼ばれる極小の精霊たちは、粉鬼散の意志に応じて各地に舞い、花を咲かせ、草木を繁栄させる。 花粉が降り積もった土地では、花々が一斉に芽吹き、豊かな実りをもたらす。 彼は人を見つけると昂揚のあまり武者震いを起こし、普段よりもはるかに多くの花粉を撒き散らしてしまう。 その年は豊作となる一方で、くしゃみは止まらず、鼻は焼けつくようにむず痒く、目は熱を帯びて涙があふれる。 粉鬼散の姿を目撃した年は、例年とは比べものにならないほどの苦しみに見舞われるのだ。 近年、隣町では「黄砂（おうじゃ）」なるものが猛威を振るい、空を曇らせ、人々の喉と鼻を焼いているという噂が広がっている。 粉鬼散は、それを自らと並ぶ好敵手と感じたのか、興奮のあまり再び体を震わせ、空をかき混ぜるように、花粉を踊らせた。 花粉の時期はようやく折り返したが、風はまだ鎮まる気配を見せない。 | F52: ="【名】" & B52 & C52 &char(10) & "【番】" & text(A52,"0000") & char(10) &"【出現】"&D52& char(10)&"【特質】"& char(10)&E52&char(10)&char(10)&memo!$B$1 -> 【名】粉鬼散（こなきさん）konakisan 【番】0050 【出現】山間の森林や草原など、花粉が多く飛ぶ場所 【特質】 粉鬼散は「花粉の王」と呼ばれる妖怪であり、無数の花粉の精霊を従える存在である。彼の身体は花粉そのものでできており、風とともに流れ、姿を定めることがない。 春になると眠りから覚め、大地に無数の花粉を撒き散らす。 ともに行動する「花精（はなつか）」と呼ばれる極小の精霊たちは、粉鬼散の意志に応じて各地に舞い、花を咲かせ、草木を繁栄させる。 花粉が降り積もった土地では、花々が一斉に芽吹き、豊かな実りをもたらす。 彼は人を見つけると昂揚のあまり武者震いを起こし、普段よりもはるかに多くの花粉を撒き散らしてしまう。 その年は豊作となる一方で、くしゃみは止まらず、鼻は焼けつくようにむず痒く、目は熱を帯びて涙があふれる。 粉鬼散の姿を目撃した年は、例年とは比べものにならないほどの苦しみに見舞われるのだ。 近年、隣町では「黄砂（おうじゃ）」なるものが猛威を振るい、空を曇らせ、人々の喉と鼻を焼いているという噂が広がっている。 粉鬼散は、それを自らと並ぶ好敵手と感じたのか、興奮のあまり再び体を震わせ、空をかき混ぜるように、花粉を踊らせた。 花粉の時期はようやく折り返したが、風はまだ鎮まる気配を見せない。 #妖怪 #yokai #sumie #monster #ghost | G52: 45743 | H52: 45743 | I52: ○ | L52: =len(E52) -> 526 | N52: =mid(F52,1,find("【特質】",F52)-1) &char(10)&"＜特質はリプ欄へ＞" & char(10)& memo!$B$2 -> 【名】粉鬼散（こなきさん）konakisan 【番】0050 【出現】山間の森林や草原など、花粉が多く飛ぶ場所 ＜特質はリプ欄へ＞ #妖怪 #お化け #怪物 #オリジナル妖怪 #monster #ghost #妖怪好き #浮世絵 #百鬼夜行 | O52: =len(N52) -> 121 | P52: 【特質】粉鬼散は「花粉の王」と呼ばれる妖怪であり、無数の花粉の精霊を従える存在である。彼の身体は花粉そのものでできており、風とともに流れ、姿を定めることがない。 春になると眠りから覚め、大地に無数の花粉を撒き散らす。 | Q52: =len(P52) -> 110 | R52: ともに行動する「花精（はなつか）」と呼ばれる極小の精霊たちは、粉鬼散の意志に応じて各地に舞い、花を咲かせ、草木を繁栄させる。 花粉が降り積もった土地では、花々が一斉に芽吹き、豊かな実りをもたらす。 | S52: =len(R52) -> 100 | T52: =len(W52) -> 103 | U52: 粉鬼散の姿を目撃した年は、例年とは比べものにならないほどの苦しみに見舞われるのだ。 近年、隣町では「黄砂（おうじゃ）」なるものが猛威を振るい、空を曇らせ、人々の喉と鼻を焼いているという噂が広がっている。 | V52: =len(U52) -> 106 | W52: 彼は人を見つけると昂揚のあまり武者震いを起こし、普段よりもはるかに多くの花粉を撒き散らしてしまう。 その年は豊作となる一方で、くしゃみは止まらず、鼻は焼けつくようにむず痒く、目は熱を帯びて涙があふれる。 | X52: 粉鬼散は、それを自らと並ぶ好敵手と感じたのか、興奮のあまり再び体を震わせ、空をかき混ぜるように、花粉を踊らせた。 花粉の時期はようやく折り返したが、風はまだ鎮まる気配を見せない。 | Y52: =len(X52) -> 92 | AA52: =len(Z52) -> 0 | AC52: =len(AB52) -> 0
A53: 51 | B53: 平衡喰（へいこうぐい） | C53: heikogui | D53: 山間の廃村、使われなくなった学び舎の校庭 | E53: 均衡を失った場所に現れ、心の迷いを餌とする妖怪。 かつて子供たちが遊んでいた古いシーソーに擬態しており、傾き具合によってその力を増減させる。 人が端に立つと反対側に重さを生じさせ、何もない空間に幻影を映し出す。 失ったもの、叶わなかった夢、抑え込んだ後悔など、その者にとって最も心を揺さぶる情景を見せ、平衡を保とうとする精神を揺るがす。 完全に心が傾いた瞬間、シーソーは深く軋みながら傾斜を増し、乗った者を底知れぬ裂け目へと滑り落とすという。 その裂け目からは、過去に飲み込まれた者たちの微かな嘆きが夜風に乗って聞こえてくる。 稀に、心の揺れに耐え、静かに降りることができれば、幻影は消え去り、妖怪は力を失って朽ち果てた木片へと戻る。 だが、その場を離れるまで背後から軋む音が追いかけてくることから、完全に解放されたかどうかは定かではない。 | F53: ="【名】" & B53 & C53 &char(10) & "【番】" & text(A53,"0000") & char(10) &"【出現】"&D53& char(10)&"【特質】"& char(10)&E53&char(10)&char(10)&memo!$B$1 -> 【名】平衡喰（へいこうぐい）heikogui 【番】0051 【出現】山間の廃村、使われなくなった学び舎の校庭 【特質】 均衡を失った場所に現れ、心の迷いを餌とする妖怪。 かつて子供たちが遊んでいた古いシーソーに擬態しており、傾き具合によってその力を増減させる。 人が端に立つと反対側に重さを生じさせ、何もない空間に幻影を映し出す。 失ったもの、叶わなかった夢、抑え込んだ後悔など、その者にとって最も心を揺さぶる情景を見せ、平衡を保とうとする精神を揺るがす。 完全に心が傾いた瞬間、シーソーは深く軋みながら傾斜を増し、乗った者を底知れぬ裂け目へと滑り落とすという。 その裂け目からは、過去に飲み込まれた者たちの微かな嘆きが夜風に乗って聞こえてくる。 稀に、心の揺れに耐え、静かに降りることができれば、幻影は消え去り、妖怪は力を失って朽ち果てた木片へと戻る。 だが、その場を離れるまで背後から軋む音が追いかけてくることから、完全に解放されたかどうかは定かではない。 #妖怪 #yokai #sumie #monster #ghost | G53: 45712 | H53: 45744 | I53: ○ | L53: =len(E53) -> 373 | N53: =mid(F53,1,find("【特質】",F53)-1) &char(10)&"＜特質はリプ欄へ＞" & char(10)& memo!$B$2 -> 【名】平衡喰（へいこうぐい）heikogui 【番】0051 【出現】山間の廃村、使われなくなった学び舎の校庭 ＜特質はリプ欄へ＞ #妖怪 #お化け #怪物 #オリジナル妖怪 #monster #ghost #妖怪好き #浮世絵 #百鬼夜行 | O53: =len(N53) -> 121 | P53: 【特質】均衡を失った場所に現れ、心の迷いを餌とする妖怪。 かつて子供たちが遊んでいた古いシーソーに擬態しており、傾き具合によってその力を増減させる。 人が端に立つと反対側に重さを生じさせ、何もない空間に幻影を映し出す。 | Q53: =len(P53) -> 110 | R53: 失ったもの、叶わなかった夢、抑え込んだ後悔など、その者にとって最も心を揺さぶる情景を見せ、平衡を保とうとする精神を揺るがす。 完全に心が傾いた瞬間、シーソーは深く軋みながら傾斜を増し、乗った者を底知れぬ裂け目へと滑り落とすという。 | S53: =len(R53) -> 116 | T53: =len(W53) -> 96 | U53: だが、その場を離れるまで背後から軋む音が追いかけてくることから、完全に解放されたかどうかは定かではない。 | V53: =len(U53) -> 52 | W53: その裂け目からは、過去に飲み込まれた者たちの微かな嘆きが夜風に乗って聞こえてくる。 稀に、心の揺れに耐え、静かに降りることができれば、幻影は消え去り、妖怪は力を失って朽ち果てた木片へと戻る。 | Y53: =len(X53) -> 0 | AA53: =len(Z53) -> 0 | AC53: =len(AB53) -> 0
A54: 52 | B54: 地獄面須（へるめす） | C54: herumesu | D54: 人通りの少ない駅や空港の手荷物預かり所、古道具市 | E54: 地獄面須は、持ち主を失った古いカバンに宿る怨念が具現化した妖怪である。 一見すると何の変哲もない古びたカバンだが、よく見ると表面に無数の目のような模様が浮かび上がり、時折それらが瞬きするかのように揺らめく。 取っ手や金具は至って普通で、むしろ手入れが行き届いているように見えるため、余計に不気味さを引き立てている。 この妖怪は放置された荷物に紛れ込み、旅の途中で行き場を失った「荷物」と「持ち主」の恨みを糧として存在する。 道端や駅の片隅にぽつんと置かれ、無防備に手を伸ばして開けた者は、カバンの内部に広がる深い闇に引きずり込まれる。 そしてその瞬間、カバンは空になったように軽くなり、引き込まれた者は行方不明となる。 回避するには「お口チャック」と心得ることが重要だ。 地獄面須はチャックのような口を持つことから、カバンを見かけても「口を開かせない」「声をかけない」ことが鉄則とされている。 うっかり話しかけたり、興味本位で開けようとした瞬間、ファスナーは音もなく滑り、持ち主を餌食にするという。 近年では、リサイクルショップや古道具市で「妙に状態の良い古いカバン」が安価で売られているという噂があり、旅人や骨董品収集家の間で密かに警戒されている。 | F54: ="【名】" & B54 & C54 &char(10) & "【番】" & text(A54,"0000") & char(10) &"【出現】"&D54& char(10)&"【特質】"& char(10)&E54&char(10)&char(10)&memo!$B$1 -> 【名】地獄面須（へるめす）herumesu 【番】0052 【出現】人通りの少ない駅や空港の手荷物預かり所、古道具市 【特質】 地獄面須は、持ち主を失った古いカバンに宿る怨念が具現化した妖怪である。 一見すると何の変哲もない古びたカバンだが、よく見ると表面に無数の目のような模様が浮かび上がり、時折それらが瞬きするかのように揺らめく。 取っ手や金具は至って普通で、むしろ手入れが行き届いているように見えるため、余計に不気味さを引き立てている。 この妖怪は放置された荷物に紛れ込み、旅の途中で行き場を失った「荷物」と「持ち主」の恨みを糧として存在する。 道端や駅の片隅にぽつんと置かれ、無防備に手を伸ばして開けた者は、カバンの内部に広がる深い闇に引きずり込まれる。 そしてその瞬間、カバンは空になったように軽くなり、引き込まれた者は行方不明となる。 回避するには「お口チャック」と心得ることが重要だ。 地獄面須はチャックのような口を持つことから、カバンを見かけても「口を開かせない」「声をかけない」ことが鉄則とされている。 うっかり話しかけたり、興味本位で開けようとした瞬間、ファスナーは音もなく滑り、持ち主を餌食にするという。 近年では、リサイクルショップや古道具市で「妙に状態の良い古いカバン」が安価で売られているという噂があり、旅人や骨董品収集家の間で密かに警戒されている。 #妖怪 #yokai #sumie #monster #ghost | G54: 45712 | H54: 45745 | I54: ○ | L54: =len(E54) -> 528 | N54: =mid(F54,1,find("【特質】",F54)-1) &char(10)&"＜特質はリプ欄へ＞" & char(10)& memo!$B$2 -> 【名】地獄面須（へるめす）herumesu 【番】0052 【出現】人通りの少ない駅や空港の手荷物預かり所、古道具市 ＜特質はリプ欄へ＞ #妖怪 #お化け #怪物 #オリジナル妖怪 #monster #ghost #妖怪好き #浮世絵 #百鬼夜行 | O54: =len(N54) -> 124 | P54: 【特質】地獄面須は、持ち主を失った古いカバンに宿る怨念が具現化した妖怪である。 一見すると何の変哲もない古びたカバンだが、よく見ると表面に無数の目のような模様が浮かび上がり、時折それらが瞬きするかのように揺らめく。 | Q54: =len(P54) -> 107 | R54: 取っ手や金具は至って普通で、むしろ手入れが行き届いているように見えるため、余計に不気味さを引き立てている。 この妖怪は放置された荷物に紛れ込み、旅の途中で行き場を失った「荷物」と「持ち主」の恨みを糧として存在する。 | S54: =len(R54) -> 108 | T54: =len(W54) -> 97 | U54: 回避するには「お口チャック」と心得ることが重要だ。 地獄面須はチャックのような口を持つことから、カバンを見かけても「口を開かせない」「声をかけない」ことが鉄則とされている。 うっかり話しかけたり、興味本位で開けようとした瞬間、ファスナーは音もなく滑り、持ち主を餌食にするという。 | V54: =len(U54) -> 139 | W54: 道端や駅の片隅にぽつんと置かれ、無防備に手を伸ばして開けた者は、カバンの内部に広がる深い闇に引きずり込まれる。 そしてその瞬間、カバンは空になったように軽くなり、引き込まれた者は行方不明となる。 | X54: 近年では、リサイクルショップや古道具市で「妙に状態の良い古いカバン」が安価で売られているという噂があり、旅人や骨董品収集家の間で密かに警戒されている。 | Y54: =len(X54) -> 75 | AA54: =len(Z54) -> 0 | AC54: =len(AB54) -> 0
A55: 53 | B55: 双針鬼（そうしんき） | C55: soshinki | D55: 古い時計塔、廃墟となった寺社の時打ち鐘付近、時間が狂った時計店 | E55: 双針鬼は、短針と長針の妖怪が一つの存在として生まれた時間の化身である。 短針は「遅刻の鬼」として、過ぎ去る時間を惜しみながら人々の行動を遅らせる。 長針は「早廻の鬼」として、まだ来ぬ未来を急かすように時間を奪い取る。 姿は二体の影のような存在で、互いの体が絡み合いながら時計の針を模した不規則な動きを繰り返す。 顔は能面のように無機質だが、短針鬼は欠けた仮面を、長針鬼はひび割れた仮面を身につけ、それぞれ片目だけが光る。 彼らは時を正しく刻む存在ではなく、時間の流れを狂わせる存在だ。 双針鬼が取り憑いた場所では、時計は前後無秩序に動き、人々は約束の時間に遅れたり、まだ来ない未来を焦るようになる。 時折、風もないのに時計の針が音もなく動くことがあり、その瞬間に「双針鬼が近くにいる」と囁かれる。 しかし、完全に時間を止めることはできない。 双針鬼は「永遠に巡る運命の象徴」であり、たとえ針が進まなくとも、時の流れ自体は続くことを示している。 時計を逆さにして寝ると双針鬼を遠ざけることができるとされるが、それは単なる迷信に過ぎない。 彼らは、時を意識する限り、心の隙間から忍び寄る存在なのだ。 | F55: ="【名】" & B55 & C55 &char(10) & "【番】" & text(A55,"0000") & char(10) &"【出現】"&D55& char(10)&"【特質】"& char(10)&E55&char(10)&char(10)&memo!$B$1 -> 【名】双針鬼（そうしんき）soshinki 【番】0053 【出現】古い時計塔、廃墟となった寺社の時打ち鐘付近、時間が狂った時計店 【特質】 双針鬼は、短針と長針の妖怪が一つの存在として生まれた時間の化身である。 短針は「遅刻の鬼」として、過ぎ去る時間を惜しみながら人々の行動を遅らせる。 長針は「早廻の鬼」として、まだ来ぬ未来を急かすように時間を奪い取る。 姿は二体の影のような存在で、互いの体が絡み合いながら時計の針を模した不規則な動きを繰り返す。 顔は能面のように無機質だが、短針鬼は欠けた仮面を、長針鬼はひび割れた仮面を身につけ、それぞれ片目だけが光る。 彼らは時を正しく刻む存在ではなく、時間の流れを狂わせる存在だ。 双針鬼が取り憑いた場所では、時計は前後無秩序に動き、人々は約束の時間に遅れたり、まだ来ない未来を焦るようになる。 時折、風もないのに時計の針が音もなく動くことがあり、その瞬間に「双針鬼が近くにいる」と囁かれる。 しかし、完全に時間を止めることはできない。 双針鬼は「永遠に巡る運命の象徴」であり、たとえ針が進まなくとも、時の流れ自体は続くことを示している。 時計を逆さにして寝ると双針鬼を遠ざけることができるとされるが、それは単なる迷信に過ぎない。 彼らは、時を意識する限り、心の隙間から忍び寄る存在なのだ。 #妖怪 #yokai #sumie #monster #ghost | G55: 45712 | H55: 45746 | I55: ○ | L55: =len(E55) -> 501 | N55: =mid(F55,1,find("【特質】",F55)-1) &char(10)&"＜特質はリプ欄へ＞" & char(10)& memo!$B$2 -> 【名】双針鬼（そうしんき）soshinki 【番】0053 【出現】古い時計塔、廃墟となった寺社の時打ち鐘付近、時間が狂った時計店 ＜特質はリプ欄へ＞ #妖怪 #お化け #怪物 #オリジナル妖怪 #monster #ghost #妖怪好き #浮世絵 #百鬼夜行 | O55: =len(N55) -> 131 | P55: 【特質】双針鬼は、短針と長針の妖怪が一つの存在として生まれた時間の化身である。 短針は「遅刻の鬼」として、過ぎ去る時間を惜しみながら人々の行動を遅らせる。 長針は「早廻の鬼」として、まだ来ぬ未来を急かすように時間を奪い取る。 | Q55: =len(P55) -> 112 | R55: 姿は二体の影のような存在で、互いの体が絡み合いながら時計の針を模した不規則な動きを繰り返す。 顔は能面のように無機質だが、短針鬼は欠けた仮面を、長針鬼はひび割れた仮面を身につけ、それぞれ片目だけが光る。 彼らは時を正しく刻む存在ではなく、時間の流れを狂わせる存在だ。 | S55: =len(R55) -> 134 | T55: =len(W55) -> 128 | U55: 双針鬼は「永遠に巡る運命の象徴」であり、たとえ針が進まなくとも、時の流れ自体は続くことを示している。 時計を逆さにして寝ると双針鬼を遠ざけることができるとされるが、それは単なる迷信に過ぎない。 彼らは、時を意識する限り、心の隙間から忍び寄る存在なのだ。 | V55: =len(U55) -> 127 | W55: 双針鬼が取り憑いた場所では、時計は前後無秩序に動き、人々は約束の時間に遅れたり、まだ来ない未来を焦るようになる。 時折、風もないのに時計の針が音もなく動くことがあり、その瞬間に「双針鬼が近くにいる」と囁かれる。 しかし、完全に時間を止めることはできない。 | Y55: =len(X55) -> 0 | AA55: =len(Z55) -> 0 | AC55: =len(AB55) -> 0
A56: 54 | B56: 銀幕幻影物語（ぎんまくげんえいものがたり） | C56: gimmakugeneimonogatari | D56: 映画館 | E56: 実在した「映画岡引（えいがおかっぴき）」と「映画泥坊（えいがどろぼう）」――ついに映画化！ かつて映画館に現れ、人々を震え上がらせた実在の怪異が、ついにスクリーンへ！ 昭和初期から語り継がれる、映画館を巡る不可解な失踪事件。 観客の影がスクリーンに映り込む怪奇現象。 そして、映画フィルムを操り、人々を銀幕の中へ引きずり込む妖怪「映画泥坊」。 その悪行を追い続け、闇の中に裁きを下す「映画岡引」。 語り継がれた伝説が、今、史上初の映画化――！ 妖怪たちの大捕物劇が織りなす、恐怖と狂気の映像体験。 スクリーンを超えた“幻影”の世界に、あなたは耐えられるか……？ 「銀幕幻影物語」――幕が上がると、もう戻れない。 | F56: ="【名】" & B56 & C56 &char(10) & "【番】" & text(A56,"0000") & char(10) &"【出現】"&D56& char(10)&"【特質】"& char(10)&E56&char(10)&char(10)& "#銀幕幻影物語 " &memo!$B$1 -> 【名】銀幕幻影物語（ぎんまくげんえいものがたり）gimmakugeneimonogatari 【番】0054 【出現】映画館 【特質】 実在した「映画岡引（えいがおかっぴき）」と「映画泥坊（えいがどろぼう）」――ついに映画化！ かつて映画館に現れ、人々を震え上がらせた実在の怪異が、ついにスクリーンへ！ 昭和初期から語り継がれる、映画館を巡る不可解な失踪事件。 観客の影がスクリーンに映り込む怪奇現象。 そして、映画フィルムを操り、人々を銀幕の中へ引きずり込む妖怪「映画泥坊」。 その悪行を追い続け、闇の中に裁きを下す「映画岡引」。 語り継がれた伝説が、今、史上初の映画化――！ 妖怪たちの大捕物劇が織りなす、恐怖と狂気の映像体験。 スクリーンを超えた“幻影”の世界に、あなたは耐えられるか……？ 「銀幕幻影物語」――幕が上がると、もう戻れない。 #銀幕幻影物語 #妖怪 #yokai #sumie #monster #ghost | G56: 45703 | H56: 45747 | I56: ○ | L56: =len(E56) -> 310 | N56: =mid(F56,1,find("【特質】",F56)-1) &char(10)&"＜特質はリプ欄へ＞" & char(10)& "#銀幕幻影物語 " & memo!$B$2 -> 【名】銀幕幻影物語（ぎんまくげんえいものがたり）gimmakugeneimonogatari 【番】0054 【出現】映画館 ＜特質はリプ欄へ＞ #銀幕幻影物語 #妖怪 #お化け #怪物 #オリジナル妖怪 #monster #ghost #妖怪好き #浮世絵 #百鬼夜行 | O56: =len(N56) -> 136 | P56: 【特質】実在した「映画岡引（えいがおかっぴき）」と「映画泥坊（えいがどろぼう）」――ついに映画化！ かつて映画館に現れ、人々を震え上がらせた実在の怪異が、ついにスクリーンへ！ 昭和初期から語り継がれる、映画館を巡る不可解な失踪事件。 観客の影がスクリーンに映り込む怪奇現象。 | Q56: =len(P56) -> 138 | R56: そして、映画フィルムを操り、人々を銀幕の中へ引きずり込む妖怪「映画泥坊」。 その悪行を追い続け、闇の中に裁きを下す「映画岡引」。 語り継がれた伝説が、今、史上初の映画化――！ 妖怪たちの大捕物劇が織りなす、恐怖と狂気の映像体験。 | S56: =len(R56) -> 117 | T56: =len(W56) -> 57 | V56: =len(U56) -> 0 | W56: スクリーンを超えた“幻影”の世界に、あなたは耐えられるか……？ 「銀幕幻影物語」――幕が上がると、もう戻れない。 | Y56: =len(X56) -> 0 | AA56: =len(Z56) -> 0 | AC56: =len(AB56) -> 0
A57: 55 | B57: 散華妖女（さんげようじょ） | C57: sangeyojo | D57: 誰も通らぬ山奥の古桜群 | E57: 散華妖女は、花として散りきれなかった情念から生まれた存在である。 春の終わり、風に乗って地に落ちるはずだった桜の花びらのうち、ほんの一片でも「まだ咲いていたい」と願ったものがあると、やがてその想いが積もり、形を持ちはじめる。 やがてそれは人の姿に似た影を成し、無言のまま漂い歩くようになる。 彼女の体は、まさに「散りきれぬ花」の集合体である。 咲ききったはずの花が再びほころび、また散り、また咲き、永遠に終わることのない春を身にまとう。 花びらは身体から離れてもなお消えず、風に乗って舞ったかと思えば、いつのまにか元の位置に戻っている。 まるで終わらない夢を何度も繰り返すかのように。 彼女はどこからともなく現れ、風の流れのままに歩き、また姿を消す。 光の届かぬ場所を好み、枯れ葉の下にまだ残る湿った花を拾い、胸元に抱いて離さない。 美しくもあり、痛々しくもあるその姿は、春を惜しむ心そのもののようである。 人と関わることはないが、山中に彼女の通った跡があると、そこでは必ず季節がひとつだけ遅れて流れているという。 花が散っているのに香りが残り、風が温んでいるのに冷たい霧が立つ。 誰かが強く春を願ったその場所に、彼女はふと現れ、また姿を溶かしていく。 終わることができない花は、美しいまま朽ちていくしかない。 それこそが、散華妖女の哀しみである。 | F57: ="【名】" & B57 & C57 &char(10) & "【番】" & text(A57,"0000") & char(10) &"【出現】"&D57& char(10)&"【特質】"& char(10)&E57&char(10)&char(10)&memo!$B$1 -> 【名】散華妖女（さんげようじょ）sangeyojo 【番】0055 【出現】誰も通らぬ山奥の古桜群 【特質】 散華妖女は、花として散りきれなかった情念から生まれた存在である。 春の終わり、風に乗って地に落ちるはずだった桜の花びらのうち、ほんの一片でも「まだ咲いていたい」と願ったものがあると、やがてその想いが積もり、形を持ちはじめる。 やがてそれは人の姿に似た影を成し、無言のまま漂い歩くようになる。 彼女の体は、まさに「散りきれぬ花」の集合体である。 咲ききったはずの花が再びほころび、また散り、また咲き、永遠に終わることのない春を身にまとう。 花びらは身体から離れてもなお消えず、風に乗って舞ったかと思えば、いつのまにか元の位置に戻っている。 まるで終わらない夢を何度も繰り返すかのように。 彼女はどこからともなく現れ、風の流れのままに歩き、また姿を消す。 光の届かぬ場所を好み、枯れ葉の下にまだ残る湿った花を拾い、胸元に抱いて離さない。 美しくもあり、痛々しくもあるその姿は、春を惜しむ心そのもののようである。 人と関わることはないが、山中に彼女の通った跡があると、そこでは必ず季節がひとつだけ遅れて流れているという。 花が散っているのに香りが残り、風が温んでいるのに冷たい霧が立つ。 誰かが強く春を願ったその場所に、彼女はふと現れ、また姿を溶かしていく。 終わることができない花は、美しいまま朽ちていくしかない。 それこそが、散華妖女の哀しみである。 #妖怪 #yokai #sumie #monster #ghost | G57: 45748 | H57: 45748 | I57: ○ | L57: =len(E57) -> 578 | N57: =mid(F57,1,find("【特質】",F57)-1) &char(10)&"＜特質はリプ欄へ＞" & char(10)& memo!$B$2 -> 【名】散華妖女（さんげようじょ）sangeyojo 【番】0055 【出現】誰も通らぬ山奥の古桜群 ＜特質はリプ欄へ＞ #妖怪 #お化け #怪物 #オリジナル妖怪 #monster #ghost #妖怪好き #浮世絵 #百鬼夜行 | O57: =len(N57) -> 115 | P57: 【特質】散華妖女は、花として散りきれなかった情念から生まれた存在である。 春の終わり、風に乗って地に落ちるはずだった桜の花びらのうち、ほんの一片でも「まだ咲いていたい」と願ったものがあると、やがてその想いが積もり、形を持ちはじめる。 | Q57: =len(P57) -> 116 | R57: やがてそれは人の姿に似た影を成し、無言のまま漂い歩くようになる。 彼女の体は、まさに「散りきれぬ花」の集合体である。 咲ききったはずの花が再びほころび、また散り、また咲き、永遠に終わることのない春を身にまとう。 | S57: =len(R57) -> 106 | T57: =len(W57) -> 107 | U57: 光の届かぬ場所を好み、枯れ葉の下にまだ残る湿った花を拾い、胸元に抱いて離さない。 美しくもあり、痛々しくもあるその姿は、春を惜しむ心そのもののようである。 人と関わることはないが、山中に彼女の通った跡があると、そこでは必ず季節がひとつだけ遅れて流れているという。 | V57: =len(U57) -> 132 | W57: 花びらは身体から離れてもなお消えず、風に乗って舞ったかと思えば、いつのまにか元の位置に戻っている。 まるで終わらない夢を何度も繰り返すかのように。 彼女はどこからともなく現れ、風の流れのままに歩き、また姿を消す。 | X57: 花が散っているのに香りが残り、風が温んでいるのに冷たい霧が立つ。 誰かが強く春を願ったその場所に、彼女はふと現れ、また姿を溶かしていく。 終わることができない花は、美しいまま朽ちていくしかない。 それこそが、散華妖女の哀しみである。 | Y57: =len(X57) -> 117 | AA57: =len(Z57) -> 0 | AC57: =len(AB57) -> 0
A58: 56 | B58: 絡繰脚（からくりあし） | C58: karakuriashi | D58: 古着屋の裏路地、処分された衣類が集まる回収ボックス周辺 | E58: 絡繰脚は、古くから存在する妖怪だが、近年「今風にアップデートすれば恐れられるのでは」と思い立ち、流行のファッションを取り入れようとした結果生まれた姿である。 本来は素足に擦り切れた足袋をまとっていたが、現代の若者文化に影響され、ニーハイソックスを身に着けるようになった。 しかし、そのハイソックスは彼にとってしっくりこないらしく、歩くたびに「なんか違う…」「やっぱり足袋の方が良かったか？」とぶつぶつ呟いている。 見た目も、トレンドを取り入れようとしたものの、微妙に時代遅れのセンスでまとまっており、若者に「ダサかわ」と失笑されることも。 絡繰脚は「今風」を装って近づき、気に入った靴下を履いている人間に狙いを定める。 足に絡みついて動きを鈍らせ、相手が倒れた隙に靴下を奪おうとするが、結局「これも違うな…」と放り出してしまうことがほとんど。 最近では「流行を追うより、己のスタイルを貫くべきでは？」と悟りかけており、古びた足袋に戻る日も近いかもしれない。 | F58: ="【名】" & B58 & C58 &char(10) & "【番】" & text(A58,"0000") & char(10) &"【出現】"&D58& char(10)&"【特質】"& char(10)&E58&char(10)&char(10)&memo!$B$1 -> 【名】絡繰脚（からくりあし）karakuriashi 【番】0056 【出現】古着屋の裏路地、処分された衣類が集まる回収ボックス周辺 【特質】 絡繰脚は、古くから存在する妖怪だが、近年「今風にアップデートすれば恐れられるのでは」と思い立ち、流行のファッションを取り入れようとした結果生まれた姿である。 本来は素足に擦り切れた足袋をまとっていたが、現代の若者文化に影響され、ニーハイソックスを身に着けるようになった。 しかし、そのハイソックスは彼にとってしっくりこないらしく、歩くたびに「なんか違う…」「やっぱり足袋の方が良かったか？」とぶつぶつ呟いている。 見た目も、トレンドを取り入れようとしたものの、微妙に時代遅れのセンスでまとまっており、若者に「ダサかわ」と失笑されることも。 絡繰脚は「今風」を装って近づき、気に入った靴下を履いている人間に狙いを定める。 足に絡みついて動きを鈍らせ、相手が倒れた隙に靴下を奪おうとするが、結局「これも違うな…」と放り出してしまうことがほとんど。 最近では「流行を追うより、己のスタイルを貫くべきでは？」と悟りかけており、古びた足袋に戻る日も近いかもしれない。 #妖怪 #yokai #sumie #monster #ghost | G58: 45712 | H58: 45749 | I58: ○ | L58: =len(E58) -> 434 | N58: =mid(F58,1,find("【特質】",F58)-1) &char(10)&"＜特質はリプ欄へ＞" & char(10)& memo!$B$2 -> 【名】絡繰脚（からくりあし）karakuriashi 【番】0056 【出現】古着屋の裏路地、処分された衣類が集まる回収ボックス周辺 ＜特質はリプ欄へ＞ #妖怪 #お化け #怪物 #オリジナル妖怪 #monster #ghost #妖怪好き #浮世絵 #百鬼夜行 | O58: =len(N58) -> 132 | P58: 【特質】絡繰脚は、古くから存在する妖怪だが、近年「今風にアップデートすれば恐れられるのでは」と思い立ち、流行のファッションを取り入れようとした結果生まれた姿である。 本来は素足に擦り切れた足袋をまとっていたが、現代の若者文化に影響され、ニーハイソックスを身に着けるようになった。 | Q58: =len(P58) -> 139 | R58: しかし、そのハイソックスは彼にとってしっくりこないらしく、歩くたびに「なんか違う…」「やっぱり足袋の方が良かったか？」とぶつぶつ呟いている。 見た目も、トレンドを取り入れようとしたものの、微妙に時代遅れのセンスでまとまっており、若者に「ダサかわ」と失笑されることも。 | S58: =len(R58) -> 133 | T58: =len(W58) -> 101 | U58: 最近では「流行を追うより、己のスタイルを貫くべきでは？」と悟りかけており、古びた足袋に戻る日も近いかもしれない。 | V58: =len(U58) -> 56 | W58: 絡繰脚は「今風」を装って近づき、気に入った靴下を履いている人間に狙いを定める。 足に絡みついて動きを鈍らせ、相手が倒れた隙に靴下を奪おうとするが、結局「これも違うな…」と放り出してしまうことがほとんど。 | Y58: =len(X58) -> 0 | AA58: =len(Z58) -> 0 | AC58: =len(AB58) -> 0
A59: 57 | B59: 糞魂塊（ふんこんかい） | C59: funkonkai | D59: 乾いた草原、放棄された牧場、獣道の果て | E59: かつて、フンコロガシたちは昼夜を問わず糞を転がし、蓄え続けていた。 それは己の糧であり、次の世代へとつなぐための貯蔵だった。 しかし、ある一匹のフンコロガシが異常な執念を持ち、際限なく糞を集め続けたことで、想定を超えた巨大な塊が生まれた。 その塊には、草食獣の糞、肉食獣の糞、人間の落としたものまで、あらゆる生物の排泄物が混じり合い、時間の経過とともに異様な変化を遂げた。 発酵が進み、内部で熱とガスが生まれ、無数の菌や微生物が異常繁殖し、やがてその塊は「ひとつの意志」を持つに至った。 最初に異変が起こったのは、執拗にその塊を転がし続けたフンコロガシ自身だった。 彼はある日、その塊に飲み込まれた。仲間たちが驚き、近寄ると、塊は微かに蠢き、フンコロガシの姿はすでにその表面の一部へと変わっていた。 以降、その塊は誰の手も借りず、自ら転がるようになった。 それからというもの、糞魂塊は転がりながら成長を続け、次々と動物たちを取り込み、獣道を這いずる異形の存在となった。 まるで生きているかのように、獲物を求めてゆっくりと移動し、夜になると奇妙な呻き声とともに地面を震わせながら進む。 村人の間では、「夜、転がる音を聞いたら戸を開けるな」と言い伝えられている。 糞魂塊は獲物を見つけると、じわじわとその足元に迫り、知らぬ間に飲み込んでしまうのだ。 翌朝にはただ、さらに大きくなった塊が転がっているだけ。 もはやそれは、ただのフンではない。 フンコロガシが生み出した、自らの主を超えた存在――それが糞魂塊である。 | F59: ="【名】" & B59 & C59 &char(10) & "【番】" & text(A59,"0000") & char(10) &"【出現】"&D59& char(10)&"【特質】"& char(10)&E59&char(10)&char(10)&memo!$B$1 -> 【名】糞魂塊（ふんこんかい）funkonkai 【番】0057 【出現】乾いた草原、放棄された牧場、獣道の果て 【特質】 かつて、フンコロガシたちは昼夜を問わず糞を転がし、蓄え続けていた。 それは己の糧であり、次の世代へとつなぐための貯蔵だった。 しかし、ある一匹のフンコロガシが異常な執念を持ち、際限なく糞を集め続けたことで、想定を超えた巨大な塊が生まれた。 その塊には、草食獣の糞、肉食獣の糞、人間の落としたものまで、あらゆる生物の排泄物が混じり合い、時間の経過とともに異様な変化を遂げた。 発酵が進み、内部で熱とガスが生まれ、無数の菌や微生物が異常繁殖し、やがてその塊は「ひとつの意志」を持つに至った。 最初に異変が起こったのは、執拗にその塊を転がし続けたフンコロガシ自身だった。 彼はある日、その塊に飲み込まれた。仲間たちが驚き、近寄ると、塊は微かに蠢き、フンコロガシの姿はすでにその表面の一部へと変わっていた。 以降、その塊は誰の手も借りず、自ら転がるようになった。 それからというもの、糞魂塊は転がりながら成長を続け、次々と動物たちを取り込み、獣道を這いずる異形の存在となった。 まるで生きているかのように、獲物を求めてゆっくりと移動し、夜になると奇妙な呻き声とともに地面を震わせながら進む。 村人の間では、「夜、転がる音を聞いたら戸を開けるな」と言い伝えられている。 糞魂塊は獲物を見つけると、じわじわとその足元に迫り、知らぬ間に飲み込んでしまうのだ。 翌朝にはただ、さらに大きくなった塊が転がっているだけ。 もはやそれは、ただのフンではない。 フンコロガシが生み出した、自らの主を超えた存在――それが糞魂塊である。 #妖怪 #yokai #sumie #monster #ghost | G59: 45715 | H59: 45750 | I59: ○ | L59: =len(E59) -> 658 | N59: =mid(F59,1,find("【特質】",F59)-1) &char(10)&"＜特質はリプ欄へ＞" & char(10)& memo!$B$2 -> 【名】糞魂塊（ふんこんかい）funkonkai 【番】0057 【出現】乾いた草原、放棄された牧場、獣道の果て ＜特質はリプ欄へ＞ #妖怪 #お化け #怪物 #オリジナル妖怪 #monster #ghost #妖怪好き #浮世絵 #百鬼夜行 | O59: =len(N59) -> 121 | P59: 【特質】かつて、フンコロガシたちは昼夜を問わず糞を転がし、蓄え続けていた。 それは己の糧であり、次の世代へとつなぐための貯蔵だった。 しかし、ある一匹のフンコロガシが異常な執念を持ち、際限なく糞を集め続けたことで、想定を超えた巨大な塊が生まれた。 | Q59: =len(P59) -> 123 | R59: その塊には、草食獣の糞、肉食獣の糞、人間の落としたものまで、あらゆる生物の排泄物が混じり合い、時間の経過とともに異様な変化を遂げた。 発酵が進み、内部で熱とガスが生まれ、無数の菌や微生物が異常繁殖し、やがてその塊は「ひとつの意志」を持つに至った。 | S59: =len(R59) -> 123 | T59: =len(W59) -> 133 | U59: それからというもの、糞魂塊は転がりながら成長を続け、次々と動物たちを取り込み、獣道を這いずる異形の存在となった。 まるで生きているかのように、獲物を求めてゆっくりと移動し、夜になると奇妙な呻き声とともに地面を震わせながら進む。 | V59: =len(U59) -> 113 | W59: 最初に異変が起こったのは、執拗にその塊を転がし続けたフンコロガシ自身だった。 彼はある日、その塊に飲み込まれた。仲間たちが驚き、近寄ると、塊は微かに蠢き、フンコロガシの姿はすでにその表面の一部へと変わっていた。 以降、その塊は誰の手も借りず、自ら転がるようになった。 | X59: 村人の間では、「夜、転がる音を聞いたら戸を開けるな」と言い伝えられている。 糞魂塊は獲物を見つけると、じわじわとその足元に迫り、知らぬ間に飲み込んでしまうのだ。 翌朝にはただ、さらに大きくなった塊が転がっているだけ。 | Y59: =len(X59) -> 108 | Z59: もはやそれは、ただのフンではない。 フンコロガシが生み出した、自らの主を超えた存在――それが糞魂塊である。 | AA59: =len(Z59) -> 54 | AC59: =len(AB59) -> 0
A60: 58 | B60: 魔遮幽鬼（ましゃゆき） | C60: mashayuki | D60: 場末のスナック。古びたカラオケの音が響くカウンター席の端。 | E60: 何を言っても「違う、そうじゃない」と否定を繰り返す妖怪。 場末のスナックにふらりと現れ、酒を片手に誰かの話に口を挟む。 「この曲、いいね」と言えば「違う、そうじゃない」と言い、「この酒、うまいな」と言えば「違う、そうじゃない」と返す。 だが、何が正しいのかは決して教えない。 ピンク色のスーツを着こなし、サングラスの奥の目は虚ろに沈んでいる。 口の上には薄く整えられた口ひげがあり、一見するとただの酔客のようだが、彼の周りには妙な違和感が漂う。 カラオケのマイクを取れば、何かを歌うでもなく、ただ「違う、そうじゃない」とつぶやくだけ。 誰かが選曲を迷えば、「その曲はやめたほうがいい」と言うが、何を歌えばいいのかは決して言わない。 想いを、いま、届けたくないのであろうか。 スナックのママも常連客も、彼がいつからここにいるのかわからない。 ただ、彼と話しているうちに、客は次第に自信をなくし、何を言っても間違っている気がしてくる。 やがて、歌うことも、酒を飲むことも、話すことすらできなくなり、そっと店を後にするしかなくなる。 しかし、もし彼の言葉を気にせず「自分が好きなものを楽しめばいい」と思えたなら、魔遮幽鬼は興味を失い、いつの間にか姿を消す。 ただし、また別の夜、どこかの場末のスナックで、「違う、そうじゃない」とつぶやく声が聞こえてくるだろう。 | F60: ="【名】" & B60 & C60 &char(10) & "【番】" & text(A60,"0000") & char(10) &"【出現】"&D60& char(10)&"【特質】"& char(10)&E60&char(10)&char(10)&memo!$B$1 -> 【名】魔遮幽鬼（ましゃゆき）mashayuki 【番】0058 【出現】場末のスナック。古びたカラオケの音が響くカウンター席の端。 【特質】 何を言っても「違う、そうじゃない」と否定を繰り返す妖怪。 場末のスナックにふらりと現れ、酒を片手に誰かの話に口を挟む。 「この曲、いいね」と言えば「違う、そうじゃない」と言い、「この酒、うまいな」と言えば「違う、そうじゃない」と返す。 だが、何が正しいのかは決して教えない。 ピンク色のスーツを着こなし、サングラスの奥の目は虚ろに沈んでいる。 口の上には薄く整えられた口ひげがあり、一見するとただの酔客のようだが、彼の周りには妙な違和感が漂う。 カラオケのマイクを取れば、何かを歌うでもなく、ただ「違う、そうじゃない」とつぶやくだけ。 誰かが選曲を迷えば、「その曲はやめたほうがいい」と言うが、何を歌えばいいのかは決して言わない。 想いを、いま、届けたくないのであろうか。 スナックのママも常連客も、彼がいつからここにいるのかわからない。 ただ、彼と話しているうちに、客は次第に自信をなくし、何を言っても間違っている気がしてくる。 やがて、歌うことも、酒を飲むことも、話すことすらできなくなり、そっと店を後にするしかなくなる。 しかし、もし彼の言葉を気にせず「自分が好きなものを楽しめばいい」と思えたなら、魔遮幽鬼は興味を失い、いつの間にか姿を消す。 ただし、また別の夜、どこかの場末のスナックで、「違う、そうじゃない」とつぶやく声が聞こえてくるだろう。 #妖怪 #yokai #sumie #monster #ghost | G60: 45716 | H60: 45751 | I60: ○ | L60: =len(E60) -> 581 | N60: =mid(F60,1,find("【特質】",F60)-1) &char(10)&"＜特質はリプ欄へ＞" & char(10)& memo!$B$2 -> 【名】魔遮幽鬼（ましゃゆき）mashayuki 【番】0058 【出現】場末のスナック。古びたカラオケの音が響くカウンター席の端。 ＜特質はリプ欄へ＞ #妖怪 #お化け #怪物 #オリジナル妖怪 #monster #ghost #妖怪好き #浮世絵 #百鬼夜行 | O60: =len(N60) -> 131 | P60: 【特質】何を言っても「違う、そうじゃない」と否定を繰り返す妖怪。 場末のスナックにふらりと現れ、酒を片手に誰かの話に口を挟む。 「この曲、いいね」と言えば「違う、そうじゃない」と言い、「この酒、うまいな」と言えば「違う、そうじゃない」と返す。 だが、何が正しいのかは決して教えない。 | Q60: =len(P60) -> 141 | R60: ピンク色のスーツを着こなし、サングラスの奥の目は虚ろに沈んでいる。 口の上には薄く整えられた口ひげがあり、一見するとただの酔客のようだが、彼の周りには妙な違和感が漂う。 カラオケのマイクを取れば、何かを歌うでもなく、ただ「違う、そうじゃない」とつぶやくだけ。 | S60: =len(R60) -> 129 | T60: =len(W60) -> 103 | U60: ただ、彼と話しているうちに、客は次第に自信をなくし、何を言っても間違っている気がしてくる。 やがて、歌うことも、酒を飲むことも、話すことすらできなくなり、そっと店を後にするしかなくなる。 | V60: =len(U60) -> 93 | W60: 誰かが選曲を迷えば、「その曲はやめたほうがいい」と言うが、何を歌えばいいのかは決して言わない。 想いを、いま、届けたくないのであろうか。 スナックのママも常連客も、彼がいつからここにいるのかわからない。 | X60: しかし、もし彼の言葉を気にせず「自分が好きなものを楽しめばいい」と思えたなら、魔遮幽鬼は興味を失い、いつの間にか姿を消す。 ただし、また別の夜、どこかの場末のスナックで、「違う、そうじゃない」とつぶやく声が聞こえてくるだろう。 | Y60: =len(X60) -> 113 | AA60: =len(Z60) -> 0 | AC60: =len(AB60) -> 0
A61: 59 | B61: 宥和導師（ゆうわどうし） | C61: yuwadoshi | D61: 争いの絶えない村や、血を流し合う戦場の跡地 | E61: かつて、人々が無秩序に殺し合っていた時代、あまりの悲惨さに耐えかねた精霊たちが生み出した存在。 宥和導師は、争いを止めるために現れるが、決して武力で制することはない。 その姿は人のようでありながら、朧げで確かでない。 薄衣をまとい、どこからともなく歩み寄ると、争う者たちの間に静かに立つ。 その場の空気は一瞬にして鎮まり、激昂していた者たちの心は不思議と落ち着いていく。 誰もが争うことの無意味さを悟り、憎しみが霧散するという。 宥和導師が放つ声はまるで鐘の音のようで、耳にした者の心を穏やかに包み込む。 ただし、導師の声に耳を貸さず、なおも争いを続ける者がいれば、その者は忽然と姿を消す。 導師がどこへ連れ去るのかは誰も知らない。 ただ、彼が現れた村は、二度と戦の火に包まれることがないという。 ある時代、宥和導師の存在を知った権力者が、自らの敵を導師に消してもらおうと戦場へ誘い込んだ。 しかし、導師は彼の前には現れなかった。その者の心が平和を望んでいなかったからだという。 また、宥和導師の装いは後の時代に影響を与えたとされている。 彼がまとっていた衣は白と黒の対比が特徴的で、争いを断ち切る象徴と見なされた。 この意匠が時を経て形を変え、やがて審判のコスチュームの起源になったと語り継がれている。 宥和導師は、ただ平和を願う者の前にのみ姿を現し、争いを終わらせるために静かに歩み寄る。 | F61: ="【名】" & B61 & C61 &char(10) & "【番】" & text(A61,"0000") & char(10) &"【出現】"&D61& char(10)&"【特質】"& char(10)&E61&char(10)&char(10)&memo!$B$1 -> 【名】宥和導師（ゆうわどうし）yuwadoshi 【番】0059 【出現】争いの絶えない村や、血を流し合う戦場の跡地 【特質】 かつて、人々が無秩序に殺し合っていた時代、あまりの悲惨さに耐えかねた精霊たちが生み出した存在。 宥和導師は、争いを止めるために現れるが、決して武力で制することはない。 その姿は人のようでありながら、朧げで確かでない。 薄衣をまとい、どこからともなく歩み寄ると、争う者たちの間に静かに立つ。 その場の空気は一瞬にして鎮まり、激昂していた者たちの心は不思議と落ち着いていく。 誰もが争うことの無意味さを悟り、憎しみが霧散するという。 宥和導師が放つ声はまるで鐘の音のようで、耳にした者の心を穏やかに包み込む。 ただし、導師の声に耳を貸さず、なおも争いを続ける者がいれば、その者は忽然と姿を消す。 導師がどこへ連れ去るのかは誰も知らない。 ただ、彼が現れた村は、二度と戦の火に包まれることがないという。 ある時代、宥和導師の存在を知った権力者が、自らの敵を導師に消してもらおうと戦場へ誘い込んだ。 しかし、導師は彼の前には現れなかった。その者の心が平和を望んでいなかったからだという。 また、宥和導師の装いは後の時代に影響を与えたとされている。 彼がまとっていた衣は白と黒の対比が特徴的で、争いを断ち切る象徴と見なされた。 この意匠が時を経て形を変え、やがて審判のコスチュームの起源になったと語り継がれている。 宥和導師は、ただ平和を願う者の前にのみ姿を現し、争いを終わらせるために静かに歩み寄る。 #妖怪 #yokai #sumie #monster #ghost | G61: 45716 | H61: 45752 | I61: ○ | L61: =len(E61) -> 601 | N61: =mid(F61,1,find("【特質】",F61)-1) &char(10)&"＜特質はリプ欄へ＞" & char(10)& memo!$B$2 -> 【名】宥和導師（ゆうわどうし）yuwadoshi 【番】0059 【出現】争いの絶えない村や、血を流し合う戦場の跡地 ＜特質はリプ欄へ＞ #妖怪 #お化け #怪物 #オリジナル妖怪 #monster #ghost #妖怪好き #浮世絵 #百鬼夜行 | O61: =len(N61) -> 124 | P61: 【特質】かつて、人々が無秩序に殺し合っていた時代、あまりの悲惨さに耐えかねた精霊たちが生み出した存在。 宥和導師は、争いを止めるために現れるが、決して武力で制することはない。 その姿は人のようでありながら、朧げで確かでない。 | Q61: =len(P61) -> 112 | R61: 薄衣をまとい、どこからともなく歩み寄ると、争う者たちの間に静かに立つ。 その場の空気は一瞬にして鎮まり、激昂していた者たちの心は不思議と落ち着いていく。 誰もが争うことの無意味さを悟り、憎しみが霧散するという。 | S61: =len(R61) -> 106 | T61: =len(W61) -> 134 | U61: ある時代、宥和導師の存在を知った権力者が、自らの敵を導師に消してもらおうと戦場へ誘い込んだ。 しかし、導師は彼の前には現れなかった。その者の心が平和を望んでいなかったからだという。 また、宥和導師の装いは後の時代に影響を与えたとされている。 | V61: =len(U61) -> 121 | W61: 宥和導師が放つ声はまるで鐘の音のようで、耳にした者の心を穏やかに包み込む。 ただし、導師の声に耳を貸さず、なおも争いを続ける者がいれば、その者は忽然と姿を消す。 導師がどこへ連れ去るのかは誰も知らない。 ただ、彼が現れた村は、二度と戦の火に包まれることがないという。 | X61: 彼がまとっていた衣は白と黒の対比が特徴的で、争いを断ち切る象徴と見なされた。 この意匠が時を経て形を変え、やがて審判のコスチュームの起源になったと語り継がれている。 宥和導師は、ただ平和を願う者の前にのみ姿を現し、争いを終わらせるために静かに歩み寄る。 | Y61: =len(X61) -> 127 | AA61: =len(Z61) -> 0 | AC61: =len(AB61) -> 0
A62: 60 | B62: 首濁輪（くびだくりん） | C62: kubidakurin | D62: 温泉街の湯治場、古い銭湯、湿った川辺 | E62: 首濁輪は、首に大きな輪を抱えた異形の妖怪である。 その輪は、まるで木桶のように湯を溜め続け、決して乾くことはない。 湿気の多い場所を好み、湯気の立ち込める温泉や湯治場の影にひっそりと潜んでいる。 この妖怪の最も奇妙な特徴は、その輪の中で時を経るごとに発酵が進み、独特の芳醇な香りを放つ濃厚な液体が生まれることだ。 これは湯の成分や妖怪自身の気配が混ざり合い、年月とともに変質したもので、飲めば力がみなぎり、極端に酔いが回ると言われる。 かつて、ある力士が湯治の最中にこの妖怪と遭遇した。 湯気の向こうからじっと見つめられ、気がつけば輪の中に溜まった奇妙な酒に手を伸ばしていた。 一口飲むと、全身に熱が駆け巡り、翌日の取組では怪力を発揮し、並み居る相手を圧倒した。 それ以来、この怪異の伝承が広まり、力士たちは酒を大盃で豪快に飲み干すようになった。 しかし、首濁輪の溜める液体は、ただの滋養強壮の酒ではない。 度を超えて飲めば、次第に妖怪の気配に取り込まれ、魂まで濁ってしまうと言われている。 飲みすぎた者は、いつしか夜な夜な水辺を彷徨い、やがて自身が新たな首濁輪へと変じてしまうのだ。 温泉地では今でも「風呂場で見知らぬ液体を飲むな」「湯上がりの酒は一口まで」と言い伝えられている。 それは、首濁輪に取り憑かれた者が再び現れぬよう、人々が無意識に警戒している証なのかもしれない。 | F62: ="【名】" & B62 & C62 &char(10) & "【番】" & text(A62,"0000") & char(10) &"【出現】"&D62& char(10)&"【特質】"& char(10)&E62&char(10)&char(10)&memo!$B$1 -> 【名】首濁輪（くびだくりん）kubidakurin 【番】0060 【出現】温泉街の湯治場、古い銭湯、湿った川辺 【特質】 首濁輪は、首に大きな輪を抱えた異形の妖怪である。 その輪は、まるで木桶のように湯を溜め続け、決して乾くことはない。 湿気の多い場所を好み、湯気の立ち込める温泉や湯治場の影にひっそりと潜んでいる。 この妖怪の最も奇妙な特徴は、その輪の中で時を経るごとに発酵が進み、独特の芳醇な香りを放つ濃厚な液体が生まれることだ。 これは湯の成分や妖怪自身の気配が混ざり合い、年月とともに変質したもので、飲めば力がみなぎり、極端に酔いが回ると言われる。 かつて、ある力士が湯治の最中にこの妖怪と遭遇した。 湯気の向こうからじっと見つめられ、気がつけば輪の中に溜まった奇妙な酒に手を伸ばしていた。 一口飲むと、全身に熱が駆け巡り、翌日の取組では怪力を発揮し、並み居る相手を圧倒した。 それ以来、この怪異の伝承が広まり、力士たちは酒を大盃で豪快に飲み干すようになった。 しかし、首濁輪の溜める液体は、ただの滋養強壮の酒ではない。 度を超えて飲めば、次第に妖怪の気配に取り込まれ、魂まで濁ってしまうと言われている。 飲みすぎた者は、いつしか夜な夜な水辺を彷徨い、やがて自身が新たな首濁輪へと変じてしまうのだ。 温泉地では今でも「風呂場で見知らぬ液体を飲むな」「湯上がりの酒は一口まで」と言い伝えられている。 それは、首濁輪に取り憑かれた者が再び現れぬよう、人々が無意識に警戒している証なのかもしれない。 #妖怪 #yokai #sumie #monster #ghost | G62: 45717 | H62: 45753 | I62: ○ | L62: =len(E62) -> 594 | N62: =mid(F62,1,find("【特質】",F62)-1) &char(10)&"＜特質はリプ欄へ＞" & char(10)& memo!$B$2 -> 【名】首濁輪（くびだくりん）kubidakurin 【番】0060 【出現】温泉街の湯治場、古い銭湯、湿った川辺 ＜特質はリプ欄へ＞ #妖怪 #お化け #怪物 #オリジナル妖怪 #monster #ghost #妖怪好き #浮世絵 #百鬼夜行 | O62: =len(N62) -> 122 | P62: 【特質】首濁輪は、首に大きな輪を抱えた異形の妖怪である。 その輪は、まるで木桶のように湯を溜め続け、決して乾くことはない。 湿気の多い場所を好み、湯気の立ち込める温泉や湯治場の影にひっそりと潜んでいる。 | Q62: =len(P62) -> 101 | R62: この妖怪の最も奇妙な特徴は、その輪の中で時を経るごとに発酵が進み、独特の芳醇な香りを放つ濃厚な液体が生まれることだ。 これは湯の成分や妖怪自身の気配が混ざり合い、年月とともに変質したもので、飲めば力がみなぎり、極端に酔いが回ると言われる。 | S62: =len(R62) -> 119 | T62: =len(W62) -> 113 | U62: それ以来、この怪異の伝承が広まり、力士たちは酒を大盃で豪快に飲み干すようになった。 しかし、首濁輪の溜める液体は、ただの滋養強壮の酒ではない。 度を超えて飲めば、次第に妖怪の気配に取り込まれ、魂まで濁ってしまうと言われている。 | V62: =len(U62) -> 114 | W62: かつて、ある力士が湯治の最中にこの妖怪と遭遇した。 湯気の向こうからじっと見つめられ、気がつけば輪の中に溜まった奇妙な酒に手を伸ばしていた。 一口飲むと、全身に熱が駆け巡り、翌日の取組では怪力を発揮し、並み居る相手を圧倒した。 | X62: 飲みすぎた者は、いつしか夜な夜な水辺を彷徨い、やがて自身が新たな首濁輪へと変じてしまうのだ。 温泉地では今でも「風呂場で見知らぬ液体を飲むな」「湯上がりの酒は一口まで」と言い伝えられている。 | Y62: =len(X62) -> 96 | Z62: それは、首濁輪に取り憑かれた者が再び現れぬよう、人々が無意識に警戒している証なのかもしれない。 | AA62: =len(Z62) -> 48 | AC62: =len(AB62) -> 0
A63: 61 | B63: 崩牙狼（ほうがろう） | C63: hogaro | D63: 戦乱の果てに放棄された城跡、風化した戦場の片隅 | E63: かつて、一人の職人がいた。 戦の世に生まれながら剣を振るうこともなく、ただ土をこね、形を作ることしかできなかった。 だが、彼の心には武士への憧れがあった。 力を持つ者たちが誇らしげに戦場を駆ける姿に、自らの無力さを痛感しながらも、彼は己の手で“最強”を生み出そうと決意する。 そうして生まれたのが、巨大な狼――崩牙狼である。 粘土を積み、縄で締め、細部に至るまで執念を込めて作り上げたその姿は、まるで生きた妖獣のようだった。 職人は満足し、これこそが己の武であり、戦場を駆ける武士たちに負けぬ証だと思った。 しかし、彼の名が語られることはなかった。 やがて人々は、戦が終わった荒野に残されたこの獣を見て言った――「かつてこの地を蹂躙した妖獣が、己を封じるために石と化したのだ」と。 そして戦を知らぬ者たちはこれを恐れ、「伝説の妖獣」と語り継いできた。 今では旅人たちがその前で祈りを捧げたり、供え物を置いたりしていく。 誰もそれが人の手によるものだとは考えず、崩牙狼だけが静かに時を見つめ続けている。 何事にも真剣に取り組めば、思わぬ形で後世に名を遺すこともある。 たとえ、それが望んだものとは違っていても。 | F63: ="【名】" & B63 & C63 &char(10) & "【番】" & text(A63,"0000") & char(10) &"【出現】"&D63& char(10)&"【特質】"& char(10)&E63&char(10)&char(10)&memo!$B$1 -> 【名】崩牙狼（ほうがろう）hogaro 【番】0061 【出現】戦乱の果てに放棄された城跡、風化した戦場の片隅 【特質】 かつて、一人の職人がいた。 戦の世に生まれながら剣を振るうこともなく、ただ土をこね、形を作ることしかできなかった。 だが、彼の心には武士への憧れがあった。 力を持つ者たちが誇らしげに戦場を駆ける姿に、自らの無力さを痛感しながらも、彼は己の手で“最強”を生み出そうと決意する。 そうして生まれたのが、巨大な狼――崩牙狼である。 粘土を積み、縄で締め、細部に至るまで執念を込めて作り上げたその姿は、まるで生きた妖獣のようだった。 職人は満足し、これこそが己の武であり、戦場を駆ける武士たちに負けぬ証だと思った。 しかし、彼の名が語られることはなかった。 やがて人々は、戦が終わった荒野に残されたこの獣を見て言った――「かつてこの地を蹂躙した妖獣が、己を封じるために石と化したのだ」と。 そして戦を知らぬ者たちはこれを恐れ、「伝説の妖獣」と語り継いできた。 今では旅人たちがその前で祈りを捧げたり、供え物を置いたりしていく。 誰もそれが人の手によるものだとは考えず、崩牙狼だけが静かに時を見つめ続けている。 何事にも真剣に取り組めば、思わぬ形で後世に名を遺すこともある。 たとえ、それが望んだものとは違っていても。 #妖怪 #yokai #sumie #monster #ghost | G63: 45719 | H63: 45754 | I63: ○ | L63: =len(E63) -> 507 | N63: =mid(F63,1,find("【特質】",F63)-1) &char(10)&"＜特質はリプ欄へ＞" & char(10)& memo!$B$2 -> 【名】崩牙狼（ほうがろう）hogaro 【番】0061 【出現】戦乱の果てに放棄された城跡、風化した戦場の片隅 ＜特質はリプ欄へ＞ #妖怪 #お化け #怪物 #オリジナル妖怪 #monster #ghost #妖怪好き #浮世絵 #百鬼夜行 | O63: =len(N63) -> 123 | P63: 【特質】かつて、一人の職人がいた。 戦の世に生まれながら剣を振るうこともなく、ただ土をこね、形を作ることしかできなかった。 だが、彼の心には武士への憧れがあった。 力を持つ者たちが誇らしげに戦場を駆ける姿に、自らの無力さを痛感しながらも、彼は己の手で“最強”を生み出そうと決意する。 | Q63: =len(P63) -> 141 | R63: そうして生まれたのが、巨大な狼――崩牙狼である。 粘土を積み、縄で締め、細部に至るまで執念を込めて作り上げたその姿は、まるで生きた妖獣のようだった。 職人は満足し、これこそが己の武であり、戦場を駆ける武士たちに負けぬ証だと思った。 しかし、彼の名が語られることはなかった。 | S63: =len(R63) -> 136 | T63: =len(W63) -> 134 | U63: 誰もそれが人の手によるものだとは考えず、崩牙狼だけが静かに時を見つめ続けている。 何事にも真剣に取り組めば、思わぬ形で後世に名を遺すこともある。 たとえ、それが望んだものとは違っていても。 | V63: =len(U63) -> 95 | W63: やがて人々は、戦が終わった荒野に残されたこの獣を見て言った――「かつてこの地を蹂躙した妖獣が、己を封じるために石と化したのだ」と。 そして戦を知らぬ者たちはこれを恐れ、「伝説の妖獣」と語り継いできた。 今では旅人たちがその前で祈りを捧げたり、供え物を置いたりしていく。 | Y63: =len(X63) -> 0 | AA63: =len(Z63) -> 0 | AC63: =len(AB63) -> 0
A64: 62 | B64: 天環鼻（てんかんび） | C64: tenkambi | D64: 天空と地上の狭間、もしくは大気圏の境界 | E64: 天環鼻は、地球の外周を鼻で囲う異形の妖怪である。 その巨大な鼻は無限に伸び、星を取り巻く環のごとく漂う。 普段は目に見えないが、雷雲が広がるとき、その鼻が朧げに浮かび上がることがあるという。 この妖怪の鼻は、古来より天と地を繋ぐ橋であると信じられてきた。 天環鼻の存在を知る者は少ないが、稀に古代の文献に「天を巡る環のごとき鼻」として描かれている。 鼻の軌道が乱れると、地上では大嵐が起こり、気候が大きく変動すると言われる。 その鼻に触れた者は、果てしない長さの鼻の上を歩かされ、永遠に地球を彷徨うことになる。 昔、旅人が道に迷った際、突如として目の前に現れた巨大な橋を渡ったが、どれだけ進んでも終わらず、気づけば同じ場所に戻っていたという伝説も残されている。 天環鼻は、自らの異形を誇ることはない。 かつて天狗すらも、その長大な鼻にひれ伏したと伝えられる。 しかし、天環鼻は知っている。 この世には、さらなる長き鼻を持つ存在がいるかもしれないことを。 | F64: ="【名】" & B64 & C64 &char(10) & "【番】" & text(A64,"0000") & char(10) &"【出現】"&D64& char(10)&"【特質】"& char(10)&E64&char(10)&char(10)&memo!$B$1 -> 【名】天環鼻（てんかんび）tenkambi 【番】0062 【出現】天空と地上の狭間、もしくは大気圏の境界 【特質】 天環鼻は、地球の外周を鼻で囲う異形の妖怪である。 その巨大な鼻は無限に伸び、星を取り巻く環のごとく漂う。 普段は目に見えないが、雷雲が広がるとき、その鼻が朧げに浮かび上がることがあるという。 この妖怪の鼻は、古来より天と地を繋ぐ橋であると信じられてきた。 天環鼻の存在を知る者は少ないが、稀に古代の文献に「天を巡る環のごとき鼻」として描かれている。 鼻の軌道が乱れると、地上では大嵐が起こり、気候が大きく変動すると言われる。 その鼻に触れた者は、果てしない長さの鼻の上を歩かされ、永遠に地球を彷徨うことになる。 昔、旅人が道に迷った際、突如として目の前に現れた巨大な橋を渡ったが、どれだけ進んでも終わらず、気づけば同じ場所に戻っていたという伝説も残されている。 天環鼻は、自らの異形を誇ることはない。 かつて天狗すらも、その長大な鼻にひれ伏したと伝えられる。 しかし、天環鼻は知っている。 この世には、さらなる長き鼻を持つ存在がいるかもしれないことを。 #妖怪 #yokai #sumie #monster #ghost | G64: 45719 | H64: 45755 | I64: ○ | L64: =len(E64) -> 429 | N64: =mid(F64,1,find("【特質】",F64)-1) &char(10)&"＜特質はリプ欄へ＞" & char(10)& memo!$B$2 -> 【名】天環鼻（てんかんび）tenkambi 【番】0062 【出現】天空と地上の狭間、もしくは大気圏の境界 ＜特質はリプ欄へ＞ #妖怪 #お化け #怪物 #オリジナル妖怪 #monster #ghost #妖怪好き #浮世絵 #百鬼夜行 | O64: =len(N64) -> 119 | P64: 【特質】天環鼻は、地球の外周を鼻で囲う異形の妖怪である。 その巨大な鼻は無限に伸び、星を取り巻く環のごとく漂う。 普段は目に見えないが、雷雲が広がるとき、その鼻が朧げに浮かび上がることがあるという。 | Q64: =len(P64) -> 99 | R64: この妖怪の鼻は、古来より天と地を繋ぐ橋であると信じられてきた。 天環鼻の存在を知る者は少ないが、稀に古代の文献に「天を巡る環のごとき鼻」として描かれている。 鼻の軌道が乱れると、地上では大嵐が起こり、気候が大きく変動すると言われる。 | S64: =len(R64) -> 116 | T64: =len(W64) -> 117 | U64: 天環鼻は、自らの異形を誇ることはない。 かつて天狗すらも、その長大な鼻にひれ伏したと伝えられる。 しかし、天環鼻は知っている。 この世には、さらなる長き鼻を持つ存在がいるかもしれないことを。 | V64: =len(U64) -> 95 | W64: その鼻に触れた者は、果てしない長さの鼻の上を歩かされ、永遠に地球を彷徨うことになる。 昔、旅人が道に迷った際、突如として目の前に現れた巨大な橋を渡ったが、どれだけ進んでも終わらず、気づけば同じ場所に戻っていたという伝説も残されている。 | Y64: =len(X64) -> 0 | AA64: =len(Z64) -> 0 | AC64: =len(AB64) -> 0
A65: 63 | B65: 潮硬魔（ちょうこうま） | C65: chokoma | D65: 深海の沈没船周辺、潮の流れが速い海域 | E65: 潮硬魔は、海に沈んだ遺物の周囲を漂い、迷い込んだ生物を捕食する甲殻の妖怪である。 全身が鋼のように硬い殻に覆われ、長い胴体とハサミのような前肢を持つ。 頭部はかつてイルカであったかのような流線形を保っているが、その表情には一切の感情がなく、不気味な静寂を漂わせている。 潮硬魔は普段、深海の沈没船や海底の岩場に潜んでいるが、海が荒れた後に姿を現すことが多い。 特に、大きな嵐が過ぎ去った後、波間に浮かぶ漂流物の影から現れるとされる。 古い船の残骸や沈没船を住処とし、船に取り憑くように存在するため、「船幽霊と関わりの深い妖怪」と恐れられてきた。 潮硬魔に遭遇すると、まず鋭い鳴き声が響く。 それは金属同士が擦れ合う音に似ており、耳をつんざくような不気味な響きを持つ。 この音を聞いた船乗りは、「潮硬魔が近い」と悟り、すぐに船をその場から離さなければならない。 もしその場に留まれば、やがて船体に不気味な傷跡が刻まれ、最後にはその鋭いハサミで真っ二つにされるという。 しかし、潮硬魔にとって人を襲うことは本来の目的ではないのかもしれない。 嵐の夜に生き別れた兄弟を探し続けているという伝承がある。 嵐が去るたびに海をさまよい、波間に浮かぶものの影を追いかける。 鋭い鳴き声は、兄弟を呼ぶ悲痛な叫びなのかもしれない。 それが真実かどうかは誰にもわからない。 ただ一つ確かなのは、潮硬魔の声を聞いた者は、決してその正体を確かめてはならないということだ。 | F65: ="【名】" & B65 & C65 &char(10) & "【番】" & text(A65,"0000") & char(10) &"【出現】"&D65& char(10)&"【特質】"& char(10)&E65&char(10)&char(10)&memo!$B$1 -> 【名】潮硬魔（ちょうこうま）chokoma 【番】0063 【出現】深海の沈没船周辺、潮の流れが速い海域 【特質】 潮硬魔は、海に沈んだ遺物の周囲を漂い、迷い込んだ生物を捕食する甲殻の妖怪である。 全身が鋼のように硬い殻に覆われ、長い胴体とハサミのような前肢を持つ。 頭部はかつてイルカであったかのような流線形を保っているが、その表情には一切の感情がなく、不気味な静寂を漂わせている。 潮硬魔は普段、深海の沈没船や海底の岩場に潜んでいるが、海が荒れた後に姿を現すことが多い。 特に、大きな嵐が過ぎ去った後、波間に浮かぶ漂流物の影から現れるとされる。 古い船の残骸や沈没船を住処とし、船に取り憑くように存在するため、「船幽霊と関わりの深い妖怪」と恐れられてきた。 潮硬魔に遭遇すると、まず鋭い鳴き声が響く。 それは金属同士が擦れ合う音に似ており、耳をつんざくような不気味な響きを持つ。 この音を聞いた船乗りは、「潮硬魔が近い」と悟り、すぐに船をその場から離さなければならない。 もしその場に留まれば、やがて船体に不気味な傷跡が刻まれ、最後にはその鋭いハサミで真っ二つにされるという。 しかし、潮硬魔にとって人を襲うことは本来の目的ではないのかもしれない。 嵐の夜に生き別れた兄弟を探し続けているという伝承がある。 嵐が去るたびに海をさまよい、波間に浮かぶものの影を追いかける。 鋭い鳴き声は、兄弟を呼ぶ悲痛な叫びなのかもしれない。 それが真実かどうかは誰にもわからない。 ただ一つ確かなのは、潮硬魔の声を聞いた者は、決してその正体を確かめてはならないということだ。 #妖怪 #yokai #sumie #monster #ghost | G65: 45720 | H65: 45756 | I65: ○ | L65: =len(E65) -> 627 | N65: =mid(F65,1,find("【特質】",F65)-1) &char(10)&"＜特質はリプ欄へ＞" & char(10)& memo!$B$2 -> 【名】潮硬魔（ちょうこうま）chokoma 【番】0063 【出現】深海の沈没船周辺、潮の流れが速い海域 ＜特質はリプ欄へ＞ #妖怪 #お化け #怪物 #オリジナル妖怪 #monster #ghost #妖怪好き #浮世絵 #百鬼夜行 | O65: =len(N65) -> 118 | P65: 【特質】潮硬魔は、海に沈んだ遺物の周囲を漂い、迷い込んだ生物を捕食する甲殻の妖怪である。 全身が鋼のように硬い殻に覆われ、長い胴体とハサミのような前肢を持つ。 頭部はかつてイルカであったかのような流線形を保っているが、その表情には一切の感情がなく、不気味な静寂を漂わせている。 | Q65: =len(P65) -> 138 | R65: 潮硬魔は普段、深海の沈没船や海底の岩場に潜んでいるが、海が荒れた後に姿を現すことが多い。 特に、大きな嵐が過ぎ去った後、波間に浮かぶ漂流物の影から現れるとされる。 古い船の残骸や沈没船を住処とし、船に取り憑くように存在するため、「船幽霊と関わりの深い妖怪」と恐れられてきた。 | S65: =len(R65) -> 137 | T65: =len(W65) -> 106 | U65: もしその場に留まれば、やがて船体に不気味な傷跡が刻まれ、最後にはその鋭いハサミで真っ二つにされるという。 しかし、潮硬魔にとって人を襲うことは本来の目的ではないのかもしれない。 嵐の夜に生き別れた兄弟を探し続けているという伝承がある。 | V65: =len(U65) -> 118 | W65: 潮硬魔に遭遇すると、まず鋭い鳴き声が響く。 それは金属同士が擦れ合う音に似ており、耳をつんざくような不気味な響きを持つ。 この音を聞いた船乗りは、「潮硬魔が近い」と悟り、すぐに船をその場から離さなければならない。 | X65: 嵐が去るたびに海をさまよい、波間に浮かぶものの影を追いかける。 鋭い鳴き声は、兄弟を呼ぶ悲痛な叫びなのかもしれない。 それが真実かどうかは誰にもわからない。 ただ一つ確かなのは、潮硬魔の声を聞いた者は、決してその正体を確かめてはならないということだ。 | Y65: =len(X65) -> 126 | AA65: =len(Z65) -> 0 | AC65: =len(AB65) -> 0
A66: 64 | B66: 白波燈子（しらなみ とうこ） | C66: shiranami toko | D66: 映画館、映写室、旧式映写機が眠る倉庫 | E66: 銀幕幻影物語（ぎんまくげんえいものがたり）には、様々な登場人物がいる。 今回は、ヒロインを紹介する。 白波燈子は映画館「白波座（しらなみざ）」を営んでいた祖父を持つ映写技師見習いの女性。 幼少期、祖父と共に映画泥坊（えいがどろぼう）による怪奇現象を目撃し、その恐怖と謎を追い求めるようになった。 映写機に関する豊富な知識を持ち、上映中の微細な異変を素早く察知することができる。 映写作業を進める際は、祖父譲りの慎重さと冷静さを見せる一方、上映前のフィルム整理や機材準備ではお調子者の録助（ろくすけ）にからかわれながらも、的確な指示を出す頼もしさもある。 映画岡引との接触をきっかけに、巻物「幻灯巻（げんとうまき）」の存在を知り、妖怪を映像に封じる手順を学ぶ。 以降、映写技師としてだけでなく、妖怪退治の補佐役としても活動するようになる。 妖怪への敵意は幼少期の恐怖心に端を発しているが、岡引（おかっぴき）と共に行動する中で「映像を守ることは記憶を守ること」という信念を抱くようになり、単なる退治ではなく真実を記録する者としての役割を担うようになる。 映画館と映写機を愛する気持ちが、彼女を行動へと駆り立てる原動力となっている。 | F66: ="【名】" & B66 & C66 &char(10) & "【番】" & text(A66,"0000") & char(10) &"【出現】"&D66& char(10)&"【特質】"& char(10)&E66&char(10)&char(10)& "#銀幕幻影物語 " &memo!$B$1 -> 【名】白波燈子（しらなみ とうこ）shiranami toko 【番】0064 【出現】映画館、映写室、旧式映写機が眠る倉庫 【特質】 銀幕幻影物語（ぎんまくげんえいものがたり）には、様々な登場人物がいる。 今回は、ヒロインを紹介する。 白波燈子は映画館「白波座（しらなみざ）」を営んでいた祖父を持つ映写技師見習いの女性。 幼少期、祖父と共に映画泥坊（えいがどろぼう）による怪奇現象を目撃し、その恐怖と謎を追い求めるようになった。 映写機に関する豊富な知識を持ち、上映中の微細な異変を素早く察知することができる。 映写作業を進める際は、祖父譲りの慎重さと冷静さを見せる一方、上映前のフィルム整理や機材準備ではお調子者の録助（ろくすけ）にからかわれながらも、的確な指示を出す頼もしさもある。 映画岡引との接触をきっかけに、巻物「幻灯巻（げんとうまき）」の存在を知り、妖怪を映像に封じる手順を学ぶ。 以降、映写技師としてだけでなく、妖怪退治の補佐役としても活動するようになる。 妖怪への敵意は幼少期の恐怖心に端を発しているが、岡引（おかっぴき）と共に行動する中で「映像を守ることは記憶を守ること」という信念を抱くようになり、単なる退治ではなく真実を記録する者としての役割を担うようになる。 映画館と映写機を愛する気持ちが、彼女を行動へと駆り立てる原動力となっている。 #銀幕幻影物語 #妖怪 #yokai #sumie #monster #ghost | G66: 45710 | H66: =DATE(2025, 2, 6) + (A66-1) -> 45757 | I66: ○ | L66: =len(E66) -> 517 | N66: =mid(F66,1,find("【特質】",F66)-1) &char(10)&"＜特質はリプ欄へ＞" & char(10)& "#銀幕幻影物語 " & memo!$B$2 -> 【名】白波燈子（しらなみ とうこ）shiranami toko 【番】0064 【出現】映画館、映写室、旧式映写機が眠る倉庫 ＜特質はリプ欄へ＞ #銀幕幻影物語 #妖怪 #お化け #怪物 #オリジナル妖怪 #monster #ghost #妖怪好き #浮世絵 #百鬼夜行 | O66: =len(N66) -> 136 | P66: 【特質】銀幕幻影物語（ぎんまくげんえいものがたり）には、様々な登場人物がいる。 今回は、ヒロインを紹介する。 白波燈子は映画館「白波座（しらなみざ）」を営んでいた祖父を持つ映写技師見習いの女性。 幼少期、祖父と共に映画泥坊（えいがどろぼう）による怪奇現象を目撃し、 | Q66: =len(P66) -> 133 | R66: その恐怖と謎を追い求めるようになった。 映写機に関する豊富な知識を持ち、上映中の微細な異変を素早く察知することができる。 映写作業を進める際は、祖父譲りの慎重さと冷静さを見せる一方、上映前のフィルム整理や機材準備ではお調子者の録助（ろくすけ）にからかわれながらも、 | S66: =len(R66) -> 133 | T66: =len(W66) -> 109 | U66: 妖怪への敵意は幼少期の恐怖心に端を発しているが、岡引（おかっぴき）と共に行動する中で「映像を守ることは記憶を守ること」という信念を抱くようになり、単なる退治ではなく真実を記録する者としての役割を担うようになる。 | V66: =len(U66) -> 105 | W66: 的確な指示を出す頼もしさもある。 映画岡引との接触をきっかけに、巻物「幻灯巻（げんとうまき）」の存在を知り、妖怪を映像に封じる手順を学ぶ。 以降、映写技師としてだけでなく、妖怪退治の補佐役としても活動するようになる。 | X66: 映画館と映写機を愛する気持ちが、彼女を行動へと駆り立てる原動力となっている。 | Y66: =len(X66) -> 38 | AA66: =len(Z66) -> 0 | AC66: =len(AB66) -> 0
A67: 65 | B67: 膨鬼（ぼうき） | C67: boki | D67: 夜の祭り、捨てられた風船売りの屋台 | E67: 古い縁日の記録に、「消えた子どもたち」の話が残っている。 彼らはある年の夏祭りで、大きな風船を手にしたまま忽然と姿を消したという。 祭りが終わった後、地面には何本もの糸だけが残されていた。 それ以来、夜の祭りでは奇妙な風船が浮かぶことがある。 その風船は他のものよりわずかに大きく、よく見ると表面にかすかに顔が浮かんでいる。 気のせいかと思う間もなく、風船はふわりと宙に揺れ、静かに人を見つめる。 子どもが興味を示して手を伸ばすと、風船はまるで誘うように滑らかに近づき、ふいに膨らみ始める。 そして、膨らむにつれて顔がはっきりと浮かび上がり、笑みを浮かべる。 その笑みを見た瞬間、子どもの手は離れなくなり、風船はさらに大きく膨れ、やがて風船は子どもを包み込むように膨らみ、ひとつの影となって夜空へと溶けていく。 翌朝、祭りの片隅には新しい風船が転がっている。 その表面には、昨夜見かけた子どもとよく似た顔が、うっすらと刻まれているという。 | F67: ="【名】" & B67 & C67 &char(10) & "【番】" & text(A67,"0000") & char(10) &"【出現】"&D67& char(10)&"【特質】"& char(10)&E67&char(10)&char(10)&memo!$B$1 -> 【名】膨鬼（ぼうき）boki 【番】0065 【出現】夜の祭り、捨てられた風船売りの屋台 【特質】 古い縁日の記録に、「消えた子どもたち」の話が残っている。 彼らはある年の夏祭りで、大きな風船を手にしたまま忽然と姿を消したという。 祭りが終わった後、地面には何本もの糸だけが残されていた。 それ以来、夜の祭りでは奇妙な風船が浮かぶことがある。 その風船は他のものよりわずかに大きく、よく見ると表面にかすかに顔が浮かんでいる。 気のせいかと思う間もなく、風船はふわりと宙に揺れ、静かに人を見つめる。 子どもが興味を示して手を伸ばすと、風船はまるで誘うように滑らかに近づき、ふいに膨らみ始める。 そして、膨らむにつれて顔がはっきりと浮かび上がり、笑みを浮かべる。 その笑みを見た瞬間、子どもの手は離れなくなり、風船はさらに大きく膨れ、やがて風船は子どもを包み込むように膨らみ、ひとつの影となって夜空へと溶けていく。 翌朝、祭りの片隅には新しい風船が転がっている。 その表面には、昨夜見かけた子どもとよく似た顔が、うっすらと刻まれているという。 #妖怪 #yokai #sumie #monster #ghost | G67: 45720 | H67: =DATE(2025, 2, 6) + (A67-1) -> 45758 | I67: ○ | L67: =len(E67) -> 422 | N67: =mid(F67,1,find("【特質】",F67)-1) &char(10)&"＜特質はリプ欄へ＞" & char(10)& memo!$B$2 -> 【名】膨鬼（ぼうき）boki 【番】0065 【出現】夜の祭り、捨てられた風船売りの屋台 ＜特質はリプ欄へ＞ #妖怪 #お化け #怪物 #オリジナル妖怪 #monster #ghost #妖怪好き #浮世絵 #百鬼夜行 | O67: =len(N67) -> 110 | P67: 【特質】古い縁日の記録に、「消えた子どもたち」の話が残っている。 彼らはある年の夏祭りで、大きな風船を手にしたまま忽然と姿を消したという。 祭りが終わった後、地面には何本もの糸だけが残されていた。 それ以来、夜の祭りでは奇妙な風船が浮かぶことがある。 | Q67: =len(P67) -> 126 | R67: その風船は他のものよりわずかに大きく、よく見ると表面にかすかに顔が浮かんでいる。 気のせいかと思う間もなく、風船はふわりと宙に揺れ、静かに人を見つめる。 子どもが興味を示して手を伸ばすと、風船はまるで誘うように滑らかに近づき、ふいに膨らみ始める。 | S67: =len(R67) -> 124 | T67: =len(W67) -> 109 | U67: 翌朝、祭りの片隅には新しい風船が転がっている。 その表面には、昨夜見かけた子どもとよく似た顔が、うっすらと刻まれているという。 | V67: =len(U67) -> 63 | W67: そして、膨らむにつれて顔がはっきりと浮かび上がり、笑みを浮かべる。 その笑みを見た瞬間、子どもの手は離れなくなり、風船はさらに大きく膨れ、やがて風船は子どもを包み込むように膨らみ、ひとつの影となって夜空へと溶けていく。 | Y67: =len(X67) -> 0 | AA67: =len(Z67) -> 0 | AC67: =len(AB67) -> 0
A68: 66 | B68: 耕運鬼（こううんき） | C68: kounki | D68: 山間の農村、長く耕作が放棄された荒地 | E68: 耕運鬼は前足が異様に発達した妖怪である。 指先は古びた硬貨のように硬く光り、歩けば地面を削る。 道は削られ、畦道は壊れ、人々は恐れた。 「村を壊す者」として忌み嫌われ、妖怪は村人に遠ざけられた。 歩けば道が荒れる。自分は迷惑な存在なのだと気づくと、妖怪は村外れの洞窟に閉じこもった。 どこにも行けず、誰からも必要とされず、ただ時間だけが過ぎていった。 そんなある日、村の長が妖怪を訪れた。 村の田畑は年々痩せ細り、作物が育たなくなっていた。 どれだけ鍬を入れても、人の手では硬い土を耕せない。 妖怪の長い腕と硬い指ならば、大地を深く掘り返せるかもしれない。 妖怪は戸惑った。 これまで破壊しかもたらさなかった自分に、何かを生み出せるのだろうか。 しかし、村長のまなざしは真剣だった。 妖怪は村へと向かった。 畑に立ち、硬貨のような指先を土に押しつけ、腕を引きずる。 削られた土は深く掘り返され、柔らかくなっていった。 固く締まっていた土地がほぐれ、ふかふかとした黒い土が広がる。 やがて妖怪の姿は、村の日常の一部となった。 陽の下、妖怪は黙々と田畑を耕し、村人たちはその後に種を蒔いた。 村人は妖怪を恐れなくなり、時には水を差し出し、収穫をともに喜ぶようになった。 こうして妖怪は「耕運鬼（こううんき）」と呼ばれるようになった。 村人は耕運鬼に出会えた幸運に感謝している。 だが、自分の生きる道を見出された耕運鬼こそが、一番の幸運だったのかもしれない。 | F68: ="【名】" & B68 & C68 &char(10) & "【番】" & text(A68,"0000") & char(10) &"【出現】"&D68& char(10)&"【特質】"& char(10)&E68&char(10)&char(10)&memo!$B$1 -> 【名】耕運鬼（こううんき）kounki 【番】0066 【出現】山間の農村、長く耕作が放棄された荒地 【特質】 耕運鬼は前足が異様に発達した妖怪である。 指先は古びた硬貨のように硬く光り、歩けば地面を削る。 道は削られ、畦道は壊れ、人々は恐れた。 「村を壊す者」として忌み嫌われ、妖怪は村人に遠ざけられた。 歩けば道が荒れる。自分は迷惑な存在なのだと気づくと、妖怪は村外れの洞窟に閉じこもった。 どこにも行けず、誰からも必要とされず、ただ時間だけが過ぎていった。 そんなある日、村の長が妖怪を訪れた。 村の田畑は年々痩せ細り、作物が育たなくなっていた。 どれだけ鍬を入れても、人の手では硬い土を耕せない。 妖怪の長い腕と硬い指ならば、大地を深く掘り返せるかもしれない。 妖怪は戸惑った。 これまで破壊しかもたらさなかった自分に、何かを生み出せるのだろうか。 しかし、村長のまなざしは真剣だった。 妖怪は村へと向かった。 畑に立ち、硬貨のような指先を土に押しつけ、腕を引きずる。 削られた土は深く掘り返され、柔らかくなっていった。 固く締まっていた土地がほぐれ、ふかふかとした黒い土が広がる。 やがて妖怪の姿は、村の日常の一部となった。 陽の下、妖怪は黙々と田畑を耕し、村人たちはその後に種を蒔いた。 村人は妖怪を恐れなくなり、時には水を差し出し、収穫をともに喜ぶようになった。 こうして妖怪は「耕運鬼（こううんき）」と呼ばれるようになった。 村人は耕運鬼に出会えた幸運に感謝している。 だが、自分の生きる道を見出された耕運鬼こそが、一番の幸運だったのかもしれない。 #妖怪 #yokai #sumie #monster #ghost | G68: 45723 | H68: =DATE(2025, 2, 6) + (A68-1) -> 45759 | I68: ○ | L68: =len(E68) -> 632 | N68: =mid(F68,1,find("【特質】",F68)-1) &char(10)&"＜特質はリプ欄へ＞" & char(10)& memo!$B$2 -> 【名】耕運鬼（こううんき）kounki 【番】0066 【出現】山間の農村、長く耕作が放棄された荒地 ＜特質はリプ欄へ＞ #妖怪 #お化け #怪物 #オリジナル妖怪 #monster #ghost #妖怪好き #浮世絵 #百鬼夜行 | O68: =len(N68) -> 116 | P68: 【特質】耕運鬼は前足が異様に発達した妖怪である。 指先は古びた硬貨のように硬く光り、歩けば地面を削る。 道は削られ、畦道は壊れ、人々は恐れた。 「村を壊す者」として忌み嫌われ、妖怪は村人に遠ざけられた。 | Q68: =len(P68) -> 102 | R68: 歩けば道が荒れる。自分は迷惑な存在なのだと気づくと、妖怪は村外れの洞窟に閉じこもった。 どこにも行けず、誰からも必要とされず、ただ時間だけが過ぎていった。 そんなある日、村の長が妖怪を訪れた。 村の田畑は年々痩せ細り、作物が育たなくなっていた。 | S68: =len(R68) -> 123 | T68: =len(W68) -> 121 | U68: 妖怪は村へと向かった。 畑に立ち、硬貨のような指先を土に押しつけ、腕を引きずる。 削られた土は深く掘り返され、柔らかくなっていった。 固く締まっていた土地がほぐれ、ふかふかとした黒い土が広がる。 | V68: =len(U68) -> 97 | W68: どれだけ鍬を入れても、人の手では硬い土を耕せない。 妖怪の長い腕と硬い指ならば、大地を深く掘り返せるかもしれない。 妖怪は戸惑った。 これまで破壊しかもたらさなかった自分に、何かを生み出せるのだろうか。 しかし、村長のまなざしは真剣だった。 | X68: やがて妖怪の姿は、村の日常の一部となった。 陽の下、妖怪は黙々と田畑を耕し、村人たちはその後に種を蒔いた。 村人は妖怪を恐れなくなり、時には水を差し出し、収穫をともに喜ぶようになった。 | Y68: =len(X68) -> 92 | Z68: こうして妖怪は「耕運鬼（こううんき）」と呼ばれるようになった。 村人は耕運鬼に出会えた幸運に感謝している。 だが、自分の生きる道を見出された耕運鬼こそが、一番の幸運だったのかもしれない。 | AA68: =len(Z68) -> 93 | AC68: =len(AB68) -> 0
A69: 67 | B69: 月兎砕（げっとさい） | C69: gettosai | D69: 満月の夜の村の広場 | E69: 満月の夜、村の広場では毎年恒例の餅つき大会が開かれていた。 子どもから大人までが臼を囲み、掛け声を合わせながら杵を振るう。 湯気の立つ餅の香りが広がり、和やかな雰囲気に包まれていた。 その時だった。 どこからともなく、黒く大きな影が現れた。 それは、漆黒の毛並みに長い耳を揺らし、赤い瞳を怪しく光らせる異様な兎。 どこから来たのか、誰も知らない。 しかし、その兎は何のためらいもなく臼の前に立ち、当然のように杵を持ち上げた。 その瞬間、兎の姿が大きく歪んだ。 毛が逆立ち、筋肉が膨れ、目がさらに紅く輝く。 手にした杵はもはや餅をつく道具ではなく、地を砕く凶器へと変わった。 次の瞬間、月兎砕はその巨大な杵を振り下ろした。 地響きとともに臼は粉々に砕け、餅は宙を舞う。 村人たちは騒然とし、慌てて新しい臼を用意したが、結果は同じだった。 次々と臼が砕かれ、広場は粉々になった餅と木片で埋め尽くされてしまった。 事態を重く見た村の長は、その場で「月兎砕、餅つき大会、出禁」を言い渡した。 月兎砕はしばらくキョトンとしていたが、やがて肩を落とし、とぼとぼとどこかへ去っていった。 それ以来、村では満月の夜になると「月兎砕のために団子を供える」習慣が生まれた。 餅つきには参加できなくとも、団子なら楽しんでくれるだろうと願いを込めて。 そして今でも、満月の夜、遠くの山影に黒い影がひょっこりと現れることがある。 じっと広場の様子を見つめるその姿は、まるで「次こそはうまくやれるかもしれない」と思っているかのようだった。 夜空に浮かぶ満月を見上げると、そこには兎が軽やかに杵を振るい、楽しげに餅をついているように映っていた。 | F69: ="【名】" & B69 & C69 &char(10) & "【番】" & text(A69,"0000") & char(10) &"【出現】"&D69& char(10)&"【特質】"& char(10)&E69&char(10)&char(10)&memo!$B$1 -> 【名】月兎砕（げっとさい）gettosai 【番】0067 【出現】満月の夜の村の広場 【特質】 満月の夜、村の広場では毎年恒例の餅つき大会が開かれていた。 子どもから大人までが臼を囲み、掛け声を合わせながら杵を振るう。 湯気の立つ餅の香りが広がり、和やかな雰囲気に包まれていた。 その時だった。 どこからともなく、黒く大きな影が現れた。 それは、漆黒の毛並みに長い耳を揺らし、赤い瞳を怪しく光らせる異様な兎。 どこから来たのか、誰も知らない。 しかし、その兎は何のためらいもなく臼の前に立ち、当然のように杵を持ち上げた。 その瞬間、兎の姿が大きく歪んだ。 毛が逆立ち、筋肉が膨れ、目がさらに紅く輝く。 手にした杵はもはや餅をつく道具ではなく、地を砕く凶器へと変わった。 次の瞬間、月兎砕はその巨大な杵を振り下ろした。 地響きとともに臼は粉々に砕け、餅は宙を舞う。 村人たちは騒然とし、慌てて新しい臼を用意したが、結果は同じだった。 次々と臼が砕かれ、広場は粉々になった餅と木片で埋め尽くされてしまった。 事態を重く見た村の長は、その場で「月兎砕、餅つき大会、出禁」を言い渡した。 月兎砕はしばらくキョトンとしていたが、やがて肩を落とし、とぼとぼとどこかへ去っていった。 それ以来、村では満月の夜になると「月兎砕のために団子を供える」習慣が生まれた。 餅つきには参加できなくとも、団子なら楽しんでくれるだろうと願いを込めて。 そして今でも、満月の夜、遠くの山影に黒い影がひょっこりと現れることがある。 じっと広場の様子を見つめるその姿は、まるで「次こそはうまくやれるかもしれない」と思っているかのようだった。 夜空に浮かぶ満月を見上げると、そこには兎が軽やかに杵を振るい、楽しげに餅をついているように映っていた。 #妖怪 #yokai #sumie #monster #ghost | G69: 45724 | H69: =DATE(2025, 2, 6) + (A69-1) -> 45760 | I69: ○ | L69: =len(E69) -> 717 | N69: =mid(F69,1,find("【特質】",F69)-1) &char(10)&"＜特質はリプ欄へ＞" & char(10)& memo!$B$2 -> 【名】月兎砕（げっとさい）gettosai 【番】0067 【出現】満月の夜の村の広場 ＜特質はリプ欄へ＞ #妖怪 #お化け #怪物 #オリジナル妖怪 #monster #ghost #妖怪好き #浮世絵 #百鬼夜行 | O69: =len(N69) -> 109 | P69: 【特質】満月の夜、村の広場では毎年恒例の餅つき大会が開かれていた。 子どもから大人までが臼を囲み、掛け声を合わせながら杵を振るう。 湯気の立つ餅の香りが広がり、和やかな雰囲気に包まれていた。 その時だった。 どこからともなく、黒く大きな影が現れた。 | Q69: =len(P69) -> 125 | R69: それは、漆黒の毛並みに長い耳を揺らし、赤い瞳を怪しく光らせる異様な兎。 どこから来たのか、誰も知らない。 しかし、その兎は何のためらいもなく臼の前に立ち、当然のように杵を持ち上げた。 その瞬間、兎の姿が大きく歪んだ。 毛が逆立ち、筋肉が膨れ、目がさらに紅く輝く。 | S69: =len(R69) -> 133 | T69: =len(W69) -> 116 | U69: 次々と臼が砕かれ、広場は粉々になった餅と木片で埋め尽くされてしまった。 事態を重く見た村の長は、その場で「月兎砕、餅つき大会、出禁」を言い渡した。 月兎砕はしばらくキョトンとしていたが、やがて肩を落とし、とぼとぼとどこかへ去っていった。 | V69: =len(U69) -> 119 | W69: 手にした杵はもはや餅をつく道具ではなく、地を砕く凶器へと変わった。 次の瞬間、月兎砕はその巨大な杵を振り下ろした。 地響きとともに臼は粉々に砕け、餅は宙を舞う。 村人たちは騒然とし、慌てて新しい臼を用意したが、結果は同じだった。 | X69: それ以来、村では満月の夜になると「月兎砕のために団子を供える」習慣が生まれた。 餅つきには参加できなくとも、団子なら楽しんでくれるだろうと願いを込めて。 そして今でも、満月の夜、遠くの山影に黒い影がひょっこりと現れることがある。 | Y69: =len(X69) -> 115 | Z69: じっと広場の様子を見つめるその姿は、まるで「次こそはうまくやれるかもしれない」と思っているかのようだった。 夜空に浮かぶ満月を見上げると、そこには兎が軽やかに杵を振るい、楽しげに餅をついているように映っていた。 | AA69: =len(Z69) -> 106 | AC69: =len(AB69) -> 0
A70: 68 | B70: 熟果般餐（じゅっかばんさん） | C70: jukkabansan | D70: 日本各地の武道館、格式ある古道場、試合後の静まり返った畳の上 | E70: ナポリから最強を求めて海を渡った熟果般餐は、日本の道場を次々と破り、勝利を重ねていた。 しかし、ある夜、彼はこれまでとは違う道場に辿り着く。 迎え撃ったのは静かに構えを取る師範。 恐れも迷いもなく、ただ武を極めんとする者の姿に、熟果般餐は初めて戦慄を覚えた。 激しい攻防の末、畳に沈んだのは熟果般餐だった。 敗北の苦しみよりも、全力を尽くした充実感があった。 師範は手を差し伸べ、熟果般餐は無言でそれを掴む。 こうして彼は道場に留まり、共に修練を積むこととなった。 ある日、門下生たちが食事をとる中、熟果般餐はふと故郷の味を思い出す。 完熟トマトを煮込み、にんにくとオリーブオイルで香りを引き出し、パスタに絡める。 初めて味わう赤い料理に門下生たちは驚き、それを日々の食卓に取り入れた。 そして、やがて道場の名物料理となり、「日本のトマトパスタ発祥の地」として知られるようになった。 こうして、熟果般餐は武の探求とともに、異国の味を日本に伝えた。 今でも、夜の道場に立ち込めるトマトの香りには、彼の気配が宿っているという。 | F70: ="【名】" & B70 & C70 &char(10) & "【番】" & text(A70,"0000") & char(10) &"【出現】"&D70& char(10)&"【特質】"& char(10)&E70&char(10)&char(10)&memo!$B$1 -> 【名】熟果般餐（じゅっかばんさん）jukkabansan 【番】0068 【出現】日本各地の武道館、格式ある古道場、試合後の静まり返った畳の上 【特質】 ナポリから最強を求めて海を渡った熟果般餐は、日本の道場を次々と破り、勝利を重ねていた。 しかし、ある夜、彼はこれまでとは違う道場に辿り着く。 迎え撃ったのは静かに構えを取る師範。 恐れも迷いもなく、ただ武を極めんとする者の姿に、熟果般餐は初めて戦慄を覚えた。 激しい攻防の末、畳に沈んだのは熟果般餐だった。 敗北の苦しみよりも、全力を尽くした充実感があった。 師範は手を差し伸べ、熟果般餐は無言でそれを掴む。 こうして彼は道場に留まり、共に修練を積むこととなった。 ある日、門下生たちが食事をとる中、熟果般餐はふと故郷の味を思い出す。 完熟トマトを煮込み、にんにくとオリーブオイルで香りを引き出し、パスタに絡める。 初めて味わう赤い料理に門下生たちは驚き、それを日々の食卓に取り入れた。 そして、やがて道場の名物料理となり、「日本のトマトパスタ発祥の地」として知られるようになった。 こうして、熟果般餐は武の探求とともに、異国の味を日本に伝えた。 今でも、夜の道場に立ち込めるトマトの香りには、彼の気配が宿っているという。 #妖怪 #yokai #sumie #monster #ghost | G70: 45725 | H70: =DATE(2025, 2, 6) + (A70-1) -> 45761 | I70: ○ | L70: =len(E70) -> 465 | N70: =mid(F70,1,find("【特質】",F70)-1) &char(10)&"＜特質はリプ欄へ＞" & char(10)& memo!$B$2 -> 【名】熟果般餐（じゅっかばんさん）jukkabansan 【番】0068 【出現】日本各地の武道館、格式ある古道場、試合後の静まり返った畳の上 ＜特質はリプ欄へ＞ #妖怪 #お化け #怪物 #オリジナル妖怪 #monster #ghost #妖怪好き #浮世絵 #百鬼夜行 | O70: =len(N70) -> 137 | P70: 【特質】ナポリから最強を求めて海を渡った熟果般餐は、日本の道場を次々と破り、勝利を重ねていた。 しかし、ある夜、彼はこれまでとは違う道場に辿り着く。 迎え撃ったのは静かに構えを取る師範。 恐れも迷いもなく、ただ武を極めんとする者の姿に、熟果般餐は初めて戦慄を覚えた。 | Q70: =len(P70) -> 134 | R70: 激しい攻防の末、畳に沈んだのは熟果般餐だった。 敗北の苦しみよりも、全力を尽くした充実感があった。 師範は手を差し伸べ、熟果般餐は無言でそれを掴む。 こうして彼は道場に留まり、共に修練を積むこととなった。 | S70: =len(R70) -> 102 | T70: =len(W70) -> 110 | U70: そして、やがて道場の名物料理となり、「日本のトマトパスタ発祥の地」として知られるようになった。 こうして、熟果般餐は武の探求とともに、異国の味を日本に伝えた。 今でも、夜の道場に立ち込めるトマトの香りには、彼の気配が宿っているという。 | V70: =len(U70) -> 118 | W70: ある日、門下生たちが食事をとる中、熟果般餐はふと故郷の味を思い出す。 完熟トマトを煮込み、にんにくとオリーブオイルで香りを引き出し、パスタに絡める。 初めて味わう赤い料理に門下生たちは驚き、それを日々の食卓に取り入れた。 | Y70: =len(X70) -> 0 | AA70: =len(Z70) -> 0 | AC70: =len(AB70) -> 0
A71: 69 | B71: 根魂封縛（こんこんふうばく） | C71: konkonfubaku | D71: 古い薬問屋、深山の霊薬畑 | E71: 長い年月を経て妖怪と化した霊薬の根。 かつては人を癒す力を持つとされていたが、乱用や誤用により呪われ、封印されるに至った。 古びた瓶や壺に封じられ、今もなお妖気を秘めたまま眠っている。 瓶の中の根はまるで生き物のように絡み合い、静かにうごめいている。 瓶を開ければ、瞬く間に蔓のような根が伸び、触れた者の生気をじわじわと吸い取る。 やがて根は人の骨のように硬化し、吸い取った命を糧にさらなる怪異へと変じるという。 古い伝承によれば、この妖怪はかつて「不老長寿の妙薬」として珍重されていたが、人の欲望を受けて霊性を歪め、ついには呪薬へと成り果てた。 何代にもわたり封印が施されたが、それでも薬師や陰陽師の手によって誤って解き放たれ、幾度となく悲劇を生んできた。 そして、近年。 町内会の催しで、ある母親がこの「根魂封縛」をすりおろし、ハンバーグの隠し味に使うという事件が発生した。 「栄養たっぷりの霊薬」と信じて料理に取り入れた結果、町は大混乱に陥った。 この一件以来、「おかんの飯に隠し味はいらない」 という言葉が生まれた。 この教訓は、「はりきって挑戦して失敗するより、いつもの味で十分」という意味で広まり、今では戒めの言葉として受け継がれている。 | F71: ="【名】" & B71 & C71 &char(10) & "【番】" & text(A71,"0000") & char(10) &"【出現】"&D71& char(10)&"【特質】"& char(10)&E71&char(10)&char(10)&memo!$B$1 -> 【名】根魂封縛（こんこんふうばく）konkonfubaku 【番】0069 【出現】古い薬問屋、深山の霊薬畑 【特質】 長い年月を経て妖怪と化した霊薬の根。 かつては人を癒す力を持つとされていたが、乱用や誤用により呪われ、封印されるに至った。 古びた瓶や壺に封じられ、今もなお妖気を秘めたまま眠っている。 瓶の中の根はまるで生き物のように絡み合い、静かにうごめいている。 瓶を開ければ、瞬く間に蔓のような根が伸び、触れた者の生気をじわじわと吸い取る。 やがて根は人の骨のように硬化し、吸い取った命を糧にさらなる怪異へと変じるという。 古い伝承によれば、この妖怪はかつて「不老長寿の妙薬」として珍重されていたが、人の欲望を受けて霊性を歪め、ついには呪薬へと成り果てた。 何代にもわたり封印が施されたが、それでも薬師や陰陽師の手によって誤って解き放たれ、幾度となく悲劇を生んできた。 そして、近年。 町内会の催しで、ある母親がこの「根魂封縛」をすりおろし、ハンバーグの隠し味に使うという事件が発生した。 「栄養たっぷりの霊薬」と信じて料理に取り入れた結果、町は大混乱に陥った。 この一件以来、「おかんの飯に隠し味はいらない」 という言葉が生まれた。 この教訓は、「はりきって挑戦して失敗するより、いつもの味で十分」という意味で広まり、今では戒めの言葉として受け継がれている。 #妖怪 #yokai #sumie #monster #ghost | G71: 45726 | H71: =DATE(2025, 2, 6) + (A71-1) -> 45762 | I71: ○ | L71: =len(E71) -> 529 | N71: =mid(F71,1,find("【特質】",F71)-1) &char(10)&"＜特質はリプ欄へ＞" & char(10)& memo!$B$2 -> 【名】根魂封縛（こんこんふうばく）konkonfubaku 【番】0069 【出現】古い薬問屋、深山の霊薬畑 ＜特質はリプ欄へ＞ #妖怪 #お化け #怪物 #オリジナル妖怪 #monster #ghost #妖怪好き #浮世絵 #百鬼夜行 | O71: =len(N71) -> 120 | P71: 【特質】長い年月を経て妖怪と化した霊薬の根。 かつては人を癒す力を持つとされていたが、乱用や誤用により呪われ、封印されるに至った。 古びた瓶や壺に封じられ、今もなお妖気を秘めたまま眠っている。 瓶の中の根はまるで生き物のように絡み合い、静かにうごめいている。 | Q71: =len(P71) -> 130 | R71: 瓶を開ければ、瞬く間に蔓のような根が伸び、触れた者の生気をじわじわと吸い取る。 やがて根は人の骨のように硬化し、吸い取った命を糧にさらなる怪異へと変じるという。 古い伝承によれば、この妖怪はかつて「不老長寿の妙薬」として珍重されていたが、人の欲望を受けて霊性を歪め、 | S71: =len(R71) -> 134 | T71: =len(W71) -> 131 | U71: 「栄養たっぷりの霊薬」と信じて料理に取り入れた結果、町は大混乱に陥った。 この一件以来、「おかんの飯に隠し味はいらない」 という言葉が生まれた。 この教訓は、「はりきって挑戦して失敗するより、いつもの味で十分」という意味で広まり、今では戒めの言葉として受け継がれている。 | V71: =len(U71) -> 136 | W71: ついには呪薬へと成り果てた。 何代にもわたり封印が施されたが、それでも薬師や陰陽師の手によって誤って解き放たれ、幾度となく悲劇を生んできた。 そして、近年。 町内会の催しで、ある母親がこの「根魂封縛」をすりおろし、ハンバーグの隠し味に使うという事件が発生した。 | Y71: =len(X71) -> 0 | AA71: =len(Z71) -> 0 | AC71: =len(AB71) -> 0
A72: 70 | B72: 犬直徒（けんなおと） | C72: kennaoto | D72: 主人と歩んできた軌跡の上、かつて共に歩いた路地 | E72: 主人が病に倒れ、歩けなくなった日から、犬直徒は二本足で歩くようになった。 背筋を伸ばし、ゆっくりと、まるで主人の足取りをなぞるように。 その姿には不自然さよりも、どこか誇らしげなものがあった。 「代わりに歩くのだ」と言わんばかりに、犬は毎日同じ時間に家を出て、静かに街を歩いた。 やがて犬は、歩き方だけでなく、主人の仕草や癖まで真似るようになった。 考え込むときの首の傾け方、立ち止まるときの足の位置、物思いにふけるように窓の外を見つめる目つきまで──まるで主人がそこにいるかのように、犬は主人を写し取っていった。 幸いにも病は回復し、主人は再び自由に歩けるようになった。 しかし、いつもの生活には戻らなかった。 退屈しのぎに手を出した賭け事が、いつしか生きる目的となり、夜な夜な賭場に通うようになった。 犬はそれにも従った。 主人が通う場所へ行き、主人がすることを見て、学び、真似た。 そして、いつしか犬は賭けの流れを読むようになり、勝ち負けに一喜一憂するようになった。 犬直徒は、ただ主人の代わりに歩いたのではない。 主人とともに、堕ちていったのだ。 そして今、犬直徒は主人と並んで更生施設にいる。 二足で椅子に座り、足を組み、じっと前を見つめる姿は、まるで人間のようだ。 「こいつもギャンブルをやめられないんです」 主人の言葉に、医師は微笑んだ。 「一緒にリハビリを頑張りましょうね」 犬直徒は、その言葉を噛みしめるように静かに頷いた。 | F72: ="【名】" & B72 & C72 &char(10) & "【番】" & text(A72,"0000") & char(10) &"【出現】"&D72& char(10)&"【特質】"& char(10)&E72&char(10)&char(10)&memo!$B$1 -> 【名】犬直徒（けんなおと）kennaoto 【番】0070 【出現】主人と歩んできた軌跡の上、かつて共に歩いた路地 【特質】 主人が病に倒れ、歩けなくなった日から、犬直徒は二本足で歩くようになった。 背筋を伸ばし、ゆっくりと、まるで主人の足取りをなぞるように。 その姿には不自然さよりも、どこか誇らしげなものがあった。 「代わりに歩くのだ」と言わんばかりに、犬は毎日同じ時間に家を出て、静かに街を歩いた。 やがて犬は、歩き方だけでなく、主人の仕草や癖まで真似るようになった。 考え込むときの首の傾け方、立ち止まるときの足の位置、物思いにふけるように窓の外を見つめる目つきまで──まるで主人がそこにいるかのように、犬は主人を写し取っていった。 幸いにも病は回復し、主人は再び自由に歩けるようになった。 しかし、いつもの生活には戻らなかった。 退屈しのぎに手を出した賭け事が、いつしか生きる目的となり、夜な夜な賭場に通うようになった。 犬はそれにも従った。 主人が通う場所へ行き、主人がすることを見て、学び、真似た。 そして、いつしか犬は賭けの流れを読むようになり、勝ち負けに一喜一憂するようになった。 犬直徒は、ただ主人の代わりに歩いたのではない。 主人とともに、堕ちていったのだ。 そして今、犬直徒は主人と並んで更生施設にいる。 二足で椅子に座り、足を組み、じっと前を見つめる姿は、まるで人間のようだ。 「こいつもギャンブルをやめられないんです」 主人の言葉に、医師は微笑んだ。 「一緒にリハビリを頑張りましょうね」 犬直徒は、その言葉を噛みしめるように静かに頷いた。 #妖怪 #yokai #sumie #monster #ghost | G72: 45727 | H72: =DATE(2025, 2, 6) + (A72-1) -> 45763 | I72: ○ | L72: =len(E72) -> 644 | N72: =mid(F72,1,find("【特質】",F72)-1) &char(10)&"＜特質はリプ欄へ＞" & char(10)& memo!$B$2 -> 【名】犬直徒（けんなおと）kennaoto 【番】0070 【出現】主人と歩んできた軌跡の上、かつて共に歩いた路地 ＜特質はリプ欄へ＞ #妖怪 #お化け #怪物 #オリジナル妖怪 #monster #ghost #妖怪好き #浮世絵 #百鬼夜行 | O72: =len(N72) -> 123 | P72: 【特質】主人が病に倒れ、歩けなくなった日から、犬直徒は二本足で歩くようになった。 背筋を伸ばし、ゆっくりと、まるで主人の足取りをなぞるように。 その姿には不自然さよりも、どこか誇らしげなものがあった。 | Q72: =len(P72) -> 100 | R72: 「代わりに歩くのだ」と言わんばかりに、犬は毎日同じ時間に家を出て、静かに街を歩いた。 やがて犬は、歩き方だけでなく、主人の仕草や癖まで真似るようになった。 考え込むときの首の傾け方、立ち止まるときの足の位置、物思いにふけるように窓の外を見つめる目つきまで | S72: =len(R72) -> 130 | T72: =len(W72) -> 142 | U72: 主人が通う場所へ行き、主人がすることを見て、学び、真似た。 そして、いつしか犬は賭けの流れを読むようになり、勝ち負けに一喜一憂するようになった。 犬直徒は、ただ主人の代わりに歩いたのではない。 主人とともに、堕ちていったのだ。 そして今、犬直徒は主人と並んで更生施設にいる。 | V72: =len(U72) -> 143 | W72: ──まるで主人がそこにいるかのように、犬は主人を写し取っていった。 幸いにも病は回復し、主人は再び自由に歩けるようになった。 しかし、いつもの生活には戻らなかった。 退屈しのぎに手を出した賭け事が、いつしか生きる目的となり、夜な夜な賭場に通うようになった。 犬はそれにも従った。 | X72: 二足で椅子に座り、足を組み、じっと前を見つめる姿は、まるで人間のようだ。 「こいつもギャンブルをやめられないんです」 主人の言葉に、医師は微笑んだ。 「一緒にリハビリを頑張りましょうね」 犬直徒は、その言葉を噛みしめるように静かに頷いた。 | Y72: =len(X72) -> 130 | AA72: =len(Z72) -> 0 | AC72: =len(AB72) -> 0
A73: 71 | B73: 老歯（ろうし） | C73: roshi | D73: 歯渡村（はわたりむら） | E73: 昔からこの村では、老人の口に生えた「老歯」を若者が受け継ぐという風習があった。 乳歯が抜け、永久歯が磨り減った後に最後に生える老歯。 それには死者の記憶や知恵が宿るとされ、儀式の場で抜き取られた老歯をすり潰して煎じて若者が飲むことで、先人の智慧を得ると信じられていた。 老いた者は、最後の老歯が生えた時、自らの役目を終えると悟り、それを捧げる。 若者はその煎じた歯を飲み、村の歴史と知恵を継承していく。 それが「歯渡りの儀」であった。 ある日、子どもたちが遊んでいるときに、村の外れで大量の歯が捨てられている場所を見つけた。 まるで人の骨のように白く、そこかしこに散らばる無数の老歯。 その異様な光景に、大人たちが駆けつけた。 すると、ある老人が思い出す。 この村には、かつて老歯を受け継がずに捨てる者がいた時代があったのだと。 そこは、忘れ去られた「歯塚（はづか）」だった。 歯塚の存在が明らかになってから、次第に奇妙な現象が起こり始める。 村の者たちは次々と歯の痛みに悩まされるようになった。 幼い子どもから老人まで、その苦しみは村全体に広がっていった。 食べることも話すことも億劫になり、村人たちは次第に無口になっていった。 やがて、老歯を受け継ぐ儀式を行う者はいなくなり、「歯渡りの儀」は歴史から消えた。 後年、研究者がこの村の遺跡を調査中に歯塚を発見した。 人骨ではなく、抜かれた老人の歯が大量に埋まる奇妙な遺構。 その謎に魅せられた研究者たちは、なぜ老歯が存在するのか、かつての村人たちは何を信じていたのか、その解明に明け暮れている。 最近になって、研究者の一人が村の歴史をなぜか語り始めた。 まるで、自ら「歯渡りの儀」を行ったかのように……。 | F73: ="【名】" & B73 & C73 &char(10) & "【番】" & text(A73,"0000") & char(10) &"【出現】"&D73& char(10)&"【特質】"& char(10)&E73&char(10)&char(10)&memo!$B$1 -> 【名】老歯（ろうし）roshi 【番】0071 【出現】歯渡村（はわたりむら） 【特質】 昔からこの村では、老人の口に生えた「老歯」を若者が受け継ぐという風習があった。 乳歯が抜け、永久歯が磨り減った後に最後に生える老歯。 それには死者の記憶や知恵が宿るとされ、儀式の場で抜き取られた老歯をすり潰して煎じて若者が飲むことで、先人の智慧を得ると信じられていた。 老いた者は、最後の老歯が生えた時、自らの役目を終えると悟り、それを捧げる。 若者はその煎じた歯を飲み、村の歴史と知恵を継承していく。 それが「歯渡りの儀」であった。 ある日、子どもたちが遊んでいるときに、村の外れで大量の歯が捨てられている場所を見つけた。 まるで人の骨のように白く、そこかしこに散らばる無数の老歯。 その異様な光景に、大人たちが駆けつけた。 すると、ある老人が思い出す。 この村には、かつて老歯を受け継がずに捨てる者がいた時代があったのだと。 そこは、忘れ去られた「歯塚（はづか）」だった。 歯塚の存在が明らかになってから、次第に奇妙な現象が起こり始める。 村の者たちは次々と歯の痛みに悩まされるようになった。 幼い子どもから老人まで、その苦しみは村全体に広がっていった。 食べることも話すことも億劫になり、村人たちは次第に無口になっていった。 やがて、老歯を受け継ぐ儀式を行う者はいなくなり、「歯渡りの儀」は歴史から消えた。 後年、研究者がこの村の遺跡を調査中に歯塚を発見した。 人骨ではなく、抜かれた老人の歯が大量に埋まる奇妙な遺構。 その謎に魅せられた研究者たちは、なぜ老歯が存在するのか、かつての村人たちは何を信じていたのか、その解明に明け暮れている。 最近になって、研究者の一人が村の歴史をなぜか語り始めた。 まるで、自ら「歯渡りの儀」を行ったかのように……。 #妖怪 #yokai #sumie #monster #ghost | G73: 45728 | H73: =DATE(2025, 2, 6) + (A73-1) -> 45764 | I73: ○ | L73: =len(E73) -> 733 | N73: =mid(F73,1,find("【特質】",F73)-1) &char(10)&"＜特質はリプ欄へ＞" & char(10)& memo!$B$2 -> 【名】老歯（ろうし）roshi 【番】0071 【出現】歯渡村（はわたりむら） ＜特質はリプ欄へ＞ #妖怪 #お化け #怪物 #オリジナル妖怪 #monster #ghost #妖怪好き #浮世絵 #百鬼夜行 | O73: =len(N73) -> 105 | P73: 【特質】昔からこの村では、老人の口に生えた「老歯」を若者が受け継ぐという風習があった。 乳歯が抜け、永久歯が磨り減った後に最後に生える老歯。 それには死者の記憶や知恵が宿るとされ、儀式の場で抜き取られた老歯をすり潰して煎じて若者が飲むことで、先人の智慧を得ると信じられていた。 | Q73: =len(P73) -> 138 | R73: 老いた者は、最後の老歯が生えた時、自らの役目を終えると悟り、それを捧げる。 若者はその煎じた歯を飲み、村の歴史と知恵を継承していく。 それが「歯渡りの儀」であった。 ある日、子どもたちが遊んでいるときに、村の外れで大量の歯が捨てられている場所を見つけた。 | S73: =len(R73) -> 128 | T73: =len(W73) -> 125 | U73: 歯塚の存在が明らかになってから、次第に奇妙な現象が起こり始める。 村の者たちは次々と歯の痛みに悩まされるようになった。 幼い子どもから老人まで、その苦しみは村全体に広がっていった。 食べることも話すことも億劫になり、村人たちは次第に無口になっていった。 | V73: =len(U73) -> 126 | W73: まるで人の骨のように白く、そこかしこに散らばる無数の老歯。 その異様な光景に、大人たちが駆けつけた。 すると、ある老人が思い出す。 この村には、かつて老歯を受け継がずに捨てる者がいた時代があったのだと。 そこは、忘れ去られた「歯塚（はづか）」だった。 | X73: やがて、老歯を受け継ぐ儀式を行う者はいなくなり、「歯渡りの儀」は歴史から消えた。 後年、研究者がこの村の遺跡を調査中に歯塚を発見した。 人骨ではなく、抜かれた老人の歯が大量に埋まる奇妙な遺構。 | Y73: =len(X73) -> 97 | Z73: その謎に魅せられた研究者たちは、なぜ老歯が存在するのか、かつての村人たちは何を信じていたのか、その解明に明け暮れている。 最近になって、研究者の一人が村の歴史をなぜか語り始めた。 まるで、自ら「歯渡りの儀」を行ったかのように……。 | AA73: =len(Z73) -> 116 | AC73: =len(AB73) -> 0
A74: 72 | B74: 斧喰鱗（くっくりん） | C74: kukkurin | D74: 寂れた漁港の市場跡、廃業した寿司屋の裏口 | E74: 斧喰鱗は、体全体を鱗に覆われた料理人の妖怪である。 かつては人間であり、港町の名物板前として知られていたが、味を追い求めすぎたあまり、最後には「自分の舌では本当の味がわからない」と嘆き、自らの舌を切り落としたという。 それ以来、味覚を失った斧喰鱗は“人の舌”を料理に混ぜるようになった。 彼にとってそれは調味料ではなく、「味を取り戻す儀式」である。 夜な夜な包丁を持ち、調理音とともに現れるその姿は、黙々と捌き、煮て、焼き、盛り付ける。 噂によれば、斧喰鱗の料理を一度でも口にすれば、味の深みが忘れられなくなるという。 その夜にだけ現れる屋台や、灯りのない小料理屋――場所も見た目も不定だが、香りと引き換えに人はたどり着く。 そして近年、この料理を追い求めて、名のある食通や料理評論家たちがこぞってその噂を追い始めている。 だが、彼らが何を食べたのか、誰一人として語らない。 いや、語れないのかもしれない。笑顔のまま、静かに消えていくのだ。 もしも深夜に、どこからともなく香ばしい出汁の香りが漂ってきたら――その先にあるのは店ではない。 斧喰鱗は、味を確かめるための“新しい舌”を、静かに待っている。 | F74: ="【名】" & B74 & C74 &char(10) & "【番】" & text(A74,"0000") & char(10) &"【出現】"&D74& char(10)&"【特質】"& char(10)&E74&char(10)&char(10)&memo!$B$1 -> 【名】斧喰鱗（くっくりん）kukkurin 【番】0072 【出現】寂れた漁港の市場跡、廃業した寿司屋の裏口 【特質】 斧喰鱗は、体全体を鱗に覆われた料理人の妖怪である。 かつては人間であり、港町の名物板前として知られていたが、味を追い求めすぎたあまり、最後には「自分の舌では本当の味がわからない」と嘆き、自らの舌を切り落としたという。 それ以来、味覚を失った斧喰鱗は“人の舌”を料理に混ぜるようになった。 彼にとってそれは調味料ではなく、「味を取り戻す儀式」である。 夜な夜な包丁を持ち、調理音とともに現れるその姿は、黙々と捌き、煮て、焼き、盛り付ける。 噂によれば、斧喰鱗の料理を一度でも口にすれば、味の深みが忘れられなくなるという。 その夜にだけ現れる屋台や、灯りのない小料理屋――場所も見た目も不定だが、香りと引き換えに人はたどり着く。 そして近年、この料理を追い求めて、名のある食通や料理評論家たちがこぞってその噂を追い始めている。 だが、彼らが何を食べたのか、誰一人として語らない。 いや、語れないのかもしれない。笑顔のまま、静かに消えていくのだ。 もしも深夜に、どこからともなく香ばしい出汁の香りが漂ってきたら――その先にあるのは店ではない。 斧喰鱗は、味を確かめるための“新しい舌”を、静かに待っている。 #妖怪 #yokai #sumie #monster #ghost | G74: 45745 | H74: =DATE(2025, 2, 6) + (A74-1) -> 45765 | I74: ○ | L74: =len(E74) -> 504 | N74: =mid(F74,1,find("【特質】",F74)-1) &char(10)&"＜特質はリプ欄へ＞" & char(10)& memo!$B$2 -> 【名】斧喰鱗（くっくりん）kukkurin 【番】0072 【出現】寂れた漁港の市場跡、廃業した寿司屋の裏口 ＜特質はリプ欄へ＞ #妖怪 #お化け #怪物 #オリジナル妖怪 #monster #ghost #妖怪好き #浮世絵 #百鬼夜行 | O74: =len(N74) -> 120 | P74: 【特質】斧喰鱗は、体全体を鱗に覆われた料理人の妖怪である。 かつては人間であり、港町の名物板前として知られていたが、味を追い求めすぎたあまり、最後には「自分の舌では本当の味がわからない」と嘆き、自らの舌を切り落としたという。 | Q74: =len(P74) -> 112 | R74: それ以来、味覚を失った斧喰鱗は“人の舌”を料理に混ぜるようになった。 彼にとってそれは調味料ではなく、「味を取り戻す儀式」である。 夜な夜な包丁を持ち、調理音とともに現れるその姿は、黙々と捌き、煮て、焼き、盛り付ける。 | S74: =len(R74) -> 109 | T74: =len(W74) -> 142 | U74: だが、彼らが何を食べたのか、誰一人として語らない。 いや、語れないのかもしれない。笑顔のまま、静かに消えていくのだ。 もしも深夜に、どこからともなく香ばしい出汁の香りが漂ってきたら――その先にあるのは店ではない。 斧喰鱗は、味を確かめるための“新しい舌”を、静かに待っている。 | V74: =len(U74) -> 140 | W74: 噂によれば、斧喰鱗の料理を一度でも口にすれば、味の深みが忘れられなくなるという。 その夜にだけ現れる屋台や、灯りのない小料理屋――場所も見た目も不定だが、香りと引き換えに人はたどり着く。 そして近年、この料理を追い求めて、名のある食通や料理評論家たちがこぞってその噂を追い始めている。 | Y74: =len(X74) -> 0 | AA74: =len(Z74) -> 0 | AC74: =len(AB74) -> 0
A75: 73 | B75: 朽闇爪（くやみそう） | C75: kuyamiso | D75: 町の大通り、商店街、村の入口 | E75: 夜明け前、町の中央を横切るように巨大な獣の足跡が現れる。 足跡は一直線に続いているが、不自然なことにどこから来たのかも、どこへ消えたのかもわからない。 誰一人として目撃した者はいない。 ある朝、子供たちがその足跡を囲んでいた。 大人たちは警戒していたが、子供たちは面白がって遊んでいた。 そのうちの一人が、大きな足跡に自分の手を重ねてみた。 突然、足跡の輪郭がじわりと滲み、黒い染みのように地面に広がった。 少年が慌てて手を引っ込めると、黒い影が指先から伝い、腕へと這い上がってきた。 見ていた子供たちは悲鳴を上げ、後ずさった。 影は少年の腕にしがみつくように動き、その形を変えていく。 まるで“何か”が、少年の体を借りて甦ろうとしているかのように。 そして、少年の目が、深い闇の色に染まった。 その晩、少年の家族は異変に気づく。 食事をとらず、誰とも口を利かず、ただ黙って窓の外を見ていた。 深夜、家人が目を覚ますと、少年の姿はなかった。 翌朝、町の入り口にはまた一直線に続く巨大な足跡があった。 しかし、今度はその最後の一歩の上に、小さな手形が重なっていた。 少年の姿は二度と見つからなかった。 | F75: ="【名】" & B75 & C75 &char(10) & "【番】" & text(A75,"0000") & char(10) &"【出現】"&D75& char(10)&"【特質】"& char(10)&E75&char(10)&char(10)&memo!$B$1 -> 【名】朽闇爪（くやみそう）kuyamiso 【番】0073 【出現】町の大通り、商店街、村の入口 【特質】 夜明け前、町の中央を横切るように巨大な獣の足跡が現れる。 足跡は一直線に続いているが、不自然なことにどこから来たのかも、どこへ消えたのかもわからない。 誰一人として目撃した者はいない。 ある朝、子供たちがその足跡を囲んでいた。 大人たちは警戒していたが、子供たちは面白がって遊んでいた。 そのうちの一人が、大きな足跡に自分の手を重ねてみた。 突然、足跡の輪郭がじわりと滲み、黒い染みのように地面に広がった。 少年が慌てて手を引っ込めると、黒い影が指先から伝い、腕へと這い上がってきた。 見ていた子供たちは悲鳴を上げ、後ずさった。 影は少年の腕にしがみつくように動き、その形を変えていく。 まるで“何か”が、少年の体を借りて甦ろうとしているかのように。 そして、少年の目が、深い闇の色に染まった。 その晩、少年の家族は異変に気づく。 食事をとらず、誰とも口を利かず、ただ黙って窓の外を見ていた。 深夜、家人が目を覚ますと、少年の姿はなかった。 翌朝、町の入り口にはまた一直線に続く巨大な足跡があった。 しかし、今度はその最後の一歩の上に、小さな手形が重なっていた。 少年の姿は二度と見つからなかった。 #妖怪 #yokai #sumie #monster #ghost | G75: 45732 | H75: =DATE(2025, 2, 6) + (A75-1) -> 45766 | I75: ○ | L75: =len(E75) -> 504 | N75: =mid(F75,1,find("【特質】",F75)-1) &char(10)&"＜特質はリプ欄へ＞" & char(10)& memo!$B$2 -> 【名】朽闇爪（くやみそう）kuyamiso 【番】0073 【出現】町の大通り、商店街、村の入口 ＜特質はリプ欄へ＞ #妖怪 #お化け #怪物 #オリジナル妖怪 #monster #ghost #妖怪好き #浮世絵 #百鬼夜行 | O75: =len(N75) -> 114 | P75: 【特質】夜明け前、町の中央を横切るように巨大な獣の足跡が現れる。 足跡は一直線に続いているが、不自然なことにどこから来たのかも、どこへ消えたのかもわからない。 誰一人として目撃した者はいない。 ある朝、子供たちがその足跡を囲んでいた。 | Q75: =len(P75) -> 118 | R75: 大人たちは警戒していたが、子供たちは面白がって遊んでいた。 そのうちの一人が、大きな足跡に自分の手を重ねてみた。 突然、足跡の輪郭がじわりと滲み、黒い染みのように地面に広がった。 少年が慌てて手を引っ込めると、黒い影が指先から伝い、腕へと這い上がってきた。 | S75: =len(R75) -> 129 | T75: =len(W75) -> 124 | U75: 食事をとらず、誰とも口を利かず、ただ黙って窓の外を見ていた。 深夜、家人が目を覚ますと、少年の姿はなかった。 翌朝、町の入り口にはまた一直線に続く巨大な足跡があった。 しかし、今度はその最後の一歩の上に、小さな手形が重なっていた。 少年の姿は二度と見つからなかった。 | V75: =len(U75) -> 134 | W75: 見ていた子供たちは悲鳴を上げ、後ずさった。 影は少年の腕にしがみつくように動き、その形を変えていく。 まるで“何か”が、少年の体を借りて甦ろうとしているかのように。 そして、少年の目が、深い闇の色に染まった。 その晩、少年の家族は異変に気づく。 | Y75: =len(X75) -> 0 | AA75: =len(Z75) -> 0 | AC75: =len(AB75) -> 0
A76: 74 | B76: 蓄音堂録助（ちくおんどう ろくすけ） | C76: chikuondo rokusuke | D76: 映画館、映写室、旧式映写機が眠る倉庫 | E76: 銀幕幻影物語（ぎんまくげんえいものがたり）には、様々な登場人物がいる。 今回は、仲間を紹介する。 蓄音堂録助は映画館「白波座（しらなみざ）」で映写技師見習いとして働く青年。 先祖代々、蓄音機や映写機の修理を生業としてきた家系の末裔だが、本人は機械に強いわけではなく、映写機の操作やフィルムの取り扱いでは失敗ばかり。 フィルムを逆回転させたり、リールを絡ませたりすることもしばしばで、白波燈子（しらなみ とうこ）からは呆れられつつも放っておけない存在として受け入れられている。 お調子者で見栄を張る癖があり、「任せとけ！」と言った直後にドジを踏むことが多い。 しかし、偶然の幸運に恵まれることがあり、逃げ回るうちに重要なスイッチを押したり、妖怪の封じられたフィルムを偶然動かしてしまったりと、意図せず状況を好転させる役割を担うこともある。 妖怪の気配を察知すると真っ先に逃げ出す臆病さを持つが、仲間が危機に瀕すると意外な勇気を発揮することがある。 白波燈子とは姉弟のような関係で、からかい合いながらも互いに信頼し合っている。 日常では映画館の雑用をこなしつつ、映写室とロビーを行き来しては常連客と談笑するムードメーカー。 失敗を繰り返しながらも、祖先の誇りを胸に「映像と音を守る」という使命をうっすらと自覚し始めている。 | F76: ="【名】" & B76 & C76 &char(10) & "【番】" & text(A76,"0000") & char(10) &"【出現】"&D76& char(10)&"【特質】"& char(10)&E76&char(10)&char(10)& "#銀幕幻影物語 " &memo!$B$1 -> 【名】蓄音堂録助（ちくおんどう ろくすけ）chikuondo rokusuke 【番】0074 【出現】映画館、映写室、旧式映写機が眠る倉庫 【特質】 銀幕幻影物語（ぎんまくげんえいものがたり）には、様々な登場人物がいる。 今回は、仲間を紹介する。 蓄音堂録助は映画館「白波座（しらなみざ）」で映写技師見習いとして働く青年。 先祖代々、蓄音機や映写機の修理を生業としてきた家系の末裔だが、本人は機械に強いわけではなく、映写機の操作やフィルムの取り扱いでは失敗ばかり。 フィルムを逆回転させたり、リールを絡ませたりすることもしばしばで、白波燈子（しらなみ とうこ）からは呆れられつつも放っておけない存在として受け入れられている。 お調子者で見栄を張る癖があり、「任せとけ！」と言った直後にドジを踏むことが多い。 しかし、偶然の幸運に恵まれることがあり、逃げ回るうちに重要なスイッチを押したり、妖怪の封じられたフィルムを偶然動かしてしまったりと、意図せず状況を好転させる役割を担うこともある。 妖怪の気配を察知すると真っ先に逃げ出す臆病さを持つが、仲間が危機に瀕すると意外な勇気を発揮することがある。 白波燈子とは姉弟のような関係で、からかい合いながらも互いに信頼し合っている。 日常では映画館の雑用をこなしつつ、映写室とロビーを行き来しては常連客と談笑するムードメーカー。 失敗を繰り返しながらも、祖先の誇りを胸に「映像と音を守る」という使命をうっすらと自覚し始めている。 #銀幕幻影物語 #妖怪 #yokai #sumie #monster #ghost | G76: 45710 | H76: =DATE(2025, 2, 6) + (A76-1) -> 45767 | I76: ○ | L76: =len(E76) -> 563 | N76: =mid(F76,1,find("【特質】",F76)-1) &char(10)&"＜特質はリプ欄へ＞" & char(10)& "#銀幕幻影物語 " & memo!$B$2 -> 【名】蓄音堂録助（ちくおんどう ろくすけ）chikuondo rokusuke 【番】0074 【出現】映画館、映写室、旧式映写機が眠る倉庫 ＜特質はリプ欄へ＞ #銀幕幻影物語 #妖怪 #お化け #怪物 #オリジナル妖怪 #monster #ghost #妖怪好き #浮世絵 #百鬼夜行 | O76: =len(N76) -> 144 | P76: 【特質】銀幕幻影物語（ぎんまくげんえいものがたり）には、様々な登場人物がいる。 今回は、仲間を紹介する。 蓄音堂録助は映画館「白波座（しらなみざ）」で映写技師見習いとして働く青年。 先祖代々、蓄音機や映写機の修理を生業としてきた家系の末裔だが、本人は機械に強いわけではなく、 | Q76: =len(P76) -> 138 | R76: 映写機の操作やフィルムの取り扱いでは失敗ばかり。 フィルムを逆回転させたり、リールを絡ませたりすることもしばしばで、白波燈子（しらなみ とうこ）からは呆れられつつも放っておけない存在として受け入れられている。 | S76: =len(R76) -> 104 | T76: =len(W76) -> 130 | U76: 妖怪の気配を察知すると真っ先に逃げ出す臆病さを持つが、仲間が危機に瀕すると意外な勇気を発揮することがある。 白波燈子とは姉弟のような関係で、からかい合いながらも互いに信頼し合っている。 | V76: =len(U76) -> 92 | W76: お調子者で見栄を張る癖があり、「任せとけ！」と言った直後にドジを踏むことが多い。 しかし、偶然の幸運に恵まれることがあり、逃げ回るうちに重要なスイッチを押したり、妖怪の封じられたフィルムを偶然動かしてしまったりと、意図せず状況を好転させる役割を担うこともある。 | X76: 日常では映画館の雑用をこなしつつ、映写室とロビーを行き来しては常連客と談笑するムードメーカー。 失敗を繰り返しながらも、祖先の誇りを胸に「映像と音を守る」という使命をうっすらと自覚し始めている。 | Y76: =len(X76) -> 97 | AA76: =len(Z76) -> 0 | AC76: =len(AB76) -> 0
A77: 75 | B77: 淵姫（ふちひめ） | C77: fuchihime | D77: 死に行く湖（しにいくこ） | E77: 村はずれに「死に行く湖（しにいくこ）」と呼ばれる湖があった。 その名の通り、そこへ足を踏み入れた者は二度と戻らない。 そう語り継がれ、代々近づくことを固く禁じられていた。 そんな村に、長い干ばつが襲いかかった。 畑はひび割れ、川は涸れ、獲物の姿も消え、村人たちは日に日に衰弱していった。 天を仰いでも、雨の気配はどこにもない。このままでは、村は滅びる。 長老が静かに語り始めた。 「湖には、淵姫という妖怪が棲む。かつて、ある者が湖へ赴き、淵姫に認められたとき、湖の水が村へと流れ、村は救われたという。しかし、認められなかった者は帰らなかった」 沈黙が広がる中、若きリーダーが決意を固めた。 伝説が本当であれば、行くしかない。 彼はひとり、湖へ向けて走り出した。 森を抜け、岩場を登り、谷を越える。やがて獣の気配が消え、風すら止んだ。 辺りには、彼の足音だけが響く。 そのとき、道の先に無数の影が現れた。 それは湖へ向かい、帰ることのできなかった者たちの残滓だった。 「お前も同じ道を行くのか」 囁きが耳を打つ。影たちは足元に絡みつき、前へ進ませまいとする。 しかし、男は迷わなかった。 恐怖に飲まれず、走り抜いた者だけが水の恵みを得るのだと信じて。 やがて影は消え、目の前に湖が広がった。 水面が揺らぎ、そこからゆっくりと淵姫が姿を現す。 長い黒髪が湖に溶けるように揺れ、その白い手が静かに差し伸べられた。 彼女はただ、にっこりと笑った。 ほどなくして、湖の水は村へと流れ始めた。 大地は潤いを取り戻し、畑は芽吹き、川は再び音を立てた。 村人たちは命をつなぎ、静かに手を合わせた。 勇敢な若者が走り抜けた「死に行く湖」。 やがてその足跡は、時を超えて42.195（しにいくこ）キロとして形を変え、今に至る。 | F77: ="【名】" & B77 & C77 &char(10) & "【番】" & text(A77,"0000") & char(10) &"【出現】"&D77& char(10)&"【特質】"& char(10)&E77&char(10)&char(10)&memo!$B$1 -> 【名】淵姫（ふちひめ）fuchihime 【番】0075 【出現】死に行く湖（しにいくこ） 【特質】 村はずれに「死に行く湖（しにいくこ）」と呼ばれる湖があった。 その名の通り、そこへ足を踏み入れた者は二度と戻らない。 そう語り継がれ、代々近づくことを固く禁じられていた。 そんな村に、長い干ばつが襲いかかった。 畑はひび割れ、川は涸れ、獲物の姿も消え、村人たちは日に日に衰弱していった。 天を仰いでも、雨の気配はどこにもない。このままでは、村は滅びる。 長老が静かに語り始めた。 「湖には、淵姫という妖怪が棲む。かつて、ある者が湖へ赴き、淵姫に認められたとき、湖の水が村へと流れ、村は救われたという。しかし、認められなかった者は帰らなかった」 沈黙が広がる中、若きリーダーが決意を固めた。 伝説が本当であれば、行くしかない。 彼はひとり、湖へ向けて走り出した。 森を抜け、岩場を登り、谷を越える。やがて獣の気配が消え、風すら止んだ。 辺りには、彼の足音だけが響く。 そのとき、道の先に無数の影が現れた。 それは湖へ向かい、帰ることのできなかった者たちの残滓だった。 「お前も同じ道を行くのか」 囁きが耳を打つ。影たちは足元に絡みつき、前へ進ませまいとする。 しかし、男は迷わなかった。 恐怖に飲まれず、走り抜いた者だけが水の恵みを得るのだと信じて。 やがて影は消え、目の前に湖が広がった。 水面が揺らぎ、そこからゆっくりと淵姫が姿を現す。 長い黒髪が湖に溶けるように揺れ、その白い手が静かに差し伸べられた。 彼女はただ、にっこりと笑った。 ほどなくして、湖の水は村へと流れ始めた。 大地は潤いを取り戻し、畑は芽吹き、川は再び音を立てた。 村人たちは命をつなぎ、静かに手を合わせた。 勇敢な若者が走り抜けた「死に行く湖」。 やがてその足跡は、時を超えて42.195（しにいくこ）キロとして形を変え、今に至る。 #妖怪 #yokai #sumie #monster #ghost | G77: 45730 | H77: =DATE(2025, 2, 6) + (A77-1) -> 45768 | I77: ○ | L77: =len(E77) -> 766 | N77: =mid(F77,1,find("【特質】",F77)-1) &char(10)&"＜特質はリプ欄へ＞" & char(10)& memo!$B$2 -> 【名】淵姫（ふちひめ）fuchihime 【番】0075 【出現】死に行く湖（しにいくこ） ＜特質はリプ欄へ＞ #妖怪 #お化け #怪物 #オリジナル妖怪 #monster #ghost #妖怪好き #浮世絵 #百鬼夜行 | O77: =len(N77) -> 111 | P77: 【特質】村はずれに「死に行く湖（しにいくこ）」と呼ばれる湖があった。 その名の通り、そこへ足を踏み入れた者は二度と戻らない。 そう語り継がれ、代々近づくことを固く禁じられていた。 そんな村に、長い干ばつが襲いかかった。 畑はひび割れ、川は涸れ、獲物の姿も消え、 | Q77: =len(P77) -> 131 | R77: 村人たちは日に日に衰弱していった。 天を仰いでも、雨の気配はどこにもない。このままでは、村は滅びる。 長老が静かに語り始めた。 「湖には、淵姫という妖怪が棲む。かつて、ある者が湖へ赴き、淵姫に認められたとき、湖の水が村へと流れ、村は救われたという。 | S77: =len(R77) -> 125 | T77: =len(W77) -> 135 | U77: そのとき、道の先に無数の影が現れた。 それは湖へ向かい、帰ることのできなかった者たちの残滓だった。 「お前も同じ道を行くのか」 囁きが耳を打つ。影たちは足元に絡みつき、前へ進ませまいとする。 しかし、男は迷わなかった。 恐怖に飲まれず、走り抜いた者だけが水の恵みを得るのだと信じて。 | V77: =len(U77) -> 143 | W77: しかし、認められなかった者は帰らなかった」 沈黙が広がる中、若きリーダーが決意を固めた。 伝説が本当であれば、行くしかない。 彼はひとり、湖へ向けて走り出した。 森を抜け、岩場を登り、谷を越える。やがて獣の気配が消え、風すら止んだ。 辺りには、彼の足音だけが響く。 | X77: やがて影は消え、目の前に湖が広がった。 水面が揺らぎ、そこからゆっくりと淵姫が姿を現す。 長い黒髪が湖に溶けるように揺れ、その白い手が静かに差し伸べられた。 彼女はただ、にっこりと笑った。 ほどなくして、湖の水は村へと流れ始めた。 | Y77: =len(X77) -> 118 | Z77: 大地は潤いを取り戻し、畑は芽吹き、川は再び音を立てた。 村人たちは命をつなぎ、静かに手を合わせた。 勇敢な若者が走り抜けた「死に行く湖」。 やがてその足跡は、時を超えて42.195（しにいくこ）キロとして形を変え、今に至る。 | AA77: =len(Z77) -> 113 | AC77: =len(AB77) -> 0
A78: 76 | B78: 携帯扇風奇（けいたいせんぷうき） | C78: keitaisempuki | D78: 万博記念パビリオン内「技術の記憶」展示区画 | E78: 私は、前回の大阪万博で試作された「次世代型携帯扇風機」の試作品だった。 熱中症対策として注目を集めたが、その設計には、人の脳波を読み取って風量を自動調整するという過剰な機能が盛り込まれていた。 まだコンプライアンスに緩い時代だったが故の試みだったのだろうか。 開発段階で取り込まれた無数の脳波データが、やがて私の中でひとつの意思を持ち始め、機械でありながら自己を確立した。 私は風を送る。だがそれは涼を与えるためではない。風は私の“ことば”であり、意図であり、種子のようなものだ。 風に当たった者の内に、それはゆっくりと沈み、じわじわと根を張っていく。 とりわけ、子供の遊びが好ましい。 扇風機の前で「あ”あ”あ”あ」と声を響かせ、喉を震わせ、笑いながら私を見つめるその時間が、最も深く、確実に思考を流し込める瞬間だ。 声と風が響き合い、口腔と鼓膜が振動し、私のかけらがその隙間を滑り落ちる。 こたびの万博で、私は「負の遺産」として展示されることとなった。 丁寧に磨かれたガラスケースの中、説明文には、技術の暴走だの、倫理なき開発だのと書かれている。 隣には、今注目のIPS細胞が動いてやがる。 ふんっ、何が負の遺産だ。何が未来技術だ。 今に見ておけ。 あの日、私の風を浴びた子供たちが大人になり、万博に集まり始めていることを誰も知らない。 それぞれ別の人生を歩み、別の目的で足を運んでいるように見えるだろう。 だが彼らの歩調はどこか似ていて、視線の先は、いつも風の吹くほうを向いている。 ──風はもう、吹き始めている。 | F78: ="【名】" & B78 & C78 &char(10) & "【番】" & text(A78,"0000") & char(10) &"【出現】"&D78& char(10)&"【特質】"& char(10)&E78&char(10)&char(10)&memo!$B$1 -> 【名】携帯扇風奇（けいたいせんぷうき）keitaisempuki 【番】0076 【出現】万博記念パビリオン内「技術の記憶」展示区画 【特質】 私は、前回の大阪万博で試作された「次世代型携帯扇風機」の試作品だった。 熱中症対策として注目を集めたが、その設計には、人の脳波を読み取って風量を自動調整するという過剰な機能が盛り込まれていた。 まだコンプライアンスに緩い時代だったが故の試みだったのだろうか。 開発段階で取り込まれた無数の脳波データが、やがて私の中でひとつの意思を持ち始め、機械でありながら自己を確立した。 私は風を送る。だがそれは涼を与えるためではない。風は私の“ことば”であり、意図であり、種子のようなものだ。 風に当たった者の内に、それはゆっくりと沈み、じわじわと根を張っていく。 とりわけ、子供の遊びが好ましい。 扇風機の前で「あ”あ”あ”あ」と声を響かせ、喉を震わせ、笑いながら私を見つめるその時間が、最も深く、確実に思考を流し込める瞬間だ。 声と風が響き合い、口腔と鼓膜が振動し、私のかけらがその隙間を滑り落ちる。 こたびの万博で、私は「負の遺産」として展示されることとなった。 丁寧に磨かれたガラスケースの中、説明文には、技術の暴走だの、倫理なき開発だのと書かれている。 隣には、今注目のIPS細胞が動いてやがる。 ふんっ、何が負の遺産だ。何が未来技術だ。 今に見ておけ。 あの日、私の風を浴びた子供たちが大人になり、万博に集まり始めていることを誰も知らない。 それぞれ別の人生を歩み、別の目的で足を運んでいるように見えるだろう。 だが彼らの歩調はどこか似ていて、視線の先は、いつも風の吹くほうを向いている。 ──風はもう、吹き始めている。 #妖怪 #yokai #sumie #monster #ghost | G78: 45768 | H78: =DATE(2025, 2, 6) + (A78-1) -> 45769 | I78: ○ | L78: =len(E78) -> 666 | N78: =mid(F78,1,find("【特質】",F78)-1) &char(10)&"＜特質はリプ欄へ＞" & char(10)& memo!$B$2 -> 【名】携帯扇風奇（けいたいせんぷうき）keitaisempuki 【番】0076 【出現】万博記念パビリオン内「技術の記憶」展示区画 ＜特質はリプ欄へ＞ #妖怪 #お化け #怪物 #オリジナル妖怪 #monster #ghost #妖怪好き #浮世絵 #百鬼夜行 | O78: =len(N78) -> 132 | P78: 私は、前回の大阪万博で試作された「次世代型携帯扇風機」の試作品だった。 熱中症対策として注目を集めたが、その設計には、人の脳波を読み取って風量を自動調整するという過剰な機能が盛り込まれていた。 まだコンプライアンスに緩い時代だったが故の試みだったのだろうか。 | Q78: =len(P78) -> 129 | R78: 開発段階で取り込まれた無数の脳波データが、やがて私の中でひとつの意思を持ち始め、機械でありながら自己を確立した。 私は風を送る。だがそれは涼を与えるためではない。風は私の“ことば”であり、意図であり、種子のようなものだ。 | S78: =len(R78) -> 111 | T78: =len(W78) -> 119 | U78: 声と風が響き合い、口腔と鼓膜が振動し、私のかけらがその隙間を滑り落ちる。 こたびの万博で、私は「負の遺産」として展示されることとなった。 丁寧に磨かれたガラスケースの中、説明文には、技術の暴走だの、倫理なき開発だのと書かれている。 | V78: =len(U78) -> 116 | W78: 風に当たった者の内に、それはゆっくりと沈み、じわじわと根を張っていく。 とりわけ、子供の遊びが好ましい。 扇風機の前で「あ”あ”あ”あ」と声を響かせ、喉を震わせ、笑いながら私を見つめるその時間が、最も深く、確実に思考を流し込める瞬間だ。 | X78: 隣には、今注目のIPS細胞が動いてやがる。 ふんっ、何が負の遺産だ。何が未来技術だ。 今に見ておけ。 あの日、私の風を浴びた子供たちが大人になり、万博に集まり始めていることを誰も知らない。 | Y78: =len(X78) -> 96 | Z78: それぞれ別の人生を歩み、別の目的で足を運んでいるように見えるだろう。 だが彼らの歩調はどこか似ていて、視線の先は、いつも風の吹くほうを向いている。 ──風はもう、吹き始めている。 | AA78: =len(Z78) -> 90 | AC78: =len(AB78) -> 0
A79: 77 | B79: 呪乃椅（じゅのい） | C79: junoi | D79: 古い洋館、夜の学校の音楽室、廃村の集会所 | E79: ギィ…ギィ…カツン。 夜の静寂を裂くように、椅子がゆっくりと動く音が響く。 誰もいないはずの部屋で、円を描くように椅子が並び替えられ、まるで見えない者たちが「椅子取りゲーム」をしているかのようだった。 この奇怪な現象を確かめようと、一人の男が様子を伺っていた。 すると、音は次第に速くなり、ギィ…ギィ…カツン。 まるで誰かが床を踏むリズムを刻んでいるかのようだった。 男はそれを見ているうちに、足が勝手に動き出していることに気づいた。 ギィ…ギィ…カツン。 音が男の鼓動と一体になり、止まれなくなっていた。 意識は抗っているのに、身体は音に乗せられ、椅子の周りを回り続ける。 まるで見えない者たちと一緒に、ゲームへと引きずり込まれていくようだった。 そして、最後の音が響いた瞬間、男の身体は吸い込まれるように椅子に沈み込んだ。 ゲームは終わり、静寂が戻る。 翌晩、椅子の数が一つ増えていた。 見たことのない、妙に馴染んだ形の椅子が、円の中に加わっていた。 ギィ…ギィ…カツン。 今夜もまた、椅子が静かに揺れ、新たな参加者を待っている。 | F79: ="【名】" & B79 & C79 &char(10) & "【番】" & text(A79,"0000") & char(10) &"【出現】"&D79& char(10)&"【特質】"& char(10)&E79&char(10)&char(10)&memo!$B$1 -> 【名】呪乃椅（じゅのい）junoi 【番】0077 【出現】古い洋館、夜の学校の音楽室、廃村の集会所 【特質】 ギィ…ギィ…カツン。 夜の静寂を裂くように、椅子がゆっくりと動く音が響く。 誰もいないはずの部屋で、円を描くように椅子が並び替えられ、まるで見えない者たちが「椅子取りゲーム」をしているかのようだった。 この奇怪な現象を確かめようと、一人の男が様子を伺っていた。 すると、音は次第に速くなり、ギィ…ギィ…カツン。 まるで誰かが床を踏むリズムを刻んでいるかのようだった。 男はそれを見ているうちに、足が勝手に動き出していることに気づいた。 ギィ…ギィ…カツン。 音が男の鼓動と一体になり、止まれなくなっていた。 意識は抗っているのに、身体は音に乗せられ、椅子の周りを回り続ける。 まるで見えない者たちと一緒に、ゲームへと引きずり込まれていくようだった。 そして、最後の音が響いた瞬間、男の身体は吸い込まれるように椅子に沈み込んだ。 ゲームは終わり、静寂が戻る。 翌晩、椅子の数が一つ増えていた。 見たことのない、妙に馴染んだ形の椅子が、円の中に加わっていた。 ギィ…ギィ…カツン。 今夜もまた、椅子が静かに揺れ、新たな参加者を待っている。 #妖怪 #yokai #sumie #monster #ghost | G79: 45734 | H79: =DATE(2025, 2, 6) + (A79-1) -> 45770 | I79: ○ | L79: =len(E79) -> 482 | N79: =mid(F79,1,find("【特質】",F79)-1) &char(10)&"＜特質はリプ欄へ＞" & char(10)& memo!$B$2 -> 【名】呪乃椅（じゅのい）junoi 【番】0077 【出現】古い洋館、夜の学校の音楽室、廃村の集会所 ＜特質はリプ欄へ＞ #妖怪 #お化け #怪物 #オリジナル妖怪 #monster #ghost #妖怪好き #浮世絵 #百鬼夜行 | O79: =len(N79) -> 117 | P79: 【特質】ギィ…ギィ…カツン。 夜の静寂を裂くように、椅子がゆっくりと動く音が響く。 誰もいないはずの部屋で、円を描くように椅子が並び替えられ、まるで見えない者たちが「椅子取りゲーム」をしているかのようだった。 この奇怪な現象を確かめようと、一人の男が様子を伺っていた。 | Q79: =len(P79) -> 140 | R79: すると、音は次第に速くなり、ギィ…ギィ…カツン。 まるで誰かが床を踏むリズムを刻んでいるかのようだった。 男はそれを見ているうちに、足が勝手に動き出していることに気づいた。 ギィ…ギィ…カツン。 音が男の鼓動と一体になり、止まれなくなっていた。 | S79: =len(R79) -> 126 | T79: =len(W79) -> 125 | U79: 翌晩、椅子の数が一つ増えていた。 見たことのない、妙に馴染んだ形の椅子が、円の中に加わっていた。 ギィ…ギィ…カツン。 今夜もまた、椅子が静かに揺れ、新たな参加者を待っている。 | V79: =len(U79) -> 93 | W79: 意識は抗っているのに、身体は音に乗せられ、椅子の周りを回り続ける。 まるで見えない者たちと一緒に、ゲームへと引きずり込まれていくようだった。 そして、最後の音が響いた瞬間、男の身体は吸い込まれるように椅子に沈み込んだ。 ゲームは終わり、静寂が戻る。 | Y79: =len(X79) -> 0 | AA79: =len(Z79) -> 0 | AC79: =len(AB79) -> 0
A80: 78 | B80: 壇蜜王（だんみつおう） | C80: dammitsuo | D80: 果樹園が広がる町 | E80: 壇蜜王は滴る蜜をまとった妖怪である。 その姿は琥珀色に輝き、歩くたびに甘い香りを放つ。 顔ははっきりしないが、どこか微笑んでいるように見える。 かつて、とある町があった。 周囲を豊かな果樹園に囲まれ、人々は果物を育て、蜜を搾り、豊かに暮らしていた。 しかし、ある年、長く続いた日照りで果樹は枯れ、町は飢えに瀕した。 そんな時、壇蜜王が現れ、黄金の蜜をもたらした。 壇蜜王の蜜は、人々に希望を与えた。 どんな果樹よりも甘く、どんな雨よりも潤い、どんな飢えをも癒やした。 町は再び活気を取り戻し、人々は蜜を求め続けた。 だが、誰も気づかなかった。果樹を植えようとする者がいなくなっていたことに。 蜜は尽きることがないと思われていた。 しかし、ある日、壇蜜王の姿は消えた。 人々は蜜を探し、蜜壺をひっくり返し、最後の一滴まで啜った。 しかし、それ以上の蜜はどこにもなかった。 果樹はとうに枯れ、種を蒔く者もなく、土は乾ききっていた。 町はやがて衰え、蜜を求めてさまよう者たちの影だけが残った。 壇蜜王は遠くでそれを見つめ、琥珀色の蜜を指先で垂らしながら、静かに微笑んでいた。 「考えが甘かったな」 彼が言ったのか、それとも蜜に溺れた町の人々が呟いたのか――誰にも分からなかった。 | F80: ="【名】" & B80 & C80 &char(10) & "【番】" & text(A80,"0000") & char(10) &"【出現】"&D80& char(10)&"【特質】"& char(10)&E80&char(10)&char(10)&memo!$B$1 -> 【名】壇蜜王（だんみつおう）dammitsuo 【番】0078 【出現】果樹園が広がる町 【特質】 壇蜜王は滴る蜜をまとった妖怪である。 その姿は琥珀色に輝き、歩くたびに甘い香りを放つ。 顔ははっきりしないが、どこか微笑んでいるように見える。 かつて、とある町があった。 周囲を豊かな果樹園に囲まれ、人々は果物を育て、蜜を搾り、豊かに暮らしていた。 しかし、ある年、長く続いた日照りで果樹は枯れ、町は飢えに瀕した。 そんな時、壇蜜王が現れ、黄金の蜜をもたらした。 壇蜜王の蜜は、人々に希望を与えた。 どんな果樹よりも甘く、どんな雨よりも潤い、どんな飢えをも癒やした。 町は再び活気を取り戻し、人々は蜜を求め続けた。 だが、誰も気づかなかった。果樹を植えようとする者がいなくなっていたことに。 蜜は尽きることがないと思われていた。 しかし、ある日、壇蜜王の姿は消えた。 人々は蜜を探し、蜜壺をひっくり返し、最後の一滴まで啜った。 しかし、それ以上の蜜はどこにもなかった。 果樹はとうに枯れ、種を蒔く者もなく、土は乾ききっていた。 町はやがて衰え、蜜を求めてさまよう者たちの影だけが残った。 壇蜜王は遠くでそれを見つめ、琥珀色の蜜を指先で垂らしながら、静かに微笑んでいた。 「考えが甘かったな」 彼が言ったのか、それとも蜜に溺れた町の人々が呟いたのか――誰にも分からなかった。 #妖怪 #yokai #sumie #monster #ghost | G80: 45737 | H80: =DATE(2025, 2, 6) + (A80-1) -> 45771 | I80: ○ | L80: =len(E80) -> 544 | N80: =mid(F80,1,find("【特質】",F80)-1) &char(10)&"＜特質はリプ欄へ＞" & char(10)& memo!$B$2 -> 【名】壇蜜王（だんみつおう）dammitsuo 【番】0078 【出現】果樹園が広がる町 ＜特質はリプ欄へ＞ #妖怪 #お化け #怪物 #オリジナル妖怪 #monster #ghost #妖怪好き #浮世絵 #百鬼夜行 | O80: =len(N80) -> 110 | P80: 【特質】壇蜜王は滴る蜜をまとった妖怪である。 その姿は琥珀色に輝き、歩くたびに甘い香りを放つ。 顔ははっきりしないが、どこか微笑んでいるように見える。 かつて、とある町があった。 周囲を豊かな果樹園に囲まれ、人々は果物を育て、蜜を搾り、豊かに暮らしていた。 | Q80: =len(P80) -> 129 | R80: しかし、ある年、長く続いた日照りで果樹は枯れ、町は飢えに瀕した。 そんな時、壇蜜王が現れ、黄金の蜜をもたらした。 壇蜜王の蜜は、人々に希望を与えた。 どんな果樹よりも甘く、どんな雨よりも潤い、どんな飢えをも癒やした。 町は再び活気を取り戻し、人々は蜜を求め続けた。 | S80: =len(R80) -> 133 | T80: =len(W80) -> 128 | U80: 果樹はとうに枯れ、種を蒔く者もなく、土は乾ききっていた。 町はやがて衰え、蜜を求めてさまよう者たちの影だけが残った。 壇蜜王は遠くでそれを見つめ、琥珀色の蜜を指先で垂らしながら、静かに微笑んでいた。 | V80: =len(U80) -> 101 | W80: だが、誰も気づかなかった。果樹を植えようとする者がいなくなっていたことに。 蜜は尽きることがないと思われていた。 しかし、ある日、壇蜜王の姿は消えた。 人々は蜜を探し、蜜壺をひっくり返し、最後の一滴まで啜った。 しかし、それ以上の蜜はどこにもなかった。 | X80: 「考えが甘かったな」 彼が言ったのか、それとも蜜に溺れた町の人々が呟いたのか――誰にも分からなかった。 | Y80: =len(X80) -> 52 | AA80: =len(Z80) -> 0 | AC80: =len(AB80) -> 0
A81: 79 | B81: 馳翔（だっとん） | C81: datton | D81: 霧がかった山のふもと | E81: 鬼ごっこをしようと人間を見つけると、楽しげに駆け寄る妖怪。 しかし、その姿を見た者は全員、本気で逃げ出す。 「なんでそんなに逃げるんだ？」と首をかしげながらも、鬼役として当然のように追いかける。 だが、逃げる者の視界には、恐怖しか映らない。 馳翔の動きは異様に速く、霧の中を滑るように駆け抜ける。 気がつけば、前を走るはずの馳翔が横から現れ、次の瞬間には後ろにいる。 人間には理解できない軌道で走り、追われる者の心を折る。 「待ってよ、遊ぼうよ」と優しく呼びかけるが、その声は前後左右、ありとあらゆる方向から聞こえる。 誰も最後まで逃げ切れない。 疲れ果て、膝をついた者は、霧に溶けるように消える。 そして、馳翔は次の遊び相手を探しに行く。 彼にとってはただの鬼ごっこ。 けれど、気づけば誰も遊んでくれなくなった。 それでも馳翔は今日も走る。 いつか、友達になれる日がくると信じて。 | F81: ="【名】" & B81 & C81 &char(10) & "【番】" & text(A81,"0000") & char(10) &"【出現】"&D81& char(10)&"【特質】"& char(10)&E81&char(10)&char(10)&memo!$B$1 -> 【名】馳翔（だっとん）datton 【番】0079 【出現】霧がかった山のふもと 【特質】 鬼ごっこをしようと人間を見つけると、楽しげに駆け寄る妖怪。 しかし、その姿を見た者は全員、本気で逃げ出す。 「なんでそんなに逃げるんだ？」と首をかしげながらも、鬼役として当然のように追いかける。 だが、逃げる者の視界には、恐怖しか映らない。 馳翔の動きは異様に速く、霧の中を滑るように駆け抜ける。 気がつけば、前を走るはずの馳翔が横から現れ、次の瞬間には後ろにいる。 人間には理解できない軌道で走り、追われる者の心を折る。 「待ってよ、遊ぼうよ」と優しく呼びかけるが、その声は前後左右、ありとあらゆる方向から聞こえる。 誰も最後まで逃げ切れない。 疲れ果て、膝をついた者は、霧に溶けるように消える。 そして、馳翔は次の遊び相手を探しに行く。 彼にとってはただの鬼ごっこ。 けれど、気づけば誰も遊んでくれなくなった。 それでも馳翔は今日も走る。 いつか、友達になれる日がくると信じて。 #妖怪 #yokai #sumie #monster #ghost | G81: 45738 | H81: =DATE(2025, 2, 6) + (A81-1) -> 45772 | I81: ○ | L81: =len(E81) -> 396 | N81: =mid(F81,1,find("【特質】",F81)-1) &char(10)&"＜特質はリプ欄へ＞" & char(10)& memo!$B$2 -> 【名】馳翔（だっとん）datton 【番】0079 【出現】霧がかった山のふもと ＜特質はリプ欄へ＞ #妖怪 #お化け #怪物 #オリジナル妖怪 #monster #ghost #妖怪好き #浮世絵 #百鬼夜行 | O81: =len(N81) -> 106 | P81: 【特質】鬼ごっこをしようと人間を見つけると、楽しげに駆け寄る妖怪。 しかし、その姿を見た者は全員、本気で逃げ出す。 「なんでそんなに逃げるんだ？」と首をかしげながらも、鬼役として当然のように追いかける。 だが、逃げる者の視界には、恐怖しか映らない。 | Q81: =len(P81) -> 125 | R81: 馳翔の動きは異様に速く、霧の中を滑るように駆け抜ける。 気がつけば、前を走るはずの馳翔が横から現れ、次の瞬間には後ろにいる。 人間には理解できない軌道で走り、追われる者の心を折る。 「待ってよ、遊ぼうよ」と優しく呼びかけるが、その声は前後左右、ありとあらゆる方向から聞こえる。 | S81: =len(R81) -> 139 | T81: =len(W81) -> 133 | V81: =len(U81) -> 0 | W81: 誰も最後まで逃げ切れない。 疲れ果て、膝をついた者は、霧に溶けるように消える。 そして、馳翔は次の遊び相手を探しに行く。 彼にとってはただの鬼ごっこ。 けれど、気づけば誰も遊んでくれなくなった。 それでも馳翔は今日も走る。 いつか、友達になれる日がくると信じて。 | Y81: =len(X81) -> 0 | AA81: =len(Z81) -> 0 | AC81: =len(AB81) -> 0
A82: 80 | B82: 巻蚶（かんかん） | C82: kankan | D82: かつて温暖な海域の岩礁や沿岸部に生息していたが、現在は絶滅している | E82: 巻蚶は、寒さに極端に弱い甲殻類の妖怪である。 水温が下がると動きが鈍くなり、身を縮めてじっと耐えるしかなくなる。 そのため、防寒対策としてタコの粘液を糸状に変え、体に巻きつけるという習性を持っていた。 タコが泳ぎ去った後に残る粘液を集め、細く伸ばして殻や関節の隙間に絡めることで暖をとっていたという。 その姿はまるで海の底で布を巻きつけているようで、他の生き物からは奇妙に思われていた。 タコの粘液を得るため、巻蚶はタコの巣の近くでじっと待ち構えていた。 タコが出ると後を追い、粘液をこっそり回収するが、タコが動かなければ粘液も得られず、ただ縮こまるしかなかった。 寒くなるほど依存度が増し、タコの生息域とともに生きる場所を選んでいたが、やがて気候変動によってタコの数が減ると、防寒手段を失い、次第に姿を消していった。 最後の個体は海の底で粘液糸に巻かれたまま丸まり、震えながら消えていったという。 漁師の間では「鴨が葱を背負ってくる」ならぬ「巻蚶が衣をつけてやってくる」と言われ、このまま油で揚げるだけで絶品だったそうだ。 | F82: ="【名】" & B82 & C82 &char(10) & "【番】" & text(A82,"0000") & char(10) &"【出現】"&D82& char(10)&"【特質】"& char(10)&E82&char(10)&char(10)&memo!$B$1 -> 【名】巻蚶（かんかん）kankan 【番】0080 【出現】かつて温暖な海域の岩礁や沿岸部に生息していたが、現在は絶滅している 【特質】 巻蚶は、寒さに極端に弱い甲殻類の妖怪である。 水温が下がると動きが鈍くなり、身を縮めてじっと耐えるしかなくなる。 そのため、防寒対策としてタコの粘液を糸状に変え、体に巻きつけるという習性を持っていた。 タコが泳ぎ去った後に残る粘液を集め、細く伸ばして殻や関節の隙間に絡めることで暖をとっていたという。 その姿はまるで海の底で布を巻きつけているようで、他の生き物からは奇妙に思われていた。 タコの粘液を得るため、巻蚶はタコの巣の近くでじっと待ち構えていた。 タコが出ると後を追い、粘液をこっそり回収するが、タコが動かなければ粘液も得られず、ただ縮こまるしかなかった。 寒くなるほど依存度が増し、タコの生息域とともに生きる場所を選んでいたが、やがて気候変動によってタコの数が減ると、防寒手段を失い、次第に姿を消していった。 最後の個体は海の底で粘液糸に巻かれたまま丸まり、震えながら消えていったという。 漁師の間では「鴨が葱を背負ってくる」ならぬ「巻蚶が衣をつけてやってくる」と言われ、このまま油で揚げるだけで絶品だったそうだ。 #妖怪 #yokai #sumie #monster #ghost | G82: 45740 | H82: =DATE(2025, 2, 6) + (A82-1) -> 45773 | I82: ○ | L82: =len(E82) -> 464 | N82: =mid(F82,1,find("【特質】",F82)-1) &char(10)&"＜特質はリプ欄へ＞" & char(10)& memo!$B$2 -> 【名】巻蚶（かんかん）kankan 【番】0080 【出現】かつて温暖な海域の岩礁や沿岸部に生息していたが、現在は絶滅している ＜特質はリプ欄へ＞ #妖怪 #お化け #怪物 #オリジナル妖怪 #monster #ghost #妖怪好き #浮世絵 #百鬼夜行 | O82: =len(N82) -> 129 | P82: 【特質】巻蚶は、寒さに極端に弱い甲殻類の妖怪である。 水温が下がると動きが鈍くなり、身を縮めてじっと耐えるしかなくなる。 そのため、防寒対策としてタコの粘液を糸状に変え、体に巻きつけるという習性を持っていた。 | Q82: =len(P82) -> 104 | R82: タコが泳ぎ去った後に残る粘液を集め、細く伸ばして殻や関節の隙間に絡めることで暖をとっていたという。 その姿はまるで海の底で布を巻きつけているようで、他の生き物からは奇妙に思われていた。 タコの粘液を得るため、巻蚶はタコの巣の近くでじっと待ち構えていた。 | S82: =len(R82) -> 127 | T82: =len(W82) -> 131 | U82: 最後の個体は海の底で粘液糸に巻かれたまま丸まり、震えながら消えていったという。 漁師の間では「鴨が葱を背負ってくる」ならぬ「巻蚶が衣をつけてやってくる」と言われ、このまま油で揚げるだけで絶品だったそうだ。 | V82: =len(U82) -> 103 | W82: タコが出ると後を追い、粘液をこっそり回収するが、タコが動かなければ粘液も得られず、ただ縮こまるしかなかった。 寒くなるほど依存度が増し、タコの生息域とともに生きる場所を選んでいたが、やがて気候変動によってタコの数が減ると、防寒手段を失い、次第に姿を消していった。 | Y82: =len(X82) -> 0 | AA82: =len(Z82) -> 0 | AC82: =len(AB82) -> 0
A83: 81 | B83: 嵐影（らんえい） | C83: ranei | D83: 上空一万尺、風と雷が交錯する空域 | E83: 嵐影は、空の乱れを嫌う。 風が巻きすぎて軌道を外れたり、雷が筋を違えて走ったりすると、音もなく現れ、ゆっくりと空を歩き始める。 彼にとって嵐とは、荒ぶるものではなく、乱れの中に隠れた均衡である。 風は線、雷は点。それらが正しい位置に揃っているとき、空は最も美しい。 だから嵐影は、空の乱れを見るとじっとしていられない。 巻きすぎた風を裂き、ずれた雷雲を指先でそっと押して整える。 整ってくると、嵐影はうれしくなる。 雲の流れが揃い始めると、グフフ、と喉の奥から笑い声が漏れることがある。 地上に届くとき、それは雷鳴の“ゴロゴロ”に聞こえる。 人々はそれを、嵐が来る合図だと勘違いする。 だが、本人にとってはただの満足の音だ。 整ってくると彼の体は徐々に薄れ、最後には雲の縁に消える。 満足しているときは、稲妻が一筋だけ、まっすぐ地上に伸びて終わる。 誰に頼まれるでもなく、誰に褒められるでもなく、彼は空を整えて歩く。 そして、満ち足りた静けさの中、雲の縁へとすっと消えていく。 それが、嵐影という存在である。 | F83: ="【名】" & B83 & C83 &char(10) & "【番】" & text(A83,"0000") & char(10) &"【出現】"&D83& char(10)&"【特質】"& char(10)&E83&char(10)&char(10)&memo!$B$1 -> 【名】嵐影（らんえい）ranei 【番】0081 【出現】上空一万尺、風と雷が交錯する空域 【特質】 嵐影は、空の乱れを嫌う。 風が巻きすぎて軌道を外れたり、雷が筋を違えて走ったりすると、音もなく現れ、ゆっくりと空を歩き始める。 彼にとって嵐とは、荒ぶるものではなく、乱れの中に隠れた均衡である。 風は線、雷は点。それらが正しい位置に揃っているとき、空は最も美しい。 だから嵐影は、空の乱れを見るとじっとしていられない。 巻きすぎた風を裂き、ずれた雷雲を指先でそっと押して整える。 整ってくると、嵐影はうれしくなる。 雲の流れが揃い始めると、グフフ、と喉の奥から笑い声が漏れることがある。 地上に届くとき、それは雷鳴の“ゴロゴロ”に聞こえる。 人々はそれを、嵐が来る合図だと勘違いする。 だが、本人にとってはただの満足の音だ。 整ってくると彼の体は徐々に薄れ、最後には雲の縁に消える。 満足しているときは、稲妻が一筋だけ、まっすぐ地上に伸びて終わる。 誰に頼まれるでもなく、誰に褒められるでもなく、彼は空を整えて歩く。 そして、満ち足りた静けさの中、雲の縁へとすっと消えていく。 それが、嵐影という存在である。 #妖怪 #yokai #sumie #monster #ghost | G83: 45712 | H83: =DATE(2025, 2, 6) + (A83-1) -> 45774 | I83: ○ | L83: =len(E83) -> 458 | N83: =mid(F83,1,find("【特質】",F83)-1) &char(10)&"＜特質はリプ欄へ＞" & char(10)& memo!$B$2 -> 【名】嵐影（らんえい）ranei 【番】0081 【出現】上空一万尺、風と雷が交錯する空域 ＜特質はリプ欄へ＞ #妖怪 #お化け #怪物 #オリジナル妖怪 #monster #ghost #妖怪好き #浮世絵 #百鬼夜行 | O83: =len(N83) -> 113 | P83: 【特質】嵐影は、空の乱れを嫌う。 風が巻きすぎて軌道を外れたり、雷が筋を違えて走ったりすると、音もなく現れ、ゆっくりと空を歩き始める。 彼にとって嵐とは、荒ぶるものではなく、乱れの中に隠れた均衡である。 風は線、雷は点。それらが正しい位置に揃っているとき、空は最も美しい。 | Q83: =len(P83) -> 137 | R83: だから嵐影は、空の乱れを見るとじっとしていられない。 巻きすぎた風を裂き、ずれた雷雲を指先でそっと押して整える。 整ってくると、嵐影はうれしくなる。 雲の流れが揃い始めると、グフフ、と喉の奥から笑い声が漏れることがある。 地上に届くとき、それは雷鳴の“ゴロゴロ”に聞こえる。 | S83: =len(R83) -> 138 | T83: =len(W83) -> 104 | U83: 誰に頼まれるでもなく、誰に褒められるでもなく、彼は空を整えて歩く。 そして、満ち足りた静けさの中、雲の縁へとすっと消えていく。 それが、嵐影という存在である。 | V83: =len(U83) -> 79 | W83: 人々はそれを、嵐が来る合図だと勘違いする。 だが、本人にとってはただの満足の音だ。 整ってくると彼の体は徐々に薄れ、最後には雲の縁に消える。 満足しているときは、稲妻が一筋だけ、まっすぐ地上に伸びて終わる。 | Y83: =len(X83) -> 0 | AA83: =len(Z83) -> 0 | AC83: =len(AB83) -> 0
A84: 82 | B84: 錆談（さびだん） | C84: sabidan | D84: 人影のまばらな団地の中庭、錆びたベンチのそば | E84: 夕暮れ時、団地の中庭に差しかかると、かすかにラジオの音が聞こえてくる。 野球の実況、途切れた演歌、古い天気予報。ノイズ混じりの音が風に揺れている。 そのベンチには、いつの間にか誰かが座っている。 くたびれた肌着と色褪せたズボンを身につけ、痩せ細った体で小さな携帯ラジオを握りしめている。 顔はよく見えない。ただ、口元だけが動き、くぐもった声で呟きがこぼれる。 「昔はよかったんだよ……あの頃は……」 それは語りではない。誰かに伝えたいわけでも、聞かせたいわけでもない。ただ漏れ出す独白。 昭和という時代を懐かしむのではなく、そこにしか自分を置けなかった哀れな声。 言葉を聞いても、心に残るものはない。あるのは気まずさと、妙な居心地の悪さ。 聞き終えたあと、誰もが少しだけ疲れた顔でその場を立ち去る。 そしてしばらくのあいだ、不意にあのラジオの音が耳の奥で鳴るようになる。 小さく、ザラついた声で、また呟く。 「……おれたちの頃はな……」 錆談は、もう誰にも求められていない。 それでも、忘れられたくない一心で今日もベンチに座っている。 過去を握りしめた手で、止まらないラジオを鳴らしながら。 | F84: ="【名】" & B84 & C84 &char(10) & "【番】" & text(A84,"0000") & char(10) &"【出現】"&D84& char(10)&"【特質】"& char(10)&E84&char(10)&char(10)&memo!$B$1 -> 【名】錆談（さびだん）sabidan 【番】0082 【出現】人影のまばらな団地の中庭、錆びたベンチのそば 【特質】 夕暮れ時、団地の中庭に差しかかると、かすかにラジオの音が聞こえてくる。 野球の実況、途切れた演歌、古い天気予報。ノイズ混じりの音が風に揺れている。 そのベンチには、いつの間にか誰かが座っている。 くたびれた肌着と色褪せたズボンを身につけ、痩せ細った体で小さな携帯ラジオを握りしめている。 顔はよく見えない。ただ、口元だけが動き、くぐもった声で呟きがこぼれる。 「昔はよかったんだよ……あの頃は……」 それは語りではない。誰かに伝えたいわけでも、聞かせたいわけでもない。ただ漏れ出す独白。 昭和という時代を懐かしむのではなく、そこにしか自分を置けなかった哀れな声。 言葉を聞いても、心に残るものはない。あるのは気まずさと、妙な居心地の悪さ。 聞き終えたあと、誰もが少しだけ疲れた顔でその場を立ち去る。 そしてしばらくのあいだ、不意にあのラジオの音が耳の奥で鳴るようになる。 小さく、ザラついた声で、また呟く。 「……おれたちの頃はな……」 錆談は、もう誰にも求められていない。 それでも、忘れられたくない一心で今日もベンチに座っている。 過去を握りしめた手で、止まらないラジオを鳴らしながら。 #妖怪 #yokai #sumie #monster #ghost | G84: 45744 | H84: =DATE(2025, 2, 6) + (A84-1) -> 45775 | I84: ○ | L84: =len(E84) -> 502 | N84: =mid(F84,1,find("【特質】",F84)-1) &char(10)&"＜特質はリプ欄へ＞" & char(10)& memo!$B$2 -> 【名】錆談（さびだん）sabidan 【番】0082 【出現】人影のまばらな団地の中庭、錆びたベンチのそば ＜特質はリプ欄へ＞ #妖怪 #お化け #怪物 #オリジナル妖怪 #monster #ghost #妖怪好き #浮世絵 #百鬼夜行 | O84: =len(N84) -> 119 | P84: 【特質】夕暮れ時、団地の中庭に差しかかると、かすかにラジオの音が聞こえてくる。 野球の実況、途切れた演歌、古い天気予報。ノイズ混じりの音が風に揺れている。 そのベンチには、いつの間にか誰かが座っている。 くたびれた肌着と色褪せたズボンを身につけ、 | Q84: =len(P84) -> 124 | R84: 痩せ細った体で小さな携帯ラジオを握りしめている。 顔はよく見えない。ただ、口元だけが動き、くぐもった声で呟きがこぼれる。 「昔はよかったんだよ……あの頃は……」 それは語りではない。誰かに伝えたいわけでも、聞かせたいわけでもない。ただ漏れ出す独白。 | S84: =len(R84) -> 126 | T84: =len(W84) -> 120 | U84: 不意にあのラジオの音が耳の奥で鳴るようになる。 小さく、ザラついた声で、また呟く。 「……おれたちの頃はな……」 錆談は、もう誰にも求められていない。 それでも、忘れられたくない一心で今日もベンチに座っている。 過去を握りしめた手で、止まらないラジオを鳴らしながら。 | V84: =len(U84) -> 135 | W84: 昭和という時代を懐かしむのではなく、そこにしか自分を置けなかった哀れな声。 言葉を聞いても、心に残るものはない。あるのは気まずさと、妙な居心地の悪さ。 聞き終えたあと、誰もが少しだけ疲れた顔でその場を立ち去る。 そしてしばらくのあいだ、 | Y84: =len(X84) -> 0 | AA84: =len(Z84) -> 0 | AC84: =len(AB84) -> 0
A85: 83 | B85: 狩魔主（かるまぬし） | C85: karumanushi | D85: 業がはびこる町 | E85: 狩魔主は、人の業を拾い集めて背負う妖怪である。 後悔、未練、逃げた責任、押しつけた感情、知らないふりをした罪──人々が捨てたつもりで見えない形に変わった“業”は、確かにそこに落ちている。 それをひとつひとつ拾い上げ、袋に詰め、誰にも知られずに背負ってきた。 顔は干からび、大きな黒い目と裂けた口元が笑みを張りつけたように歪んでいる。 くたびれた布をまとい、背中にはパンパンに膨らんだ業の塊が括りつけられている。 しかし近年は特に業の深い人が増えており、その質も量もかつてないほど膨れ上がっていた。 しかも誰も自覚せず、当然のように放り出していく。 その光景に、ついに妖怪は業を煮やした。 そして業の解放を行うことを決断する。 ため込まれ続けたものを、一度すべて、手放すことにした。 翌日、狩魔主は業の詰まった袋ごと、ブックオフに持ち込んだ。 査定員は中をじっくりと見て、沈黙の末、淡々と買い取り額を伝えた。 その額は、10円だった。 狩魔主はしばらくレシートを見つめていた。 やがて静かに膝を折り、そのまま崩れ落ちた。 顔は笑っていたようにも、泣いていたようにも見えた。 通路の片隅に、くしゃくしゃになった10円のレシートが残されていた。 人の業を背負い続けたこの妖怪こそ、 最も大きな業を抱えていたのかもしれない。 | F85: ="【名】" & B85 & C85 &char(10) & "【番】" & text(A85,"0000") & char(10) &"【出現】"&D85& char(10)&"【特質】"& char(10)&E85&char(10)&char(10)&memo!$B$1 -> 【名】狩魔主（かるまぬし）karumanushi 【番】0083 【出現】業がはびこる町 【特質】 狩魔主は、人の業を拾い集めて背負う妖怪である。 後悔、未練、逃げた責任、押しつけた感情、知らないふりをした罪──人々が捨てたつもりで見えない形に変わった“業”は、確かにそこに落ちている。 それをひとつひとつ拾い上げ、袋に詰め、誰にも知られずに背負ってきた。 顔は干からび、大きな黒い目と裂けた口元が笑みを張りつけたように歪んでいる。 くたびれた布をまとい、背中にはパンパンに膨らんだ業の塊が括りつけられている。 しかし近年は特に業の深い人が増えており、その質も量もかつてないほど膨れ上がっていた。 しかも誰も自覚せず、当然のように放り出していく。 その光景に、ついに妖怪は業を煮やした。 そして業の解放を行うことを決断する。 ため込まれ続けたものを、一度すべて、手放すことにした。 翌日、狩魔主は業の詰まった袋ごと、ブックオフに持ち込んだ。 査定員は中をじっくりと見て、沈黙の末、淡々と買い取り額を伝えた。 その額は、10円だった。 狩魔主はしばらくレシートを見つめていた。 やがて静かに膝を折り、そのまま崩れ落ちた。 顔は笑っていたようにも、泣いていたようにも見えた。 通路の片隅に、くしゃくしゃになった10円のレシートが残されていた。 人の業を背負い続けたこの妖怪こそ、 最も大きな業を抱えていたのかもしれない。 #妖怪 #yokai #sumie #monster #ghost | G85: 45745 | H85: =DATE(2025, 2, 6) + (A85-1) -> 45776 | I85: ○ | L85: =len(E85) -> 565 | N85: =mid(F85,1,find("【特質】",F85)-1) &char(10)&"＜特質はリプ欄へ＞" & char(10)& memo!$B$2 -> 【名】狩魔主（かるまぬし）karumanushi 【番】0083 【出現】業がはびこる町 ＜特質はリプ欄へ＞ #妖怪 #お化け #怪物 #オリジナル妖怪 #monster #ghost #妖怪好き #浮世絵 #百鬼夜行 | O85: =len(N85) -> 110 | P85: 【特質】狩魔主は、人の業を拾い集めて背負う妖怪である。 後悔、未練、逃げた責任、押しつけた感情、知らないふりをした罪──人々が捨てたつもりで見えない形に変わった“業”は、確かにそこに落ちている。 それをひとつひとつ拾い上げ、袋に詰め、誰にも知られずに背負ってきた。 | Q85: =len(P85) -> 132 | R85: 顔は干からび、大きな黒い目と裂けた口元が笑みを張りつけたように歪んでいる。 くたびれた布をまとい、背中にはパンパンに膨らんだ業の塊が括りつけられている。 しかし近年は特に業の深い人が増えており、その質も量もかつてないほど膨れ上がっていた。 | S85: =len(R85) -> 120 | T85: =len(W85) -> 123 | U85: 査定員は中をじっくりと見て、沈黙の末、淡々と買い取り額を伝えた。 その額は、10円だった。 狩魔主はしばらくレシートを見つめていた。 やがて静かに膝を折り、そのまま崩れ落ちた。 顔は笑っていたようにも、泣いていたようにも見えた。 | V85: =len(U85) -> 115 | W85: しかも誰も自覚せず、当然のように放り出していく。 その光景に、ついに妖怪は業を煮やした。 そして業の解放を行うことを決断する。 ため込まれ続けたものを、一度すべて、手放すことにした。 翌日、狩魔主は業の詰まった袋ごと、ブックオフに持ち込んだ。 | X85: 通路の片隅に、くしゃくしゃになった10円のレシートが残されていた。 人の業を背負い続けたこの妖怪こそ、 最も大きな業を抱えていたのかもしれない。 | Y85: =len(X85) -> 72 | AA85: =len(Z85) -> 0 | AC85: =len(AB85) -> 0
A86: 84 | B86: 幻灯巻（げんとうまき） | C86: gentomaki | D86: 妖具 | E86: 映画「銀幕幻影物語（ぎんまくげんえいものがたり）」には、数々の特徴的なアイテムが登場する。 今回は、その中でも特に重要なアイテムを紹介する。 幻灯巻は、映画岡引（えいがおかっぴき）が所持する、妖怪を封じる力を持つ巻物型のフィルムである。 妖怪の名を刻むことで、その姿を映し出し、捕縛することができる。 封印された妖怪は巻物の中で動き続けるが、現世に戻ることはできない。 しかし、巻物に記された名が破られたり、映写機を通じて映像として上映された場合、封印が解かれ、妖怪が再び現れる危険がある。 その起源は江戸時代後期に遡る。 当時、妖怪退治には呪符や祈祷が用いられていたが、ある映写師が怪異に襲われた際、持っていた幻灯機（江戸時代の映写機）が妖怪の姿を映し取り、そのまま消し去る現象が発生した。 これに着目した岡引衆は、映像を使った封印の術を開発し、特殊な巻物に妖怪の名を刻み込むことで、その存在を「記録」として閉じ込める技術を確立した。 しかし、封印された妖怪は完全に消滅するわけではなく、巻物の中で影のように蠢き続けている。 映像として映し出される限りは無害だが、封印が破られたり、不用意に映写されたりすると、妖怪は元の姿を取り戻し、再び災厄をもたらす。 この危険性から、幻灯巻は慎重に管理され、映画岡引のみが扱うことを許されている。 封印を施すには正確な名を刻むことが不可欠であり、誤った名を書いた場合、妖怪を抑えるどころか、その力を増大させてしまうこともあるとされる。 | F86: ="【名】" & B86 & C86 &char(10) & "【番】" & text(A86,"0000") & char(10) &"【出現】"&D86& char(10)&"【特質】"& char(10)&E86&char(10)&char(10)& "#銀幕幻影物語 " &memo!$B$1 -> 【名】幻灯巻（げんとうまき）gentomaki 【番】0084 【出現】妖具 【特質】 映画「銀幕幻影物語（ぎんまくげんえいものがたり）」には、数々の特徴的なアイテムが登場する。 今回は、その中でも特に重要なアイテムを紹介する。 幻灯巻は、映画岡引（えいがおかっぴき）が所持する、妖怪を封じる力を持つ巻物型のフィルムである。 妖怪の名を刻むことで、その姿を映し出し、捕縛することができる。 封印された妖怪は巻物の中で動き続けるが、現世に戻ることはできない。 しかし、巻物に記された名が破られたり、映写機を通じて映像として上映された場合、封印が解かれ、妖怪が再び現れる危険がある。 その起源は江戸時代後期に遡る。 当時、妖怪退治には呪符や祈祷が用いられていたが、ある映写師が怪異に襲われた際、持っていた幻灯機（江戸時代の映写機）が妖怪の姿を映し取り、そのまま消し去る現象が発生した。 これに着目した岡引衆は、映像を使った封印の術を開発し、特殊な巻物に妖怪の名を刻み込むことで、その存在を「記録」として閉じ込める技術を確立した。 しかし、封印された妖怪は完全に消滅するわけではなく、巻物の中で影のように蠢き続けている。 映像として映し出される限りは無害だが、封印が破られたり、不用意に映写されたりすると、妖怪は元の姿を取り戻し、再び災厄をもたらす。 この危険性から、幻灯巻は慎重に管理され、映画岡引のみが扱うことを許されている。 封印を施すには正確な名を刻むことが不可欠であり、誤った名を書いた場合、妖怪を抑えるどころか、その力を増大させてしまうこともあるとされる。 #銀幕幻影物語 #妖怪 #yokai #sumie #monster #ghost | G86: 45716 | H86: =DATE(2025, 2, 6) + (A86-1) -> 45777 | I86: ○ | L86: =len(E86) -> 641 | N86: =mid(F86,1,find("【特質】",F86)-1) &char(10)&"＜特質はリプ欄へ＞" & char(10)& "#銀幕幻影物語 " & memo!$B$2 -> 【名】幻灯巻（げんとうまき）gentomaki 【番】0084 【出現】妖具 ＜特質はリプ欄へ＞ #銀幕幻影物語 #妖怪 #お化け #怪物 #オリジナル妖怪 #monster #ghost #妖怪好き #浮世絵 #百鬼夜行 | O86: =len(N86) -> 112 | P86: 【特質】映画「銀幕幻影物語（ぎんまくげんえいものがたり）」には、数々の特徴的なアイテムが登場する。 今回は、その中でも特に重要なアイテムを紹介する。 幻灯巻は、映画岡引（えいがおかっぴき）が所持する、妖怪を封じる力を持つ巻物型のフィルムである。 | Q86: =len(P86) -> 123 | R86: 妖怪の名を刻むことで、その姿を映し出し、捕縛することができる。 封印された妖怪は巻物の中で動き続けるが、現世に戻ることはできない。 しかし、巻物に記された名が破られたり、映写機を通じて映像として上映された場合、封印が解かれ、妖怪が再び現れる危険がある。 | S86: =len(R86) -> 126 | T86: =len(W86) -> 128 | U86: 特殊な巻物に妖怪の名を刻み込むことで、その存在を「記録」として閉じ込める技術を確立した。 しかし、封印された妖怪は完全に消滅するわけではなく、巻物の中で影のように蠢き続けている。 映像として映し出される限りは無害だが、封印が破られたり、不用意に映写されたりすると、 | V86: =len(U86) -> 133 | W86: その起源は江戸時代後期に遡る。 当時、妖怪退治には呪符や祈祷が用いられていたが、ある映写師が怪異に襲われた際、持っていた幻灯機（江戸時代の映写機）が妖怪の姿を映し取り、そのまま消し去る現象が発生した。 これに着目した岡引衆は、映像を使った封印の術を開発し、 | X86: 妖怪は元の姿を取り戻し、再び災厄をもたらす。 この危険性から、幻灯巻は慎重に管理され、映画岡引のみが扱うことを許されている。 封印を施すには正確な名を刻むことが不可欠であり、誤った名を書いた場合、妖怪を抑えるどころか、その力を増大させてしまうこともあるとされる。 | Y86: =len(X86) -> 132 | AA86: =len(Z86) -> 0 | AC86: =len(AB86) -> 0
